Workbook

Sheet To Be Quote Fields
A1: Jira Id | B1: RCA Label | C1: RCA API | D1: Created By | E1: Conga API | F1: Standard/Existing/New | G1: Logic in RCA | H1: Related Components | I1: Approval/Product/Pricing
B2: Account Name | C2: AccountId | F2: Standard
B3: Additional To | C3: AdditionalAddress | F3: Standard
B4: Additional To Name | C4: AdditionalName | F4: Standard
B5: Adjustment Type | C5: Adjustment_Type__c | D5: Harcharan | F5: New
B6: Adjustment Distribution Logic | C6: AdjustmentDistributionLogic | F6: Standard
B7: Annual Commit Approval Partner Program | C7: Annual_Commit_Approval_Partner_Program__c | D7: Harcharan
B8: Applied Discount | C8: AppliedDiscount | F8: Standard
B9: Applied Discount Amount | C9: AppliedDiscountAmount | F9: Standard
B10: NSP Approval # | C10: Approval__c | F10: Exisitng
B11: NSP Approval Date | C11: Approval_Date__c | F11: Exisitng
B12: 承認申請日時 | C12: ApprovalRequestDateTime__c | F12: Exisitng
B13: 承認申請時利益率 | C13: ApprovalRequestProfitsRate__c | F13: Exisitng
B14: 備考（メモ） | C14: bikou_memo__c | F14: Exisitng
B15: Billing Frequency Modified | C15: Billing_Frequency_Modified__c | D15: Harcharan | F15: New
B16: Bill To | C16: BillingAddress | F16: Standard
B17: Bill To Name | C17: BillingName | F17: Standard
B18: Bill To Contact | C18: BillToContactId | F18: Standard
B19: Calculation Status | C19: CalculationStatus | F19: Standard
B20: Can Create Quote Line Items | C20: CanCreateQuoteLineItems | F20: Standard
B21: case status | C21: case_status__c | D21: Srilekha
B22: Channel | C22: Channel__c | F22: Exisitng
B23: Charge Type | C23: Charge_Type__c | D23: Harcharan
B24: Clone Quote ID | C24: Clone_Quote_ID__c | F24: Exisitng
B25: Clone Quote Status | C25: Clone_Quote_Status__c | F25: Exisitng
B26: Clone Quote Total Price | C26: Clone_Quote_Total__c | F26: Exisitng
B27: Clone Quote Total Price Diff | C27: Clone_Quote_Total_Price_Diff__c | F27: Exisitng
B28: Company | C28: Company__c | F28: Exisitng
B29: Console | C29: Console__c | D29: Harcharan
B30: Contact Name | C30: ContactId | F30: Standard
B31: Contract | C31: ContractId | F31: Standard
B32: 作成日 | C32: CreateDate__c | F32: Exisitng
B33: Quote Currency | C33: CurrencyIsoCode | F33: Standard
B34: Opp Reg # | C34: DAN__c | F34: Exisitng
B35: Opp Reg Expiration Date | C35: DAN_Expiration_Date__c | F35: Exisitng
B36: Deal ID | C36: Deal_ID__c | F36: Exisitng
B37: Deal Reg Discount | C37: Deal_Reg_Discount__c | F37: Exisitng
B38: Description | C38: Description | F38: Standard
B39: DigiCert Email | C39: DigiCert_Email__c | F39: Exisitng
B40: DigiCert Phone | C40: DigiCert_Phone__c | F40: Exisitng
B41: Digicert Platinum Support Count | C41: Digicert_Platinum_Support_Count__c | D41: Harcharan
B42: デジタル印表示フラグ | C42: digitalsignhyoujiflag__c | F42: Exisitng
B43: Discount | C43: Discount | F43: Standard
B44: Discount Amount | C44: Discount_Amount__c | F44: Exisitng
B45: DiscountRequestNo | C45: DiscountRequestNo__c | F45: Exisitng
B46: Distributor | C46: Distributor__c | F46: Exisitng
B47: DSSM Entitlement Change | C47: DSSM_Entitlement_Change__c | D47: Harcharan
B48: 営業担当者 | C48: eigyoutantousha__c | F48: Exisitng
B49: Email | C49: Email | F49: Standard
B50: Execution Status | C50: Execution_Status__c | D50: Srilekha | F50: New
B51: Expiration Date | C51: ExpirationDate | F51: Standard
B52: Fax | C52: Fax | F52: Standard
B53: Discount | C53: Full_Discount__c | F53: Exisitng
B54: 総計 | C54: Grand_Total__c | F54: Exisitng
B55: Grand Total | C55: GrandTotal
B56: Highest IPP Category Attribute Discount | C56: Highest_IPP_Category_Attribute_Discount__c
B57: 本社名 | C57: Honsyamei__c | F57: Exisitng
B58: Quote ID | C58: Id | F58: Standard
B59: Include Offline CA | C59: Include_Offline_CA__c
B60: Included Onetime Autoinvoice | C60: Included_Onetime_Autoinvoice__c
B61: Includes Ascertia Appliance | C61: Includes_Ascertia_Appliance__c
B62: Includes Customer Hosted | C62: Includes_Customer_Hosted__c
B63: Includes Threat Detection | C63: Includes_Threat_Detection__c
B64: Primary | C64: IsSyncing | F64: Standard
B65: JDE管理用見積ID | C65: JDEKanriID__c | F65: Exisitng
B66: 見積番号(Japan SFDC) | C66: JPQuoteNumber__c | F66: Exisitng
B67: 受注日 | C67: Jutyuubi__c | F67: Exisitng
B68: 注文番号 | C68: kakusakityuumonbangou__c | F68: Exisitng
B69: 客先提出フラグ | C69: KyakusakiTeishutuFlg__c | F69: Exisitng
B70: Last Priced Date | C70: LastPricedDate | F70: Standard
B71: Legal Entity | C71: LegalEntityId | F71: Standard
B72: Line Item Discount Total | C72: Line_Item_Discount_Total__c | F72: Exisitng
B73: Line Groups | C73: LineGroupCount | F73: Standard
B74: Line Items | C74: LineItemCount | F74: Standard
B75: 追加メールアドレス | C75: mailsendaddress__c | F75: Exisitng
... B95: Requested Expiration Date Justification | C95: Non_Standard_Expiration_Date_Justific__c | F95: Exisitng
B96: Non-Standard Selling Term | C96: Non_Standard_Selling_Term__c
B97: 備考 | C97: Notes__c | F97: Exisitng
B98: Notes to Partner | C98: Notes_to_Partner__c | F98: Exisitng
B99: 納品先表示 | C99: nouhinsakihyouji__c | F99: Exisitng
B100: 納期 | C100: nouki__c | F100: Exisitng
B101: 納期表示 | C101: noukihyouji__c | F101: Exisitng
B102: NSP Approval Auto | C102: NSP_Approval_Auto__c | F102: Exisitng
B103: NSP Justification/ Reasoning | C103: NSP_Justification_Reasoning__c | F103: Exisitng
B104: Opportunity Close Date | C104: Opportunity_Close_Date__c | F104: Exisitng
B105: Opportunity Name | C105: Opportunity_Name__c | F105: Exisitng
B106: Opportunity Type | C106: Opportunity_Type__c | F106: Exisitng
B107: Opportunity Name | C107: OpportunityId | F107: Standard
B108: Original Action Type | C108: OriginalActionType | F108: Standard
B109: Owner | C109: Owner__c | F109: Exisitng
B110: Owner Region | C110: Owner_Region__c
B111: Owner Name | C111: OwnerId | F111: Standard
B112: Parent Quote PriceBookId | C112: Parent_Quote_PriceBookId__c | F112: Exisitng
B113: Partner Authorization Level | C113: Partner_Authorization_Level__c | F113: Exisitng
B114: Partner Discount | C114: Partner_Discount__c | F114: Exisitng
B115: Partner Name | C115: Partner_Name__c | F115: Exisitng
B116: Partner Geo | C116: Partner_Region__c | F116: Exisitng
B117: Partner Sells Motion | C117: Partner_Sells_Motion__c
B118: Partner Type | C118: Partner_Type__c | F118: Exisitng
B119: Partner Account | C119: PartnerAccountId | F119: Standard
...

Sheet QuoteProposal - Fields
A1: Object | C1: Quote/Proposal
A2: API Name | C2: Apttus_Proposal__Proposal__c
O3: Field-Level Security for Profile
A4: NO | B4: Field Label | C4: API Name | D4: Data Type | E4: Length | F4: Field Type | G4: Required | H4: Picklist Values | I4: Formula | J4: Extend ID | K4: Track History | L4: Description | M4: Help Text | N4: Proposal Layout V2 | O4: Admin | P4: Customer Surveys Profile | Q4: DC Customer Support Portal | R4: DC Legal | S4: DC MM NetNew Sales | T4: DC NetNew Sales | U4: DC Order Management | V4: DC SDR NetNew Sales | W4: DC Sales | X4: DC Sales Ops | Y4: DC Sales Supervisor | Z4: DC Services | AA4: DC Services Supervisor | AB4: DC System Admin - System Accounts | AC4: DigiCert Support Portal Profile | AD4: Live Agent Chat Profile | AE4: Mocana Customer Service Desk | AF4: Mocana Support Desk Profile | AG4: Read Only | AH4: Salesforce API Only System Integrations | AI4: Vercara (Read Only)
A5: 1 | B5: Record ID | C5: Id | D5: id | F5: Standard | G5: Required | N5: =VLOOKUP(B5,'Sheet 1'!$B$2:$C$108,2,FALSE) -> #N/A | O5: - | P5: - | Q5: - | R5: - | S5: - | T5: - | U5: - | V5: - | W5: - | X5: - | Y5: - | Z5: - | AA5: - | AB5: - | AC5: - | AD5: - | AE5: - | AF5: - | AG5: - | AH5: - | AI5: -
A6: 2 | B6: Owner ID | C6: OwnerId | D6: Lookup (Group,User) | F6: Standard | G6: Required | N6: =VLOOKUP(B6,'Sheet 1'!$B$2:$C$108,2,FALSE) -> #N/A | O6: - | P6: - | Q6: - | R6: - | S6: - | T6: - | U6: - | V6: - | W6: - | X6: - | Y6: - | Z6: - | AA6: - | AB6: - | AC6: - | AD6: - | AE6: - | AF6: - | AG6: - | AH6: - | AI6: -
A7: 3 | B7: Deleted | C7: IsDeleted | D7: Checkbox | F7: Standard | N7: =VLOOKUP(B7,'Sheet 1'!$B$2:$C$108,2,FALSE) -> #N/A | O7: - | P7: - | Q7: - | R7: - | S7: - | T7: - | U7: - | V7: - | W7: - | X7: - | Y7: - | Z7: - | AA7: - | AB7: - | AC7: - | AD7: - | AE7: - | AF7: - | AG7: - | AH7: - | AI7: -
A8: 4 | B8: Proposal ID | C8: Name | D8: Auto Number | E8: 80 | F8: Standard | G8: Required | N8: =VLOOKUP(B8,'Sheet 1'!$B$2:$C$108,2,FALSE) -> V2 | O8: - | P8: - | Q8: - | R8: - | S8: - | T8: - | U8: - | V8: - | W8: - | X8: - | Y8: - | Z8: - | AA8: - | AB8: - | AC8: - | AD8: - | AE8: - | AF8: - | AG8: - | AH8: - | AI8: -
A9: 5 | B9: Currency ISO Code | C9: CurrencyIsoCode | D9: Picklist | F9: Standard | H9: AUD;BMD;BRL;GBP;CAD;CLP;CNY;DKK;EUR;HKD;INR;ILS;JPY;KRW;MXN;NZD;NOK;PLN;RUB;SAR;SGD;ZAR;SEK;CHF;TWD;USD;AED | N9: =VLOOKUP(B9,'Sheet 1'!$B$2:$C$108,2,FALSE) -> #N/A | O9: - | P9: - | Q9: - | R9: - | S9: - | T9: - | U9: - | V9: - | W9: - | X9: - | Y9: - | Z9: - | AA9: - | AB9: - | AC9: - | AD9: - | AE9: - | AF9: - | AG9: - | AH9: - | AI9: -
A10: 6 | B10: Record Type ID | C10: RecordTypeId | D10: Lookup (Record Type) | F10: Standard | N10: =VLOOKUP(B10,'Sheet 1'!$B$2:$C$108,2,FALSE) -> #N/A | O10: - | P10: - | Q10: - | R10: - | S10: - | T10: - | U10: - | V10: - | W10: - | X10: - | Y10: - | Z10: - | AA10: - | AB10: - | AC10: - | AD10: - | AE10: - | AF10: - | AG10: - | AH10: - | AI10: -
A11: 7 | B11: Created Date | C11: CreatedDate | D11: Date/Time | F11: Standard | G11: Required | N11: =VLOOKUP(B11,'Sheet 1'!$B$2:$C$108,2,FALSE) -> #N/A | O11: - | P11: - | Q11: - | R11: - | S11: - | T11: - | U11: - | V11: - | W11: - | X11: - | Y11: - | Z11: - | AA11: - | AB11: - | AC11: - | AD11: - | AE11: - | AF11: - | AG11: - | AH11: - | AI11: -
A12: 8 | B12: Created By ID | C12: CreatedById | D12: Lookup (User) | F12: Standard | G12: Required | N12: =VLOOKUP(B12,'Sheet 1'!$B$2:$C$108,2,FALSE) -> #N/A | O12: - | P12: - | Q12: - | R12: - | S12: - | T12: - | U12: - | V12: - | W12: - | X12: - | Y12: - | Z12: - | AA12: - | AB12: - | AC12: - | AD12: - | AE12: - | AF12: - | AG12: - | AH12: - | AI12: -
A13: 9 | B13: Last Modified Date | C13: LastModifiedDate | D13: Date/Time | F13: Standard | G13: Required | N13: =VLOOKUP(B13,'Sheet 1'!$B$2:$C$108,2,FALSE) -> #N/A | O13: - | P13: - | Q13: - | R13: - | S13: - | T13: - | U13: - | V13: - | W13: - | X13: - | Y13: - | Z13: - | AA13: - | AB13: - | AC13: - | AD13: - | AE13: - | AF13: - | AG13: - | AH13: - | AI13: -
A14: 10 | B14: Last Modified By ID | C14: LastModifiedById | D14: Lookup (User) | F14: Standard | G14: Required | N14: =VLOOKUP(B14,'Sheet 1'!$B$2:$C$108,2,FALSE) -> #N/A | O14: - | P14: - | Q14: - | R14: - | S14: - | T14: - | U14: - | V14: - | W14: - | X14: - | Y14: - | Z14: - | AA14: - | AB14: - | AC14: - | AD14: - | AE14: - | AF14: - | AG14: - | AH14: - | AI14: -
A15: 11 | B15: System Modstamp | C15: SystemModstamp | D15: Date/Time | F15: Standard | G15: Required | N15: =VLOOKUP(B15,'Sheet 1'!$B$2:$C$108,2,FALSE) -> #N/A | O15: - | P15: - | Q15: - | R15: - | S15: - | T15: - | U15: - | V15: - | W15: - | X15: - | Y15: - | Z15: - | AA15: - | AB15: - | AC15: - | AD15: - | AE15: - | AF15: - | AG15: - | AH15: - | AI15: -
A16: 12 | B16: Last Activity Date | C16: LastActivityDate | D16: Date | F16: Standard | N16: =VLOOKUP(B16,'Sheet 1'!$B$2:$C$108,2,FALSE) -> #N/A | O16: - | P16: - | Q16: - | R16: - | S16: - | T16: - | U16: - | V16: - | W16: - | X16: - | Y16: - | Z16: - | AA16: - | AB16: - | AC16: - | AD16: - | AE16: - | AF16: - | AG16: - | AH16: - | AI16: -
A17: 13 | B17: Last Viewed Date | C17: LastViewedDate | D17: Date/Time | F17: Standard | N17: =VLOOKUP(B17,'Sheet 1'!$B$2:$C$108,2,FALSE) -> #N/A | O17: - | P17: - | Q17: - | R17: - | S17: - | T17: - | U17: - | V17: - | W17: - | X17: - | Y17: - | Z17: - | AA17: - | AB17: - | AC17: - | AD17: - | AE17: - | AF17: - | AG17: - | AH17: - | AI17: -
A18: 14 | B18: Last Referenced Date | C18: LastReferencedDate | D18: Date/Time | F18: Standard | N18: =VLOOKUP(B18,'Sheet 1'!$B$2:$C$108,2,FALSE) -> #N/A | O18: - | P18: - | Q18: - | R18: - | S18: - | T18: - | U18: - | V18: - | W18: - | X18: - | Y18: - | Z18: - | AA18: - | AB18: - | AC18: - | AD18: - | AE18: - | AF18: - | AG18: - | AH18: - | AI18: -
A19: 15 | B19: Account | C19: Apttus_Proposal__Account__c | D19: Lookup (Account) | F19: Custom | K19: ✓ | L19: Prospect Account | N19: =VLOOKUP(B19,'Sheet 1'!$B$2:$C$108,2,FALSE) -> V2 | O19: Editable | P19: Invisible | Q19: Invisible | R19: Editable | S19: Invisible | T19: Invisible | U19: Editable | V19: Editable | W19: Editable | X19: Editable | Y19: Editable | Z19: Editable | AA19: Editable | AB19: Editable | AC19: Invisible | AD19: Invisible | AE19: Editable | AF19: Invisible | AG19: Editable | AH19: Editable | AI19: Invisible
A20: 16 | B20: Approval Stage | C20: Apttus_Proposal__Approval_Stage__c | D20: Picklist | F20: Custom | H20: Draft;Approval Required;In Review;Approved;Generated;Presented;Accepted;Denied;Cancelled | K20: ✓ | L20: The proposal approval stage | N20: =VLOOKUP(B20,'Sheet 1'!$B$2:$C$108,2,FALSE) -> V2 | O20: Editable | P20: Invisible | Q20: Invisible | R20: Editable | S20: Invisible | T20: Invisible | U20: Editable | V20: Editable | W20: Editable | X20: Editable | Y20: Editable | Z20: Editable | AA20: Editable | AB20: Editable | AC20: Invisible | AD20: Invisible | AE20: Editable | AF20: Invisible | AG20: Editable | AH20: Editable | AI20: Invisible
A21: 17 | B21: Create Agreement | C21: Apttus_Proposal__CreateAgreement__c | D21: Formula (Text) | E21: 1300 | F21: Custom | I21: IF (ISPICKVAL(Apttus_Proposal__Approval_Stage__c, "Accepted") , IF($User.UIThemeDisplayed == 'Theme4d',HYPERLINK("/one/one.app#/alohaRedirect/apex/Apttus_Proposal__ProposalAgreementCreate?id="&Id, IMAGE("/resource/Apttus_Proposal__Button_CreateAgreement", "Create Agreement"),"_self"),HYPERLINK("/apex/Apttus_Proposal__ProposalAgreementCreate?id="&Id, IMAGE("/resource/Apttus_Proposal__Button_CreateAgreement", "Create Agreement"),"_self")), NULL) | L21: Create Agreement, if the proposal is accepted. | N21: =VLOOKUP(B21,'Sheet 1'!$B$2:$C$108,2,FALSE) -> #N/A | O21: Read-Only | P21: Invisible | Q21: Invisible | R21: Editable | S21: Invisible | T21: Invisible | U21: Read-Only | V21: Editable | W21: Read-Only | X21: Read-Only | Y21: Editable | Z21: Editable | AA21: Editable | AB21: Editable | AC21: Invisible | AD21: Invisible | AE21: Editable | AF21: Invisible | AG21: Editable | AH21: Editable | AI21: Invisible
A22: 18 | B22: Description | C22: Apttus_Proposal__Description__c | D22: Long Text Area | E22: 32000 | F22: Custom | L22: The proposal description | N22: =VLOOKUP(B22,'Sheet 1'!$B$2:$C$108,2,FALSE) -> V2 | O22: Editable | P22: Invisible | Q22: Invisible | R22: Editable | S22: Invisible | T22: Invisible | U22: Editable | V22: Editable | W22: Editable | X22: Editable | Y22: Editable | Z22: Editable | AA22: Editable | AB22: Editable | AC22: Invisible | AD22: Invisible | AE22: Editable | AF22: Invisible | AG22: Editable | AH22: Editable | AI22: Invisible
A23: 19 | B23: Discount % | C23: Apttus_Proposal__Discount_Percent__c | D23: Percent | F23: Custom | N23: =VLOOKUP(B23,'Sheet 1'!$B$2:$C$108,2,FALSE) -> #N/A | O23: Editable | P23: Invisible | Q23: Invisible | R23: Editable | S23: Invisible | T23: Invisible | U23: Editable | V23: Editable | W23: Editable | X23: Editable | Y23: Editable | Z23: Editable | AA23: Editable | AB23: Editable | AC23: Invisible | AD23: Invisible | AE23: Editable | AF23: Invisible | AG23: Editable | AH23: Editable | AI23: Invisible
A24: 20 | B24: Expected End Date | C24: Apttus_Proposal__ExpectedEndDate__c | D24: Date | F24: Custom | L24: The expected end date for products and services | N24: =VLOOKUP(B24,'Sheet 1'!$B$2:$C$108,2,FALSE) -> #N/A | O24: Editable | P24: Invisible | Q24: Invisible | R24: Editable | S24: Invisible | T24: Invisible | U24: Editable | V24: Editable | W24: Editable | X24: Editable | Y24: Editable | Z24: Editable | AA24: Editable | AB24: Editable | AC24: Invisible | AD24: Invisible | AE24: Editable | AF24: Invisible | AG24: Editable | AH24: Editable | AI24: Invisible
A25: 21 | B25: Expected Start Date | C25: Apttus_Proposal__ExpectedStartDate__c | D25: Date | F25: Custom | L25: The expected start date for products and services | N25: =VLOOKUP(B25,'Sheet 1'!$B$2:$C$108,2,FALSE) -> V2 | O25: Editable | P25: Invisible | Q25: Invisible | R25: Editable | S25: Invisible | T25: Invisible | U25: Editable | V25: Editable | W25: Editable | X25: Editable | Y25: Editable | Z25: Editable | AA25: Editable | AB25: Editable | AC25: Invisible | AD25: Invisible | AE25: Editable | AF25: Invisible | AG25: Editable | AH25: Editable | AI25: Invisible
A26: 22 | B26: Generate | C26: Apttus_Proposal__Generate__c | D26: Formula (Text) | E26: 1300 | F26: Custom | I26: IF (Apttus_Proposal__ReadyToGenerate__c, IF($User.UIThemeDisplayed == 'Theme4d',HYPERLINK("/one/one.app#/alohaRedirect/apex/Apttus_Proposal__ProposalGenerate?id="&Id, IMAGE("/resource/Apttus_Proposal__Button_Generate", "Generate"),"_self"),HYPERLINK("/apex/Apttus_Proposal__ProposalGenerate?id="&Id, IMAGE("/resource/Apttus_Proposal__Button_Generate", "Generate"),"_self")), NULL) | L26: Generate a quote/proposal | M26: Generate a quote/proposal | N26: =VLOOKUP(B26,'Sheet 1'!$B$2:$C$108,2,FALSE) -> #N/A | O26: Read-Only | P26: Invisible | Q26: Invisible | R26: Editable | S26: Invisible | T26: Invisible | U26: Read-Only | V26: Editable | W26: Read-Only | X26: Read-Only | Y26: Editable | Z26: Editable | AA26: Editable | AB26: Editable | AC26: Invisible | AD26: Invisible | AE26: Editable | AF26: Invisible | AG26: Editable | AH26: Editable | AI26: Invisible
A27: 23 | B27: Grand Total | C27: Apttus_Proposal__Grand_Total__c | D27: Formula (Currency) | F27: Custom | I27: Apttus_Proposal__Net_Amount__c + Apttus_Proposal__Shipping_Handling__c + Apttus_Proposal__Sales_Tax_Amount__c | N27: =VLOOKUP(B27,'Sheet 1'!$B$2:$C$108,2,FALSE) -> #N/A | O27: Read-Only | P27: Invisible | Q27: Invisible | R27: Editable | S27: Invisible | T27: Invisible | U27: Read-Only | V27: Editable | W27: Read-Only | X27: Read-Only | Y27: Editable | Z27: Editable | AA27: Editable | AB27: Editable | AC27: Invisible | AD27: Invisible | AE27: Editable | AF27: Invisible | AG27: Editable | AH27: Editable | AI27: Invisible
A28: 24 | B28: Internal Deadline | C28: Apttus_Proposal__Internal_Deadline__c | D28: Date | F28: Custom | N28: =VLOOKUP(B28,'Sheet 1'!$B$2:$C$108,2,FALSE) -> #N/A | O28: Editable | P28: Invisible | Q28: Invisible | R28: Editable | S28: Invisible | T28: Invisible | U28: Editable | V28: Editable | W28: Editable | X28: Editable | Y28: Editable | Z28: Editable | AA28: Editable | AB28: Editable | AC28: Invisible | AD28: Invisible | AE28: Editable | AF28: Invisible | AG28: Editable | AH28: Editable | AI28: Invisible
A29: 25 | B29: Make Primary | C29: Apttus_Proposal__MakePrimary__c | D29: Formula (Text) | E29: 1300 | F29: Custom | I29: IF (AND(LEN(Apttus_Proposal__Opportunity__c ) > 0, NOT(Apttus_Proposal__Primary__c)), HYPERLINK("/apex/Apttus_Proposal__ProposalMakePrimary?id="&Id, IMAGE("/resource/Apttus_Proposal__Button_MakePrimary", "Make Primary"),"_self"), NULL) | L29: Make the quote/proposal primary for the associated opportunity | N29: =VLOOKUP(B29,'Sheet 1'!$B$2:$C$108,2,FALSE) -> #N/A | O29: Read-Only | P29: Invisible | Q29: Invisible | R29: Editable | S29: Invisible | T29: Invisible | U29: Read-Only | V29: Editable | W29: Read-Only | X29: Read-Only | Y29: Editable | Z29: Editable | AA29: Editable | AB29: Editable | AC29: Invisible | AD29: Invisible | AE29: Editable | AF29: Invisible | AG29: Editable | AH29: Editable | AI29: Invisible
A30: 26 | B30: Net Amount | C30: Apttus_Proposal__Net_Amount__c | D30: Formula (Currency) | F30: Custom | I30: Apttus_Proposal__Amount__c * (1 - Apttus_Proposal__Discount_Percent__c ) | N30: =VLOOKUP(B30,'Sheet 1'!$B$2:$C$108,2,FALSE) -> #N/A | O30: Read-Only | P30: Invisible | Q30: Invisible | R30: Editable | S30: Invisible | T30: Invisible | U30: Read-Only | V30: Editable | W30: Read-Only | X30: Read-Only | Y30: Editable | Z30: Editable | AA30: Editable | AB30: Editable | AC30: Invisible | AD30: Invisible | AE30: Editable | AF30: Invisible | AG30: Editable | AH30: Editable | AI30: Invisible
A31: 27 | B31: Opportunity | C31: Apttus_Proposal__Opportunity__c | D31: Lookup (Opportunity) | F31: Custom | L31: The related opportunity | N31: =VLOOKUP(B31,'Sheet 1'!$B$2:$C$108,2,FALSE) -> V2 | O31: Editable | P31: Invisible | Q31: Invisible | R31: Editable | S31: Invisible | T31: Invisible | U31: Editable | V31: Editable | W31: Editable | X31: Editable | Y31: Editable | Z31: Editable | AA31: Editable | AB31: Editable | AC31: Invisible | AD31: Invisible | AE31: Editable | AF31: Invisible | AG31: Editable | AH31: Editable | AI31: Invisible
A32: 28 | B32: Payment Term | C32: Apttus_Proposal__Payment_Term__c | D32: Picklist | F32: Custom | H32: Net 30;Net 30 EoM | N32: =VLOOKUP(B32,'Sheet 1'!$B$2:$C$108,2,FALSE) -> V2 | O32: Editable | P32: Invisible | Q32: Invisible | R32: Editable | S32: Invisible | T32: Invisible | U32: Editable | V32: Editable | W32: Editable | X32: Editable | Y32: Editable | Z32: Editable | AA32: Editable | AB32: Editable | AC32: Invisible | AD32: Invisible | AE32: Editable | AF32: Invisible | AG32: Editable | AH32: Editable | AI32: Invisible
A33: 29 | B33: Present | C33: Apttus_Proposal__Present__c | D33: Formula (Text) | E33: 1300 | F33: Custom | I33: IF (Apttus_Proposal__ReadyToPresent__c, IF($User.UIThemeDisplayed == 'Theme4d',HYPERLINK("/one/one.app#/alohaRedirect/apex/Apttus_Proposal__ProposalPresent?id="&Id, IMAGE("/resource/Apttus_Proposal__Button_Present", "Present"),"_self"),HYPERLINK("/apex/Apttus_Proposal__ProposalPresent?id="&Id, IMAGE("/resource/Apttus_Proposal__Button_Present", "Present"),"_self")), NULL) | L33: Present the quote/proposal | N33: =VLOOKUP(B33,'Sheet 1'!$B$2:$C$108,2,FALSE) -> #N/A | O33: Read-Only | P33: Invisible | Q33: Invisible | R33: Editable | S33: Invisible | T33: Invisible | U33: Read-Only | V33: Editable | W33: Read-Only | X33: Read-Only | Y33: Editable | Z33: Editable | AA33: Editable | AB33: Editable | AC33: Invisible | AD33: Invisible | AE33: Editable | AF33: Invisible | AG33: Editable | AH33: Editable | AI33: Invisible
A34: 30 | B34: Presented Date | C34: Apttus_Proposal__Presented_Date__c | D34: Date | F34: Custom | L34: The date the quote/proposal was presented to the customer | N34: =VLOOKUP(B34,'Sheet 1'!$B$2:$C$108,2,FALSE) -> #N/A | O34: Editable | P34: Invisible | Q34: Invisible | R34: Editable | S34: Invisible | T34: Invisible | U34: Editable | V34: Editable | W34: Editable | X34: Editable | Y34: Editable | Z34: Editable | AA34: Editable | AB34: Editable | AC34: Invisible | AD34: Invisible | AE34: Editable | AF34: Invisible | AG34: Editable | AH34: Editable | AI34: Invisible
A35: 31 | B35: Preview | C35: Apttus_Proposal__Preview__c | D35: Formula (Text) | E35: 1300 | F35: Custom | I35: IF($User.UIThemeDisplayed == 'Theme4d',HYPERLINK("/one/one.app#/alohaRedirect/apex/Apttus_Proposal__ProposalGenerate?id="&Id & "&action=Preview", IMAGE("/resource/Apttus_Proposal__Button_Preview", "Preview"),"_self"),HYPERLINK("/apex/Apttus_Proposal__ProposalGenerate?id="&Id & "&action=Preview", IMAGE("/resource/Apttus_Proposal__Button_Preview", "Preview"),"_self")) | L35: Preview a quote/proposal | M35: Preview a quote/proposal | N35: =VLOOKUP(B35,'Sheet 1'!$B$2:$C$108,2,FALSE) -> V2 | O35: Read-Only | P35: Invisible | Q35: Invisible | R35: Editable | S35: Invisible | T35: Invisible | U35: Read-Only | V35: Editable | W35: Read-Only | X35: Read-Only | Y35: Editable | Z35: Editable | AA35: Editable | AB35: Editable | AC35: Invisible | AD35: Invisible | AE35: Editable | AF35: Invisible | AG35: Editable | AH35: Editable | AI35: Invisible
A36: 32 | B36: Primary Contact | C36: Apttus_Proposal__Primary_Contact__c | D36: Lookup (Contact) | F36: Custom | L36: The primary contact associated with the quote/proposal | N36: =VLOOKUP(B36,'Sheet 1'!$B$2:$C$108,2,FALSE) -> #N/A | O36: Editable | P36: Invisible | Q36: Invisible | R36: Editable | S36: Invisible | T36: Invisible | U36: Editable | V36: Editable | W36: Editable | X36: Editable | Y36: Editable | Z36: Editable | AA36: Editable | AB36: Editable | AC36: Invisible | AD36: Invisible | AE36: Editable | AF36: Invisible | AG36: Editable | AH36: Editable | AI36: Invisible
A37: 33 | B37: Primary | C37: Apttus_Proposal__Primary__c | D37: Checkbox | F37: Custom | K37: ✓ | L37: Indicates whether the quote/proposal is the primary quote to update the related opportunity | N37: =VLOOKUP(B37,'Sheet 1'!$B$2:$C$108,2,FALSE) -> V2 | O37: Editable | P37: Invisible | Q37: Invisible | R37: Editable | S37: Invisible | T37: Invisible | U37: Editable | V37: Editable | W37: Editable | X37: Editable | Y37: Editable | Z37: Editable | AA37: Editable | AB37: Editable | AC37: Invisible | AD37: Invisible | AE37: Editable | AF37: Invisible | AG37: Editable | AH37: Editable | AI37: Invisible
A38: 34 | B38: Proposal Approval Date | C38: Apttus_Proposal__Proposal_Approval_Date__c | D38: Date | F38: Custom | L38: The date the quote/proposal was approved | N38: =VLOOKUP(B38,'Sheet 1'!$B$2:$C$108,2,FALSE) -> #N/A | O38: Editable | P38: Invisible | Q38: Invisible | R38: Editable | S38: Invisible | T38: Invisible | U38: Editable | V38: Editable | W38: Editable | X38: Editable | Y38: Editable | Z38: Editable | AA38: Editable | AB38: Editable | AC38: Invisible | AD38: Invisible | AE38: Editable | AF38: Invisible | AG38: Editable | AH38: Editable | AI38: Invisible
A39: 35 | B39: Proposal Category | C39: Apttus_Proposal__Proposal_Category__c | D39: Picklist | F39: Custom | H39: Quote;Proposal | L39: The quote/proposal category | M39: The quote/proposal category | N39: =VLOOKUP(B39,'Sheet 1'!$B$2:$C$108,2,FALSE) -> #N/A | O39: Editable | P39: Invisible | Q39: Invisible | R39: Editable | S39: Invisible | T39: Invisible | U39: Editable | V39: Editable | W39: Editable | X39: Editable | Y39: Editable | Z39: Editable | AA39: Editable | AB39: Editable | AC39: Invisible | AD39: Invisible | AE39: Editable | AF39: Invisible | AG39: Editable | AH39: Editable | AI39: Invisible
A40: 36 | B40: Proposal Expiration Date | C40: Apttus_Proposal__Proposal_Expiration_Date__c | D40: Date | F40: Custom | L40: The quote/proposal expiration date | N40: =VLOOKUP(B40,'Sheet 1'!$B$2:$C$108,2,FALSE) -> #N/A | O40: Editable | P40: Invisible | Q40: Invisible | R40: Editable | S40: Invisible | T40: Invisible | U40: Editable | V40: Editable | W40: Editable | X40: Editable | Y40: Editable | Z40: Editable | AA40: Editable | AB40: Editable | AC40: Invisible | AD40: Invisible | AE40: Editable | AF40: Invisible | AG40: Editable | AH40: Editable | AI40: Invisible
A41: 37 | B41: Proposal Name | C41: Apttus_Proposal__Proposal_Name__c | D41: Text | E41: 255 | F41: Custom | N41: =VLOOKUP(B41,'Sheet 1'!$B$2:$C$108,2,FALSE) -> V2 | O41: Editable | P41: Invisible | Q41: Invisible | R41: Editable | S41: Invisible | T41: Invisible | U41: Editable | V41: Editable | W41: Editable | X41: Editable | Y41: Editable | Z41: Editable | AA41: Editable | AB41: Editable | AC41: Invisible | AD41: Invisible | AE41: Editable | AF41: Invisible | AG41: Editable | AH41: Editable | AI41: Invisible
A42: 38 | B42: RFP Intake Date | C42: Apttus_Proposal__RFP_Intake_Date__c | D42: Date | F42: Custom | N42: =VLOOKUP(B42,'Sheet 1'!$B$2:$C$108,2,FALSE) -> #N/A | O42: Editable | P42: Invisible | Q42: Invisible | R42: Editable | S42: Invisible | T42: Invisible | U42: Editable | V42: Editable | W42: Editable | X42: Editable | Y42: Editable | Z42: Editable | AA42: Editable | AB42: Editable | AC42: Invisible | AD42: Invisible | AE42: Editable | AF42: Invisible | AG42: Editable | AH42: Editable | AI42: Invisible
A43: 39 | B43: RFP Response Due Date | C43: Apttus_Proposal__RFP_Response_Due_Date__c | D43: Date | F43: Custom | N43: =VLOOKUP(B43,'Sheet 1'!$B$2:$C$108,2,FALSE) -> #N/A | O43: Editable | P43: Invisible | Q43: Invisible | R43: Editable | S43: Invisible | T43: Invisible | U43: Editable | V43: Editable | W43: Editable | X43: Editable | Y43: Editable | Z43: Editable | AA43: Editable | AB43: Editable | AC43: Invisible | AD43: Invisible | AE43: Editable | AF43: Invisible | AG43: Editable | AH43: Editable | AI43: Invisible
A44: 40 | B44: RFP Stage | C44: Apttus_Proposal__RFP_Stage__c | D44: Picklist | F44: Custom | H44: Expected;Received;First Revision;Technical Input;Pricing;Internal Approval;Final Draft;Submitted | N44: =VLOOKUP(B44,'Sheet 1'!$B$2:$C$108,2,FALSE) -> #N/A | O44: Editable | P44: Invisible | Q44: Invisible | R44: Editable | S44: Invisible | T44: Invisible | U44: Editable | V44: Editable | W44: Editable | X44: Editable | Y44: Editable | Z44: Editable | AA44: Editable | AB44: Editable | AC44: Invisible | AD44: Invisible | AE44: Editable | AF44: Invisible | AG44: Editable | AH44: Editable | AI44: Invisible
A45: 41 | B45: RFP Value | C45: Apttus_Proposal__RFP_Value__c | D45: Currency | F45: Custom | N45: =VLOOKUP(B45,'Sheet 1'!$B$2:$C$108,2,FALSE) -> #N/A | O45: Editable | P45: Invisible | Q45: Invisible | R45: Editable | S45: Invisible | T45: Invisible | U45: Editable | V45: Editable | W45: Editable | X45: Editable | Y45: Editable | Z45: Editable | AA45: Editable | AB45: Editable | AC45: Invisible | AD45: Invisible | AE45: Editable | AF45: Invisible | AG45: Editable | AH45: Editable | AI45: Invisible
A46: 42 | B46: Ready To Generate | C46: Apttus_Proposal__ReadyToGenerate__c | D46: Checkbox | F46: Custom | L46: Indicates whether the proposal is ready for generation | N46: =VLOOKUP(B46,'Sheet 1'!$B$2:$C$108,2,FALSE) -> #N/A | O46: Editable | P46: Invisible | Q46: Invisible | R46: Editable | S46: Invisible | T46: Invisible | U46: Editable | V46: Editable | W46: Editable | X46: Editable | Y46: Editable | Z46: Editable | AA46: Editable | AB46: Editable | AC46: Invisible | AD46: Invisible | AE46: Editable | AF46: Invisible | AG46: Editable | AH46: Editable | AI46: Invisible
A47: 43 | B47: Ready To Present | C47: Apttus_Proposal__ReadyToPresent__c | D47: Checkbox | F47: Custom | L47: Indicates whether the proposal is ready for presentation | N47: =VLOOKUP(B47,'Sheet 1'!$B$2:$C$108,2,FALSE) -> #N/A | O47: Editable | P47: Invisible | Q47: Invisible | R47: Editable | S47: Invisible | T47: Invisible | U47: Editable | V47: Editable | W47: Editable | X47: Editable | Y47: Editable | Z47: Editable | AA47: Editable | AB47: Editable | AC47: Invisible | AD47: Invisible | AE47: Editable | AF47: Invisible | AG47: Editable | AH47: Editable | AI47: Invisible
A48: 44 | B48: Related Quote/Proposal | C48: Apttus_Proposal__RelatedProposalId__c | D48: Lookup (Quote/Proposal) | F48: Custom | L48: ID of the related or parent quote/proposal | M48: ID of the related or parent quote/proposal | N48: =VLOOKUP(B48,'Sheet 1'!$B$2:$C$108,2,FALSE) -> #N/A | O48: Editable | P48: Invisible | Q48: Invisible | R48: Editable | S48: Invisible | T48: Invisible | U48: Editable | V48: Editable | W48: Editable | X48: Editable | Y48: Editable | Z48: Editable | AA48: Editable | AB48: Editable | AC48: Invisible | AD48: Invisible | AE48: Editable | AF48: Invisible | AG48: Editable | AH48: Editable | AI48: Invisible
A49: 45 | B49: Request Approval | C49: Apttus_Proposal__Request_Approval__c | D49: Formula (Text) | E49: 1300 | F49: Custom | I49: HYPERLINK("/servlet/servlet.Integration?lid=01N700000009u2c&eid="&Id, IMAGE("/servlet/servlet.ImageServer?oid=00D70000000JXTN&id=01570000000e6nU", "Submit") ) | N49: =VLOOKUP(B49,'Sheet 1'!$B$2:$C$108,2,FALSE) -> #N/A | O49: Read-Only | P49: Invisible | Q49: Invisible | R49: Editable | S49: Invisible | T49: Invisible | U49: Read-Only | V49: Editable | W49: Read-Only | X49: Read-Only | Y49: Editable | Z49: Editable | AA49: Editable | AB49: Editable | AC49: Invisible | AD49: Invisible | AE49: Editable | AF49: Invisible | AG49: Editable | AH49: Editable | AI49: Invisible
A50: 46 | B50: Risk Factors | C50: Apttus_Proposal__Risk_Factors__c | D50: Picklist (Multi-Select) | F50: Custom | H50: Turnaround Time;Price Pressure;Technical Delivery | L50: The risk factors associated with the quote/proposal | N50: =VLOOKUP(B50,'Sheet 1'!$B$2:$C$108,2,FALSE) -> #N/A | O50: Editable | P50: Invisible | Q50: Invisible | R50: Editable | S50: Invisible | T50: Invisible | U50: Editable | V50: Editable | W50: Editable | X50: Editable | Y50: Editable | Z50: Editable | AA50: Editable | AB50: Editable | AC50: Invisible | AD50: Invisible | AE50: Editable | AF50: Invisible | AG50: Editable | AH50: Editable | AI50: Invisible
A51: 47 | B51: Sales Tax Amount | C51: Apttus_Proposal__Sales_Tax_Amount__c | D51: Formula (Currency) | F51: Custom | I51: Apttus_Proposal__Net_Amount__c * Apttus_Proposal__Sales_Tax_Percent__c | N51: =VLOOKUP(B51,'Sheet 1'!$B$2:$C$108,2,FALSE) -> #N/A | O51: Read-Only | P51: Invisible | Q51: Invisible | R51: Editable | S51: Invisible | T51: Invisible | U51: Read-Only | V51: Editable | W51: Read-Only | X51: Read-Only | Y51: Editable | Z51: Editable | AA51: Editable | AB51: Editable | AC51: Invisible | AD51: Invisible | AE51: Editable | AF51: Invisible | AG51: Editable | AH51: Editable | AI51: Invisible
A52: 48 | B52: Sales Tax % | C52: Apttus_Proposal__Sales_Tax_Percent__c | D52: Percent | F52: Custom | N52: =VLOOKUP(B52,'Sheet 1'!$B$2:$C$108,2,FALSE) -> #N/A | O52: Editable | P52: Invisible | Q52: Invisible | R52: Editable | S52: Invisible | T52: Invisible | U52: Editable | V52: Editable | W52: Editable | X52: Editable | Y52: Editable | Z52: Editable | AA52: Editable | AB52: Editable | AC52: Invisible | AD52: Invisible | AE52: Editable | AF52: Invisible | AG52: Editable | AH52: Editable | AI52: Invisible
A53: 49 | B53: Send Proposal | C53: Apttus_Proposal__SendProposal__c | D53: Formula (Text) | E53: 1300 | F53: Custom | I53: IF (Apttus_Proposal__ReadyToGenerate__c, IF($User.UIThemeDisplayed == 'Theme4d',HYPERLINK("/one/one.app#/alohaRedirect/apex/Apttus_Proposal__DocGen?id="&Id + "&context=proposal" + "&name="&Name, IMAGE("/resource/Apttus_Proposal__Button_SendProposal", "Send Proposal"),"_self"), HYPERLINK("/apex/Apttus_Proposal__DocGen?id="&Id + "&context=proposal" + "&name="&Name, IMAGE("/resource/Apttus_Proposal__Button_SendProposal", "Send Proposal"),"_self")), NULL) | L53: Generate and send a quote/proposal | M53: Generate and send a quote/proposal | N53: =VLOOKUP(B53,'Sheet 1'!$B$2:$C$108,2,FALSE) -> #N/A | O53: Read-Only | P53: Invisible | Q53: Invisible | R53: Editable | S53: Invisible | T53: Invisible | U53: Read-Only | V53: Editable | W53: Read-Only | X53: Read-Only | Y53: Editable | Z53: Editable | AA53: Editable | AB53: Editable | AC53: Invisible | AD53: Invisible | AE53: Editable | AF53: Invisible | AG53: Editable | AH53: Editable | AI53: Invisible
A54: 50 | B54: Shipping & Handling | C54: Apttus_Proposal__Shipping_Handling__c | D54: Currency | F54: Custom | N54: =VLOOKUP(B54,'Sheet 1'!$B$2:$C$108,2,FALSE) -> #N/A | O54: Editable | P54: Invisible | Q54: Invisible | R54: Editable | S54: Invisible | T54: Invisible | U54: Editable | V54: Editable | W54: Editable | X54: Editable | Y54: Editable | Z54: Editable | AA54: Editable | AB54: Editable | AC54: Invisible | AD54: Invisible | AE54: Editable | AF54: Invisible | AG54: Editable | AH54: Editable | AI54: Invisible
A55: 51 | B55: Special Terms | C55: Apttus_Proposal__Special_Terms__c | D55: Text Area | E55: 255 | F55: Custom | L55: The special terms associated with the quote/proposal | N55: =VLOOKUP(B55,'Sheet 1'!$B$2:$C$108,2,FALSE) -> #N/A | O55: Editable | P55: Invisible | Q55: Invisible | R55: Editable | S55: Invisible | T55: Invisible | U55: Editable | V55: Editable | W55: Editable | X55: Editable | Y55: Editable | Z55: Editable | AA55: Editable | AB55: Editable | AC55: Invisible | AD55: Invisible | AE55: Editable | AF55: Invisible | AG55: Editable | AH55: Editable | AI55: Invisible
A56: 52 | B56: Strategic Importance | C56: Apttus_Proposal__Strategic_Importance__c | D56: Picklist | F56: Custom | H56: Not Strategic;Medium;High;Must Win | L56: The strategic importance of the quote/proposal | N56: =VLOOKUP(B56,'Sheet 1'!$B$2:$C$108,2,FALSE) -> #N/A | O56: Editable | P56: Invisible | Q56: Invisible | R56: Editable | S56: Invisible | T56: Invisible | U56: Editable | V56: Editable | W56: Editable | X56: Editable | Y56: Editable | Z56: Editable | AA56: Editable | AB56: Editable | AC56: Invisible | AD56: Invisible | AE56: Editable | AF56: Invisible | AG56: Editable | AH56: Editable | AI56: Invisible
A57: 53 | B57: Submit For Approval | C57: Apttus_Proposal__SubmitForApproval__c | D57: Formula (Text) | E57: 1300 | F57: Custom | I57: IF (ISPICKVAL(Apttus_Proposal__Approval_Stage__c, "Approval Required"), HYPERLINK("/apex/Apttus_Proposal__ProposalSubmit?id="&Id, IMAGE("/resource/Apttus_Proposal__Button_SubmitForApproval", "Submit for Approval"),"_self"), NULL) | L57: Submit the quote/proposal for approval | N57: =VLOOKUP(B57,'Sheet 1'!$B$2:$C$108,2,FALSE) -> #N/A | O57: Read-Only | P57: Invisible | Q57: Invisible | R57: Editable | S57: Invisible | T57: Invisible | U57: Read-Only | V57: Editable | W57: Read-Only | X57: Read-Only | Y57: Editable | Z57: Editable | AA57: Editable | AB57: Editable | AC57: Invisible | AD57: Invisible | AE57: Editable | AF57: Invisible | AG57: Editable | AH57: Editable | AI57: Invisible
A58: 54 | B58: Valid Until Date | C58: Apttus_Proposal__Valid_Until_Date__c | D58: Date | F58: Custom | L58: The date until the quote/proposal is valid | N58: =VLOOKUP(B58,'Sheet 1'!$B$2:$C$108,2,FALSE) -> V2 | O58: Editable | P58: Invisible | Q58: Invisible | R58: Editable | S58: Invisible | T58: Invisible | U58: Editable | V58: Editable | W58: Editable | X58: Editable | Y58: Editable | Z58: Editable | AA58: Editable | AB58: Editable | AC58: Invisible | AD58: Invisible | AE58: Editable | AF58: Invisible | AG58: Editable | AH58: Editable | AI58: Invisible
A59: 55 | B59: Amount | C59: Apttus_Proposal__Amount__c | D59: Roll-Up Summary | F59: Custom | N59: =VLOOKUP(B59,'Sheet 1'!$B$2:$C$108,2,FALSE) -> #N/A | O59: Read-Only | P59: Invisible | Q59: Invisible | R59: Editable | S59: Invisible | T59: Invisible | U59: Read-Only | V59: Editable | W59: Read-Only | X59: Read-Only | Y59: Editable | Z59: Editable | AA59: Editable | AB59: Editable | AC59: Invisible | AD59: Invisible | AE59: Editable | AF59: Invisible | AG59: Editable | AH59: Editable | AI59: Invisible
A60: 56 | B60: ABO Type | C60: Apttus_QPConfig__ABOType__c | D60: Picklist | F60: Custom | H60: New;Add-on;Renewal | L60: The asset based order type | M60: The asset based order type | N60: =VLOOKUP(B60,'Sheet 1'!$B$2:$C$108,2,FALSE) -> #N/A | O60: Editable | P60: Invisible | Q60: Invisible | R60: Editable | S60: Invisible | T60: Invisible | U60: Editable | V60: Editable | W60: Editable | X60: Editable | Y60: Editable | Z60: Editable | AA60: Editable | AB60: Editable | AC60: Invisible | AD60: Invisible | AE60: Editable | AF60: Invisible | AG60: Editable | AH60: Editable | AI60: Invisible
A61: 57 | B61: Accept | C61: Apttus_QPConfig__Accept__c | D61: Formula (Text) | E61: 1300 | F61: Custom | I61: IF (ISPICKVAL(Apttus_Proposal__Approval_Stage__c, "Presented"), HYPERLINK("/apex/Apttus_QPConfig__ProposalAccept?id="&Id, IMAGE("/resource/Apttus_QPConfig__Button_Accept", "Accept"),"_self"), NULL) | L61: Accept the quote/proposal | N61: =VLOOKUP(B61,'Sheet 1'!$B$2:$C$108,2,FALSE) -> #N/A | O61: Read-Only | P61: Invisible | Q61: Invisible | R61: Editable | S61: Invisible | T61: Invisible | U61: Read-Only | V61: Editable | W61: Read-Only | X61: Read-Only | Y61: Editable | Z61: Editable | AA61: Editable | AB61: Editable | AC61: Invisible | AD61: Invisible | AE61: Editable | AF61: Invisible | AG61: Editable | AH61: Editable | AI61: Invisible
A62: 58 | B62: Auto Activate Order ? | C62: Apttus_QPConfig__AutoActivateOrder__c | D62: Checkbox | F62: Custom | L62: Indicates whether the order associated with the quote/proposal will be automatically activated when the quote/proposal is accepted. | M62: Indicates whether the order associated with the quote/proposal will be automatically activated when the quote/proposal is accepted. | N62: =VLOOKUP(B62,'Sheet 1'!$B$2:$C$108,2,FALSE) -> #N/A | O62: Editable | P62: Invisible | Q62: Invisible | R62: Editable | S62: Invisible | T62: Invisible | U62: Editable | V62: Editable | W62: Editable | X62: Editable | Y62: Editable | Z62: Editable | AA62: Editable | AB62: Editable | AC62: Invisible | AD62: Invisible | AE62: Editable | AF62: Invisible | AG62: Editable | AH62: Editable | AI62: Invisible
A63: 59 | B63: Auto Create Bill ? | C63: Apttus_QPConfig__AutoCreateBill__c | D63: Checkbox | F63: Custom | L63: Indicates whether billing schedules would be created for the order associated with the quote/proposal when the quote/proposal is accepted. | M63: Indicates whether billing schedules would be created for the order associated with the quote/proposal when the quote/proposal is accepted. | N63: =VLOOKUP(B63,'Sheet 1'!$B$2:$C$108,2,FALSE) -> #N/A | O63: Editable | P63: Invisible | Q63: Invisible | R63: Editable | S63: Invisible | T63: Invisible | U63: Editable | V63: Editable | W63: Editable | X63: Editable | Y63: Editable | Z63: Editable | AA63: Editable | AB63: Editable | AC63: Invisible | AD63: Invisible | AE63: Editable | AF63: Invisible | AG63: Editable | AH63: Editable | AI63: Invisible
A64: 60 | B64: Auto Create Revenue ? | C64: Apttus_QPConfig__AutoCreateRevenue__c | D64: Checkbox | F64: Custom | L64: Indicates whether revenue schedules would be created for the order associated with the quote/proposal when the quote/proposal is accepted. | M64: Indicates whether revenue schedules would be created for the order associated with the quote/proposal when the quote/proposal is accepted. | N64: =VLOOKUP(B64,'Sheet 1'!$B$2:$C$108,2,FALSE) -> #N/A | O64: Editable | P64: Invisible | Q64: Invisible | R64: Editable | S64: Invisible | T64: Invisible | U64: Editable | V64: Editable | W64: Editable | X64: Editable | Y64: Editable | Z64: Editable | AA64: Editable | AB64: Editable | AC64: Invisible | AD64: Invisible | AE64: Editable | AF64: Invisible | AG64: Editable | AH64: Editable | AI64: Invisible
A65: 61 | B65: Bill To | C65: Apttus_QPConfig__BillToAccountId__c | D65: Lookup (Account) | F65: Custom | K65: ✓ | L65: ID of the bill to account associated with the quote/proposal | M65: For a Direct Deal, Account (End Customer) is the Bill To whereas for an Indirect Deal, Partner Account is the Bill To. | N65: =VLOOKUP(B65,'Sheet 1'!$B$2:$C$108,2,FALSE) -> V2 | O65: Editable | P65: Invisible | Q65: Invisible | R65: Editable | S65: Invisible | T65: Invisible | U65: Editable | V65: Editable | W65: Editable | X65: Editable | Y65: Editable | Z65: Editable | AA65: Editable | AB65: Editable | AC65: Invisible | AD65: Invisible | AE65: Editable | AF65: Invisible | AG65: Editable | AH65: Editable | AI65: Invisible
A66: 62 | B66: Billing Preference | C66: Apttus_QPConfig__BillingPreferenceId__c | D66: Lookup (Billing Preference) | F66: Custom | L66: ID of the associated billing preference | M66: ID of the associated billing preference | N66: =VLOOKUP(B66,'Sheet 1'!$B$2:$C$108,2,FALSE) -> #N/A | O66: Editable | P66: Invisible | Q66: Invisible | R66: Editable | S66: Invisible | T66: Invisible | U66: Editable | V66: Editable | W66: Editable | X66: Editable | Y66: Editable | Z66: Editable | AA66: Editable | AB66: Editable | AC66: Invisible | AD66: Invisible | AE66: Editable | AF66: Invisible | AG66: Editable | AH66: Editable | AI66: Invisible
A67: 63 | B67: Configuration Finalized Date | C67: Apttus_QPConfig__ConfigurationFinalizedDate__c | D67: Date/Time | F67: Custom | L67: Date when the configuration was finalized for the quote/proposal | N67: =VLOOKUP(B67,'Sheet 1'!$B$2:$C$108,2,FALSE) -> V2 | O67: Editable | P67: Invisible | Q67: Invisible | R67: Editable | S67: Invisible | T67: Invisible | U67: Editable | V67: Editable | W67: Editable | X67: Editable | Y67: Editable | Z67: Editable | AA67: Editable | AB67: Editable | AC67: Invisible | AD67: Invisible | AE67: Editable | AF67: Invisible | AG67: Editable | AH67: Editable | AI67: Invisible
A68: 64 | B68: Configuration Sync Date | C68: Apttus_QPConfig__ConfigurationSyncDate__c | D68: Date/Time | F68: Custom | L68: Date when the configuration was synchronized for the quote/proposal | M68: Date when the configuration was synchronized for the quote/proposal | N68: =VLOOKUP(B68,'Sheet 1'!$B$2:$C$108,2,FALSE) -> #N/A | O68: Editable | P68: Invisible | Q68: Invisible | R68: Editable | S68: Invisible | T68: Invisible | U68: Editable | V68: Editable | W68: Editable | X68: Editable | Y68: Editable | Z68: Editable | AA68: Editable | AB68: Editable | AC68: Invisible | AD68: Invisible | AE68: Editable | AF68: Invisible | AG68: Editable | AH68: Editable | AI68: Invisible
A69: 65 | B69: Configure Products (NG) | C69: Apttus_QPConfig__ConfigureNG__c | D69: Formula (Text) | E69: 1300 | F69: Custom | I69: IF ( LEN( Apttus_QPConfig__PriceListId__c ) > 0 , HYPERLINK("/apex/Apttus_QPConfig__ProposalConfiguration?id=" &Id & "&flow=NGDefault", IMAGE("/resource/Apttus_QPConfig__Button_Configure", "Configure Products"),"_self"), NULL) | L69: Configure products for the quote/proposal | N69: =VLOOKUP(B69,'Sheet 1'!$B$2:$C$108,2,FALSE) -> #N/A | O69: Read-Only | P69: Invisible | Q69: Invisible | R69: Editable | S69: Invisible | T69: Invisible | U69: Read-Only | V69: Editable | W69: Read-Only | X69: Read-Only | Y69: Editable | Z69: Editable | AA69: Editable | AB69: Editable | AC69: Invisible | AD69: Invisible | AE69: Editable | AF69: Invisible | AG69: Editable | AH69: Editable | AI69: Invisible
A70: 66 | B70: Configure Products | C70: Apttus_QPConfig__Configure__c | D70: Formula (Text) | E70: 1300 | F70: Custom | I70: IF ( LEN( Apttus_QPConfig__PriceListId__c ) > 0 , HYPERLINK("/apex/Apttus_QPConfig__ProposalConfiguration?id=" &Id & "&flow=Default", IMAGE("/resource/Apttus_QPConfig__Button_Configure", "Configure Products"),"_self"), NULL) | L70: Configure products for the quote/proposal | N70: =VLOOKUP(B70,'Sheet 1'!$B$2:$C$108,2,FALSE) -> #N/A | O70: Read-Only | P70: Invisible | Q70: Invisible | R70: Editable | S70: Invisible | T70: Invisible | U70: Read-Only | V70: Editable | W70: Read-Only | X70: Read-Only | Y70: Editable | Z70: Editable | AA70: Editable | AB70: Editable | AC70: Invisible | AD70: Invisible | AE70: Editable | AF70: Invisible | AG70: Editable | AH70: Editable | AI70: Invisible
A71: 67 | B71: Intent | C71: Apttus_QPConfig__Intent__c | D71: Picklist | F71: Custom | H71: Order;Price Agreement;Contract | L71: The intent associated with the quote/proposal | M71: The intent associated with the quote/proposal | N71: =VLOOKUP(B71,'Sheet 1'!$B$2:$C$108,2,FALSE) -> #N/A | O71: Editable | P71: Invisible | Q71: Invisible | R71: Editable | S71: Invisible | T71: Invisible | U71: Editable | V71: Editable | W71: Editable | X71: Editable | Y71: Editable | Z71: Editable | AA71: Editable | AB71: Editable | AC71: Invisible | AD71: Invisible | AE71: Editable | AF71: Invisible | AG71: Editable | AH71: Editable | AI71: Invisible
A72: 68 | B72: Is Auto Accepted | C72: Apttus_QPConfig__IsAutoAccepted__c | D72: Checkbox | F72: Custom | L72: Indicates whether the quote/proposal was accepted by an auto system operation | M72: Indicates whether the quote/proposal was accepted by an auto system operation | N72: =VLOOKUP(B72,'Sheet 1'!$B$2:$C$108,2,FALSE) -> #N/A | O72: Editable | P72: Invisible | Q72: Invisible | R72: Editable | S72: Invisible | T72: Invisible | U72: Editable | V72: Editable | W72: Editable | X72: Editable | Y72: Editable | Z72: Editable | AA72: Editable | AB72: Editable | AC72: Invisible | AD72: Invisible | AE72: Editable | AF72: Invisible | AG72: Editable | AH72: Editable | AI72: Invisible
A73: 69 | B73: Is System Generated | C73: Apttus_QPConfig__IsSystemGenerated__c | D73: Checkbox | F73: Custom | L73: Indicates whether this is a system generated quote | M73: Indicates whether this is a system generated quote | N73: =VLOOKUP(B73,'Sheet 1'!$B$2:$C$108,2,FALSE) -> #N/A | O73: Editable | P73: Invisible | Q73: Invisible | R73: Editable | S73: Invisible | T73: Invisible | U73: Editable | V73: Editable | W73: Editable | X73: Editable | Y73: Editable | Z73: Editable | AA73: Editable | AB73: Editable | AC73: Invisible | AD73: Invisible | AE73: Editable | AF73: Invisible | AG73: Editable | AH73: Editable | AI73: Invisible
A74: 70 | B74: Is Task Pending | C74: Apttus_QPConfig__IsTaskPending__c | D74: Checkbox | F74: Custom | L74: Indicates whether there are any tasks pending for the quote | M74: Indicates whether there are any tasks pending for the quote | N74: =VLOOKUP(B74,'Sheet 1'!$B$2:$C$108,2,FALSE) -> #N/A | O74: Editable | P74: Invisible | Q74: Invisible | R74: Editable | S74: Invisible | T74: Invisible | U74: Editable | V74: Editable | W74: Editable | X74: Editable | Y74: Editable | Z74: Editable | AA74: Editable | AB74: Editable | AC74: Invisible | AD74: Invisible | AE74: Editable | AF74: Invisible | AG74: Editable | AH74: Editable | AI74: Invisible
A75: 71 | B75: Legal Entity | C75: Apttus_QPConfig__LegalEntityId__c | D75: Lookup (Legal Entity) | F75: Custom | L75: ID of the legal entity associated with the quote/proposal. This links the asset to a legal entity and will be used for downstream billing and revenue functions. | M75: ID of the legal entity associated with the quote/proposal. This links the asset to a legal entity and will be used for downstream billing and revenue functions. | N75: =VLOOKUP(B75,'Sheet 1'!$B$2:$C$108,2,FALSE) -> #N/A | O75: Editable | P75: Invisible | Q75: Invisible | R75: Editable | S75: Invisible | T75: Invisible | U75: Editable | V75: Editable | W75: Editable | X75: Editable | Y75: Editable | Z75: Editable | AA75: Editable | AB75: Editable | AC75: Invisible | AD75: Invisible | AE75: Editable | AF75: Invisible | AG75: Editable | AH75: Editable | AI75: Invisible
A76: 72 | B76: Location | C76: Apttus_QPConfig__LocationId__c | D76: Lookup (Account Location) | F76: Custom | L76: ID of the associated account location | M76: ID of the associated account location | N76: =VLOOKUP(B76,'Sheet 1'!$B$2:$C$108,2,FALSE) -> #N/A | O76: Editable | P76: Invisible | Q76: Invisible | R76: Editable | S76: Invisible | T76: Invisible | U76: Editable | V76: Editable | W76: Editable | X76: Editable | Y76: Editable | Z76: Editable | AA76: Editable | AB76: Editable | AC76: Invisible | AD76: Invisible | AE76: Editable | AF76: Invisible | AG76: Editable | AH76: Editable | AI76: Invisible
A77: 73 | B77: PO Date | C77: Apttus_QPConfig__PODate__c | D77: Date | F77: Custom | L77: The purchase order date | M77: The purchase order date | N77: =VLOOKUP(B77,'Sheet 1'!$B$2:$C$108,2,FALSE) -> #N/A | O77: Editable | P77: Invisible | Q77: Invisible | R77: Editable | S77: Invisible | T77: Invisible | U77: Editable | V77: Editable | W77: Editable | X77: Editable | Y77: Editable | Z77: Editable | AA77: Editable | AB77: Editable | AC77: Invisible | AD77: Invisible | AE77: Editable | AF77: Invisible | AG77: Editable | AH77: Editable | AI77: Invisible
A78: 74 | B78: PO Number | C78: Apttus_QPConfig__PONumber__c | D78: Text | E78: 255 | F78: Custom | L78: The purchase order number | M78: The purchase order number | N78: =VLOOKUP(B78,'Sheet 1'!$B$2:$C$108,2,FALSE) -> #N/A | O78: Editable | P78: Invisible | Q78: Invisible | R78: Editable | S78: Invisible | T78: Invisible | U78: Editable | V78: Editable | W78: Editable | X78: Editable | Y78: Editable | Z78: Editable | AA78: Editable | AB78: Editable | AC78: Invisible | AD78: Invisible | AE78: Editable | AF78: Invisible | AG78: Editable | AH78: Editable | AI78: Invisible
A79: 75 | B79: Parent Quote/Proposal | C79: Apttus_QPConfig__ParentProposalId__c | D79: Lookup (Quote/Proposal) | F79: Custom | L79: ID of the parent quote/proposal | M79: ID of the parent quote/proposal | N79: =VLOOKUP(B79,'Sheet 1'!$B$2:$C$108,2,FALSE) -> #N/A | O79: Editable | P79: Invisible | Q79: Invisible | R79: Editable | S79: Invisible | T79: Invisible | U79: Editable | V79: Editable | W79: Editable | X79: Editable | Y79: Editable | Z79: Editable | AA79: Editable | AB79: Editable | AC79: Invisible | AD79: Invisible | AE79: Editable | AF79: Invisible | AG79: Editable | AH79: Editable | AI79: Invisible
A80: 76 | B80: Payment Term | C80: Apttus_QPConfig__PaymentTermId__c | D80: Lookup (Payment Term) | F80: Custom | L80: ID of the payment term associated with the quote/proposal | M80: Payment term associated with this quote/proposal | N80: =VLOOKUP(B80,'Sheet 1'!$B$2:$C$108,2,FALSE) -> V2 | O80: Editable | P80: Invisible | Q80: Invisible | R80: Editable | S80: Invisible | T80: Invisible | U80: Editable | V80: Editable | W80: Editable | X80: Editable | Y80: Editable | Z80: Editable | AA80: Editable | AB80: Editable | AC80: Invisible | AD80: Invisible | AE80: Editable | AF80: Invisible | AG80: Editable | AH80: Editable | AI80: Invisible
A81: 77 | B81: Price List | C81: Apttus_QPConfig__PriceListId__c | D81: Lookup (Price List) | F81: Custom | L81: ID of the associated price list | N81: =VLOOKUP(B81,'Sheet 1'!$B$2:$C$108,2,FALSE) -> V2 | O81: Read-Only | P81: Invisible | Q81: Read-Only | R81: Read-Only | S81: Read-Only | T81: Read-Only | U81: Read-Only | V81: Read-Only | W81: Read-Only | X81: Read-Only | Y81: Read-Only | Z81: Read-Only | AA81: Read-Only | AB81: Read-Only | AC81: Invisible | AD81: Invisible | AE81: Read-Only | AF81: Invisible | AG81: Read-Only | AH81: Read-Only | AI81: Read-Only
A82: 78 | B82: Pricing Date | C82: Apttus_QPConfig__PricingDate__c | D82: Date/Time | F82: Custom | L82: The pricing date, The product list price is determined based on this date. | N82: =VLOOKUP(B82,'Sheet 1'!$B$2:$C$108,2,FALSE) -> #N/A | O82: Editable | P82: Invisible | Q82: Invisible | R82: Editable | S82: Invisible | T82: Invisible | U82: Editable | V82: Editable | W82: Editable | X82: Editable | Y82: Editable | Z82: Editable | AA82: Editable | AB82: Editable | AC82: Invisible | AD82: Invisible | AE82: Editable | AF82: Invisible | AG82: Editable | AH82: Editable | AI82: Invisible
A83: 79 | B83: Purchase Identifier | C83: Apttus_QPConfig__PurchaseId__c | D83: Text | E83: 255 | F83: Custom | L83: The default purchase identifier associated with the quote/proposal | M83: The default purchase identifier associated with the quote/proposal | N83: =VLOOKUP(B83,'Sheet 1'!$B$2:$C$108,2,FALSE) -> #N/A | O83: Editable | P83: Invisible | Q83: Invisible | R83: Editable | S83: Invisible | T83: Invisible | U83: Editable | V83: Editable | W83: Editable | X83: Editable | Y83: Editable | Z83: Editable | AA83: Editable | AB83: Editable | AC83: Invisible | AD83: Invisible | AE83: Editable | AF83: Invisible | AG83: Editable | AH83: Editable | AI83: Invisible
A84: 80 | B84: QTC Profile | C84: Apttus_QPConfig__QTCProfile__c | D84: Picklist | F84: Custom | H84: Regular;Split | L84: The QTC profile associated with the quote/proposal | M84: “Regular” will process the quote as a single entity. Select “Split” before clicking on Configure Products to allow the subdivision of the quote into multiple smaller quotes for business/volume related reasons or multiple sold to accounts. | N84: =VLOOKUP(B84,'Sheet 1'!$B$2:$C$108,2,FALSE) -> #N/A | O84: Editable | P84: Invisible | Q84: Invisible | R84: Editable | S84: Invisible | T84: Invisible | U84: Editable | V84: Editable | W84: Editable | X84: Editable | Y84: Editable | Z84: Editable | AA84: Editable | AB84: Editable | AC84: Invisible | AD84: Invisible | AE84: Editable | AF84: Invisible | AG84: Editable | AH84: Editable | AI84: Invisible
A85: 81 | B85: Ready For Activation Date | C85: Apttus_QPConfig__ReadyForActivationDate__c | D85: Date/Time | F85: Custom | L85: The date the order is ready for activation. The order is activated on this date. | M85: The date the order is ready for activation. The order is activated on this date. | N85: =VLOOKUP(B85,'Sheet 1'!$B$2:$C$108,2,FALSE) -> #N/A | O85: Editable | P85: Invisible | Q85: Invisible | R85: Editable | S85: Invisible | T85: Invisible | U85: Editable | V85: Editable | W85: Editable | X85: Editable | Y85: Editable | Z85: Editable | AA85: Editable | AB85: Editable | AC85: Invisible | AD85: Invisible | AE85: Editable | AF85: Invisible | AG85: Editable | AH85: Editable | AI85: Invisible
A86: 82 | B86: Ready For Billing Date | C86: Apttus_QPConfig__ReadyForBillingDate__c | D86: Date/Time | F86: Custom | L86: The date when the order is ready for billing. The billing schedules are created on this date. | M86: The date when the order is ready for billing. The billing schedules are created on this date. | N86: =VLOOKUP(B86,'Sheet 1'!$B$2:$C$108,2,FALSE) -> #N/A | O86: Editable | P86: Invisible | Q86: Invisible | R86: Editable | S86: Invisible | T86: Invisible | U86: Editable | V86: Editable | W86: Editable | X86: Editable | Y86: Editable | Z86: Editable | AA86: Editable | AB86: Editable | AC86: Invisible | AD86: Invisible | AE86: Editable | AF86: Invisible | AG86: Editable | AH86: Editable | AI86: Invisible
A87: 83 | B87: Ready For Fulfillment Date | C87: Apttus_QPConfig__ReadyForFulfillmentDate__c | D87: Date/Time | F87: Custom | L87: The date the order is ready for fulfillment. The order is fulfilled on this date. | M87: The date the order is ready for fulfillment. The order is fulfilled on this date. | N87: =VLOOKUP(B87,'Sheet 1'!$B$2:$C$108,2,FALSE) -> #N/A | O87: Editable | P87: Invisible | Q87: Invisible | R87: Editable | S87: Invisible | T87: Invisible | U87: Editable | V87: Editable | W87: Editable | X87: Editable | Y87: Editable | Z87: Editable | AA87: Editable | AB87: Editable | AC87: Invisible | AD87: Invisible | AE87: Editable | AF87: Invisible | AG87: Editable | AH87: Editable | AI87: Invisible
A88: 84 | B88: Ready For Revenue Recognition Date | C88: Apttus_QPConfig__ReadyForRevRecDate__c | D88: Date/Time | F88: Custom | L88: The date when the order is ready for revenue recognition. The revenue schedules are created on this date. | M88: The date when the order is ready for revenue recognition. The revenue schedules are created on this date. | N88: =VLOOKUP(B88,'Sheet 1'!$B$2:$C$108,2,FALSE) -> #N/A | O88: Editable | P88: Invisible | Q88: Invisible | R88: Editable | S88: Invisible | T88: Invisible | U88: Editable | V88: Editable | W88: Editable | X88: Editable | Y88: Editable | Z88: Editable | AA88: Editable | AB88: Editable | AC88: Invisible | AD88: Invisible | AE88: Editable | AF88: Invisible | AG88: Editable | AH88: Editable | AI88: Invisible
A89: 85 | B89: Ship To | C89: Apttus_QPConfig__ShipToAccountId__c | D89: Lookup (Account) | F89: Custom | L89: ID of the ship to account associated with the quote/proposal | M89: ID of the ship to account associated with the quote/proposal | N89: =VLOOKUP(B89,'Sheet 1'!$B$2:$C$108,2,FALSE) -> #N/A | O89: Editable | P89: Invisible | Q89: Invisible | R89: Editable | S89: Invisible | T89: Invisible | U89: Editable | V89: Editable | W89: Editable | X89: Editable | Y89: Editable | Z89: Editable | AA89: Editable | AB89: Editable | AC89: Invisible | AD89: Invisible | AE89: Editable | AF89: Invisible | AG89: Editable | AH89: Editable | AI89: Invisible
A90: 86 | B90: Sync Asset Changes To Quote | C90: Apttus_QPConfig__SyncAssetChangesToQuote__c | D90: Checkbox | F90: Custom | L90: Indicates whether asset changes are synchronized to open quotes | M90: Indicates whether asset changes are synchronized to open quotes | N90: =VLOOKUP(B90,'Sheet 1'!$B$2:$C$108,2,FALSE) -> #N/A | O90: Editable | P90: Invisible | Q90: Invisible | R90: Editable | S90: Invisible | T90: Invisible | U90: Editable | V90: Editable | W90: Editable | X90: Editable | Y90: Editable | Z90: Editable | AA90: Editable | AB90: Editable | AC90: Invisible | AD90: Invisible | AE90: Editable | AF90: Invisible | AG90: Editable | AH90: Editable | AI90: Invisible
A91: 87 | B91: Synchronize with Opportunity | C91: Apttus_QPConfig__SyncWithOpportunity__c | D91: Formula (Text) | E91: 1300 | F91: Custom | I91: IF ( AND(LEN(Apttus_Proposal__Opportunity__c ) > 0, Apttus_Proposal__Primary__c) , HYPERLINK("/apex/Apttus_QPConfig__ProposalSyncWithOpportunity?id=" &Id, IMAGE("/resource/Apttus_QPConfig__Button_SynchronizeWithOpportunity", "Sync with Opportunity"),"_self"), NULL) | L91: Synchronize the quote/proposal with the associated opportunity | N91: =VLOOKUP(B91,'Sheet 1'!$B$2:$C$108,2,FALSE) -> #N/A | O91: Read-Only | P91: Invisible | Q91: Invisible | R91: Editable | S91: Invisible | T91: Invisible | U91: Read-Only | V91: Editable | W91: Read-Only | X91: Read-Only | Y91: Editable | Z91: Editable | AA91: Editable | AB91: Editable | AC91: Invisible | AD91: Invisible | AE91: Editable | AF91: Invisible | AG91: Editable | AH91: Editable | AI91: Invisible
A92: 88 | B92: Configure Products | C92: Apttus_QPAsset__ConfigureWithAssets__c | D92: Formula (Text) | E92: 1300 | F92: Custom | I92: IF ( LEN( Apttus_QPConfig__PriceListId__c ) > 0 , HYPERLINK("/apex/Apttus_QPAsset__ProposalConfiguration?id=" &Id, IMAGE("/resource/Apttus_QPConfig__Button_Configure", "Configure Products"),"_self"), NULL) | L92: Configure products (with assets) for the quote/proposal | M92: Configure products (with assets) for the quote/proposal | N92: =VLOOKUP(B92,'Sheet 1'!$B$2:$C$108,2,FALSE) -> #N/A | O92: Read-Only | P92: Invisible | Q92: Invisible | R92: Editable | S92: Invisible | T92: Invisible | U92: Read-Only | V92: Editable | W92: Read-Only | X92: Read-Only | Y92: Editable | Z92: Editable | AA92: Editable | AB92: Editable | AC92: Invisible | AD92: Invisible | AE92: Editable | AF92: Invisible | AG92: Editable | AH92: Editable | AI92: Invisible
A93: 89 | B93: Approval Status | C93: Apttus_QPApprov__Approval_Status__c | D93: Picklist | F93: Custom | H93: None;Approval Required;Not Submitted;Pending Approval;Approved;Rejected;Cancelled | K93: ✓ | L93: The quote approval status | N93: =VLOOKUP(B93,'Sheet 1'!$B$2:$C$108,2,FALSE) -> #N/A | O93: Editable | P93: Invisible | Q93: Invisible | R93: Editable | S93: Invisible | T93: Invisible | U93: Editable | V93: Editable | W93: Editable | X93: Editable | Y93: Editable | Z93: Editable | AA93: Editable | AB93: Editable | AC93: Invisible | AD93: Invisible | AE93: Editable | AF93: Invisible | AG93: Editable | AH93: Editable | AI93: Invisible
A94: 90 | B94: Create Agreement With Line Items | C94: Apttus_QPComply__CreateAgreementWithLineItems__c | D94: Formula (Text) | E94: 1300 | F94: Custom | I94: IF (ISPICKVAL(Apttus_Proposal__Approval_Stage__c, "Accepted") , HYPERLINK("/apex/Apttus_QPComply__ProposalAgreementCreate?id=" &Id, IMAGE("/resource/Apttus_QPComply__Button_CreateAgreementWithLineItems", "Create Agreement with Line Items"),"_self"), NULL) | L94: Create Agreement with line items, if the proposal is accepted. | N94: =VLOOKUP(B94,'Sheet 1'!$B$2:$C$108,2,FALSE) -> #N/A | O94: Read-Only | P94: Invisible | Q94: Invisible | R94: Editable | S94: Invisible | T94: Invisible | U94: Read-Only | V94: Editable | W94: Read-Only | X94: Read-Only | Y94: Editable | Z94: Editable | AA94: Editable | AB94: Editable | AC94: Invisible | AD94: Invisible | AE94: Editable | AF94: Invisible | AG94: Editable | AH94: Editable | AI94: Invisible
A95: 91 | B95: Master Agreement | C95: Apttus_QPComply__MasterAgreementId__c | D95: Lookup (Agreement) | F95: Custom | L95: ID of the master agreement associated with the quote/proposal | M95: ID of the master agreement associated with the quote/proposal | N95: =VLOOKUP(B95,'Sheet 1'!$B$2:$C$108,2,FALSE) -> #N/A | O95: Editable | P95: Invisible | Q95: Invisible | R95: Editable | S95: Invisible | T95: Invisible | U95: Editable | V95: Editable | W95: Editable | X95: Editable | Y95: Editable | Z95: Editable | AA95: Editable | AB95: Editable | AC95: Invisible | AD95: Invisible | AE95: Editable | AF95: Invisible | AG95: Editable | AH95: Editable | AI95: Invisible
A96: 92 | B96: Check eSignature Status | C96: Apttus_QPDSign__CheckESignatureStatus__c | D96: Formula (Text) | E96: 1300 | F96: Custom | I96: IF( ISPICKVAL(Apttus_Proposal__Approval_Stage__c,"Presented"), HYPERLINK("/apex/Apttus_DocuApi__DocuSignEnvStatusByEnvId?envelopeparentid="&Id, IMAGE("/resource/Apttus_DocuApi__CheckStatus","Check eSignature Status"), "_self"), NULL) | L96: Sales Rep checks the eSignature status for a given Quote when Recipients have not yet finished signing | M96: Sales Rep checks the eSignature status for a given Quote when Recipients have not yet finished signing | N96: =VLOOKUP(B96,'Sheet 1'!$B$2:$C$108,2,FALSE) -> #N/A | O96: Read-Only | P96: Invisible | Q96: Invisible | R96: Editable | S96: Invisible | T96: Invisible | U96: Read-Only | V96: Editable | W96: Read-Only | X96: Read-Only | Y96: Editable | Z96: Editable | AA96: Editable | AB96: Editable | AC96: Invisible | AD96: Invisible | AE96: Editable | AF96: Invisible | AG96: Editable | AH96: Editable | AI96: Invisible
A97: 93 | B97: Recall E-Signature Request | C97: Apttus_QPDSign__RecallESignatureRequest__c | D97: Formula (Text) | E97: 1300 | F97: Custom | I97: IF( ISPICKVAL(Apttus_Proposal__Approval_Stage__c,"Presented"), HYPERLINK("/apex/Apttus_DocuApi__DocuSignRecallEnvByEnvId?envelopeparentid="&Id, IMAGE("/resource/Apttus_DocuApi__RecallEnvelope","Recall E-Signature Request"), "_self"), NULL ) | L97: Recall E-Signature request | M97: Recall E-Signature request | N97: =VLOOKUP(B97,'Sheet 1'!$B$2:$C$108,2,FALSE) -> #N/A | O97: Read-Only | P97: Invisible | Q97: Invisible | R97: Editable | S97: Invisible | T97: Invisible | U97: Read-Only | V97: Editable | W97: Read-Only | X97: Read-Only | Y97: Editable | Z97: Editable | AA97: Editable | AB97: Editable | AC97: Invisible | AD97: Invisible | AE97: Editable | AF97: Invisible | AG97: Editable | AH97: Editable | AI97: Invisible
A98: 94 | B98: Send For eSignature | C98: Apttus_QPDSign__SendForESignature__c | D98: Formula (Text) | E98: 1300 | F98: Custom | I98: IF( ISPICKVAL(Apttus_Proposal__Approval_Stage__c,"Generated"), HYPERLINK("/apex/Apttus_QPDSign__QPDocuSignCreateEnvelope?id="&Id, IMAGE("/resource/Apttus_DocuApi__eSignature","Send For eSignatures"), "_self"), NULL ) | L98: Sales Rep sends proposal document with DocuSign eSignature Tag for primary contact | M98: Sales Rep sends proposal document with DocuSign eSignature Tag for primary contact | N98: =VLOOKUP(B98,'Sheet 1'!$B$2:$C$108,2,FALSE) -> #N/A | O98: Read-Only | P98: Invisible | Q98: Invisible | R98: Editable | S98: Invisible | T98: Invisible | U98: Read-Only | V98: Editable | W98: Read-Only | X98: Read-Only | Y98: Editable | Z98: Editable | AA98: Editable | AB98: Editable | AC98: Invisible | AD98: Invisible | AE98: Editable | AF98: Invisible | AG98: Editable | AH98: Editable | AI98: Invisible
A99: 95 | B99: Correct E-Signature Document | C99: Apttus_QPDSign__ViewESignatureDocument__c | D99: Formula (Text) | E99: 1300 | F99: Custom | I99: IF( ISPICKVAL(Apttus_Proposal__Approval_Stage__c,"Presented"), HYPERLINK("/apex/Apttus_DocuApi__DocuSignViewExistingEnvelope?envelopeparentid="&Id, IMAGE("/resource/Apttus_DocuApi__ViewEnvelope","Correct E-Signature Document"), "_blank"), NULL) | L99: Correct E-Signature document | M99: Correct E-Signature document | N99: =VLOOKUP(B99,'Sheet 1'!$B$2:$C$108,2,FALSE) -> #N/A | O99: Read-Only | P99: Invisible | Q99: Invisible | R99: Editable | S99: Invisible | T99: Invisible | U99: Read-Only | V99: Editable | W99: Read-Only | X99: Read-Only | Y99: Editable | Z99: Editable | AA99: Editable | AB99: Editable | AC99: Invisible | AD99: Invisible | AE99: Editable | AF99: Invisible | AG99: Editable | AH99: Editable | AI99: Invisible
A100: 96 | B100: Accept Quote | C100: APTS_Accept_Quote__c | D100: Formula (Text) | E100: 1300 | F100: Custom | I100: IF( AND(OR( AND( APTS_Includes_PKI_CPF__c > 0, NOT( ISBLANK( Apttus_Proposal__Account__r.APTS_Legal_Name__c)), ISPICKVAL( Apttus_Proposal__Approval_Stage__c, "Presented") ), AND( APTS_Includes_PKI_CPF__c == 0, ISPICKVAL( Apttus_Proposal__Approval_Stage__c, "Presented") )), NOT( APTS_Account_Credit_Hold__c ) , NOT( Apttus_Proposal__Opportunity__r.APTS_Is_Opportunity_Split_Process_Failed__c && Id = Apttus_Proposal__Opportunity__r.APTS_Synced_Quote_Proposal__c ) ) , IF ($User.Country = "Japan", HYPERLINK("/apex/Apttus_QPConfig__ProposalAccept?id="&Id, IMAGE("/resource/JP_Accept", "承諾する"),"_self"),HYPERLINK("/apex/Apttus_QPConfig__ProposalAccept?id="&Id, IMAGE("/resource/Apttus_QPConfig__Button_Accept", "Accept"),"_self")), NULL) | M100: To enable the button, Stage must be "Presented". If Quote LoB is "PKI (CPF)" then Account Legal Name is also required. | N100: =VLOOKUP(B100,'Sheet 1'!$B$2:$C$108,2,FALSE) -> #N/A | O100: Read-Only | P100: Invisible | Q100: Invisible | R100: Read-Only | S100: Invisible | T100: Invisible | U100: Read-Only | V100: Invisible | W100: Read-Only | X100: Read-Only | Y100: Invisible | Z100: Invisible | AA100: Invisible | AB100: Invisible | AC100: Invisible | AD100: Invisible | AE100: Invisible | AF100: Invisible | AG100: Invisible | AH100: Invisible | AI100: Invisible
...

Sheet RFP Layout
A1: Object | C1: Quote/Proposal | D1: Record Type | E1: RFP
A2: API Name | C2: Apttus_Proposal__Proposal__c | D2: Layout Name | E2: RFP Layout
A4: NO | B4: Label | C4: API Name | D4: Data Type | E4: Position | G4: Readonly | H4: Required | I4: Note
A5: Information (Header visible on edit only)
A6: 1 | B6: Proposal ID | C6: Name | D6: Text | E6: ✓ | G6: Readonly | I6: Required Field
A7: 2 | B7: Owner | C7: OwnerId | D7: Lookup (Group,User) | F7: ✓ | G7: Readonly | I7: Required Field
A8: 3 | B8: Proposal Name | C8: Apttus_Proposal__Proposal_Name__c | D8: Text | E8: ✓ | H8: Required
A9: 4 | B9: Record Type | C9: RecordTypeId | D9: Lookup (Record Type) | F9: ✓ | G9: Readonly
A10: 5 | B10: Opportunity | C10: Apttus_Proposal__Opportunity__c | D10: Lookup (Opportunity) | E10: ✓ | H10: Required
A11: 6 | B11: Account | C11: Apttus_Proposal__Account__c | D11: Lookup (Account) | F11: ✓
A12: 7 | B12: Description | C12: Apttus_Proposal__Description__c | D12: Long Text Area | E12: ✓
A13: 8 | B13: Account Cert Central ID | C13: APTS_CertCentral_Acct_ID__c | D13: Text | F13: ✓ | G13: Readonly
A14: 9 | B14: Special Terms | C14: Apttus_Proposal__Special_Terms__c | D14: Text Area | E14: ✓
A15: 10 | B15: Primary Contact | C15: Apttus_Proposal__Primary_Contact__c | D15: Lookup (Contact) | F15: ✓
A16: 11 | B16: Amount | C16: Apttus_Proposal__Amount__c | D16: Currency | E16: ✓ | G16: Readonly
A17: 12 | B17: Approval Stage | C17: Apttus_Proposal__Approval_Stage__c | D17: Picklist | F17: ✓ | G17: Readonly
A18: 13 | B18: Make Primary | C18: Apttus_Proposal__MakePrimary__c | D18: Text | E18: ✓ | G18: Readonly
A19: 14 | B19: Strategic Importance | C19: Apttus_Proposal__Strategic_Importance__c | D19: Picklist | F19: ✓
A20: 15 | B20: Bulk Purchase Amount | C20: APTS_Bulk_Purchase_Amount__c | D20: Currency | E20: ✓
A21: 16 | B21: Risk Factors | C21: Apttus_Proposal__Risk_Factors__c | D21: Picklist (Multi-Select) | F21: ✓
A22: 17 | B22: Billing Rule Changed | C22: APTS_Billing_Rule_Changed__c | D22: Checkbox | E22: ✓
A23: 18 | B23: Ready To Generate | C23: Apttus_Proposal__ReadyToGenerate__c | D23: Checkbox | F23: ✓
A24: 19 | B24: Quote Primary Contact | C24: APTS_Quote_Primary_Contact__c | D24: Lookup (Contact) | E24: ✓
A25: 20 | B25: Created By | C25: CreatedById | D25: Lookup (User) | F25: ✓ | G25: Readonly | I25: Required Field
A26: 21 | B26: Auto Renew | C26: APTS_Flat_Fee_Auto_Renew__c | D26: Checkbox | E26: ✓
A27: 22 | B27: Last Modified By | C27: LastModifiedById | D27: Lookup (User) | F27: ✓ | G27: Readonly | I27: Required Field
A28: 23 | B28: Additional CA Approval | C28: APTS_Additional_CA_Approval__c | D28: Checkbox | E28: ✓
A29: 24 | B29: DigiCert One ID | C29: DigiCert_One_ID__c | D29: Text | F29: ✓ | G29: Readonly
A30: 25 | B30: Partner Cert Central ID | C30: APTS_CertCentral_Partner_ID__c | D30: Text | E30: ✓ | G30: Readonly
A31: 26 | B31: Territory | C31: APTS_Territory__c | D31: Text | E31: ✓ | G31: Readonly
A32: 27 | B32: Hold-off Invoicing | C32: APTS_Hold_off_Invoicing__c | D32: Checkbox | E32: ✓
A33: 28 | B33: Tax Amount (Japan) | C33: Tax_Amount__c | D33: Number (18, 0) | E33: ✓ | G33: Readonly
A34: 29 | B34: Owner (Jap) | C34: Owner_Jap__c | D34: Text | E34: ✓ | G34: Readonly
A35: 30 | B35: Project MATTER | C35: APTS_Project_MATTER__c | D35: Checkbox | E35: ✓ | G35: Readonly
A36: RFP Dates
A37: 31 | B37: RFP Intake Date | C37: Apttus_Proposal__RFP_Intake_Date__c | D37: Date | E37: ✓
A38: 32 | B38: Internal Deadline | C38: Apttus_Proposal__Internal_Deadline__c | D38: Date | F38: ✓
A39: 33 | B39: RFP Response Due Date | C39: Apttus_Proposal__RFP_Response_Due_Date__c | D39: Date | E39: ✓
A40: 34 | B40: Presented Date | C40: Apttus_Proposal__Presented_Date__c | D40: Date | F40: ✓
A41: 35 | B41: Valid Until Date | C41: Apttus_Proposal__Valid_Until_Date__c | D41: Date | E41: ✓
A42: RFP Actions
A44: Buttons
A46: Edit | Delete | Clone | Change Owner | Change Record Type | Printable View | Sharing | Sharing Hierarchy | Edit Labels
A48: Related Lists
A50: NO | B50: Label | C50: API Name | D50: Data Type | E50: Sort
A51: Line Items (Apttus_Proposal__Proposal_Line_Item__c)
A52: New | Change Owner
A53: 1 | B53: Line Item Id | C53: Name | D53: Auto Number
A54: 2 | B54: Product | C54: Apttus_Proposal__Product__r.Name | D54: Text
A55: 3 | B55: Quantity | C55: Apttus_Proposal__Quantity__c | D55: Number (9, 0)
A56: 4 | B56: Unit Net Price | C56: Apttus_Proposal__Unit_Net_Price__c | D56: Formula (Currency)
A57: 5 | B57: Ext Net Price | C57: Apttus_Proposal__Ext_Net_Price__c | D57: Formula (Currency)
A58: Approval History (ProcessInstanceHistory)
A59: Approve | Reject | Reassign | Recall
A60: 1 | B60: Date | C60: CreatedDate | D60: Date/Time | E60: DESC
A61: 2 | B61: Status | C61: StepStatus | D61: Picklist
A62: 3 | B62: Assigned To | C62: OriginalActor.Name | D62: Text
A63: 4 | B63: Actual Approver | C63: Actor.Name | D63: Text
A64: 5 | B64: Comments | C64: Comments | D64: Text
A65: Open Activities (OpenActivity)
A66: New Task | New Event | New Meeting Request
A67: 1 | B67: Subject | C67: Subject | D67: combobox
A68: 2 | B68: Name | C68: Who.Name | D68: Text
A69: 3 | B69: Task | C69: IsTask | D69: Checkbox
A70: 4 | B70: Due Date | C70: ActivityDate | D70: Date | E70: ASC
A71: 5 | B71: Status | C71: Status | D71: Picklist
A72: 6 | B72: Priority | C72: Priority | D72: Picklist
A73: 7 | B73: Assigned To | C73: Owner.Name | D73: Text
A74: Activity History (ActivityHistory)
A75: Log a Call | Mail Merge | Send an Email | Compose Gmail | Request Update | View All
A76: 1 | B76: Subject | C76: Subject | D76: combobox
A77: 2 | B77: Name | C77: Who.Name | D77: Text
A78: 3 | B78: Task | C78: IsTask | D78: Checkbox
A79: 4 | B79: Due Date | C79: ActivityDate | D79: Date | E79: DESC
A80: 5 | B80: Assigned To | C80: Owner.Name | D80: Text
A81: 6 | B81: Last Modified Date/Time | C81: LastModifiedDate | D81: Date/Time | E81: DESC
A82: Notes & Attachments (CombinedAttachment)
A83: Upload Files
A84: 1 | B84: Title | C84: Title | D84: Text
A85: 2 | B85: Type | C85: RecordType | D85: Text
A86: 3 | B86: Created By | C86: CreatedBy
A87: 4 | B87: Last Modified | C87: LastModifiedDate | D87: Date/Time | E87: DESC
A88: 5 | B88: File Type | C88: FileType | D88: Text
A89: 6 | B89: Size | C89: ContentSize | D89: Integer (0, 0)
A90: 7 | B90: File Extension | C90: FileExtension | D90: Text
A91: 8 | B91: Content URL | C91: ContentUrl | D91: URL
A92: 9 | B92: External Data Source | C92: ExternalDataSourceName | D92: Text
A93: 10 | B93: Type | C93: ExternalDataSourceType | D93: Picklist

Sheet RCA Quote - Fields
A1: Object | C1: Quote
A2: API Name | C2: Quote
I3: Conga Fields
A4: NO | B4: Field Label | C4: API Name | D4: Data Type | E4: Data Type | F4: Data Type | G4: Required | H4: Picklist Values | I4: Conga Field Label | J4: Field type | K4: Required | L4: Comments
A5: 1 | B5: Quote ID | C5: Id | D5: id | F5: Standard | G5: Required | I5: Record ID | J5: Standard | K5: Required
A6: 2 | B6: Owner ID | C6: OwnerId | D6: Lookup (Group,User) | F6: Standard | G6: Required | I6: Owner ID | J6: Standard | K6: Required
A7: 3 | B7: Deleted | C7: IsDeleted | D7: Checkbox | F7: Standard | I7: Deleted | J7: Standard
A8: 4 | B8: Quote Name | C8: Name | D8: Text | E8: 255 | F8: Standard | G8: Required | I8: Proposal Name | J8: Custom
A9: 5 | B9: Opportunity ID | C9: OpportunityId | D9: Master-Detail (Opportunity) | F9: Standard | I9: Opportunity | J9: Custom
A10: 6 | B10: Price Book ID | C10: Pricebook2Id | D10: Lookup (Price Book) | F10: Standard | I10: Price List | J10: Custom
A11: 7 | B11: Contact ID | C11: ContactId | D11: Lookup (Contact) | F11: Standard
A12: 8 | B12: Quote Number | C12: QuoteNumber | D12: Auto Number | E12: 30 | F12: Standard | G12: Required | I12: Proposal ID | J12: Standard | K12: Required
A13: 9 | B13: Syncing | C13: IsSyncing | D13: Checkbox | F13: Standard
A14: 10 | B14: Shipping and Handling | C14: ShippingHandling | D14: Currency | F14: Standard | I14: Shipping & Handling | J14: Custom
A15: 11 | B15: Tax | C15: Tax | D15: Currency | F15: Standard
A16: 12 | B16: Status | C16: Status | D16: Picklist | F16: Standard | H16: Draft;Needs Review;In Review;Approved;Rejected;Presented;Accepted;Denied | L16: Need to check if Apttus_QPApprov__Approval_Status__c / Apttus_Proposal__Approval_Stage__c fields from Conga can be considered
A17: 13 | B17: Expiration Date | C17: ExpirationDate | D17: Date | F17: Standard | I17: Proposal Expiration Date | J17: Custom
A18: 14 | B18: Description | C18: Description | D18: Long Text Area | E18: 32000 | F18: Standard | I18: Description | J18: Custom
A19: 15 | B19: Subtotal | C19: Subtotal | D19: Roll-Up Summary | F19: Standard
A20: 16 | B20: Total Price | C20: TotalPrice | D20: Roll-Up Summary | F20: Standard
A21: 17 | B21: Line Items | C21: LineItemCount | D21: Roll-Up Summary | F21: Standard
A22: 18 | B22: Bill To Street | C22: BillingStreet | D22: Text Area | E22: 255 | F22: Standard | L22: It will Auto Populate from BillTo Address
A23: 19 | B23: Bill To City | C23: BillingCity | D23: Text | E23: 40 | F23: Standard | L23: It will Auto Populate from BillTo Address
A24: 20 | B24: Bill To State/Province | C24: BillingState | D24: Text | E24: 80 | F24: Standard | L24: It will Auto Populate from BillTo Address
A25: 21 | B25: Bill To Zip/Postal Code | C25: BillingPostalCode | D25: Text | E25: 20 | F25: Standard | L25: It will Auto Populate from BillTo Address
A26: 22 | B26: Bill To Country | C26: BillingCountry | D26: Text | E26: 80 | F26: Standard | L26: It will Auto Populate from BillTo Address
A27: 23 | B27: Bill To Latitude | C27: BillingLatitude | D27: Number (3, 15) | E27: 18 | F27: Standard
A28: 24 | B28: Bill To Longitude | C28: BillingLongitude | D28: Number (3, 15) | E28: 18 | F28: Standard
A29: 25 | B29: Bill To Geocode Accuracy | C29: BillingGeocodeAccuracy | D29: Picklist | F29: Standard | H29: Address;NearAddress;Block;Street;ExtendedZip;Zip;Neighborhood;City;County;State;Unknown
A30: 26 | B30: Bill To | C30: BillingAddress | D30: Address | F30: Standard | I30: Bill To | J30: Custom
A31: 27 | B31: Ship To Street | C31: ShippingStreet | D31: Text Area | E31: 255 | F31: Standard | L31: It will Auto Populate from ShipTo Address
A32: 28 | B32: Ship To City | C32: ShippingCity | D32: Text | E32: 40 | F32: Standard | L32: It will Auto Populate from ShipTo Address
A33: 29 | B33: Ship To State/Province | C33: ShippingState | D33: Text | E33: 80 | F33: Standard | L33: It will Auto Populate from ShipTo Address
A34: 30 | B34: Ship To Zip/Postal Code | C34: ShippingPostalCode | D34: Text | E34: 20 | F34: Standard | L34: It will Auto Populate from ShipTo Address
A35: 31 | B35: Ship To Country | C35: ShippingCountry | D35: Text | E35: 80 | F35: Standard | L35: It will Auto Populate from ShipTo Address
A36: 32 | B36: Ship To Latitude | C36: ShippingLatitude | D36: Number (3, 15) | E36: 18 | F36: Standard
A37: 33 | B37: Ship To Longitude | C37: ShippingLongitude | D37: Number (3, 15) | E37: 18 | F37: Standard
A38: 34 | B38: Ship To Geocode Accuracy | C38: ShippingGeocodeAccuracy | D38: Picklist | F38: Standard | H38: Address;NearAddress;Block;Street;ExtendedZip;Zip;Neighborhood;City;County;State;Unknown
A39: 35 | B39: Ship To | C39: ShippingAddress | D39: Address | F39: Standard | I39: Ship To | J39: Custom
A40: 36 | B40: Quote To Street | C40: QuoteToStreet | D40: Text Area | E40: 255 | F40: Standard
A41: 37 | B41: Quote To City | C41: QuoteToCity | D41: Text | E41: 40 | F41: Standard
A42: 38 | B42: Quote To State/Province | C42: QuoteToState | D42: Text | E42: 80 | F42: Standard
A43: 39 | B43: Quote To Zip/Postal Code | C43: QuoteToPostalCode | D43: Text | E43: 20 | F43: Standard
A44: 40 | B44: Quote To Country | C44: QuoteToCountry | D44: Text | E44: 80 | F44: Standard
A45: 41 | B45: Quote To Latitude | C45: QuoteToLatitude | D45: Number (3, 15) | E45: 18 | F45: Standard
A46: 42 | B46: Quote To Longitude | C46: QuoteToLongitude | D46: Number (3, 15) | E46: 18 | F46: Standard
A47: 43 | B47: Quote To Geocode Accuracy | C47: QuoteToGeocodeAccuracy | D47: Picklist | F47: Standard | H47: Address;NearAddress;Block;Street;ExtendedZip;Zip;Neighborhood;City;County;State;Unknown
A48: 44 | B48: Quote To | C48: QuoteToAddress | D48: Address | F48: Standard
A49: 45 | B49: Additional To Street | C49: AdditionalStreet | D49: Text Area | E49: 255 | F49: Standard
A50: 46 | B50: Additional To City | C50: AdditionalCity | D50: Text | E50: 40 | F50: Standard
A51: 47 | B51: Additional To State/Province | C51: AdditionalState | D51: Text | E51: 80 | F51: Standard
A52: 48 | B52: Additional To Zip/Postal Code | C52: AdditionalPostalCode | D52: Text | E52: 20 | F52: Standard
A53: 49 | B53: Additional To Country | C53: AdditionalCountry | D53: Text | E53: 80 | F53: Standard
A54: 50 | B54: Additional To Latitude | C54: AdditionalLatitude | D54: Number (3, 15) | E54: 18 | F54: Standard
A55: 51 | B55: Additional To Longitude | C55: AdditionalLongitude | D55: Number (3, 15) | E55: 18 | F55: Standard
A56: 52 | B56: Additional To Geocode Accuracy | C56: AdditionalGeocodeAccuracy | D56: Picklist | F56: Standard | H56: Address;NearAddress;Block;Street;ExtendedZip;Zip;Neighborhood;City;County;State;Unknown
A57: 53 | B57: Additional To | C57: AdditionalAddress | D57: Address | F57: Standard
A58: 54 | B58: Bill To Name | C58: BillingName | D58: Text | E58: 255 | F58: Standard
A59: 55 | B59: Ship To Name | C59: ShippingName | D59: Text | E59: 255 | F59: Standard
A60: 56 | B60: Quote To Name | C60: QuoteToName | D60: Text | E60: 255 | F60: Standard
A61: 57 | B61: Additional To Name | C61: AdditionalName | D61: Text | E61: 255 | F61: Standard
A62: 58 | B62: Email | C62: Email | D62: Email | F62: Standard
A63: 59 | B63: Phone | C63: Phone | D63: Phone | E63: 40 | F63: Standard
A64: 60 | B64: Fax | C64: Fax | D64: Phone | E64: 40 | F64: Standard
A65: 61 | B65: Contract ID | C65: ContractId | D65: Lookup (Contract) | F65: Standard
A66: 62 | B66: Sales Transaction Type ID | C66: SalesTransactionTypeId | D66: Lookup (Sales Transaction Type) | F66: Standard
A67: 63 | B67: Transaction Type | C67: TransactionType | D67: Picklist | F67: Standard
A68: 64 | B68: Contract ID | C68: PricingContractId | D68: Lookup (Contract) | F68: Standard
A69: 65 | B69: Calculation Status | C69: CalculationStatus | D69: Picklist | F69: Standard | H69: NotStarted;TaxCalculationWaiting;TaxCalculationInProcess;TaxCalculationFailed;TaxCalculationSuccess;PriceCalculationQueued;PriceCalculationInProgress;PriceCalculationFailed;CompletedWithoutPricing;Saving;SaveFailedOrIncomplete;CompletedWithPricing;CompletedWithTax;QuoteRequestPartiallySaved;QuoteRequestFailed;ConfigurationInProgress;ConfigurationFailed;ReconciliationInProgress;ReconciliationFailed;QueuedForConfiguration;QueuedForPricingAndSaving
A70: 66 | B70: Total Tax Amount | C70: TotalTaxAmount | D70: Roll-Up Summary | F70: Standard
A71: 67 | B71: Total Price With Tax | C71: TotalPriceWithTax | D71: Currency | F71: Standard | I71: Total Quote Value with Tax (Japan) | J71: Custom
A72: 68 | B72: Account ID | C72: AccountId | D72: Lookup (Account) | F72: Standard | I72: Account | J72: Custom
A73: 69 | B73: Account ID | C73: QuoteAccountId | D73: Lookup (Account) | F73: Standard
A74: 70 | B74: Discount | C74: Discount | D74: Percent | F74: Standard | I74: Total Quote Discount % | J74: Custom
A75: 71 | B75: Grand Total | C75: GrandTotal | D75: Currency | F75: Standard | I75: Grand Total | J75: Custom
A76: 72 | B76: Can Create Quote Line Items | C76: CanCreateQuoteLineItems | D76: Checkbox | F76: Standard
A77: 73 | B77: Contact ID | C77: BillToContactId | D77: Lookup (Contact) | F77: Standard | I77: Billing Contact | J77: Custom
A78: 74 | B78: Partner Account ID | C78: PartnerAccountId | D78: Lookup (Account) | F78: Standard | I78: Bill To Partner / Distributor Label | J78: Custom
A79: 75 | B79: Last Priced Date | C79: LastPricedDate | D79: Date/Time | F79: Standard
A80: 76 | B80: Original Action Type | C80: OriginalActionType | D80: Picklist | F80: Standard | H80: Add;Amend;Cancel;Renew;No Change
A81: 77 | B81: Start Date | C81: StartDate | D81: Date | F81: Standard
A82: 78 | B82: Legal Entity ID | C82: LegalEntityId | D82: Lookup (Legal Entity) | F82: Standard | I82: Legal Entity | J82: Custom
A83: 79 | B83: Validation Result | C83: ValidationResult | D83: Picklist | F83: Standard | H83: TransactionIncomplete;MissingContributor
I84: Currency ISO Code | J84: Standard
I85: Record Type ID | J85: Standard
I86: Approval Stage | J86: Custom
I87: Create Agreement | J87: Custom
I88: Expected End Date | J88: Custom
I89: Expected Start Date | J89: Custom
I90: Generate | J90: Custom
I91: Grand Total | J91: Custom
I92: Make Primary | J92: Custom
I93: Net Amount | J93: Custom
I94: Payment Term | J94: Custom
I95: Present | J95: Custom
... I607: MSP Partner Discount | J607: Custom

Sheet As Is Quote Layout 
A1: # | B1: Label | C1: Data Type | D1: ReadOnly/Editable | E1: Forsys Comments | F1: Clarification | G1: Business Justification | H1: Source of population | I1: Comments
A2: Quote Details section
A3: 1 | B3: Proposal ID | C3: Text | D3: R | E3: It will be auto populated by system | H3: S
A4: 2 | B4: Owner | C4: Lookup (Group,User) | D4: E | E4: It will be auto populated by system but user can change the owner of the quote | F4: Up to which stage the ownership of the quote can be changed? | G4: [RB] No validation today | H4: S
A5: 3 | B5: Proposal Name | C5: Text | D5: E | E5: It will be auto populated by system but user can edit it | F5: How it needs to be defaulted? (For eg. Account _OppName ) | G5: [RB] I believe its just Opty name | H5: O
A6: 4 | B6: Quote Type | C6: Picklist | D6: E | E6: It will be auto populated by system based on the Opportunity type | F6: 1. Is there any mapping between Opportunity type, Opportunity Contract Type and Quote Type? 2. Based on which field from the Opportunity, Quote Type needs to be defaulted? | G6: [RB] No. Default is Standard | H6: S | I6: Getting populated from APTS_ProposalTrigger_Handler Apex class
A7: 5 | B7: Deal Type | C7: Picklist | D7: E | E7: It is user selection field | H7: U | I7: It is used in Approval Rules
A8: 6 | B8: Approval Stage | C8: Picklist | D8: R | E8: It will be auto populated by system and default value will be Draft. | H8: S | I8: Getting updated from APTS_ProposalTrigger_Handler and APTS_CancelProposalExtension Apex classes. If APTS_Revert_to_Presented__c field is reverted to true and Approval stage is accepted then the Approval stage gets updated to Presented in APTS_Proposal_Before_Save_Flow flow
A9: 7 | B9: Valid Until Date | C9: Date | D9: E | E9: It will be auto populated by system and default value will be current date + 60 days User can edit it. | F9: Are there any validations required to restrict the update of this field based on Quote stage? | G9: [RB] No validation today | H9: S | I9: Getting populated from APTS_Default_Start_Date_on_Proposal Flow | K9: S- System Populated Fields O- Fields coming from Opportunity D- Derived from flow or code U- User input fields A- Account related fields
A10: 8 | B10: Primary | C10: Checkbox | D10: R | E10: System will automatically mark it once the quote is Approved | F10: Is there any requirement to mark the first quote as Primary by default? | G10: [RB] Yes | H10: S | I10: Getting populated from APTS_MarkPrimaryAndSyncWithOpportunity Apex class where we are making it as true. We are marking Apttus_Proposal__Primary__c as false in APTS_CancelProposalExtension Apex class
A11: 9 | B11: Auto Renew | C11: Checkbox | D11: E | E11: It needs to be checked by user | F11: In which use cases user will mark this checkbox ? | G11: [RB] Couple of validation rules - restricted for Subscription. | H11: U | I11: It is used in Approval Rules
A12: 10 | B12: Revert to Presented | C12: Checkbox | D12: E | E12: It needs to be checked by user | F12: 1. In which use cases user will mark this checkbox ? 2. Is it still required in To be? | G12: [RB] When they want to revert from accepted. I didnt think this was required in To be. You may confirm. | H12: U
A13: 11 | B13: CPI Adjustment | C13: Checkbox | D13: R | E13: It will be set by system based on some criteria | F13: For what all use cases this field will set to True? | G13: [RB] Based on attribute configuration for Subscription | H13: D | I13: Getting populated from Set_CPI_Adjustment_Check_on_Proposal Flow
A14: 12 | B14: Template Type | C14: Picklist | D14: E | E14: Detailed Quote Template Short Quote Template It will be defaulted by system to Short Quote Template. | F14: 1. Are these values still valid in To Be? | G14: [RB] My guess is not - may need to confirm. | H14: U
A15: 13 | B15: Description | C15: Long Text Area | D15: E | E15: It is user input field | F15: 1.Is this field being referred in Quote Template? 2. What kind of description this field will contain? | G15: [RB] It was at one point, not sure if any of the templates still use it | H15: U
A16: 14 | B16: Contract Type | C16: Picklist | D16: R | E16: It will be auto populated by system based on the Opportunity contract type In RCA, it will be user input field | F16: Need the mapping between Opportunity Contract Type and Quote Contract Type | G16: [RB] Derived via Formula field | H16: D | I16: Getting populated from Set_Contract_Type_and_Template_selection_on_Quote_Proposal flow
A17: 15 | B17: Credit Reason | C17: Picklist | D17: E | E17: It is user selection field | H17: U
A18: 16 | B18: Template Selection | C18: Picklist | D18: E | E18: It is user selection field | H18: U
A19: 17 | B19: Credit Amount | C19: Currency | D19: R | E19: It will be auto populated by system | F19: 1. From where this field value needs to be pulled? | G19: [RB] In case of Entrust credit, I believe its pulled in upon cart finalization. For other credits, its user entered. | H19: D | I19: Getting populated from APTS_ProposalTrigger_Handler Apex class
A20: 18 | B20: Template Comments | C20: Long Text Area | D20: E | E20: It is user input field | H20: U
A21: 19 | B21: Approve Credit | C21: Checkbox | D21: R | E21: It will be auto populated by system | F21: 1. From where this field value needs to be pulled? | G21: [RB] Derived via Formula field | H21: D | I21: It is a formula field. IF(TEXT(APTS_Credit_Reason__c) = 'Entrust Credit' && ((NOT(ISNULL(APTS_Approved_Credit_Amount__c)) && NOT(ISNULL(APTS_CREDIT_AMOUNT__c)) && ROUND(APTS_CREDIT_AMOUNT__c,0) <= ROUND(APTS_Approved_Credit_Amount__c,0)) || (ISPICKVAL( Apttus_QPApprov__Approval_Status__c , 'Approved')) ),TRUE, IF(TEXT(APTS_Credit_Reason__c) = 'Entrust Credit' && ( (NOT(ISNULL(APTS_Approved_Credit_Amount__c)) && NOT(ISNULL(APTS_CREDIT_AMOUNT__c)) && ROUND(APTS_CREDIT_AMOUNT__c,0) > ROUND(APTS_Approved_Credit_Amount__c,0)) || (ISNULL(APTS_Approved_Credit_Amount__c) && NOT(ISNULL(APTS_CREDIT_AMOUNT__c)) ) ),FALSE, IF(/*TEXT(APTS_Credit_Reason__c) = 'Revocation Credit'*/NOT(ISBLANK(TEXT(APTS_Credit_Reason__c))) && NOT(ISPICKVAL(APTS_Credit_Reason__c,"Entrust Credit")) && ISPICKVAL( Apttus_QPApprov__Approval_Status__c , 'Approved'),TRUE,FALSE)))
A22: 20 | B22: Allow Multiple Agreements (OF & SFA) | C22: Checkbox | D22: E | E22: It needs to be checked by user | F22: For what all use cases this field will set to True? | G22: [RB] User entered when they want to create multiple agreements -just used for validation. If the agreement creation flow is changing, will it still be required? | H22: U
A23: 21 | B23: Disable Consumption Report View in CC | C23: Checkbox | D23: E | E23: It needs to be checked by user | F23: For what all use cases this field will set to True? | G23: [RB] When Partner Sales motion is sell-with and for Subscriotion contract | H23: U
A24: Account & Contact section
A25: 1 | B25: Opportunity | C25: Lookup (Opportunity) | D25: R | E25: It will be auto populated by system with the Opportuniy from which the Quote is created | H25: O
A26: 2 | B26: Quote Primary Contact | C26: Lookup (Contact) | D26: E | E26: It should be defaulted with the Account Contact from which the Opportunity is created. User can edit it | H26: O
A27: 3 | B27: Account | C27: Lookup (Account) | D27: R | E27: It will be auto populated by system with Opportunity Account | H27: O
A28: 4 | B28: Billing Contact | C28: Lookup (Contact) | E28: It is user input field. User can select the approriate contact from the Lookup | F28: Are there any restrictions for the Billing Contact that only specific Contacts should be displayed? | G28: [RB] Related contacts only | H28: U
A29: 5 | B29: Account Segment | C29: Text | D29: R | E29: It will be defaulted from the selected Account | H29: A
A30: 6 | B30: Account Payment Term | C30: Text | D30: R | E30: It will be defaulted from the selected Account | H30: A
A31: 7 | B31: Account Cert Central ID | C31: Text | D31: R | E31: It will be defaulted from the selected Account | H31: A
A32: 8 | B32: Payment Term | C32: Lookup (Payment Term) | D32: E | E32: It should be defaulted with the Account Payment Term but user can edit it | H32: A
A33: 9 | B33: Bill To Partner / Distributor | C33: Lookup (Account) | D33: E | E33: In case of Direct deal it should be selected as same Account and in case of Indirect deal it should be selected with Partner Account | F33: Are there any restrictions for selection of this field? | G33: [RB] Pulled from the opty, user entry not allowed CS: In current system it is editable field and only at quote level user is selecting the deal type. | H33: U
A34: 10 | B34: Contract Type (Existing) | C34: Text | D34: R | E34: It is a Formula field and pulling the value from Account | F34: Is this field driving any business logic? | G34: [RB] I believe it is in the Agreement stage to supersede existing contract | H34: A
A35: 11 | B35: Partner Cert Central ID | C35: Text | D35: R | E35: It should be defaulted from Partner Account | H35: A
A36: 12 | B36: Contract Start Date (Existing) | C36: Date | D36: R | E36: It is a Formula field and pulling the value from Account | F36: Is this field driving any business logic? | G36: [RB] I believe it is in the Agreement stage to supersede existing contract | H36: A
A37: 13 | B37: Partner Channel | C37: Text | D37: R | E37: It is a Formula field based on the Partner Sales Motion field value from the Opportunity | F37: What is the significance of this field and where it is being used? | G37: [RB] Informational only | H37: O
A38: 14 | B38: Contract End Date (Existing) | C38: Date | D38: R | E38: It is a Formula field and pulling the value from Account | F38: Is this field driving any business logic? | G38: [RB] I believe it is in the Agreement stage to supersede existing contract | H38: A
A39: 15 | B39: Marketplace Partner Account | C39: Lookup (Account) | D39: R | F39: with which Partner Account this field will be populated and what are the use cases where this Account is required? | G39: [RB] For marketplace Sell with deal
A40: 16 | B40: Support Level (Existing) | C40: Text | D40: R | E40: It is a Formula field and pulling the value from Account | H40: A
A41: 17 | B41: Bill To | C41: Lookup (Account) | D41: R | E41: For a Direct Deal, Account (End Customer) is the Bill To whereas for an Indirect Deal, Partner Account is the Bill To. | H41: S
A42: 18 | B42: Support Level (New) | C42: Text | D42: R | F42: How this field value will be pulled? | G42: [RB] Support level being quoted in the cart | H42: D | I42: Getting populated from flow_Populate_Quote_Proposal_fields_after_finalization It is used in Approval Rules
A43: 19 | B43: Bill To Billing Legal Entity | C43: Text | D43: R | E43: It is a Formula field based on the Bill To Account | H43: A
A44: 20 | B44: Previous Proposal | C44: Lookup (Quote/Proposal) | D44: E | F44: What is the significance of this field and in which use case this field will be entered by user? | G44: [RB] Lookup to the proposal being renewed/terminated | H44: U
A45: 21 | B45: Account Credit Hold | C45: Checkbox | D45: R | E45: It is a Formula field and pulling the value from Bill To Account If Account Credit Hold is checked, you will not be able to use 'Configure Products' and proceed with this quote. Please contact the Finance team. | H45: A
A46: 22 | B46: Previous Order | C46: Lookup (Apttus Order) | F46: What is the significance of this field and in which use case this field will be entered by user? | G46: [RB] Lookup to the order being renewed/terminated | H46: U
A47: 23 | B47: Account Credit Check Status | C47: Text | D47: R | E47: It is a Formula field and pulling the value from Bill To Account Account Credit Check needs to be Approved and is one of the criteria for the ‘Create Order Form/MSA' button to be enabled. | H47: A
A48: Billing Preference Info section
A49: 1 | B49: Contract Type Template | C49: Text | D49: R | F49: What is the significance of this field and how this field will be derived? | G49: [RB] Drives template selection | H49: D | I49: Getting populated from Set_Contract_Type_and_Template_selection_on_Quote_Proposal flow It is used in Approval Rules
A50: 2 | B50: Requested Credit Limit | C50: Currency | D50: R | F50: What is the significance of this field and how this field will be derived? | G50: [RB] Derived based on contract type and used by integration downstream | H50: D | I50: Getting populated from APTS_ProposalTrigger_Handler Apex class. And also assigning Requested credit limit in APTS_Proposal_Before_Save_Flow Flow It is used in Approval Rules
A51: 3 | B51: Contract Length | C51: Number (16, 2) | D51: R | F51: What is the significance of this field and how this field will be derived? | G51: [RB] Duration based on Start and End Date of the contract | H51: S | I51: Getting populated from APTS_ProposalTrigger_Handler Apex class
A52: 4 | B52: Requested Credit Limit Override | C52: Currency | D52: R | F52: What is the significance of this field and how this field will be derived? | G52: [RB] User entered when seeking approval | H52: U
A53: 5 | B53: Price List | C53: Lookup (Price List) | D53: R | E53: It will be auto populated based on the Opportunity currency | H53: S
A54: 6 | B54: Per Cert Expected Annual Spend | C54: Currency | D54: R | F54: What is the significance of this field and how this field will be derived? | G54: [RB] Attribute value - used in templates, support calculation | H54: D | I54: Getting populated from APTS_ProposalTrigger_Handler Apex class
A55: 7 | B55: Territory | C55: Text | D55: R | E55: The Name of the Territory associated with the Opportunity that is linked to the current Proposal record. Flow Name:Proposal Before Save Flow | F55: Is it referring to the Opportunity field? | G55: [RB] Yes | H55: O
A56: 8 | B56: Pricing Region | C56: Picklist | D56: R | F56: From where this will be derived? | G56: [RB] Derived based on Country on proposal creation. | H56: D | I56: Getting populated from APTS_Proposal_Before_Save_Flow Flow
A57: Pricing section
A58: 1 | B58: Total Seat-based MSRP | C58: Currency | D58: R | F58: Are these fields value calculated based on the cart totals and is it being pulled from Cart Summary Totals? | H58: D | I58: Getting populated from APTS_ProposalTrigger_Handler Apex class
A59: 2 | B59: Total Quote MSRP | C59: Currency | D59: R | H59: D | I59: It is a formula field. (APTS_Total_PKI_MSRP__c + APTS_Total_Certificate_based_MSRP__c)
A60: 3 | B60: Total Seat-based Value | C60: Currency | D60: R | H60: D | I60: Getting populated from APTS_ProposalTrigger_Handler Apex class.
A61: 4 | B61: Total Quote Value | C61: Currency | D61: R | H61: D | I61: It is a formula field. if((IsBlank(APTS_Total_Cert_Based_Net_Amount__c) || APTS_Total_Cert_Based_Net_Amount__c = 0) && (IsBlank(APTS_Total_Seat_Based_Net_Amount__c ) || APTS_Total_Seat_Based_Net_Amount__c = 0) && (IsBlank(APTS_Total_Cert_Based_Support_Net_Amount__c) || APTS_Total_Cert_Based_Support_Net_Amount__c = 0),APTS_Total_PKI_Value__c + APTS_Total_SSL_Value__c,if(APTS_Pricing_Type__c > 0 || APTS_Contract_Type_Template__c == 'BULK-D' || APTS_Contract_Type_Template__c == 'PC' || APTS_Contract_Type_Template__c == 'Ongoing', APTS_Total_Cert_Based_Net_Amount__c+ APTS_Total_Seat_Based_Net_Amount__c + APTS_Total_Cert_Based_Support_Net_Amount__c +APTS_Total_Seat_Based_Support_Net_Amount__c ,APTS_Total_Cert_Based_Net_Amount__c+ APTS_Total_Seat_Based_Net_Amount__c +APTS_Total_Seat_Based_Support_Net_Amount__c ))
A62: 5 | B62: Total Seat-based Discount % | C62: Percent | D62: R | H62: D | I62: It is a formula field. IF( APTS_Total_PKI_MSRP__c <> 0, APTS_Total_PKI_Discount__c / APTS_Total_PKI_MSRP__c, 0 )
A63: 6 | B63: Total Quote Amount (USD) | C63: Number (16, 2) | D63: R | G63: [RB] Either calculated on cart finalization via code or rollup summary fields | H63: D | I63: It is a formula field. IF(TEXT(CurrencyIsoCode) = 'USD', APTS_Total_Quote_Value__c, APTS_Total_Quote_Value__c / CURRENCYRATE(TEXT(CurrencyIsoCode)))
A64: 7 | B64: Total Certificate-based MSRP | C64: Currency | D64: R | H64: D | I64: Getting populated from APTS_ProposalTrigger_Handler Apex class.
A65: 8 | B65: Total Support Value | C65: Currency | D65: R | H65: D | I65: It is a formula field. IF(NOT(ISBLANK(APTS_Total_Support_Cert_based_Value__c)) || NOT(ISBLANK(APTS_Total_Support_Seat_based_Value__c)), APTS_Total_Support_Cert_based_Value__c+ APTS_Total_Support_Seat_based_Value__c,0) It is used in Approval Rules
A66: 9 | B66: Total Certificate-based Value | C66: Currency | D66: R | H66: D | I66: Getting populated from APTS_ProposalTrigger_Handler Apex class.
A67: 10 | B67: Total Quote Discount % | C67: Percent | D67: R | H67: D | I67: It is a formula field. IF( APTS_Total_Quote_MSRP__c <> 0, APTS_Total_Quote_Discount__c / ( APTS_Total_Quote_Discount__c + APTS_Total_Quote_Value__c), 0 )
A68: 11 | B68: Total Support (Cert-based) MSRP | C68: Currency | D68: R | H68: D | I68: It is a Rollup Summary field. 1. Filter Criteria: (DescriptionequalsDigicert Standard Support,Digicert Business Support,Digicert Premium Support,Basic Support,Platinum Support, Gold Support,Digicert Business Plus Support) and (Product ConfigurationequalsCertificate-based,Partner) 2. Field to Aggregate: Proposal Line Item: Total Line MSRP
A69: 12 | B69: Annual Commit Discount % | C69: Number (14, 4) | D69: E | E69: It is a user input field | F69: 1. Who is responsible for providing input for this field and at which stage and in which all use cases, user will provide value for this field? 2. Once user provide input for this field, how this discount will be applied to the configured quote? | G69: [RB] System calculated in the cart | H69: U
A70: 13 | B70: Total Certificate-based Discount % | C70: Percent | D70: R | F70: Are these fields value calculated based on the cart totals and is it being pulled from Cart Summary Totals? | G70: [RB] Calculated on cart finalization via code | H70: D | I70: It is a formula field. IF( APTS_Total_Certificate_based_MSRP__c <> 0, 1 - (IF(APTS_Contract_Type_Template__c == 'BULK-D' || APTS_Contract_Type_Template__c == 'PC' || APTS_Contract_Type_Template__c == 'Ongoing',APTS_Total_Cert_Based_Net_Amount__c + APTS_Total_Cert_Based_Support_Net_Amount__c,APTS_Total_Cert_Based_Net_Amount__c) / APTS_Total_Certificate_based_MSRP__c) , 0)
A71: 14 | B71: Total Manual Discount % | C71: Percent | D71: R | H71: D | I71: It is a formula field. IF( APTS_Total_Quote_MSRP__c <> 0, APTS_Total_Manual_Discount__c / ( APTS_Total_Manual_Discount__c + APTS_Total_Quote_Value__c), 0 ) It is used in Approval Rules
A72: 15 | B72: Tax Amount (Japan) | C72: Number (18, 0) | D72: R | F72: From where this field value will be pulled? | G72: [RB] Hardcoded for Japan only | H72: S | I72: It is a formula field. IF( TEXT(Apttus_Proposal__Account__r.APTS_Billing_Legal_Entity__c)=='541' ,FLOOR(APTS_Total_Quote_Value__c * 0.1),0)
A73: 16 | B73: Max Line Item Manual Discount | C73: Percent | D73: R | F73: Are these fields value calculated based on the cart totals and is it being pulled from Cart Summary Totals? | G73: [RB] Calculated in code or via formula field | H73: D | I73: It is a Rollup summary field. 1. Filter Criteria: Descriptionnot equal toDigicert Standard Support,Digicert Business Support,Digicert Premium Support,DigiCert Platinum Support, DIGICERT PKI PLATFORM - PLATINUM SUPPORT - 12 MONTHS,Digicert Business Plus Support 2. Field to aggregate: Proposal Line Item: Manual Discount %
A74: 17 | B74: Total Quote Value with Tax (Japan) | C74: Currency | D74: R | H74: D | I74: It is a formula field. IF(TEXT(Apttus_Proposal__Account__r.APTS_Billing_Legal_Entity__c)=='541', APTS_Total_Quote_Value__c + Tax_Amount__c, 0)
A75: 18 | B75: Approved (Entrust) Credit Amount | C75: Currency | D75: E | E75: It is a user input field | F75: 1. What is the significance of this field? 2. Who is responsible for providing input for this field and at which stage and in which all use cases, user will provide value for this field? | G75: [RB] Maximum pre approved entrust credit system calculated | H75: U
A76: Partner Program Info section
A77: 1 | B77: DigiCert-branded Cert Discount(Default) | C77: Percent | D77: R | F77: From where this field value will be pulled? | G77: [RB] custom metadata type | H77: S | I77: Getting populated from APTS_ProposalTrigger_Handler Apex class.
A78: 2 | B78: Marketplace Partner Contact | C78: Lookup (Contact) | D78: R | E78: This expression retrieves the Marketplace Partner Contact ID (Contact record ID) from the Opportunity that is linked to the current Proposal. Flow Name : Set or Reset Fields on Quote Creation | F78: Is this the contact associated with the Marketplace Partner Account? | G78: [RB] opty | H78: O
A79: 3 | B79: DigiCert-branded Certificate Discount | C79: Percent | D79: R | F79: From where this field value will be pulled? | G79: [RB] Attribute in the cart or from the Partner Account | H79: D | I79: Getting populated from APTS_ProposalTrigger_Handler Apex class.
A80: 4 | B80: Marketplace Partner Seller ID | C80: Text | D80: R | E80: It is a Formula field, fetching value from Opportunity | H80: O
A81: 5 | B81: Pro Serv/3rd Party/Support Discount(Def) | C81: Percent | D81: R | F81: From where this field value will be pulled? | G81: [RB] custom metadata type | H81: S | I81: Getting populated from APTS_ProposalTrigger_Handler Apex class.
A82: 6 | B82: Partner Sales Motion | C82: Text | D82: R | E82: It is a Formula field, fetching value from Opportunity | H82: O | I82: It is used in Approval Rules
A83: 7 | B83: Pro Services/3rd Party/Support Discount | C83: Percent | D83: R | F83: From where this field value will be pulled? | G83: [RB] Attribute in the cart or from the Partner Account | H83: D | I83: Getting populated from APTS_ProposalTrigger_Handler Apex class.
A84: 8 | B84: Partner Sales Motion Type | C84: Text | D84: R | E84: It is a Formula field, fetching value from Opportunity | H84: O
A85: 9 | B85: Velocity-branded Cert Discount(Default) | C85: Percent | D85: R | F85: From where this field value will be pulled? | G85: [RB] custom metadata type | H85: S | I85: Getting populated from APTS_ProposalTrigger_Handler Apex class.
A86: 10 | B86: Inline Reseller | C86: Text | D86: R | E86: It is a Formula field, fetching value from Opportunity | H86: O
A87: 11 | B87: Velocity-branded Certificate Discount | C87: Percent | D87: R | F87: From where this field value will be pulled? | G87: [RB] Attribute in the cart or from the Partner Account | H87: D | I87: Getting populated from APTS_ProposalTrigger_Handler Apex class.
A88: 12 | B88: Inline Reseller Contact | C88: Lookup (Contact) | D88: E | E88: the value stored in the “Inline Reseller Contact” field on the Opportunity related to the current Proposal Flow Name : Set or Reset Fields on Quote Creation | F88: Is this the contact associated with the Inline Reseller Account? | H88: O
A89: 13 | B89: Deal Registration Discount (Default) | C89: Percent | D89: R | E89: The APTS_Seat_based_discount__c field flows from Partner Account → Proposal → Line Item Attributes, is used for discount approvals, and influences non-registered discount calculations for specific partner sales motions. Apex Class:APTS_ProposalTrigger_Handler Apex Class:APTS_ProductAttributeValueTriggerHandler Apex Class:APTS_ProductAttributeValueTriggerHandler | F89: From where this field value will be pulled? | G89: [RB] Opty | H89: O
A90: 14 | B90: Partner Program Eligible? | C90: Checkbox | D90: R | E90: It is Formula field | H90: D | I90: It is a formula field. IF( ISPICKVAL(Apttus_Proposal__Opportunity__r.Partner_Sales_Motion__c , 'Marketplace Sell-With') && NOT(ISPICKVAL(APTS_Deal_Type__c,'Direct')) , APTS_Marketplace_Partner_Account_IPP__c , Apttus_QPConfig__BillToAccountId__r.APTS_Partner_Program_Discount__c && NOT(ISPICKVAL(APTS_Deal_Type__c,'Direct')))
A91: 15 | B91: Deal Registration Discount | C91: Percent | D91: R | F91: From where this field value will be pulled? | G91: [RB] Attribute in the cart or from the Partner Account | H91: D | I91: Getting populated from APTS_ProposalTrigger_Handler Apex class.
A92: 16 | B92: Deal Registered | C92: Checkbox | D92: R | E92: It is Formula field | H92: D | I92: It is a formula field. APTS_Deal_Registration_Partner__c = Apttus_Proposal__Opportunity__r.Reseller__c && Apttus_Proposal__Opportunity__r.ImpartnerPRM__IsDealRegistration__c
A93: 17 | B93: Non-Deal Registration discount (Default) | C93: Percent | D93: R | F93: From where this field value will be pulled? | G93: [RB] custom metadata type | H93: S | I93: Getting populated from APTS_ProposalTrigger_Handler Apex class.
A94: 18 | B94: Partner Contract Type | C94: Picklist | D94: R | E94: Populated during cart finalization (beforeUpdate) Values: 'Bulk Draw Down', 'Bulk', 'Pay-As-You-Go', 'Ongoing', or null Determined by: Product code (PC/BULK-D), Bulk Flex setting, Pay Go/Ongoing attribute, or copied from Partner Account Cleared: When partner program eligibility conditions fail | F94: Based on which field this field value selection will happen? | G94: [RB] Same field on Opty | H94: O
A95: 19 | B95: Non-Deal Registration discount | C95: Percent | D95: R | F95: From where this field value will be pulled? | G95: [RB] Attribute in the cart or from the Partner Account | H95: D | I95: Getting populated from APTS_ProposalTrigger_Handler Apex class.
A96: 20 | B96: Allow Overage | C96: Picklist | D96: R | F96: Based on which field this field value selection will happen? | G96: [RB] Attribute in the cart or from the Partner Account | H96: D | I96: Getting populated from APTS_ProposalTrigger_Handler Apex class.
A97: 21 | B97: MSP Partner Discount | C97: Percent | D97: E | F97: Who is responsible for providing input for this field and at which stage and in which all use cases, user will provide value for this field? | G97: [RB] Field on Partner Account | H97: A
A98: 22 | B98: Bulk Draw Down? | C98: Checkbox | D98: R | F98: How this field value will be set to True? | G98: [RB] Field on Partner Account | H98: A
A99: 23 | B99: Partner Tier | C99: Text | D99: R | E99: It is a formula field and fetching value from Bill To Account | H99: A
A100: 24 | B100: Contract Status | C100: Picklist | D100: R | E100: Track partner contract state - Copies from Account to Proposal Control partner program eligibility - Specific statuses enable discounts and partner benefits Activate partner contracts - Signed statuses trigger various discount and configuration settings Reset on finalization - Cleared when cart is finalized for certain deal types Key Contract Statuses recognized: 'Signed DC POF' 'Amendment/Other - Signed' 'MPA Agreed (Click-through)' 'MRA -Signed' 'TSG MRA' 'Pending DC POF' (set by the system) The field serves as a critical control point for determining whether partner program discounts and settings should be applied to the Proposal. | F100: Based on which field this field value selection will happen? | G100: [RB] Field on Opty | H100: O
...

Sheet As Is Quote Backend fields
A1: NO | B1: Field Label | C1: API Name | D1: Data Type | E1: Field Type | F1: Is field Used ?? | G1: Forsys Comments
A2: 1 | B2: Record ID | C2: Id | D2: id | E2: Standard | F2: =VLOOKUP(C2,'Sheet 1'!$E$2:$F$92,2,FALSE) -> #N/A | G2: It can be replaced with standard RCA Quote Object field
A3: 2 | B3: Owner ID | C3: OwnerId | D3: Lookup (Group,User) | E3: Standard | F3: =VLOOKUP(C3,'Sheet 1'!$E$2:$F$92,2,FALSE) -> #N/A | G3: It can be replaced with standard RCA Quote Object field
A4: 3 | B4: Deleted | C4: IsDeleted | D4: Checkbox | E4: Standard | F4: =VLOOKUP(C4,'Sheet 1'!$E$2:$F$92,2,FALSE) -> #N/A | G4: It can be replaced with standard RCA Quote Object field
A5: 5 | B5: Currency ISO Code | C5: CurrencyIsoCode | D5: Picklist | E5: Standard | F5: =VLOOKUP(C5,'Sheet 1'!$E$2:$F$92,2,FALSE) -> #N/A
A6: 6 | B6: Record Type ID | C6: RecordTypeId | D6: Lookup (Record Type) | E6: Standard | F6: =VLOOKUP(C6,'Sheet 1'!$E$2:$F$92,2,FALSE) -> #N/A | G6: It can be replaced with standard RCA Quote Object field
A7: 7 | B7: Created Date | C7: CreatedDate | D7: Date/Time | E7: Standard | F7: =VLOOKUP(C7,'Sheet 1'!$E$2:$F$92,2,FALSE) -> #N/A | G7: It can be replaced with standard RCA Quote Object field
A8: 8 | B8: Created By ID | C8: CreatedById | D8: Lookup (User) | E8: Standard | F8: =VLOOKUP(C8,'Sheet 1'!$E$2:$F$92,2,FALSE) -> #N/A | G8: It can be replaced with standard RCA Quote Object field
A9: 9 | B9: Last Modified Date | C9: LastModifiedDate | D9: Date/Time | E9: Standard | F9: =VLOOKUP(C9,'Sheet 1'!$E$2:$F$92,2,FALSE) -> #N/A
A10: 10 | B10: Last Modified By ID | C10: LastModifiedById | D10: Lookup (User) | E10: Standard | F10: =VLOOKUP(C10,'Sheet 1'!$E$2:$F$92,2,FALSE) -> #N/A | G10: It can be replaced with standard RCA Quote Object field
A11: 11 | B11: System Modstamp | C11: SystemModstamp | D11: Date/Time | E11: Standard | F11: =VLOOKUP(C11,'Sheet 1'!$E$2:$F$92,2,FALSE) -> #N/A
A12: 12 | B12: Last Activity Date | C12: LastActivityDate | D12: Date | E12: Standard | F12: =VLOOKUP(C12,'Sheet 1'!$E$2:$F$92,2,FALSE) -> #N/A
A13: 13 | B13: Last Viewed Date | C13: LastViewedDate | D13: Date/Time | E13: Standard | F13: =VLOOKUP(C13,'Sheet 1'!$E$2:$F$92,2,FALSE) -> #N/A
A14: 14 | B14: Last Referenced Date | C14: LastReferencedDate | D14: Date/Time | E14: Standard | F14: =VLOOKUP(C14,'Sheet 1'!$E$2:$F$92,2,FALSE) -> #N/A
A15: 17 | B15: Create Agreement | C15: Apttus_Proposal__CreateAgreement__c | D15: Formula (Text) | E15: Custom | F15: =VLOOKUP(C15,'Sheet 1'!$E$2:$F$92,2,FALSE) -> #N/A | G15: Not Required in RCA
A16: 19 | B16: Discount % | C16: Apttus_Proposal__Discount_Percent__c | D16: Percent | E16: Custom | F16: =VLOOKUP(C16,'Sheet 1'!$E$2:$F$92,2,FALSE) -> not used
A17: 20 | B17: Expected End Date | C17: Apttus_Proposal__ExpectedEndDate__c | D17: Date | E17: Custom | F17: =VLOOKUP(C17,'Sheet 1'!$E$2:$F$92,2,FALSE) -> #N/A | G17: Used in apex:APTS_ProposalTrigger_Handler
A18: 22 | B18: Generate | C18: Apttus_Proposal__Generate__c | D18: Formula (Text) | E18: Custom | F18: =VLOOKUP(C18,'Sheet 1'!$E$2:$F$92,2,FALSE) -> #N/A | G18: Not Required in RCA
A19: 23 | B19: Grand Total | C19: Apttus_Proposal__Grand_Total__c | D19: Formula (Currency) | E19: Custom | F19: =VLOOKUP(C19,'Sheet 1'!$E$2:$F$92,2,FALSE) -> #N/A | G19: Do we have any standard field in RCA Quote object to capture the Quote Total?
A20: 24 | B20: Internal Deadline | C20: Apttus_Proposal__Internal_Deadline__c | D20: Date | E20: Custom | F20: =VLOOKUP(C20,'Sheet 1'!$E$2:$F$92,2,FALSE) -> not used
A21: 25 | B21: Make Primary | C21: Apttus_Proposal__MakePrimary__c | D21: Formula (Text) | E21: Custom | F21: =VLOOKUP(C21,'Sheet 1'!$E$2:$F$92,2,FALSE) -> #N/A | G21: It will be replaced with Start Sync action in RCA
A22: 26 | B22: Net Amount | C22: Apttus_Proposal__Net_Amount__c | D22: Formula (Currency) | E22: Custom | F22: =VLOOKUP(C22,'Sheet 1'!$E$2:$F$92,2,FALSE) -> #N/A | G22: Not Required in RCA
A23: 29 | B23: Present | C23: Apttus_Proposal__Present__c | D23: Formula (Text) | E23: Custom | F23: =VLOOKUP(C23,'Sheet 1'!$E$2:$F$92,2,FALSE) -> #N/A | G23: Not Required in RCA
A24: 30 | B24: Presented Date | C24: Apttus_Proposal__Presented_Date__c | D24: Date | E24: Custom | F24: =VLOOKUP(C24,'Sheet 1'!$E$2:$F$92,2,FALSE) -> #N/A | G24: No Reference
A25: 32 | B25: Primary Contact | C25: Apttus_Proposal__Primary_Contact__c | D25: Lookup (Contact) | E25: Custom | F25: =VLOOKUP(C25,'Sheet 1'!$E$2:$F$92,2,FALSE) -> #N/A
A26: 34 | B26: Proposal Approval Date | C26: Apttus_Proposal__Proposal_Approval_Date__c | D26: Date | E26: Custom | F26: =VLOOKUP(C26,'Sheet 1'!$E$2:$F$92,2,FALSE) -> not used
A27: 35 | B27: Proposal Category | C27: Apttus_Proposal__Proposal_Category__c | D27: Picklist | E27: Custom | F27: =VLOOKUP(C27,'Sheet 1'!$E$2:$F$92,2,FALSE) -> #N/A
A28: 36 | B28: Proposal Expiration Date | C28: Apttus_Proposal__Proposal_Expiration_Date__c | D28: Date | E28: Custom | F28: =VLOOKUP(C28,'Sheet 1'!$E$2:$F$92,2,FALSE) -> not used
A29: 38 | B29: RFP Intake Date | C29: Apttus_Proposal__RFP_Intake_Date__c | D29: Date | E29: Custom | F29: =VLOOKUP(C29,'Sheet 1'!$E$2:$F$92,2,FALSE) -> not used
A30: 39 | B30: RFP Response Due Date | C30: Apttus_Proposal__RFP_Response_Due_Date__c | D30: Date | E30: Custom | F30: =VLOOKUP(C30,'Sheet 1'!$E$2:$F$92,2,FALSE) -> not used
A31: 40 | B31: RFP Stage | C31: Apttus_Proposal__RFP_Stage__c | D31: Picklist | E31: Custom | F31: =VLOOKUP(C31,'Sheet 1'!$E$2:$F$92,2,FALSE) -> not used
A32: 41 | B32: RFP Value | C32: Apttus_Proposal__RFP_Value__c | D32: Currency | E32: Custom | F32: =VLOOKUP(C32,'Sheet 1'!$E$2:$F$92,2,FALSE) -> not used
A33: 42 | B33: Ready To Generate | C33: Apttus_Proposal__ReadyToGenerate__c | D33: Checkbox | E33: Custom | F33: =VLOOKUP(C33,'Sheet 1'!$E$2:$F$92,2,FALSE) -> #N/A
A34: 43 | B34: Ready To Present | C34: Apttus_Proposal__ReadyToPresent__c | D34: Checkbox | E34: Custom | F34: =VLOOKUP(C34,'Sheet 1'!$E$2:$F$92,2,FALSE) -> #N/A
A35: 44 | B35: Related Quote/Proposal | C35: Apttus_Proposal__RelatedProposalId__c | D35: Lookup (Quote/Proposal) | E35: Custom | F35: =VLOOKUP(C35,'Sheet 1'!$E$2:$F$92,2,FALSE) -> not used
A36: 45 | B36: Request Approval | C36: Apttus_Proposal__Request_Approval__c | D36: Formula (Text) | E36: Custom | F36: =VLOOKUP(C36,'Sheet 1'!$E$2:$F$92,2,FALSE) -> #N/A | G36: Not Required in RCA
A37: 46 | B37: Risk Factors | C37: Apttus_Proposal__Risk_Factors__c | D37: Picklist (Multi-Select) | E37: Custom | F37: =VLOOKUP(C37,'Sheet 1'!$E$2:$F$92,2,FALSE) -> not used
A38: 47 | B38: Sales Tax Amount | C38: Apttus_Proposal__Sales_Tax_Amount__c | D38: Formula (Currency) | E38: Custom | F38: =VLOOKUP(C38,'Sheet 1'!$E$2:$F$92,2,FALSE) -> #N/A | G38: Not Required in RCA
A39: 48 | B39: Sales Tax % | C39: Apttus_Proposal__Sales_Tax_Percent__c | D39: Percent | E39: Custom | F39: =VLOOKUP(C39,'Sheet 1'!$E$2:$F$92,2,FALSE) -> not used
A40: 49 | B40: Send Proposal | C40: Apttus_Proposal__SendProposal__c | D40: Formula (Text) | E40: Custom | F40: =VLOOKUP(C40,'Sheet 1'!$E$2:$F$92,2,FALSE) -> #N/A | G40: Not Required in RCA
A41: 50 | B41: Shipping & Handling | C41: Apttus_Proposal__Shipping_Handling__c | D41: Currency | E41: Custom | F41: =VLOOKUP(C41,'Sheet 1'!$E$2:$F$92,2,FALSE) -> not used
A42: 51 | B42: Special Terms | C42: Apttus_Proposal__Special_Terms__c | D42: Text Area | E42: Custom | F42: =VLOOKUP(C42,'Sheet 1'!$E$2:$F$92,2,FALSE) -> not used
A43: 52 | B43: Strategic Importance | C43: Apttus_Proposal__Strategic_Importance__c | D43: Picklist | E43: Custom | F43: =VLOOKUP(C43,'Sheet 1'!$E$2:$F$92,2,FALSE) -> not used
A44: 53 | B44: Submit For Approval | C44: Apttus_Proposal__SubmitForApproval__c | D44: Formula (Text) | E44: Custom | F44: =VLOOKUP(C44,'Sheet 1'!$E$2:$F$92,2,FALSE) -> #N/A | G44: It will be replaced with Submit for Approval action in RCA
A45: 55 | B45: Amount | C45: Apttus_Proposal__Amount__c | D45: Roll-Up Summary | E45: Custom | F45: =VLOOKUP(C45,'Sheet 1'!$E$2:$F$92,2,FALSE) -> #N/A | G45: it is a Roll -Up Summary
A46: 56 | B46: ABO Type | C46: Apttus_QPConfig__ABOType__c | D46: Picklist | E46: Custom | F46: =VLOOKUP(C46,'Sheet 1'!$E$2:$F$92,2,FALSE) -> #N/A
A47: 57 | B47: Accept | C47: Apttus_QPConfig__Accept__c | D47: Formula (Text) | E47: Custom | F47: =VLOOKUP(C47,'Sheet 1'!$E$2:$F$92,2,FALSE) -> #N/A | G47: It will be replaced with Create Order action in RCA
A48: 58 | B48: Auto Activate Order ? | C48: Apttus_QPConfig__AutoActivateOrder__c | D48: Checkbox | E48: Custom | F48: =VLOOKUP(C48,'Sheet 1'!$E$2:$F$92,2,FALSE) -> #N/A
A49: 59 | B49: Auto Create Bill ? | C49: Apttus_QPConfig__AutoCreateBill__c | D49: Checkbox | E49: Custom | F49: =VLOOKUP(C49,'Sheet 1'!$E$2:$F$92,2,FALSE) -> #N/A
A50: 60 | B50: Auto Create Revenue ? | C50: Apttus_QPConfig__AutoCreateRevenue__c | D50: Checkbox | E50: Custom | F50: =VLOOKUP(C50,'Sheet 1'!$E$2:$F$92,2,FALSE) -> #N/A
A51: 62 | B51: Billing Preference | C51: Apttus_QPConfig__BillingPreferenceId__c | D51: Lookup (Billing Preference) | E51: Custom | F51: =VLOOKUP(C51,'Sheet 1'!$E$2:$F$92,2,FALSE) -> #N/A
A52: 64 | B52: Configuration Sync Date | C52: Apttus_QPConfig__ConfigurationSyncDate__c | D52: Date/Time | E52: Custom | F52: =VLOOKUP(C52,'Sheet 1'!$E$2:$F$92,2,FALSE) -> not used
A53: 65 | B53: Configure Products (NG) | C53: Apttus_QPConfig__ConfigureNG__c | D53: Formula (Text) | E53: Custom | F53: =VLOOKUP(C53,'Sheet 1'!$E$2:$F$92,2,FALSE) -> #N/A
A54: 66 | B54: Configure Products | C54: Apttus_QPConfig__Configure__c | D54: Formula (Text) | E54: Custom | F54: =VLOOKUP(C54,'Sheet 1'!$E$2:$F$92,2,FALSE) -> #N/A
A55: 67 | B55: Intent | C55: Apttus_QPConfig__Intent__c | D55: Picklist | E55: Custom | F55: =VLOOKUP(C55,'Sheet 1'!$E$2:$F$92,2,FALSE) -> not used
A56: 68 | B56: Is Auto Accepted | C56: Apttus_QPConfig__IsAutoAccepted__c | D56: Checkbox | E56: Custom | F56: =VLOOKUP(C56,'Sheet 1'!$E$2:$F$92,2,FALSE) -> #N/A
A57: 69 | B57: Is System Generated | C57: Apttus_QPConfig__IsSystemGenerated__c | D57: Checkbox | E57: Custom | F57: =VLOOKUP(C57,'Sheet 1'!$E$2:$F$92,2,FALSE) -> #N/A
A58: 70 | B58: Is Task Pending | C58: Apttus_QPConfig__IsTaskPending__c | D58: Checkbox | E58: Custom | F58: =VLOOKUP(C58,'Sheet 1'!$E$2:$F$92,2,FALSE) -> #N/A
A59: 71 | B59: Legal Entity | C59: Apttus_QPConfig__LegalEntityId__c | D59: Lookup (Legal Entity) | E59: Custom | F59: =VLOOKUP(C59,'Sheet 1'!$E$2:$F$92,2,FALSE) -> not used
... A72: 86 | B72: Sync Asset Changes To Quote | C72: Apttus_QPConfig__SyncAssetChangesToQuote__c | D72: Checkbox | E72: Custom | F72: =VLOOKUP(C72,'Sheet 1'!$E$2:$F$92,2,FALSE) -> #N/A
A73: 87 | B73: Synchronize with Opportunity | C73: Apttus_QPConfig__SyncWithOpportunity__c | D73: Formula (Text) | E73: Custom | F73: =VLOOKUP(C73,'Sheet 1'!$E$2:$F$92,2,FALSE) -> #N/A | G73: It will be replaced with Sync with Opportunity action in RCA
A74: 88 | B74: Configure Products | C74: Apttus_QPAsset__ConfigureWithAssets__c | D74: Formula (Text) | E74: Custom | F74: =VLOOKUP(C74,'Sheet 1'!$E$2:$F$92,2,FALSE) -> #N/A
A75: 89 | B75: Approval Status | C75: Apttus_QPApprov__Approval_Status__c | D75: Picklist | E75: Custom | F75: =VLOOKUP(C75,'Sheet 1'!$E$2:$F$92,2,FALSE) -> #N/A | G75: Need to check with Ramesh if there is any standard field on RCA Quote object to track the Approval Status
A76: 90 | B76: Create Agreement With Line Items | C76: Apttus_QPComply__CreateAgreementWithLineItems__c | D76: Formula (Text) | E76: Custom | F76: =VLOOKUP(C76,'Sheet 1'!$E$2:$F$92,2,FALSE) -> #N/A
A77: 91 | B77: Master Agreement | C77: Apttus_QPComply__MasterAgreementId__c | D77: Lookup (Agreement) | E77: Custom | F77: =VLOOKUP(C77,'Sheet 1'!$E$2:$F$92,2,FALSE) -> not used
A78: 92 | B78: Check eSignature Status | C78: Apttus_QPDSign__CheckESignatureStatus__c | D78: Formula (Text) | E78: Custom | F78: =VLOOKUP(C78,'Sheet 1'!$E$2:$F$92,2,FALSE) -> #N/A
A79: 93 | B79: Recall E-Signature Request | C79: Apttus_QPDSign__RecallESignatureRequest__c | D79: Formula (Text) | E79: Custom | F79: =VLOOKUP(C79,'Sheet 1'!$E$2:$F$92,2,FALSE) -> #N/A
A80: 94 | B80: Send For eSignature | C80: Apttus_QPDSign__SendForESignature__c | D80: Formula (Text) | E80: Custom | F80: =VLOOKUP(C80,'Sheet 1'!$E$2:$F$92,2,FALSE) -> #N/A | G80: It will be replaced with eSignature action in RCA
A81: 95 | B81: Correct E-Signature Document | C81: Apttus_QPDSign__ViewESignatureDocument__c | D81: Formula (Text) | E81: Custom | F81: =VLOOKUP(C81,'Sheet 1'!$E$2:$F$92,2,FALSE) -> #N/A
A82: 96 | B82: Accept Quote | C82: APTS_Accept_Quote__c | D82: Formula (Text) | E82: Custom | F82: =VLOOKUP(C82,'Sheet 1'!$E$2:$F$92,2,FALSE) -> #N/A | G82: It will be replaced with Create Order action in RCA. Need to consider the existing Formula
A83: 97 | B83: Account Billing Preference | C83: APTS_Account_Billing_Preference__c | D83: Formula (Text) | E83: Custom | F83: =VLOOKUP(C83,'Sheet 1'!$E$2:$F$92,2,FALSE) -> not used
A84: 102 | B84: Approval LoB | C84: APTS_Approval_LoB__c | D84: Formula (Text) | E84: Custom | F84: =VLOOKUP(C84,'Sheet 1'!$E$2:$F$92,2,FALSE) -> #N/A
A85: 103 | B85: Approved 1st Year Price | C85: APTS_Approved_1st_Year_Price__c | D85: Currency | E85: Custom | F85: =VLOOKUP(C85,'Sheet 1'!$E$2:$F$92,2,FALSE) -> not used
A86: 104 | B86: Basic Growth Percent | C86: APTS_Basic_Growth_Percent__c | D86: Formula (Percent) | E86: Custom | F86: =VLOOKUP(C86,'Sheet 1'!$E$2:$F$92,2,FALSE) -> #N/A
A87: 105 | B87: Basic Growth | C87: APTS_Basic_Growth__c | D87: Number (16, 2) | E87: Custom | F87: =VLOOKUP(C87,'Sheet 1'!$E$2:$F$92,2,FALSE) -> not used
A88: 107 | B88: Billing Country Code | C88: APTS_Billing_Country_Code__c | D88: Formula (Text) | E88: Custom | F88: =VLOOKUP(C88,'Sheet 1'!$E$2:$F$92,2,FALSE) -> #N/A
A89: 108 | B89: Cart Needs Repricing | C89: APTS_Cart_Needs_Repricing__c | D89: Checkbox | E89: Custom | F89: =VLOOKUP(C89,'Sheet 1'!$E$2:$F$92,2,FALSE) -> #N/A | G89: Used in apex:APTS_ProposalTrigger_Handler
A90: 109 | B90: Configure DC Cart | C90: APTS_Configure_DC_Cart__c | D90: Formula (Text) | E90: Custom | F90: =VLOOKUP(C90,'Sheet 1'!$E$2:$F$92,2,FALSE) -> #N/A | G90: It will be replaced with Browse catalog action in RCA. Need to consider the existing Formula
A91: 111 | B91: Create Order Form/MSA | C91: APTS_Create_Order_Form_MSA__c | D91: Formula (Text) | E91: Custom | F91: =VLOOKUP(C91,'Sheet 1'!$E$2:$F$92,2,FALSE) -> #N/A | G91: It can be replaced with Create Agreement RCA action. Need to check with Karthik that do we need to consider the existing Formula or not?
A92: 112 | B92: Custom Payment Term Value | C92: APTS_Custom_Payment_Term_Value__c | D92: Formula (Number) | E92: Custom | F92: =VLOOKUP(C92,'Sheet 1'!$E$2:$F$92,2,FALSE) -> #N/A
A93: 113 | B93: Custom Payment Terms | C93: APTS_Custom_Payment_Terms__c | D93: Text | E93: Custom | F93: =VLOOKUP(C93,'Sheet 1'!$E$2:$F$92,2,FALSE) -> not used
A94: 116 | B94: ELA Calculator Version Counter | C94: APTS_ELA_Calculator_Version_Counter__c | D94: Number (18, 0) | E94: Custom | F94: =VLOOKUP(C94,'Sheet 1'!$E$2:$F$92,2,FALSE) -> #N/A | G94: No Reference
A95: 117 | B95: Generate & Send Proposal | C95: APTS_Generate_Send_Proposal__c | D95: Formula (Text) | E95: Custom | F95: =VLOOKUP(C95,'Sheet 1'!$E$2:$F$92,2,FALSE) -> #N/A | G95: It can be replaced with Generate action in RCA but need to check with Neelima/Karthik that do we need to consider the existing Formula or not
A96: 118 | B96: Has PKI | C96: APTS_Has_PKI__c | D96: Checkbox | E96: Custom | F96: =VLOOKUP(C96,'Sheet 1'!$E$2:$F$92,2,FALSE) -> #N/A | G96: Used in apex:APTS_ProposalTrigger_Handler
A97: 119 | B97: Is Default Currency? | C97: APTS_Is_Default_Currency__c | D97: Formula (Checkbox) | E97: Custom | F97: =VLOOKUP(C97,'Sheet 1'!$E$2:$F$92,2,FALSE) -> #N/A
A98: 120 | B98: Legal Entity Name | C98: APTS_Legal_Entity_Name__c | D98: Formula (Text) | E98: Custom | F98: =VLOOKUP(C98,'Sheet 1'!$E$2:$F$92,2,FALSE) -> #N/A
A99: 121 | B99: My Approvals | C99: APTS_My_Approvals__c | D99: Formula (Text) | E99: Custom | F99: =VLOOKUP(C99,'Sheet 1'!$E$2:$F$92,2,FALSE) -> #N/A | G99: It can be replaced with standard Approvals action to check the status of Approval Request
A100: 122 | B100: Opportunity Currency | C100: APTS_Opportunity_CurrencyIsoCode__c | D100: Formula (Text) | E100: Custom | F100: =VLOOKUP(C100,'Sheet 1'!$E$2:$F$92,2,FALSE) -> #N/A
A101: 123 | B101: PKI Sales Leader Region | C101: APTS_PKI_Sales_Leader_Region__c | D101: Formula (Text) | E101: Custom | F101: =VLOOKUP(C101,'Sheet 1'!$E$2:$F$92,2,FALSE) -> #N/A
A102: 124 | B102: Predicted Growth Percentage | C102: APTS_Predicted_Growth_Percentage__c | D102: Formula (Percent) | E102: Custom | F102: =VLOOKUP(C102,'Sheet 1'!$E$2:$F$92,2,FALSE) -> #N/A
A103: 125 | B103: Predicted Growth | C103: APTS_Predicted_Growth__c | D103: Number (3, 3) | E103: Custom | F103: =VLOOKUP(C103,'Sheet 1'!$E$2:$F$92,2,FALSE) -> not used
A104: 126 | B104: Predicted Quota Growth Percentage | C104: APTS_Predicted_Quota_Growth_Percentage__c | D104: Formula (Percent) | E104: Custom | F104: =VLOOKUP(C104,'Sheet 1'!$E$2:$F$92,2,FALSE) -> #N/A
A105: 127 | B105: Predicted Quota Growth | C105: APTS_Predicted_Quota_Growth__c | D105: Number (3, 3) | E105: Custom | F105: =VLOOKUP(C105,'Sheet 1'!$E$2:$F$92,2,FALSE) -> not used
A106: 128 | B106: Preview & Submit Approvals | C106: APTS_Preview_Submit_Approvals__c | D106: Formula (Text) | E106: Custom | F106: =VLOOKUP(C106,'Sheet 1'!$E$2:$F$92,2,FALSE) -> #N/A | G106: Need to check with Karthik/Neelima if we are going to provide Preview functionality or are we going to allow Generate Quote Template before Quote Approvals in RCA. If Yes we might need to consider the existing Formula
A107: 131 | B107: Progress Chevron | C107: APTS_Progress_Chevron__c | D107: Formula (Text) | E107: Custom | F107: =VLOOKUP(C107,'Sheet 1'!$E$2:$F$92,2,FALSE) -> #N/A | G107: Need to check with Neelima that do we need to consider the Progress Chevron images from Existing system or will it be OOTB RCA?
A108: 132 | B108: Quote LoB | C108: APTS_Quote_LoB__c | D108: Picklist | E108: Custom | F108: =VLOOKUP(C108,'Sheet 1'!$E$2:$F$92,2,FALSE) -> #N/A | G108: Used in apex:APTS_ProposalTrigger_Handler It is used in Approval Rules
A109: 133 | B109: Opportunity Owner Manager ID | C109: APTS_Quote_Owner_Manager_ID__c | D109: Formula (Text) | E109: Custom | F109: =VLOOKUP(C109,'Sheet 1'!$E$2:$F$92,2,FALSE) -> #N/A
A110: 134 | B110: SSL Sales Leader ID | C110: APTS_SSL_Sales_Leader_ID__c | D110: Formula (Text) | E110: Custom | F110: =VLOOKUP(C110,'Sheet 1'!$E$2:$F$92,2,FALSE) -> #N/A
A111: 135 | B111: SS Pro Growth Percent | C111: APTS_SS_Pro_Growth_Percent__c | D111: Formula (Percent) | E111: Custom | F111: =VLOOKUP(C111,'Sheet 1'!$E$2:$F$92,2,FALSE) -> #N/A
A112: 136 | B112: SS Pro Growth | C112: APTS_SS_Pro_Growth__c | D112: Number (10, 4) | E112: Custom | F112: =VLOOKUP(C112,'Sheet 1'!$E$2:$F$92,2,FALSE) -> not used
...

Sheet Product Configuration-Analysis
A1: Field Label | B1: API Name | C1: Data Type | D1: Comments (Line Item Obj) | E1: Apex Classes | F1: Flow | G1: Custom Field (On Product Configuration Object) 1 | H1: Custom Field (On Product Configuration Object) 2 | I1: Custom Field (On Line Item Object) 1 | J1: Custom Field (On Line Item Object) 2 | K1: Custom Field (On Product Attribute Value) 1
A2: Record ID | B2: Id | C2: id
A3: Owner ID | B3: OwnerId | C3: Lookup (Group,User)
A4: Deleted | B4: IsDeleted | C4: Checkbox
A5: Configuration Name | B5: Name | C5: Text
A6: Currency ISO Code | B6: CurrencyIsoCode | C6: Picklist
A7: Created Date | B7: CreatedDate | C7: Date/Time
A8: Created By ID | B8: CreatedById | C8: Lookup (User)
A9: Last Modified Date | B9: LastModifiedDate | C9: Date/Time
A10: Last Modified By ID | B10: LastModifiedById | C10: Lookup (User)
A11: System Modstamp | B11: SystemModstamp | C11: Date/Time
A12: Last Activity Date | B12: LastActivityDate | C12: Date
A13: Sold To | B13: Apttus_Config2__AccountId__c | C13: Lookup (Account)
... A37: Intent | B37: Apttus_Config2__Intent__c | C37: Picklist
A38: Is Price Pending | B38: Apttus_Config2__IsPricePending__c | C38: Checkbox | D38: The field is referenced only in a Flow | F38: Product Configuration Before Save Handler
A39: Is Task Pending | B39: Apttus_Config2__IsTaskPending__c | C39: Checkbox
A40: Is Transient | B40: Apttus_Config2__IsTransient__c | C40: Checkbox
A41: Is Validation Pending | B41: Apttus_Config2__IsValidationPending__c | C41: Checkbox
A42: Legal Entity | B42: Apttus_Config2__LegalEntityId__c | C42: Lookup (Legal Entity)
A43: Line Items Awaiting Price | B43: Apttus_Config2__LineItemsAwaitingPrice__c | C43: Text
A44: Location | B44: Apttus_Config2__LocationId__c | C44: Lookup (Account Location)
A45: Order | B45: Apttus_Config2__OrderId__c | C45: Lookup (Apttus Order)
A46: Parent Configuration | B46: Apttus_Config2__ParentConfigurationId__c | C46: Lookup (Product Configuration)
A47: Payment Term | B47: Apttus_Config2__PaymentTermId__c | C47: Lookup (Payment Term)
A48: Price List | B48: Apttus_Config2__PriceListId__c | C48: Lookup (Price List)
A49: Primordial | B49: Apttus_Config2__PrimordialId__c | C49: Lookup (Product Configuration)
A50: Purchase Identifier | B50: Apttus_Config2__PurchaseId__c | C50: Text
... A53: Ship To | B53: Apttus_Config2__ShipToAccountId__c | C53: Lookup (Account)
A54: Status | B54: Apttus_Config2__Status__c | C54: Picklist | D54: The field is referenced only in a Flow and Apex class | E54: APTS_ELACalculatorLaunchController, APTS_ProposalTrigger_Handler, APTS_ValidationCallback, APTS_ValidationCallbackTest, APTS_RampLineNumberBatchTest, APTS_AnnualSummaryUpdate_Batch, APTS_AnnualSummaryUpdate_BatchTest, APTS_ValidationCallbackTestNew | F54: Populate Quote/Proposal fields after finalization, Proposal Line Item Before Save Flow
A55: Summary Group Type | B55: Apttus_Config2__SummaryGroupType__c | C55: Picklist
A56: Use Type | B56: Apttus_Config2__UseType__c | C56: Picklist
A57: Version Number | B57: Apttus_Config2__VersionNumber__c | C57: Number (4, 0) | D57: The field is referenced only in a Apex class | E57: APTS_ProposalTrigger_Handler
A58: Base Relation Count | B58: Apttus_Config2__BaseRelationCount__c | C58: Roll-Up Summary
A59: Number Of Items | B59: Apttus_Config2__NumberOfItems__c | C59: Roll-Up Summary
A60: Quote/Proposal | B60: Apttus_QPConfig__Proposald__c | C60: Lookup (Quote/Proposal)
A61: Agreement | B61: Apttus_CMConfig__AgreementId__c | C61: Lookup (Agreement)
A62: Approval Preview Status | B62: Apttus_CQApprov__Approval_Preview_Status__c | C62: Picklist
A63: Approval Status | B63: Apttus_CQApprov__Approval_Status__c | C63: Picklist
A64: Business Object Reference | B64: Apttus_CQApprov__BusinessObjectRefId__c | C64: Text
A65: Line Item Approval Status | B65: Apttus_CQApprov__LineItem_Approval_Status__c | C65: Picklist
A66: Current User LoB | B66: APTS_Current_User_LoB__c | C66: Formula (Text)
A67: Deal Type | B67: APTS_Deal_Type__c | C67: Formula (Text)
A68: Split Criteria Key | B68: Apttus_Config2__SplitCriteriaKey__c | C68: Text
A69: Task Completed Date | B69: Apttus_Config2__TaskCompletedDate__c | C69: Date/Time
... A81: Min Start Date | B81: APTS_Min_Start_Date__c | C81: Roll-Up Summary
A82: Temp Digicert Branded Discounts | B82: APTS_Temp_Digicert_Branded_Discounts__c | C82: Percent | D82: The field is referenced only in a Apex class | E82: APTS_ProductAttributeValueTriggerHandler
A83: Max End Date | B83: APTS_Max_End_Date__c | C83: Roll-Up Summary
A84: Temp fulfilment/unregistered discount | B84: APTS_Temp_fulfilment_unreg_discount__c | C84: Percent | D84: The field is referenced only in a Apex class | E84: APTS_ProductAttributeValueTriggerHandler
A85: Temp Velocity Branded Discount | B85: APTS_Temp_Velocity_Branded_Discount__c | C85: Percent
A86: Opportunity Alliance Involved | B86: APTS_Opportunity_Alliance_Involved__c | C86: Formula (Text)
A87: Alliance Involved | B87: APTS_Alliance_Involved__c | C87: Text
A88: PendingTask | B88: Apttus_Config2__PendingTask__c | C88: Picklist
A89: Account Segment | B89: APTS_Account_Segment__c | C89: Formula (Text)
A90: Paid Support Existing Deal Check | B90: APTS_Paid_Support_Existing_Deal_Check__c | C90: Formula (Text)
A91: Basic Support Count | B91: APTS_Basic_Support_Count__c | C91: Roll-Up Summary
A92: Deprecated Support Product Count | B92: APTS_Deprecated_Support_Product_Count__c | C92: Roll-Up Summary
A93: Digicert Business Support Count | B93: APTS_Digicert_Business_Support_Count__c | C93: Roll-Up Summary
A94: Digicert Premium Support Count | B94: APTS_Digicert_Premium_Support_Count__c | C94: Roll-Up Summary
A95: Digicert Standard Support Count | B95: APTS_Digicert_Standard_Support_Count__c | C95: Roll-Up Summary
A96: Total Net Price (Premium Support) | B96: APTS_Total_Net_Price_Premium_Support__c | C96: Roll-Up Summary
... A101: Total Net Price (Premium Support) USD | B101: APTS_Total_Net_Price_Premium_Support_USD__c | C101: Formula (Currency)
A102: Temp Deal Registration Discount | B102: APTS_Temp_Seat_based_discount__c | C102: Percent | D102: The field is referenced only in a Apex class | E102: APTS_ProductAttributeValueTriggerHandler
A103: Maximum End Date (Primary Lines) | B103: APTS_Maximum_End_Date_Primary_Lines__c | C103: Roll-Up Summary
A104: Maximum Start Date (Primary Lines) | B104: APTS_Maximum_Start_Date_Primary_Lines__c | C104: Roll-Up Summary
A105: Minimum End Date (Primary Lines) | B105: APTS_Minimum_End_Date_Primary_Lines__c | C105: Roll-Up Summary
A106: Minimum Start Date (Primary Lines) | B106: APTS_Minimum_Start_Date_Primary_Lines__c | C106: Roll-Up Summary
A107: Start and End Date Check | B107: APTS_Start_and_End_Date_Check__c | C107: Formula (Checkbox)
A108: Total Cert Based Standalone Prod Count | B108: APTS_TotalCertBasedStandalone_Prod_Count__c | C108: Roll-Up Summary
A109: Total Cert Based Bundle Product Count | B109: APTS_Total_Cert_Based_Bundle_Prod_Count__c | C109: Roll-Up Summary
A110: Total Count Of Primary Lines | B110: APTS_Total_Count_Of_Primary_Lines__c | C110: Roll-Up Summary
A111: Total Seat Based Product Count | B111: APTS_Total_Seat_Based_Product_Count__c | C111: Roll-Up Summary
A112: 1st Year Seat Based Support Delta Amount | B112: APTS_1stYearSeatBasedSupportDeltaAmount__c | C112: Currency | D112: The field is referenced only in a Flow | F112: Product Configuration Before Save Handler, Populate Quote/Proposal fields after finalization
A113: 1st Year Seat Based Support Net Amount | B113: APTS_1stYear_SeatBased_Support_NetAmount__c | C113: Currency | D113: The field is referenced only in a Flow | F113: Product Configuration Before Save Handler, Populate Quote/Proposal fields after finalization
A114: 1st Yr SeatBased Support Asset Net Price | B114: APTS_1stYrSeatBasedSupportAssetNetPrice__c | C114: Currency | D114: The field is referenced only in a Flow | F114: Product Configuration Before Save Handler, Populate Quote/Proposal fields after finalization
A115: 1st Year Seat Based Asset Net Price | B115: APTS_1st_Year_Seat_Based_Asset_Net_Price__c | C115: Currency | D115: The field is referenced only in a Flow | F115: Product Configuration Before Save Handler, Populate Quote/Proposal fields after finalization
A116: 1st Year Seat Based Delta Amount | B116: APTS_1st_Year_Seat_Based_Delta_Amount__c | C116: Currency | D116: The field is referenced only in a Flow | F116: Product Configuration Before Save Handler, Populate Quote/Proposal fields after finalization
A117: ABO Quote/Proposal Product Active Count | B117: APTS_ABO_QProposal_ProductActiveCount__c | C117: Number (18, 0) | D117: The field is referenced only in a Flow and Custom formula field | F117: Product Configuration Before Save Handler | G117: Check for Partial ABO = APTS_ABO_QProposal_ProductActiveCount__c <> APTS_Previous_QProposal_Active_Counts__c && TEXT(Apttus_QPConfig__Proposald__r.APTS_ABO_Type_Custom__c ) = 'Amendment'
A118: ABO Type | B118: APTS_ABO_Type_Custom__c | C118: Picklist | D118: The field is referenced only in a Flow and Custom formula field | F118: Product Configuration Before Save Handler, Populate Quote/Proposal fields after finalization | G118: Mismatch btwn ABO Type & Lines added = IF(CONTAINS(TEXT(APTS_ABO_Type_Custom__c ),"Amend") && (CONTAINS(TEXT( APTS_ABO_Cart_Type_Custom__c ),"Amend") || CONTAINS(TEXT( APTS_ABO_Cart_Type_Custom__c ),"New")),'No', IF(CONTAINS(TEXT(APTS_ABO_Type_Custom__c ),"Renew") && (APTS_Count_of_Renewed_Certs__c > 0 || APTS_Count_of_Renewed_Seat_based__c > 0 || APTS_Count_of_New_Certs__c > 0 || APTS_Count_of_New_Seat_based__c > 0)/*(CONTAINS(TEXT( APTS_ABO_Cart_Type_Custom__c ),"Renew") || CONTAINS(TEXT( APTS_ABO_Cart_Type_Custom__c ),"New"))*/,'No', IF(CONTAINS(TEXT(APTS_ABO_Type_Custom__c ),"Terminat") && CONTAINS(TEXT( APTS_ABO_Cart_Type_Custom__c ),"Terminat"),'No', IF(CONTAINS(TEXT(APTS_ABO_Type_Custom__c ),"New") && CONTAINS(TEXT( APTS_ABO_Cart_Type_Custom__c ),"New"),'No', IF(ISBLANK(TEXT(APTS_ABO_Cart_Type_Custom__c)) , 'No','Yes'))))) | I118: EffectiveAmendmentDate not earlier Check = IF( TEXT(Apttus_Config2__ConfigurationId__r.APTS_ABO_Type_Custom__c) = 'Amended' && NOT(ISBLANK(Apttus_Config2__AttributeValueId__r.APTS_Effective_Amendment_Date__c)) && NOT(ISBLANK(APTS_Asset_Effective_Amendment_Date__c)) && Apttus_Config2__AttributeValueId__r.APTS_Effective_Amendment_Date__c < APTS_Asset_Effective_Amendment_Date__c ,'Yes','No' )
A119: Amended Cert Count Price Decrease | B119: APTS_Amended_Cert_Count_Adj_Decrease__c | C119: Number (18, 0) | D119: The field is referenced only in a Flow | F119: Product Configuration Before Save Handler, Populate Quote/Proposal fields after finalization
A120: Amended Cert Count Qty -Decrease | B120: APTS_Amended_Cert_Count_Qty_Decrease__c | C120: Number (18, 0) | D120: The field is referenced only in a Flow | F120: Product Configuration Before Save Handler, Populate Quote/Proposal fields after finalization
A121: Amended Seat Count Price Decrease | B121: APTS_Amended_Seat_Count_Adj_Decrease__c | C121: Number (18, 0) | D121: The field is referenced only in a Flow | F121: Product Configuration Before Save Handler, Populate Quote/Proposal fields after finalization
A122: Amended Seat Count Qty -Decrease | B122: APTS_Amended_Seat_Count_Qty_Decrease__c | C122: Number (18, 0) | D122: The field is referenced only in a Flow | F122: Product Configuration Before Save Handler, Populate Quote/Proposal fields after finalization
A123: Annual Commit Discount | B123: APTS_Annual_Commit_Discount__c | C123: Percent | D123: The field is referenced only in a Flow | F123: Product Configuration Before Save Handler, Populate Quote/Proposal fields after finalization
A124: Asset Annual Commit Discount | B124: APTS_Asset_Annual_Commit_Discount__c | C124: Percent | D124: The field is referenced only in a Flow | F124: Product Configuration Before Save Handler, Populate Quote/Proposal fields after finalization
A125: Changed Support Amount | B125: APTS_Changed_Support_Amount__c | C125: Currency | D125: The field is referenced only in a Flow | F125: Product Configuration Before Save Handler, Populate Quote/Proposal fields after finalization
A126: Contract Template Selector | B126: APTS_Contract_Template_Selector__c | C126: Text | D126: The field is referenced only in a Flow, apex class and custom formula field | E126: APTS_ValidationCallbackTest, APTS_PricingCallback, APTS_ValidationCallbackTestNew | F126: Product Configuration Before Save Handler | G126: Throw Error on Cart for Partner deals? = Apttus_QPConfig__Proposald__r.APTS_Partner_Program_Eligible__c && NOT( Apttus_QPConfig__Proposald__r.APTS_Partner_Contract_Active__c ) && (ISPICKVAL( Apttus_QPConfig__Proposald__r.Apttus_Proposal__Opportunity__r.Partner_Sales_Motion__c , 'Sell-with') && Apttus_Config2__BillToAccountId__c <> Apttus_Config2__AccountId__c) && ISBLANK(APTS_Contract_Template_Selector__c) | H126: Partner Support Check = IF( NOT(ISBLANK(APTS_Partner_Tier__c)) && (TEXT(Apttus_QPConfig__Proposald__r.APTS_Deal_Type__c) = 'Indirect with Discretionary Discount' || TEXT(Apttus_QPConfig__Proposald__r.APTS_Deal_Type__c) = 'Indirect without Discretionary Discount') && (APTS_Contract_Template_Selector__c = 'PC' || APTS_Contract_Template_Selector__c = 'Ongoing' || APTS_Contract_Template_Selector__c = 'BULK-D'), 'Yes','No') | K126: Contract Type Selector (Configuration) = Apttus_Config2__LineItemId__r.Apttus_Config2__ConfigurationId__r.APTS_Contract_Template_Selector__c
A127: Contract fee Line COUNT | B127: APTS_Contract_fee_Line_COUNT__c | C127: Number (18, 0) | D127: The field is referenced only in a Flow and custom formula field | F127: Product Configuration Before Save Handler | G127: Fire Validation for Standalone SSL = APTS_N_of_SSL_Standalone_Products__c > 1 || (APTS_N_of_SSL_Standalone_Products__c >0 && APTS_Contract_fee_Line_COUNT__c > 0)
A128: Count of Amended Certs | B128: APTS_Count_of_Amended_Certs__c | C128: Number (18, 0) | D128: The field is referenced only in a Flow | F128: Product Configuration Before Save Handler, Populate Quote/Proposal fields after finalization
A129: Count of Amended Seat-based | B129: APTS_Count_of_Amended_Seat_based__c | C129: Number (18, 0) | D129: The field is referenced only in a Flow and custom formula field | F129: Product Configuration Before Save Handler, Populate Quote/Proposal fields after finalization | G129: OnlyNewLinesAdded_Warning = IF(Apttus_QPConfig__Proposald__r.Apttus_Proposal__Opportunity__r.RecordType.DeveloperName = 'Expansion' && APTS_Count_of_New_Seat_based__c > 0 && APTS_Count_of_Amended_Seat_based__c = 0,'Amendment' ,IF(Apttus_QPConfig__Proposald__r.Apttus_Proposal__Opportunity__r.RecordType.DeveloperName = 'Renewal' && APTS_Count_of_New_Seat_based__c > 0 && APTS_Count_of_Renewed_Seat_based__c = 0,'Renewal','None') )
A130: Count of Cancelled Certs | B130: APTS_Count_of_Cancelled_Certs__c | C130: Number (18, 0) | D130: The field is referenced only in a Flow and custom formula field | F130: Product Configuration Before Save Handler, Populate Quote/Proposal fields after finalization | I130: Termination CR Criteria = IF( (Apttus_Config2__ConfigurationId__r.APTS_Count_of_Cancelled_Certs__c > 0 || Apttus_Config2__ConfigurationId__r.APTS_Count_of_Cancelled_Seat_based__c > 0) && Apttus_Config2__ConfigurationId__r.APTS_Quote_ABO_Type__c = 'Amendment' && APTS_Product_Code__c <> 'SUP - 1' && TEXT(Apttus_Config2__LineStatus__c) = 'Cancelled' && Apttus_Config2__IsOptionRollupLine__c = false,'Yes','No') | J130: Support Termination CR = IF( Apttus_Config2__ConfigurationId__r.APTS_Count_of_Cancelled_Certs__c > 0 && Apttus_Config2__ConfigurationId__r.APTS_Digicert_Business_Support_Count__c = 0 && Apttus_Config2__ConfigurationId__r.APTS_Digicert_Business_Supprt_Plus_Count__c = 0 && Apttus_Config2__ConfigurationId__r.APTS_Digicert_Premium_Support_Count__c = 0 && Apttus_Config2__ConfigurationId__r.APTS_Digicert_Standard_Support_Count__c = 0 && TEXT(Apttus_Config2__LineType__c) = 'Option' && Apttus_Config2__ConfigurationId__r.APTS_Quote_ABO_Type__c = 'Amendment' && CONTAINS(APTS_Product_Code__c, 'SUP -') && TEXT(Apttus_Config2__LineStatus__c) = 'Cancelled' && Apttus_Config2__IsOptionRollupLine__c = false,'Yes','No')
A131: Count of Cancelled Seat-based | B131: APTS_Count_of_Cancelled_Seat_based__c | C131: Number (18, 0) | D131: The field is referenced only in a Flow and custom formula field | F131: Product Configuration Before Save Handler, Populate Quote/Proposal fields after finalization | I131: Termination CR Criteria = IF( (Apttus_Config2__ConfigurationId__r.APTS_Count_of_Cancelled_Certs__c > 0 || Apttus_Config2__ConfigurationId__r.APTS_Count_of_Cancelled_Seat_based__c > 0) && Apttus_Config2__ConfigurationId__r.APTS_Quote_ABO_Type__c = 'Amendment' && APTS_Product_Code__c <> 'SUP - 1' && TEXT(Apttus_Config2__LineStatus__c) = 'Cancelled' && Apttus_Config2__IsOptionRollupLine__c = false,'Yes','No')
A132: Count of New Certs | B132: APTS_Count_of_New_Certs__c | C132: Number (18, 0) | G132: Mismatch btwn ABO Type & Lines added = IF(CONTAINS(TEXT(APTS_ABO_Type_Custom__c ),"Amend") && (CONTAINS(TEXT( APTS_ABO_Cart_Type_Custom__c ),"Amend") || CONTAINS(TEXT( APTS_ABO_Cart_Type_Custom__c ),"New")),'No', IF(CONTAINS(TEXT(APTS_ABO_Type_Custom__c ),"Renew") && (APTS_Count_of_Renewed_Certs__c > 0 || APTS_Count_of_Renewed_Seat_based__c > 0 || APTS_Count_of_New_Certs__c > 0 || APTS_Count_of_New_Seat_based__c > 0)/*(CONTAINS(TEXT( APTS_ABO_Cart_Type_Custom__c ),"Renew") || CONTAINS(TEXT( APTS_ABO_Cart_Type_Custom__c ),"New"))*/,'No', IF(CONTAINS(TEXT(APTS_ABO_Type_Custom__c ),"Terminat") && CONTAINS(TEXT( APTS_ABO_Cart_Type_Custom__c ),"Terminat"),'No', IF(CONTAINS(TEXT(APTS_ABO_Type_Custom__c ),"New") && CONTAINS(TEXT( APTS_ABO_Cart_Type_Custom__c ),"New"),'No', IF(ISBLANK(TEXT(APTS_ABO_Cart_Type_Custom__c)) , 'No','Yes')))))
A133: Count of New Seat-based | B133: APTS_Count_of_New_Seat_based__c | C133: Number (18, 0) | D133: The field is referenced only in a Flow and custom formula field | F133: Product Configuration Before Save Handler, Populate Quote/Proposal fields after finalization | G133: Mismatch btwn ABO Type & Lines added = IF(CONTAINS(TEXT(APTS_ABO_Type_Custom__c ),"Amend") && (CONTAINS(TEXT( APTS_ABO_Cart_Type_Custom__c ),"Amend") || CONTAINS(TEXT( APTS_ABO_Cart_Type_Custom__c ),"New")),'No', IF(CONTAINS(TEXT(APTS_ABO_Type_Custom__c ),"Renew") && (APTS_Count_of_Renewed_Certs__c > 0 || APTS_Count_of_Renewed_Seat_based__c > 0 || APTS_Count_of_New_Certs__c > 0 || APTS_Count_of_New_Seat_based__c > 0)/*(CONTAINS(TEXT( APTS_ABO_Cart_Type_Custom__c ),"Renew") || CONTAINS(TEXT( APTS_ABO_Cart_Type_Custom__c ),"New"))*/,'No', IF(CONTAINS(TEXT(APTS_ABO_Type_Custom__c ),"Terminat") && CONTAINS(TEXT( APTS_ABO_Cart_Type_Custom__c ),"Terminat"),'No', IF(CONTAINS(TEXT(APTS_ABO_Type_Custom__c ),"New") && CONTAINS(TEXT( APTS_ABO_Cart_Type_Custom__c ),"New"),'No', IF(ISBLANK(TEXT(APTS_ABO_Cart_Type_Custom__c)) , 'No','Yes'))))) | H133: OnlyNewLinesAdded_Warning = IF(Apttus_QPConfig__Proposald__r.Apttus_Proposal__Opportunity__r.RecordType.DeveloperName = 'Expansion' && APTS_Count_of_New_Seat_based__c > 0 && APTS_Count_of_Amended_Seat_based__c = 0,'Amendment' ,IF(Apttus_QPConfig__Proposald__r.Apttus_Proposal__Opportunity__r.RecordType.DeveloperName = 'Renewal' && APTS_Count_of_New_Seat_based__c > 0 && APTS_Count_of_Renewed_Seat_based__c = 0,'Renewal','None') )
A134: Count of Renewed Certs | B134: APTS_Count_of_Renewed_Certs__c | C134: Number (18, 0) | D134: The field is referenced only in a Flow and custom formula field | F134: Product Configuration Before Save Handler, Populate Quote/Proposal fields after finalization | G134: Mismatch btwn ABO Type & Lines added = IF(CONTAINS(TEXT(APTS_ABO_Type_Custom__c ),"Amend") && (CONTAINS(TEXT( APTS_ABO_Cart_Type_Custom__c ),"Amend") || CONTAINS(TEXT( APTS_ABO_Cart_Type_Custom__c ),"New")),'No', IF(CONTAINS(TEXT(APTS_ABO_Type_Custom__c ),"Renew") && (APTS_Count_of_Renewed_Certs__c > 0 || APTS_Count_of_Renewed_Seat_based__c > 0 || APTS_Count_of_New_Certs__c > 0 || APTS_Count_of_New_Seat_based__c > 0)/*(CONTAINS(TEXT( APTS_ABO_Cart_Type_Custom__c ),"Renew") || CONTAINS(TEXT( APTS_ABO_Cart_Type_Custom__c ),"New"))*/,'No', IF(CONTAINS(TEXT(APTS_ABO_Type_Custom__c ),"Terminat") && CONTAINS(TEXT( APTS_ABO_Cart_Type_Custom__c ),"Terminat"),'No', IF(CONTAINS(TEXT(APTS_ABO_Type_Custom__c ),"New") && CONTAINS(TEXT( APTS_ABO_Cart_Type_Custom__c ),"New"),'No', IF(ISBLANK(TEXT(APTS_ABO_Cart_Type_Custom__c)) , 'No','Yes')))))
A135: Count of Renewed Seat-based | B135: APTS_Count_of_Renewed_Seat_based__c | C135: Number (18, 0) | D135: The field is referenced only in a Flow and custom formula field | F135: Product Configuration Before Save Handler, Populate Quote/Proposal fields after finalization | G135: Mismatch btwn ABO Type & Lines added = IF(CONTAINS(TEXT(APTS_ABO_Type_Custom__c ),"Amend") && (CONTAINS(TEXT( APTS_ABO_Cart_Type_Custom__c ),"Amend") || CONTAINS(TEXT( APTS_ABO_Cart_Type_Custom__c ),"New")),'No', IF(CONTAINS(TEXT(APTS_ABO_Type_Custom__c ),"Renew") && (APTS_Count_of_Renewed_Certs__c > 0 || APTS_Count_of_Renewed_Seat_based__c > 0 || APTS_Count_of_New_Certs__c > 0 || APTS_Count_of_New_Seat_based__c > 0)/*(CONTAINS(TEXT( APTS_ABO_Cart_Type_Custom__c ),"Renew") || CONTAINS(TEXT( APTS_ABO_Cart_Type_Custom__c ),"New"))*/,'No', IF(CONTAINS(TEXT(APTS_ABO_Type_Custom__c ),"Terminat") && CONTAINS(TEXT( APTS_ABO_Cart_Type_Custom__c ),"Terminat"),'No', IF(CONTAINS(TEXT(APTS_ABO_Type_Custom__c ),"New") && CONTAINS(TEXT( APTS_ABO_Cart_Type_Custom__c ),"New"),'No', IF(ISBLANK(TEXT(APTS_ABO_Cart_Type_Custom__c)) , 'No','Yes'))))) | H135: OnlyNewLinesAdded_Warning = IF(Apttus_QPConfig__Proposald__r.Apttus_Proposal__Opportunity__r.RecordType.DeveloperName = 'Expansion' && APTS_Count_of_New_Seat_based__c > 0 && APTS_Count_of_Amended_Seat_based__c = 0,'Amendment' ,IF(Apttus_QPConfig__Proposald__r.Apttus_Proposal__Opportunity__r.RecordType.DeveloperName = 'Renewal' && APTS_Count_of_New_Seat_based__c > 0 && APTS_Count_of_Renewed_Seat_based__c = 0,'Renewal','None') )
A136: Overall Total Delta Amount | B136: APTS_Delta_Net_Amount__c | C136: Currency | D136: The field is referenced only in a Flow | F136: Product Configuration Before Save Handler, Populate Quote/Proposal fields after finalization
A137: Has SSL? | B137: APTS_Has_SSL__c | C137: Checkbox | D137: The field is referenced only in a Flow | F137: Product Configuration Before Save Handler, Populate Quote/Proposal fields after finalization
A138: # of SSL Standalone Products | B138: APTS_N_of_SSL_Standalone_Products__c | C138: Number (18, 0) | D138: The field is referenced only in a Flow and custom formula field | F138: Product Configuration Before Save Handler | G138: Fire Validation for Standalone SSL = APTS_N_of_SSL_Standalone_Products__c > 1 || (APTS_N_of_SSL_Standalone_Products__c >0 && APTS_Contract_fee_Line_COUNT__c > 0)
A139: Original Order ID | B139: APTS_Original_Order_ID__c | C139: Text | D139: The field is referenced only in a Flow | F139: Product Configuration Before Save Handler, Populate Quote/Proposal fields after finalization
A140: Original Proposal ID | B140: APTS_Original_Proposal_ID__c | C140: Text | D140: The field is referenced only in a Flow | F140: Product Configuration Before Save Handler, Populate Quote/Proposal fields after finalization
...

Sheet To Be Quote Fields Layout
B1: Label | C1: Data Type | D1: ReadOnly/Editable | E1: Conga API | F1: RCA API | G1: RCA Label | H1: RCA Data Type | I1: Standard/Custom | J1: Layout field | K1: Comments | O1: Created or not | Q1: Approvals applicable field
A2: Quote Details section
A3: 1 | B3: Proposal ID | C3: Auto Number | D3: R | E3: Name | F3: QuoteNumber | G3: Quote Number | H3: Auto Number | I3: S | J3: Y
A4: 2 | B4: Owner | C4: Lookup (Group,User) | D4: E | E4: OwnerId | F4: OwnerId | G4: Owner ID | H4: Lookup (Group,User) | I4: S | J4: Y
A5: 3 | B5: Proposal Name | C5: Text | D5: E | E5: Apttus_Proposal__Proposal_Name__c | F5: Name | G5: Quote Name | H5: Text | I5: S | J5: Y
A6: 4 | B6: Quote Type | C6: Picklist | D6: E | E6: APTS_Quote_Type__c | F6: RCA_Quote_Type__c | G6: Quote Type | H6: Picklist | I6: C | J6: Y
A7: 5 | B7: Deal Type | C7: Picklist | D7: E | E7: APTS_Deal_Type__c | F7: RCA_Deal_Type__c | I7: C | J7: Y | Q7: Yes
A8: 6 | B8: Approval Stage | C8: Picklist | D8: R | E8: Apttus_Proposal__Approval_Stage__c | F8: Status | G8: Status | H8: Picklist | I8: S | J8: Y
A9: 7 | B9: Valid Until Date | C9: Date | D9: E | E9: Apttus_Proposal__Valid_Until_Date__c | G9: Expiration Date | H9: Date | I9: S | J9: Y
A10: 8 | B10: Primary | C10: Checkbox | D10: R | E10: Apttus_Proposal__Primary__c | G10: IsSyncing | H10: Checkbox | I10: S | J10: Y
A11: 9 | B11: Auto Renew | C11: Checkbox | D11: E | E11: APTS_Flat_Fee_Auto_Renew__c | F11: RCA_Flat_Fee_Auto_Renew__c | I11: C | J11: Y
A12: 10 | B12: Revert to Presented | D12: E | E12: APTS_Revert_to_Presented__c | K12: Not Required
A13: 11 | B13: CPI Adjustment | C13: Checkbox | D13: R | E13: APTS_CPI_Adjustment__c | F13: RCA_CPI_Adjustment__c | I13: C | J13: Y
A14: 12 | B14: Template Type | C14: Picklist | D14: E | E14: APTS_Template_Type__c | F14: RCA_Template_Type__c | G14: Template Type | H14: Picklist | J14: Y | K14: Do we need this field in To Be? (Pavan/Karthik)
A15: 13 | B15: Description | C15: Long Text Area | D15: E | E15: Apttus_Proposal__Description__c | I15: ? | J15: Y | K15: Do we need this field in To Be? (Pavan/Karthik)
A16: 14 | B16: Contract Type | C16: Picklist | D16: R | E16: APTS_Contract_Type_Values__c | F16: RCA_Contract_Type_Values__c | G16: Contract Type | H16: Picklist | I16: C | J16: Y
A17: 15 | B17: Credit Reason | C17: Picklist | D17: E | E17: APTS_Credit_Reason__c | F17: RCA_Credit_Reason__c | G17: Credit Reason | H17: Picklist | I17: C | J17: Y
A18: 16 | B18: Template Selection | C18: Picklist | D18: E | E18: APTS_Template_Selection__c | I18: ? | J18: Y | K18: Do we need this field in To Be? (Pavan/Karthik)
A19: 17 | B19: Credit Amount | C19: Currency | D19: R | E19: APTS_CREDIT_AMOUNT__c | F19: RCA_CREDIT_AMOUNT__c | G19: Credit Amount | H19: Currency | I19: C | J19: Y
A20: 18 | B20: Template Comments | C20: Long Text Area | D20: E | E20: APTS_Template_Comments__c | F20: RCA_Template_Comments__c | G20: Template Comments | H20: Long Text Area | I20: C | J20: Y
A21: 19 | B21: Approve Credit | C21: Formula (Checkbox) | D21: R | E21: APTS_APPLY_CREDIT__c | F21: RCA_APPLY_CREDIT__c | G21: Approve Credit | H21: Formula (Checkbox) | I21: C | J21: Y
A22: 20 | B22: Allow Multiple Agreements (OF & SFA) | C22: Checkbox | D22: E | E22: APTS_Multiple_Agreements_required__c | F22: RCA_Multiple_Agreements_required__c | G22: Allow Multiple Agreements (OF & SFA) | H22: Checkbox | I22: C | J22: Y
A23: 21 | B23: Disable Consumption Report View in CC | C23: Checkbox | D23: E | E23: APTS_DisableConsumptionReportViewinCertC__c | F23: RCA_DisableConsumptionReportViewinCertC__c | G23: Disable Consumption Report View in CC | H23: Checkbox | I23: C | J23: Y
A24: Account & Contact section (Need to rename as "Account, Contact & Address Information")
A25: 1 | B25: Opportunity | C25: Lookup (Opportunity) | D25: R | E25: Apttus_Proposal__Opportunity__c | G25: Opportunity ID | H25: Master-Detail (Opportunity) | I25: S | J25: Y
A26: 2 | B26: Quote Primary Contact | C26: Lookup (Contact) | D26: E | E26: APTS_Quote_Primary_Contact__c | F26: RCA_Quote_Primary_Contact__c | G26: Contact ID | H26: Lookup (Contact) | I26: S | J26: Y
A27: 3 | B27: Copy Primary Contact Address | C27: Checkbox | D27: E | E27: APTS_Copy_Primary_Contact_Address__c | I27: C | J27: Y | K27: Moved from Order to Quote
A28: 4 | B28: Account | C28: Lookup (Account) | D28: R | E28: Apttus_Proposal__Account__c | G28: Account ID | H28: Lookup (Account) | I28: S | J28: Y
A29: 5 | B29: Account Segment | C29: Formula (Text) | D29: R | E29: Account_Segment__c | F29: RCA__Account_Segment__c | I29: C | J29: Y
A30: 6 | B30: Account Payment Term | C30: Formula (Text) | D30: R | E30: APTS_Account_Payment_Term__c | F30: RCA_Account_Payment_Term__c | I30: C | J30: Y
A31: 7 | B31: Account Cert Central ID | C31: Formula (Text) | D31: R | E31: APTS_CertCentral_Acct_ID__c | F31: RCA_CertCentral_Acct_ID__c | I31: C | J31: Y
A32: 8 | B32: Payment Term | C32: Lookup (Payment Term) | D32: E | E32: Apttus_QPConfig__PaymentTermId__c | J32: Y
A33: 9 | B33: Bill To Partner / Distributor | C33: Lookup (Account) | D33: E | E33: APTS_Deal_Registration_Partner__c | F33: RCA_Deal_Registration_Partner__c | G33: Partner Account ID | H33: Lookup (Account) | I33: S | J33: Y
A34: 10 | B34: Partner Cert Central ID | C34: Formula (Text) | D34: R | E34: APTS_CertCentral_Partner_ID__c | F34: RCA_Partner_Cert_Central_ID__c | I34: C | J34: Y
A35: 11 | B35: Partner Channel | C35: Formula (Text) | D35: R | E35: APTS_Partner_Channel__c | F35: RCA_Partner_Channel__c | I35: C | J35: Y
A36: 12 | B36: Contract Type (Existing) | C36: Formula (Text) | D36: R | E36: APTS_Contract_Type_Existing__c | F36: RCA_Contract_Type_Existing__c | I36: C | J36: Y
A37: 13 | B37: Contract Start Date (Existing) | C37: Formula (Date) | D37: R | E37: APTS_Contract_Start_Date_Existing__c | F37: RCA_Contract_Start_Date_Existing__c | I37: C | J37: Y
A38: 14 | B38: Contract End Date (Existing) | C38: Formula (Date) | D38: R | E38: APTS_Contract_End_Date_Existing__c | F38: RCA_Contract_End_Date_Existing__c | I38: C | J38: Y
A39: 15 | B39: Marketplace Partner Account | C39: Lookup (Account) | D39: R | E39: APTS_MarketplacePartnerAccount__c | F39: RCA_MarketplacePartnerAccount__c | I39: C | J39: Y
A40: 16 | B40: Support Level (Existing) | C40: Formula (Text) | D40: R | E40: APTS_Support_Level_Account__c | F40: RCA_Support_Level_Account__c | I40: C | J40: Y
A41: 17 | B41: Support Level (New) | C41: Text | D41: R | E41: APTS_Quote_Support_Level__c | F41: RCA_Quote_Support_Level__c | I41: C | J41: Y
A42: 18 | B42: Previous Proposal | C42: Lookup (Quote/Proposal) | D42: E | E42: APTS_Previous_Proposal__c | F42: RCA_Previous_Proposal__c | I42: C | J42: Y | K42: It will be lookup to RCA Quote object
A43: 19 | B43: Previous Order | C43: Lookup (Apttus Order) | E43: APTS_Previous_Order__c | F43: RCA_Previous_Order__c | I43: C | J43: Y | K43: It will be lookup to RCA Order object
A44: 20 | B44: Account Credit Hold | C44: Formula (Checkbox) | D44: R | E44: APTS_Account_Credit_Hold__c | F44: RCA_Account_Credit_Hold__c | I44: C | J44: Y
A45: 21 | B45: Account Credit Check Status | C45: Formula (Text) | D45: R | E45: APTS_Account_Credit_Check_Status__c | F45: RCA_Account_Credit_Check_Status__c | I45: C | J45: Y
A46: 22 | B46: Bill To | C46: Lookup (Account) | D46: R | E46: Apttus_QPConfig__BillToAccountId__c | F46: RCA_QPConfig_BillToAccountId__c | I46: C | J46: Y | L46: RCA_BillToAccountId__c
A47: 23 | B47: Bill To (Local) | C47: Formula (Text) | D47: R | E47: APTS_Bill_To_Local__c | F47: RCA__Bill_To_Local__c | I47: C | J47: Y | K47: Moved from Order to Quote
A48: 24 | B48: Billing Contact | C48: Lookup (Contact) | E48: APTS_Billing_Contact__c | G48: Contact ID | H48: Lookup (Contact) | I48: S | J48: Y
A49: 25 | B49: Bill To Billing Legal Entity | C49: Formula (Text) | D49: R | E49: APTS_Bill_To_Billing_Legal_Entity__c | F49: RCA_Bill_To_Billing_Legal_Entity__c | I49: C | J49: Y
A50: 26 | B50: Bill To CertCentral Acct ID | C50: Formula (Text) | D50: R | E50: Bill_To_CertCentral_Acct_ID__c | F50: RCA_Bill_To_CertCentral_Acct_ID__c | K50: Moved from Order to Quote
A51: 27 | B51: Bill To Address | C51: Formula (Text) | E51: Bill_To_Address__c | F51: RCA_Bill_To_Address__c | K51: Moved from Order to Quote
A52: 28 | B52: Alt Bill To Address | C52: Text | E52: APTS_Alt_Bill_To_Address__c | F52: RCA_Alt_Bill_To_Address__c | K52: Moved from Order to Quote
A53: 29 | B53: Alt Bill To City | C53: Text | E53: APTS_Alt_Bill_To_City__c | F53: RCA_Alt_Bill_To_City__c | K53: Moved from Order to Quote
A54: 30 | B54: Alt Bill To State | C54: Picklist | E54: APTS_Alt_Bill_To_State__c | F54: RCA_Alt_Bill_To_State__c | K54: Moved from Order to Quote
A55: 31 | B55: Alt Bill To Postal Code | C55: Text | E55: APTS_Alt_Bill_To_Postal_Code__c | F55: RCA_Alt_Bill_To_Postal_Code__c | K55: Moved from Order to Quote
A56: 32 | B56: Alt Bill To Country | C56: Picklist | E56: APTS_Alt_Bill_To_Country__c | F56: RCA_Alt_Bill_To_CoRCA_untry__c | K56: Moved from Order to Quote
A57: 33 | B57: Alt Bill To Country Code | C57: Picklist | E57: APTS_Alt_Bill_To_Country_Code__c | F57: RCA_Alt_Bill_To_Country_Code__c | K57: Moved from Order to Quote
A58: 34 | B58: Billing Contact (Local) | C58: Formula (Text) | E58: APTS_Billing_Contact_Local__c | F58: RCA_Billing_Contact_Local__c | K58: Moved from Order to Quote
A59: 35 | B59: Billing Contact 2 | C59: Email | E59: APTS_Billing_Contact_2__c | F59: RCA_Billing_Contact_2__c | K59: Moved from Order to Quote
A60: 36 | B60: Billing Contact 3 | C60: Email | E60: APTS_Billing_Contact_3__c | F60: RCA_Billing_Contact_3__c | K60: Moved from Order to Quote
A61: 37 | B61: Bill-To Department | C61: Formula (Text) | E61: APTS_Bill_To_Department__c | F61: RCA_Bill_To_Department__c | K61: Moved from Order to Quote
A62: 38 | B62: VAT ID Required? | C62: Checkbox | E62: APTS_VAT_Required__c | F62: RCA_VAT_Required__c | K62: Moved from Order to Quote
... A65: 41 | B65: Copy Billing Contact Address | C65: Checkbox | E65: Copy_Billing_Contact_Address__c | F65: RCA_Copy_Billing_Contact_Address__c | K65: Moved from Order to Quote
A66: 42 | B66: Sold To | C66: Lookup (Account) | K66: Moved from Order to Quote
A67: 43 | B67: Sold To (Local) | C67: Formula (Text) | E67: APTS_Sold_To_Local__c | F67: RCA_Sold_To_Local__c | K67: Moved from Order to Quote
A68: 44 | B68: Sold To CertCentral Acct ID | C68: Formula (Text) | E68: APTS_CertCentral_Acct_ID__c | F68: RCA_CertCentral_Acct_ID__c | K68: Moved from Order to Quote
A69: 45 | B69: Sold To Billing Legal Entity | C69: Formula (Text) | E69: APTS_Sold_To_Billing_Legal_Entity__c | F69: RCA_Sold_To_Billing_Legal_Entity__c | K69: Moved from Order to Quote
A70: 46 | B70: Sold To Address | C70: Formula (Text) | E70: Sold_To_Address__c | F70: RCA_Sold_To_Address__c | K70: Moved from Order to Quote
A71: 47 | B71: Alt Sold To Address | C71: Text | E71: APTS_Alt_Sold_To_Address__c | F71: RCA_Alt_Sold_To_Address__c | K71: Moved from Order to Quote
A72: 48 | B72: Alt Sold To City | C72: Text | E72: APTS_Alt_Sold_To_City__c | F72: RCA_Alt_Sold_To_City__c | K72: Moved from Order to Quote
A73: 49 | B73: Alt Sold To State | C73: Picklist | E73: APTS_Alt_Sold_To_State__c | F73: RCA_Alt_Sold_To_State__c | K73: Moved from Order to Quote
A74: 50 | B74: Alt Sold To Postal Code | C74: Text | E74: APTS_Alt_Sold_To_Postal_Code__c | F74: RCA_Alt_Sold_To_Postal_Code__c | K74: Moved from Order to Quote
A75: 51 | B75: Alt Sold To Country | C75: Picklist | E75: APTS_Alt_Sold_To_Country__c | F75: RCA_Alt_Sold_To_Country__c | K75: Moved from Order to Quote
A76: 52 | B76: Alt Sold To Country Code | C76: Picklist | E76: APTS_Alt_Sold_To_Country_Code__c | F76: RCA_Alt_Sold_To_Country_Code__c | K76: Moved from Order to Quote
A77: Billing Preference Info section
A78: 1 | B78: Contract Type Template | C78: Text | D78: R | E78: APTS_Contract_Type_Template__c | F78: RCA_Contract_Type_Template__c | I78: ? | J78: Y | K78: Do we need this field in To Be? (Pavan/Karthik)
A79: 2 | B79: Requested Credit Limit | C79: Currency | D79: R | E79: APTS_Requested_Credit_Limit__c | F79: RCA_Requested_Credit_Limit__c | I79: C | J79: Y
A80: 3 | B80: Contract Length | C80: Number (16, 2) | D80: R | E80: APTS_ContractLength__c | F80: RCA_ContractLength__c | I80: C | J80: Y
A81: 4 | B81: Requested Credit Limit Override | C81: Currency | D81: R | E81: APTS_Requested_Credit_Limit_Override__c | F81: RCA_Requested_Credit_Limit_Override__c | I81: C | J81: Y
A82: 5 | B82: Price List | C82: Lookup (Price List) | D82: R | E82: Apttus_QPConfig__PriceListId__c | G82: Price Book ID | H82: Lookup (Price Book) | I82: S | J82: Y
A83: 6 | B83: Per Cert Expected Annual Spend | C83: Currency | D83: R | E83: APTS_Per_Cert_Expected_Annual_Spend__c | F83: RCA_Per_Cert_Expected_Annual_Spend__c | I83: C | J83: Y
A84: 7 | B84: Territory | C84: Formula (Text) | D84: R | E84: APTS_Territory__c | F84: RCA_Territory__c | I84: C | J84: Y
A85: 8 | B85: Pricing Region | C85: Picklist | D85: R | E85: APTS_Pricing_Region__c | F85: RCA_Pricing_Region__c | I85: C | J85: Y
A86: Pricing section
A87: 1 | B87: Total Seat-based MSRP | C87: Currency | D87: R | E87: APTS_Total_PKI_MSRP__c | F87: RCA_Total_PKI_MSRP__c | I87: C | J87: Y
A88: 2 | B88: Total Quote MSRP | C88: Formula (Currency) | D88: R | E88: APTS_Total_Quote_MSRP__c | F88: RCA_Total_Quote_MSRP__c | I88: C | J88: Y
A89: 3 | B89: Total Seat-based Value | C89: Currency | D89: R | E89: APTS_Total_PKI_Value__c | F89: RCA_Total_PKI_Value__c | I89: C | J89: Y
A90: 4 | B90: Total Quote Value | C90: Formula (Currency) | D90: R | E90: APTS_Total_Quote_Value__c | F90: RCA_Total_Quote_Value__c | I90: C | J90: Y
A91: 5 | B91: Total Seat-based Discount % | C91: Formula (Percent) | D91: R | E91: APTS_Total_PKI_Discount_Percent__c | F91: RCA_Total_PKI_Discount_Percent__c | I91: C | J91: Y
A92: 6 | B92: Total Quote Amount (USD) | C92: Formula (Number) | D92: R | E92: APTS_Total_Quote_Amount_USD__c | F92: RCA_Total_Quote_Amount_USD__c | I92: C | J92: Y
A93: 7 | B93: Total Certificate-based MSRP | C93: Currency | D93: R | E93: APTS_Total_SSL_MSRP__c | F93: RCA_Total_SSL_MSRP__c | I93: C | J93: Y
A94: 8 | B94: Total Support Value | C94: Formula (Currency) | D94: R | E94: APTS_Total_Support_Value__c | F94: RCA_Total_Support_Value__c | I94: C | J94: Y
A95: 9 | B95: Total Certificate-based Value | C95: Currency | D95: R | E95: APTS_Total_SSL_Value__c | F95: RCA_Total_SSL_Value__c | I95: C | J95: Y
A96: 10 | B96: Total Quote Discount % | C96: Formula (Percent) | D96: R | E96: APTS_Total_Quote_Discount_Percent__c | F96: RCA_Total_Quote_Discount_Percent__c | I96: C | J96: Y
A97: 11 | B97: Total Support (Cert-based) MSRP | C97: Roll-Up Summary | D97: R | E97: APTS_Total_Support_Certificate_basedMSRP__c | F97: RCA_Total_Support_Certificate_basedMSRP__c | I97: C | J97: Y
A98: 12 | B98: Annual Commit Discount % | C98: Number (14, 4) | D98: E | E98: APTS_Annual_Commit_Discount__c | F98: RCA_Annual_Commit_Discount__c | I98: C | J98: Y
... A104: 18 | B104: Approved (Entrust) Credit Amount | C104: Currency | D104: E | E104: APTS_Approved_Credit_Amount__c | F104: RCA_Approved_Credit_Amount__c | I104: C | J104: Y
A105: Partner Program Info section
A106: 1 | B106: DigiCert-branded Cert Discount(Default) | C106: Percent | D106: R | E106: APTS_Digicert_Branded_Default_Discount__c | F106: RCA_Digicert_Branded_Default_Discount__c | I106: C | J106: Y
A107: 2 | B107: Marketplace Partner Contact | C107: Lookup (Contact) | D107: R | E107: APTS_Marketplace_Partner_Contact__c | F107: RCA_Marketplace_Partner_Contact__c | I107: C | J107: Y
...

Sheet Sheet 1
A1: Quote Proposal | B1: Layout V2
A2: Record ID | B2: Proposal ID | C2: V2 | E2: Apttus_Proposal__Discount_Percent__c | F2: not used
A3: Owner ID | B3: Owner | C3: V2 | E3: Apttus_Proposal__Internal_Deadline__c | F3: not used
A4: Deleted | B4: Proposal Name | C4: V2 | E4: Apttus_Proposal__Proposal_Approval_Date__c | F4: not used
A5: Proposal ID | B5: Quote Type | C5: V2 | E5: Apttus_Proposal__Proposal_Expiration_Date__c | F5: not used
A6: Currency ISO Code | B6: Deal Type | C6: V2 | E6: Apttus_Proposal__RFP_Intake_Date__c | F6: not used
A7: Record Type ID | B7: Approval Stage | C7: V2 | E7: Apttus_Proposal__RFP_Response_Due_Date__c | F7: not used
A8: Created Date | B8: Valid Until Date | C8: V2 | E8: Apttus_Proposal__RFP_Stage__c | F8: not used
A9: Created By ID | B9: Primary | C9: V2 | E9: Apttus_Proposal__RFP_Value__c | F9: not used
A10: Last Modified Date | B10: Auto Renew | C10: V2 | E10: Apttus_Proposal__RelatedProposalId__c | F10: not used
A11: Last Modified By ID | B11: Revert to Presented | C11: V2 | E11: Apttus_Proposal__Risk_Factors__c | F11: not used
A12: System Modstamp | B12: CPI Adjustment | C12: V2 | E12: Apttus_Proposal__Sales_Tax_Percent__c | F12: not used
A13: Last Activity Date | B13: Template Type | C13: V2 | E13: Apttus_Proposal__Shipping_Handling__c | F13: not used
... A92: Master Agreement | B92: Partner Contract Type | C92: V2 | E92: APTS_Year_5_Net_Total__c | F92: not used
A93: Check eSignature Status | B93: Non-Deal Registration discount | C93: V2
A94: Recall E-Signature Request | B94: Allow Overage | C94: V2
A95: Send For eSignature | B95: MSP Partner Discount | C95: V2
A96: Correct E-Signature Document | B96: Bulk Draw Down? | C96: V2
A97: Accept Quote | B97: Partner Tier | C97: V2
A98: Account Billing Preference | B98: Contract Status | C98: V2
A99: Account Credit Check Status | B99: Contract Renewal Date | C99: V2
A100: Account Credit Hold | B100: Annual Commit? | C100: V2
A101: Account Legal Name | B101: Bulk Commit Amount | C101: V2
A102: Account Payment Term | B102: Created By | C102: V2
A103: Approval LoB | B103: Configuration Start Date | C103: V2
A104: Approved 1st Year Price | B104: Last Modified By | C104: V2
... A108: Billing Country Code | B108: Preview | C108: V2
A109: Cart Needs Repricing
A110: Configure DC Cart
A111: Contract Type Template
A112: Create Order Form/MSA
A113: Custom Payment Term Value
A114: Custom Payment Terms
A115: Bill To Partner / Distributor
A116: Deal Type
A117: ELA Calculator Version Counter
A118: Generate & Send Proposal
A119: Has PKI
A120: Is Default Currency?
... A638: MSP Partner Discount
