Workbook

Sheet Sheet1
A1: _ | B1: Id | C1: ExternalId | D1: RCA_ExternalId__c | E1: Type
A2: [Product2] | B2: 01tWC00000AYBXxYAP | C2: 01t4z000008h0NLAAY
A3: [Product2] | B3: 01tWC00000AYBXyYAP | C3: 01t4z000008iBW3AAM
A4: [Product2] | B4: 01tWC00000AYBXzYAP | C4: 01t4z000008iBW4AAM
A5: [Product2] | B5: 01tWC00000AYBY1YAP | C5: 01t4z000008jjfJAAQ
A6: [Product2] | B6: 01tWC00000AYBY2YAP | C6: 01t0z000007f40zAAA
A7: [Product2] | B7: 01tWC00000AYBY3YAP | C7: 01t0z000007f410AAA
A8: [Product2] | B8: 01tWC00000AYBY4YAP | C8: 01t0z000007f411AAA
A9: [Product2] | B9: 01tWC00000AYBY5YAP | C9: 01t0z000007f412AAA
A10: [Product2] | B10: 01tWC00000AYBY6YAP | C10: 01t0z000007f413AAA
A11: [Product2] | B11: 01tWC00000AYBY7YAP | C11: 01t0z000007f414AAA
A12: [Product2] | B12: 01tWC00000AYBY8YAP | C12: 01t0z000007f415AAA
A13: [Product2] | B13: 01tWC00000AYBY9YAP | C13: 01t0z000007f416AAA
... A428: [Product2] | B428: 01tWC00000BLkDVYA1 | C428: 01tVu000000UDcZIAW

Sheet Sheet8
A1: _ | B1: Id | C1: CreatedDate | D1: Type | E1: Name | F1: LastModifiedDate | G1: IsActive | H1: ExternalId
A2: [Product2] | B2: 01tdp000009QOCnAAO | C2: 2025-12-16T01:48:46.000+0000 | D2: Bundle | E2: CertCentral Subscription (Annual Commit) | F2: 2025-12-16T01:48:46.000+0000 | G2: TRUE
A3: [Product2] | B3: 01tdp000009QL0QAAW | C3: 2025-12-16T01:18:53.000+0000 | D3: Bundle | E3: CertCentral Bulk Dollar | F3: 2025-12-16T01:18:53.000+0000 | G3: TRUE
A4: [Product2] | B4: 01tdp000009QN3pAAG | C4: 2025-12-16T01:18:37.000+0000 | D4: Bundle | E4: CertCentral Bulk Units | F4: 2025-12-16T01:18:37.000+0000 | G4: TRUE
A5: [Product2] | B5: 01tdp000009QN3qAAG | C5: 2025-12-16T01:18:37.000+0000 | D5: Bundle | E5: CertCentral PerCert | F5: 2025-12-16T01:18:37.000+0000 | G5: TRUE
A6: [Product2] | B6: 01tdp000009H4gPAAS | C6: 2025-12-09T03:54:57.000+0000 | E6: DigiCert Trust Lifecycle Manager - Organizational Certificate Private Root Creation and Maintenance | F6: 2025-12-09T03:54:57.000+0000 | G6: TRUE
A7: [Product2] | B7: 01tdp000009H4gQAAS | C7: 2025-12-09T03:54:57.000+0000 | E7: DigiCert Trust Lifecycle Manager - Private Code Signing Certificates Private Root Creation and Maintenance | F7: 2025-12-09T03:54:57.000+0000 | G7: TRUE
A8: [Product2] | B8: 01tdp000009H4gLAAS | C8: 2025-12-09T03:54:57.000+0000 | E8: DIGICERT PKI PLATFORM - WEB GATEWAY INSPECTION - 12 MONTHS Private Root Creation and Maintenance | F8: 2025-12-09T03:54:57.000+0000 | G8: TRUE
A9: [Product2] | B9: 01tdp000009H4gSAAS | C9: 2025-12-09T03:54:57.000+0000 | E9: DigiCert Trust Lifecycle Manager - User Seat Private Root Creation and Maintenance | F9: 2025-12-09T03:54:57.000+0000 | G9: TRUE
A10: [Product2] | B10: 01tdp000009H4gTAAS | C10: 2025-12-09T03:54:57.000+0000 | E10: DigiCert Trust Lifecycle Manager - Web Gateway Inspection Private Root Creation and Maintenance | F10: 2025-12-09T03:54:57.000+0000 | G10: TRUE
A11: [Product2] | B11: 01tdp000009H4gRAAS | C11: 2025-12-09T03:54:57.000+0000 | E11: DigiCert Trust Lifecycle Manager - Private Server Seat Private Root Creation and Maintenance | F11: 2025-12-09T03:54:57.000+0000 | G11: TRUE
A12: [Product2] | B12: 01tdp000009H4gMAAS | C12: 2025-12-09T03:54:57.000+0000 | E12: DigiCert Software Trust Manager - Code Signing Account Creation and Maintenance | F12: 2025-12-09T03:54:57.000+0000 | G12: TRUE
A13: [Product2] | B13: 01tdp000009H4gNAAS | C13: 2025-12-09T03:54:57.000+0000 | E13: DigiCert Software Trust Manager - Threat Detection Account Creation and Maintenance | F13: 2025-12-09T03:54:57.000+0000 | G13: TRUE
A14: [Product2] | B14: 01tdp000009H4gOAAS | C14: 2025-12-09T03:54:57.000+0000 | E14: DigiCert Trust Lifecycle Manager - Device Seat Private Root Creation and Maintenance | F14: 2025-12-09T03:54:57.000+0000 | G14: TRUE
A15: [Product2] | B15: 01tdp000009H4ekAAC | C15: 2025-12-09T03:54:56.000+0000 | E15: Digicert Device Trust Manager - Essentials Private Root Creation and Maintenance | F15: 2025-12-09T03:54:56.000+0000 | G15: TRUE
A16: [Product2] | B16: 01tdp000009H4ejAAC | C16: 2025-12-09T03:54:56.000+0000 | E16: Digicert Device Trust Manager - Advanced Private Root Creation and Maintenance | F16: 2025-12-09T03:54:56.000+0000 | G16: TRUE
A17: [Product2] | B17: 01tdp000009H4emAAC | C17: 2025-12-09T03:54:56.000+0000 | E17: DIGICERT DOCUMENT TRUST MANAGER FOR ORGANIZATIONS - 12 MONTHS Account Creation and Maintenance | F17: 2025-12-09T03:54:56.000+0000 | G17: TRUE
... A27: [Product2] | B27: 01tdp000009H4elAAC | C27: 2025-12-09T03:54:56.000+0000 | E27: DIGICERT DOCUMENT TRUST MANAGER FOR INDIVIDUALS - 12 MONTHS Account Creation and Maintenance | F27: 2025-12-09T03:54:56.000+0000 | G27: TRUE
A28: [Product2] | B28: 01tdp000009H4DLAA0 | C28: 2025-12-09T03:41:13.000+0000 | D28: Bundle | E28: ELA (C2000) – Semi-Annual Billing | F28: 2025-12-09T03:41:13.000+0000 | G28: TRUE
A29: [Product2] | B29: 01tdp000009H4DJAA0 | C29: 2025-12-09T03:41:13.000+0000 | D29: Bundle | E29: Flat Fee | F29: 2025-12-09T03:41:13.000+0000 | G29: TRUE
A30: [Product2] | B30: 01tdp000009H4DKAA0 | C30: 2025-12-09T03:41:13.000+0000 | D30: Bundle | E30: ELA (C2000) - Annual Billing | F30: 2025-12-09T03:41:13.000+0000 | G30: TRUE
A31: [Product2] | B31: 01tdp000009H4DMAA0 | C31: 2025-12-09T03:41:13.000+0000 | D31: Bundle | E31: ELA (C2000) - Quarterly Billing | F31: 2025-12-09T03:41:13.000+0000 | G31: TRUE
A32: [Product2] | B32: 01tdp000009GN6qAAG | C32: 2025-12-08T20:45:02.000+0000 | E32: Ascertia Level 2 support 24x7x365 | F32: 2025-12-15T17:29:23.000+0000 | G32: FALSE
A33: [Product2] | B33: 01tdp000009GN6pAAG | C33: 2025-12-08T20:45:02.000+0000 | E33: Ascertia Installation guidance via Basecamp | F33: 2025-12-15T17:29:23.000+0000 | G33: FALSE
A34: [Product2] | B34: 01tdp000009GN6oAAG | C34: 2025-12-08T20:45:02.000+0000 | E34: Ascertia SigningHub rebranded mobile app | F34: 2025-12-15T17:29:23.000+0000 | G34: FALSE
A35: [Product2] | B35: 01tdp000009GN6kAAG | C35: 2025-12-08T20:45:02.000+0000 | E35: DIGICERT DOCUMENT TRUST MANAGER ADDITIONAL SIGNINGS | F35: 2025-12-15T17:29:23.000+0000 | G35: FALSE
A36: [Product2] | B36: 01tdp000009GN5VAAW | C36: 2025-12-08T20:45:02.000+0000 | E36: DIGICERT DOCUMENT TRUST MANAGER FOR INDIVIDUALS - 12 MONTHS | F36: 2025-12-15T17:29:23.000+0000 | G36: FALSE
A37: [Product2] | B37: 01tdp000009GN5OAAW | C37: 2025-12-08T20:45:02.000+0000 | E37: DigiCert GSMA v2 - DS (1 cert: Authentication) | F37: 2025-12-15T17:29:23.000+0000 | G37: FALSE
A38: [Product2] | B38: 01tdp000009GN5JAAW | C38: 2025-12-08T20:45:02.000+0000 | E38: Ascertia ADSS SAM Appliance - Annual Support | F38: 2025-12-15T17:29:23.000+0000 | G38: FALSE
A39: [Product2] | B39: 01tdp000009GN5IAAW | C39: 2025-12-08T20:45:02.000+0000 | E39: Ascertia ADSS SAM Appliance - Hardware | F39: 2025-12-15T17:29:23.000+0000 | G39: FALSE
A40: [Product2] | B40: 01tdp000009GN5EAAW | C40: 2025-12-08T20:45:02.000+0000 | E40: 3rd Party Hardware Offerings | F40: 2025-12-15T17:29:23.000+0000 | G40: FALSE
A41: [Product2] | B41: 01tdp000009GN5BAAW | C41: 2025-12-08T20:45:02.000+0000 | E41: 3rd Party Offerings | F41: 2025-12-15T17:29:23.000+0000 | G41: FALSE
A42: [Product2] | B42: 01tdp000009GN3rAAG | C42: 2025-12-08T20:45:01.000+0000 | E42: Thales DPoD | F42: 2025-12-15T17:29:23.000+0000 | G42: FALSE
A43: [Product2] | B43: 01tdp000009GN3jAAG | C43: 2025-12-08T20:45:01.000+0000 | E43: DigiCert Additional CA | F43: 2025-12-15T17:29:23.000+0000 | G43: FALSE
... A46: [Product2] | B46: 01tdp000009GMxLAAW | C46: 2025-12-08T20:45:00.000+0000 | E46: Private Root CA Creation and Maintenance | F46: 2025-12-15T17:29:23.000+0000 | G46: FALSE
A47: [Product2] | B47: 01tdp000009GMxJAAW | C47: 2025-12-08T20:45:00.000+0000 | D47: Bundle | E47: Subscription Services - In Active [Do Not Use] | F47: 2025-12-16T01:30:24.000+0000 | G47: FALSE
A48: [Product2] | B48: 01tdp000009GMxIAAW | C48: 2025-12-08T20:45:00.000+0000 | E48: Common Mark Certificate | F48: 2025-12-15T17:29:23.000+0000 | G48: FALSE
A49: [Product2] | B49: 01tdp000009GMxBAAW | C49: 2025-12-08T20:45:00.000+0000 | E49: EU Qualified Website Authentication Certificate (QWAC) PSD2 | F49: 2025-12-15T17:29:23.000+0000 | G49: FALSE
A50: [Product2] | B50: 01tdp000009GMx7AAG | C50: 2025-12-08T20:45:00.000+0000 | E50: Digicert Business Support | F50: 2025-12-15T17:29:23.000+0000 | G50: FALSE
A51: [Product2] | B51: 01tdp000009GMu7AAG | C51: 2025-12-08T20:44:57.000+0000 | E51: Premium (Class 2 S/MIME) | F51: 2025-12-15T17:29:23.000+0000 | G51: FALSE
A52: [Product2] | B52: 01tdp000009GMamAAG | C52: 2025-12-08T20:37:45.000+0000 | E52: Ascertia Service License | F52: 2025-12-15T17:29:23.000+0000 | G52: FALSE
A53: [Product2] | B53: 01tdp000009GMaVAAW | C53: 2025-12-08T20:37:45.000+0000 | E53: 3rd Party Professional Services Offerings | F53: 2025-12-15T17:29:23.000+0000 | G53: FALSE
A54: [Product2] | B54: 01tdp000009GMZ0AAO | C54: 2025-12-08T20:37:45.000+0000 | E54: DigiCert MSP Hub | F54: 2025-12-15T17:29:23.000+0000 | G54: FALSE
A55: [Product2] | B55: 01tdp000009GMXSAA4 | C55: 2025-12-08T20:37:45.000+0000 | E55: Ascertia Signature Unit Pack | F55: 2025-12-15T17:29:23.000+0000 | G55: FALSE
A56: [Product2] | B56: 01tdp000009GMUOAA4 | C56: 2025-12-08T20:37:43.000+0000 | E56: DigiCert KeyLocker | F56: 2025-12-15T17:29:23.000+0000 | G56: FALSE
A57: [Product2] | B57: 01tdp000009GMU9AAO | C57: 2025-12-08T20:37:43.000+0000 | E57: Digicert Premium Support | F57: 2025-12-15T17:29:23.000+0000 | G57: FALSE
A58: [Product2] | B58: 01tdp000009GMUDAA4 | C58: 2025-12-08T20:37:43.000+0000 | E58: EU Electronic Seal | F58: 2025-12-15T17:29:23.000+0000 | G58: FALSE
A59: [Product2] | B59: 01tdp000009GMUEAA4 | C59: 2025-12-08T20:37:43.000+0000 | E59: EU Electronic Seal PSD2 | F59: 2025-12-15T17:29:23.000+0000 | G59: FALSE
... A1996: [Product2] | B1996: 01tVu00000NwTuuIAF | C1996: 2025-06-25T10:27:19.000+0000 | E1996: DigiCert DNS - Essentials | F1996: 2025-12-08T20:34:03.000+0000 | G1996: TRUE
A1997: [Product2] | B1997: 01tVu00000NtnndIAB | C1997: 2025-06-24T15:01:44.000+0000 | E1997: DigiCert MSP Hub | F1997: 2025-12-16T01:18:31.000+0000 | G1997: TRUE | H1997: 01tVu00000NtnndIAB
A1998: [Product2] | B1998: 01tVu00000NSSlvIAH | C1998: 2025-06-14T19:39:32.000+0000 | E1998: DigiCert X9 TLS Subscription | F1998: 2025-12-08T20:34:03.000+0000 | G1998: FALSE
A1999: [Product2] | B1999: 01tVu00000NSaJRIA1 | C1999: 2025-06-14T19:05:59.000+0000 | E1999: DigiCert X9 TLS | F1999: 2025-12-16T01:18:42.000+0000 | G1999: TRUE | H1999: 01tVu00000NSaJRIA1
A2000: [Product2] | B2000: 01tVu00000L9mJ3IAJ | C2000: 2025-04-24T01:53:48.000+0000 | E2000: Document Signing for Business - Employee 3 - year | F2000: 2025-12-08T20:34:03.000+0000 | G2000: TRUE
A2001: [Product2] | B2001: 01tVu00000L9hOEIAZ | C2001: 2025-04-24T01:53:36.000+0000 | E2001: Document Signing for Business - Employee 2 - year | F2001: 2025-12-08T20:34:03.000+0000 | G2001: TRUE
A2002: [Product2] | B2002: 01tVu00000L9jQ3IAJ | C2002: 2025-04-24T01:52:37.000+0000 | E2002: Document Signing for Business - Group - 3 year | F2002: 2025-12-08T20:34:03.000+0000 | G2002: TRUE
A2003: [Product2] | B2003: 01tVu00000L9mFpIAJ | C2003: 2025-04-24T01:52:23.000+0000 | E2003: Document Signing for Business - Group - 2 year | F2003: 2025-12-08T20:34:03.000+0000 | G2003: TRUE
A2004: [Product2] | B2004: 01tVu00000L9m9NIAR | C2004: 2025-04-24T01:51:11.000+0000 | E2004: Document Signing for Individual - 3 year | F2004: 2025-12-08T20:34:03.000+0000 | G2004: TRUE
A2005: [Product2] | B2005: 01tVu00000L9m7lIAB | C2005: 2025-04-24T01:50:56.000+0000 | E2005: Document Signing for Individual - 2 year | F2005: 2025-12-08T20:34:03.000+0000 | G2005: TRUE
A2006: [Product2] | B2006: 01tVu00000KEqo1IAD | C2006: 2025-04-03T00:07:32.000+0000 | E2006: Authentication for Individual - 2 Year | F2006: 2025-12-08T20:34:03.000+0000 | G2006: TRUE
A2007: [Product2] | B2007: 01tVu00000KEjQ8IAL | C2007: 2025-04-03T00:05:37.000+0000 | E2007: Authentication for Employee - 2 Year | F2007: 2025-12-08T20:34:03.000+0000 | G2007: TRUE
A2008: [Product2] | B2008: 01tVu00000KEocYIAT | C2008: 2025-04-03T00:01:01.000+0000 | E2008: Secure Email for Organization - 3 Year | F2008: 2025-12-08T20:34:03.000+0000 | G2008: TRUE
A2009: [Product2] | B2009: 01tVu00000KEdkOIAT | C2009: 2025-04-03T00:00:03.000+0000 | E2009: Secure Email for Organization - 2 Year | F2009: 2025-12-08T20:34:03.000+0000 | G2009: TRUE
A2010: [Product2] | B2010: 01tVu00000KEmUKIA1 | C2010: 2025-04-02T23:55:33.000+0000 | E2010: Secure Email for Individual Mailbox - 3 Year | F2010: 2025-12-08T20:34:03.000+0000 | G2010: TRUE
A2011: [Product2] | B2011: 01tVu00000KEg5XIAT | C2011: 2025-04-02T23:54:25.000+0000 | E2011: Secure Email for Individual Mailbox - 2 Year | F2011: 2025-12-08T20:34:03.000+0000 | G2011: TRUE
... A2013: [Product2] | B2013: 01tVu00000KEld4IAD | C2013: 2025-04-02T23:46:14.000+0000 | E2013: Secure Email for Employee - 2 Year | F2013: 2025-12-08T20:34:03.000+0000 | G2013: TRUE
A2014: [Product2] | B2014: 01tVu00000K4JtOIAV | C2014: 2025-03-30T08:56:41.000+0000 | E2014: Secure Email for Business [Sponsor] (Units) | F2014: 2025-12-16T01:18:42.000+0000 | G2014: TRUE | H2014: 01tVu00000K4JtOIAV
A2015: [Product2] | B2015: 01tVu00000K4LAPIA3 | C2015: 2025-03-30T08:56:10.000+0000 | E2015: Secure Email for Individual [Mailbox] (Units) | F2015: 2025-12-16T01:18:42.000+0000 | G2015: TRUE | H2015: 01tVu00000K4LAPIA3
A2016: [Product2] | B2016: 01tVu00000K4IsVIAV | C2016: 2025-03-30T08:55:41.000+0000 | E2016: Secure Email for Organization (Units) | F2016: 2025-12-16T01:18:42.000+0000 | G2016: TRUE | H2016: 01tVu00000K4IsVIAV
A2017: [Product2] | B2017: 01tVu00000Jp203IAB | C2017: 2025-03-24T19:24:44.000+0000 | E2017: Authentication for Individual | F2017: 2025-12-16T01:18:31.000+0000 | G2017: TRUE | H2017: 01tVu00000Jp203IAB
A2018: [Product2] | B2018: 01tVu00000JozlMIAR | C2018: 2025-03-24T19:22:22.000+0000 | E2018: Authentication for Employee | F2018: 2025-12-16T01:18:31.000+0000 | G2018: TRUE | H2018: 01tVu00000JozlMIAR
A2019: [Product2] | B2019: 01tVu00000JOqvTIAT | C2019: 2025-03-13T19:29:27.000+0000 | E2019: Private SSL OV Wildcard Subscription | F2019: 2025-12-08T20:34:03.000+0000 | G2019: TRUE
A2020: [Product2] | B2020: 01tVu00000JOsxBIAT | C2020: 2025-03-13T19:20:59.000+0000 | E2020: Private SSL OV FQDN Subscription | F2020: 2025-12-08T20:34:03.000+0000 | G2020: TRUE
A2021: [Product2] | B2021: 01tVu00000H8ArjIAF | C2021: 2025-01-21T06:18:31.000+0000 | E2021: Secure Email for Individual - 2 Year | F2021: 2025-12-08T20:34:03.000+0000 | G2021: TRUE
A2022: [Product2] | B2022: 01tVu00000H8GkAIAV | C2022: 2025-01-21T06:18:22.000+0000 | E2022: Secure Email for Business - 2 Year | F2022: 2025-12-08T20:34:03.000+0000 | G2022: TRUE
A2023: [Product2] | B2023: 01tVu00000FzZOSIA3 | C2023: 2024-12-21T15:15:35.000+0000 | E2023: Digicert Device Trust Manager - Advanced | F2023: 2025-12-16T01:18:31.000+0000 | G2023: TRUE | H2023: 01tVu00000FzZOSIA3
A2024: [Product2] | B2024: 01tVu00000FzdH0IAJ | C2024: 2024-12-21T15:15:09.000+0000 | E2024: Digicert Device Trust Manager - Premium | F2024: 2025-12-08T20:34:03.000+0000 | G2024: FALSE
A2025: [Product2] | B2025: 01tVu00000FzWTlIAN | C2025: 2024-12-21T12:00:32.000+0000 | E2025: Digicert Device Trust Manager - Essentials | F2025: 2025-12-16T01:18:31.000+0000 | G2025: TRUE | H2025: 01tVu00000FzWTlIAN
A2026: [Product2] | B2026: 01tVu00000DDlMbIAL | C2026: 2024-10-17T18:00:41.000+0000 | E2026: Common Mark Certificate (Units) | F2026: 2025-12-16T01:18:31.000+0000 | G2026: TRUE | H2026: 01tVu00000DDlMbIAL
A2027: [Product2] | B2027: 01tVu00000CruTNIAZ | C2027: 2024-10-09T19:35:53.000+0000 | E2027: GATEKEEPER 2.0 INDIVIDUAL - INDIVIDUAL CERTIFICATE | F2027: 2025-12-08T20:34:03.000+0000 | G2027: TRUE
A2028: [Product2] | B2028: 01tVu00000CruRlIAJ | C2028: 2024-10-09T19:35:46.000+0000 | E2028: GATEKEEPER 2.0 BUSINESS - STANDARD CERTIFICATE | F2028: 2025-12-08T20:34:03.000+0000 | G2028: TRUE
A2029: [Product2] | B2029: 01tVu00000CrZyTIAV | C2029: 2024-10-09T19:35:39.000+0000 | E2029: GATEKEEPER 2.0 BUSINESS - MANAGER CERTIFICATE | F2029: 2025-12-08T20:34:03.000+0000 | G2029: TRUE
A2030: [Product2] | B2030: 01tVu00000CrhBFIAZ | C2030: 2024-10-09T19:35:31.000+0000 | E2030: GATEKEEPER 2.0 BUSINESS - DEVICE CERTIFICATE | F2030: 2025-12-08T20:34:03.000+0000 | G2030: TRUE
A2031: [Product2] | B2031: 01tVu00000CroxTIAR | C2031: 2024-10-09T19:35:23.000+0000 | E2031: GATEKEEPER 2.0 BUSINESS - ACCOUNT SETUP | F2031: 2025-12-08T20:34:03.000+0000 | G2031: TRUE
A2032: [Product2] | B2032: 01tVu00000CnENwIAN | C2032: 2024-10-08T13:53:51.000+0000 | E2032: PKIo Private Services Server Subscription | F2032: 2025-12-08T20:34:03.000+0000 | G2032: TRUE
A2033: [Product2] | B2033: 01tVu00000CnQfBIAV | C2033: 2024-10-08T13:52:30.000+0000 | E2033: PKIo Private Professional - Authentication/Encryption Hardware Token Subscription | F2033: 2025-12-08T20:34:03.000+0000 | G2033: TRUE
A2034: [Product2] | B2034: 01tVu00000CnQbxIAF | C2034: 2024-10-08T13:51:44.000+0000 | E2034: PKIo Private Person - Authentication/Encryption Hardware Token Subscription | F2034: 2025-12-08T20:34:03.000+0000 | G2034: TRUE
A2035: [Product2] | B2035: 01tVu00000CnE7qIAF | C2035: 2024-10-08T13:50:50.000+0000 | E2035: PKIo Citizen - Authentication/Encryption Hardware Token Subscription | F2035: 2025-12-08T20:34:03.000+0000 | G2035: TRUE
A2036: [Product2] | B2036: 01tVu00000CCGZyIAP | C2036: 2024-09-25T13:49:39.000+0000 | E2036: Digicert Device Trust Manager | F2036: 2025-12-08T20:34:03.000+0000 | G2036: FALSE
A2037: [Product2] | B2037: 01tVu000009Cas9IAC | C2037: 2024-07-25T18:26:20.000+0000 | E2037: EU Qualified Website Authentication Certificate Subscription | F2037: 2025-12-08T20:34:03.000+0000 | G2037: TRUE
A2038: [Product2] | B2038: 01tVu000009CalhIAC | C2038: 2024-07-25T18:26:12.000+0000 | E2038: EU Qualified Website Authentication Certificate PSD2 Subscription | F2038: 2025-12-08T20:34:03.000+0000 | G2038: TRUE
... A2057: [Product2] | B2057: 01tVu00000922gbIAA | C2057: 2024-07-22T20:39:21.000+0000 | E2057: Key Locker - 100 Signatures Subscription | F2057: 2025-12-08T20:34:03.000+0000 | G2057: FALSE
A2058: [Product2] | B2058: 01tVu000006Hg4EIAS | C2058: 2024-05-26T18:12:03.000+0000 | E2058: Digicert Business Plus Support | F2058: 2025-12-16T01:18:31.000+0000 | G2058: TRUE | H2058: 01tVu000006Hg4EIAS
A2059: [Product2] | B2059: 01tVu000004md83IAA | C2059: 2024-04-23T15:44:30.000+0000 | E2059: DigiCert Standard Plus Support | F2059: 2025-12-08T20:34:03.000+0000 | G2059: TRUE
A2060: [Product2] | B2060: 01tVu000004mdjAIAQ | C2060: 2024-04-23T15:35:16.000+0000 | E2060: Document Signing for Individual Subscription | F2060: 2025-12-08T20:34:03.000+0000 | G2060: TRUE
A2061: [Product2] | B2061: 01tVu000004mVQdIAM | C2061: 2024-04-23T15:34:56.000+0000 | E2061: Document Signing for Individual (Personal) - Own Hardware Token Subscription | F2061: 2025-12-08T20:34:03.000+0000 | G2061: TRUE
A2062: [Product2] | B2062: 01tVu000004mOKKIA2 | C2062: 2024-04-23T15:34:28.000+0000 | E2062: Document Signing for Individual (Personal) - Digicert Hardware Token Subscription | F2062: 2025-12-08T20:34:03.000+0000 | G2062: TRUE
A2063: [Product2] | B2063: 01tVu000004mbmAIAQ | C2063: 2024-04-23T15:34:07.000+0000 | E2063: Document Signing for Business Group Subscription | F2063: 2025-12-08T20:34:03.000+0000 | G2063: TRUE
A2064: [Product2] | B2064: 01tVu000004mSFsIAM | C2064: 2024-04-23T15:33:45.000+0000 | E2064: Document Signing for Business Employee Subscription | F2064: 2025-12-08T20:34:03.000+0000 | G2064: TRUE
A2065: [Product2] | B2065: 01tVu000004md6QIAQ | C2065: 2024-04-23T15:33:24.000+0000 | E2065: Document Signing for Business Employee - Own Hardware Token Subscription | F2065: 2025-12-08T20:34:03.000+0000 | G2065: TRUE
A2066: [Product2] | B2066: 01tVu000004mai3IAA | C2066: 2024-04-23T15:33:04.000+0000 | E2066: Document Signing for Business Employee - Digicert Hardware Token Subscription | F2066: 2025-12-08T20:34:03.000+0000 | G2066: TRUE
...

Sheet Sheet4
A1: _ | B1: Id | C1: Name | D1: ExternalId | E1: RCA_ExternalId__c
A2: [Product2] | B2: 01t0z000006tlRPAAY | C2: DIGICERT PKI PLATFORM (GEMALTO) USB AUTHENTICATOR E5110 PLUS NO PIN 3YR WARRANTY | D2: 01t0z000006tlRPAAY | E2: 01t0z000006tlRPAAY
A3: [Product2] | B3: 01t0z00000753eyAAA | C3: DIGICERT NON-FEDERAL SSP PKI 7.5 ADDITIONAL PRIVATE CA | D3: 01t0z00000753eyAAA | E3: 01t0z00000753eyAAA
A4: [Product2] | B4: 01t0z00000753f0AAA | C4: DIGICERT NON-FEDERAL SSP PKI 7.5 CO-BRANDED SEATS | D4: 01t0z00000753f0AAA | E4: 01t0z00000753f0AAA
A5: [Product2] | B5: 01t0z00000753kPAAQ | C5: DIGICERT PKI PLATFORM 7.5 PRIVATE SEATS | D5: 01t0z00000753kPAAQ | E5: 01t0z00000753kPAAQ
A6: [Product2] | B6: 01t0z000007548oAAA | C6: DIGICERT FEDERAL SSP PKI 7.5 CO-BRANDED SEATS | D6: 01t0z000007548oAAA | E6: 01t0z000007548oAAA
A7: [Product2] | B7: 01t0z00000754KzAAI | C7: DIGICERT PKI PLATFORM 7.5 USER SEATS | D7: 01t0z00000754KzAAI | E7: 01t0z00000754KzAAI
A8: [Product2] | B8: 01t0z00000754QkAAI | C8: DIGICERT FEDERAL SSP PKI 7.5 ADDITIONAL PRIVATE CA | D8: 01t0z00000754QkAAI | E8: 01t0z00000754QkAAI
A9: [Product2] | B9: 01t0z00000755CYAAY | C9: DIGICERT PKI PLATFORM - PLATINUM SUPPORT - 12 MONTHS | D9: 01t0z00000755CYAAY | E9: 01t0z00000755CYAAY
A10: [Product2] | B10: 01t0z0000076pLFAAY | C10: DIGICERT ADDITIONAL CA | D10: 01t0z0000076pLFAAY | E10: 01t0z0000076pLFAAY
A11: [Product2] | B11: 01t0z0000076pM7AAI | C11: DIGICERT PKI PLATFORM FOR SMARTPHONE FENICS MONTHLY FEE FOR CERTIFICATE | D11: 01t0z0000076pM7AAI | E11: 01t0z0000076pM7AAI
A12: [Product2] | B12: 01t0z0000076pPeAAI | C12: DIGICERT PKI PLATFORM AA MODULE FEE | D12: 01t0z0000076pPeAAI | E12: 01t0z0000076pPeAAI
... A428: [Product2] | B428: 01tVu00000NtnndIAB | C428: DigiCert MSP Hub | D428: 01tVu00000NtnndIAB | E428: 01tVu00000NtnndIAB

Sheet Sheet5
A1: _ | B1: Id | C1: Name | D1: ExternalId
A2: [Product2] | B2: 01tWC00000AYBXxYAP | C2: Grid Robot Name | D2: 01t4z000008h0NLAAY | E2: {=XLOOKUP(D:D, Sheet4!B:B,Sheet4!C:C, "Name", 0)} -> Grid Robot Name
A3: [Product2] | B3: 01tWC00000AYBXyYAP | C3: Verified Mark Certificate FQDN Price | D3: 01t4z000008iBW3AAM | E3: {=XLOOKUP(D:D, Sheet4!B:B,Sheet4!C:C, "Name", 0)} -> Verified Mark Certificate FQDN Price
A4: [Product2] | B4: 01tWC00000AYBXzYAP | C4: Verified Mark Certificate | D4: 01t4z000008iBW4AAM | E4: {=XLOOKUP(D:D, Sheet4!B:B,Sheet4!C:C, "Name", 0)} -> Verified Mark Certificate
A5: [Product2] | B5: 01tWC00000AYBY1YAP | C5: Code Signing (Units) | D5: 01t4z000008jjfJAAQ | E5: {=XLOOKUP(D:D, Sheet4!B:B,Sheet4!C:C, "Name", 0)} -> Code Signing (Units)
A6: [Product2] | B6: 01tWC00000AYBY2YAP | C6: Authentication Only | D6: 01t0z000007f40zAAA | E6: {=XLOOKUP(D:D, Sheet4!B:B,Sheet4!C:C, "Name", 0)} -> Authentication Only
A7: [Product2] | B7: 01tWC00000AYBY3YAP | C7: Authentication Only - Non-Repudiation | D7: 01t0z000007f410AAA | E7: {=XLOOKUP(D:D, Sheet4!B:B,Sheet4!C:C, "Name", 0)} -> Authentication Only - Non-Repudiation
A8: [Product2] | B8: 01tWC00000AYBY4YAP | C8: Authentication Plus | D8: 01t0z000007f411AAA | E8: {=XLOOKUP(D:D, Sheet4!B:B,Sheet4!C:C, "Name", 0)} -> Authentication Plus
A9: [Product2] | B9: 01tWC00000AYBY5YAP | C9: Authentication Plus (AD Integration) | D9: 01t0z000007f412AAA | E9: {=XLOOKUP(D:D, Sheet4!B:B,Sheet4!C:C, "Name", 0)} -> Authentication Plus (AD Integration)
A10: [Product2] | B10: 01tWC00000AYBY6YAP | C10: Basic EV | D10: 01t0z000007f413AAA | E10: {=XLOOKUP(D:D, Sheet4!B:B,Sheet4!C:C, "Name", 0)} -> Basic EV
A11: [Product2] | B11: 01tWC00000AYBY7YAP | C11: Basic EV FQDN SAN | D11: 01t0z000007f414AAA | E11: {=XLOOKUP(D:D, Sheet4!B:B,Sheet4!C:C, "Name", 0)} -> Basic EV FQDN SAN
A12: [Product2] | B12: 01tWC00000AYBY8YAP | C12: Basic OV | D12: 01t0z000007f415AAA | E12: {=XLOOKUP(D:D, Sheet4!B:B,Sheet4!C:C, "Name", 0)} -> Basic OV
A13: [Product2] | B13: 01tWC00000AYBY9YAP | C13: Basic OV FQDN SAN | D13: 01t0z000007f416AAA | E13: {=XLOOKUP(D:D, Sheet4!B:B,Sheet4!C:C, "Name", 0)} -> Basic OV FQDN SAN
... A428: [Product2] | B428: 01tWC00000BLkDVYA1 | C428: Dedicated offline root HSM – Cancellation Fee | D428: 01tVu000000UDcZIAW | E428: {=XLOOKUP(D:D, Sheet4!B:B,Sheet4!C:C, "Name", 0)} -> Dedicated offline root HSM – Cancellation Fee

Sheet Delete from DCFull
A1: _ | B1: Id | C1: _CreatedDate | D1: _LastModifiedDate | E1: _ | F1: _RCA_ExternalId__c | G1: _Type | H1: __Status | I1: __Id | J1: __Action | K1: __Errors
A2: [Product2] | B2: 01tdp000009GMUIAA4 | C2: 2025-12-08T20:37:43.000+0000 | D2: 2025-12-08T20:37:43.000+0000 | F2: 01tWC00000AYBa0YAH | H2: Succeeded | I2: 01tdp000009GMUIAA4 | J2: Deleted
A3: [Product2] | B3: 01tdp000009GMxDAAW | C3: 2025-12-08T20:45:00.000+0000 | D3: 2025-12-08T20:45:00.000+0000 | F3: 01tWC00000AYBa1YAH | H3: Succeeded | I3: 01tdp000009GMxDAAW | J3: Deleted
A4: [Product2] | B4: 01tdp000009GMUJAA4 | C4: 2025-12-08T20:37:43.000+0000 | D4: 2025-12-08T20:37:43.000+0000 | F4: 01tWC00000AYBa2YAH | H4: Succeeded | I4: 01tdp000009GMUJAA4 | J4: Deleted
A5: [Product2] | B5: 01tdp000009GMUKAA4 | C5: 2025-12-08T20:37:43.000+0000 | D5: 2025-12-08T20:37:43.000+0000 | F5: 01tWC00000AYBa3YAH | H5: Succeeded | I5: 01tdp000009GMUKAA4 | J5: Deleted
A6: [Product2] | B6: 01tdp000009GMxEAAW | C6: 2025-12-08T20:45:00.000+0000 | D6: 2025-12-08T20:45:00.000+0000 | F6: 01tWC00000AYBa4YAH | H6: Succeeded | I6: 01tdp000009GMxEAAW | J6: Deleted
A7: [Product2] | B7: 01tdp000009GMxFAAW | C7: 2025-12-08T20:45:00.000+0000 | D7: 2025-12-08T20:45:00.000+0000 | F7: 01tWC00000AYBa5YAH | H7: Succeeded | I7: 01tdp000009GMxFAAW | J7: Deleted
A8: [Product2] | B8: 01tdp000009GMxGAAW | C8: 2025-12-08T20:45:00.000+0000 | D8: 2025-12-08T20:45:00.000+0000 | F8: 01tWC00000AYBa6YAH | H8: Succeeded | I8: 01tdp000009GMxGAAW | J8: Deleted
A9: [Product2] | B9: 01tdp000009GMULAA4 | C9: 2025-12-08T20:37:43.000+0000 | D9: 2025-12-08T20:37:43.000+0000 | F9: 01tWC00000AYBa7YAH | H9: Succeeded | I9: 01tdp000009GMULAA4 | J9: Deleted
A10: [Product2] | B10: 01tdp000009GMUMAA4 | C10: 2025-12-08T20:37:43.000+0000 | D10: 2025-12-08T20:37:43.000+0000 | F10: 01tWC00000AYBa8YAH | H10: Succeeded | I10: 01tdp000009GMUMAA4 | J10: Deleted
A11: [Product2] | B11: 01tdp000009GMUNAA4 | C11: 2025-12-08T20:37:43.000+0000 | D11: 2025-12-08T20:37:43.000+0000 | F11: 01tWC00000AYBa9YAH | H11: Succeeded | I11: 01tdp000009GMUNAA4 | J11: Deleted
A12: [Product2] | B12: 01tdp000009GMxHAAW | C12: 2025-12-08T20:45:00.000+0000 | D12: 2025-12-08T20:45:00.000+0000 | F12: 01tWC00000AYBaAYAX | H12: Succeeded | I12: 01tdp000009GMxHAAW | J12: Deleted
A13: [Product2] | B13: 01tdp000009GMxIAAW | C13: 2025-12-08T20:45:00.000+0000 | D13: 2025-12-08T20:45:00.000+0000 | F13: 01tWC00000AYBaBYAX | H13: Failed | I13: 01tdp000009GMxIAAW | K13: DELETE_FAILED: Your attempt to delete Common Mark Certificate could not be completed because it is associated with the following quote line items.: Test_Quote-4 []
A14: [Product2] | B14: 01tdp000009GMxKAAW | C14: 2025-12-08T20:45:00.000+0000 | D14: 2025-12-08T20:45:00.000+0000 | F14: 01tWC00000AYBaDYAX | H14: Succeeded | I14: 01tdp000009GMxKAAW | J14: Deleted
A15: [Product2] | B15: 01tdp000009GMxLAAW | C15: 2025-12-08T20:45:00.000+0000 | D15: 2025-12-08T20:45:00.000+0000 | F15: 01tWC00000AYBaEYAX | H15: Failed | I15: 01tdp000009GMxLAAW | K15: DELETE_FAILED: Your attempt to delete Private Root CA Creation and Maintenance could not be completed because it is associated with the following quote line items.: Test_Quote-4 []
A16: [Product2] | B16: 01tdp000009GMxMAAW | C16: 2025-12-08T20:45:00.000+0000 | D16: 2025-12-08T20:45:00.000+0000 | F16: 01tWC00000AYBaFYAX | H16: Succeeded | I16: 01tdp000009GMxMAAW | J16: Deleted
A17: [Product2] | B17: 01tdp000009GMxNAAW | C17: 2025-12-08T20:45:00.000+0000 | D17: 2025-12-08T20:45:00.000+0000 | F17: 01tWC00000AYBaGYAX | H17: Succeeded | I17: 01tdp000009GMxNAAW | J17: Deleted
A18: [Product2] | B18: 01tdp000009GMxOAAW | C18: 2025-12-08T20:45:00.000+0000 | D18: 2025-12-08T20:45:00.000+0000 | F18: 01tWC00000AYBaHYAX | H18: Succeeded | I18: 01tdp000009GMxOAAW | J18: Deleted
A19: [Product2] | B19: 01tdp000009GMUOAA4 | C19: 2025-12-08T20:37:43.000+0000 | D19: 2025-12-08T20:37:43.000+0000 | F19: 01tWC00000AYBaIYAX | H19: Failed | I19: 01tdp000009GMUOAA4 | K19: DELETE_FAILED: Your attempt to delete DigiCert KeyLocker could not be completed because it is associated with the following quote line items.: Test_Quote-4 []
A20: [Product2] | B20: 01tdp000009GMUPAA4 | C20: 2025-12-08T20:37:43.000+0000 | D20: 2025-12-08T20:37:43.000+0000 | F20: 01tWC00000AYBaJYAX | H20: Failed | I20: 01tdp000009GMUPAA4 | K20: DELETE_FAILED: Your attempt to delete Digicert Business Plus Support could not be completed because it is associated with the following asset action sources.: AAS-000000007 Your attempt to delete Digicert Business Plus Support could not be completed because it is associated with the following opportunity products.: New Logo - 2026 - 3 Day Blinds - Your attempt to delete Digicert Business Plus Support could not be completed because it is associated with the following order products.: 0000000009 Your attempt to delete Digicert Business Plus Support could not be completed because it is associated with the following quote line items.: Test Quote, Test_Quote_1, Test, Test_Quote_3 []
A21: [Product2] | B21: 01tdp000009GMxPAAW | C21: 2025-12-08T20:45:00.000+0000 | D21: 2025-12-08T20:45:00.000+0000 | F21: 01tWC00000AYBaKYAX | H21: Succeeded | I21: 01tdp000009GMxPAAW | J21: Deleted
A22: [Product2] | B22: 01tdp000009GMxQAAW | C22: 2025-12-08T20:45:00.000+0000 | D22: 2025-12-08T20:45:00.000+0000 | F22: 01tWC00000AYBaLYAX | H22: Succeeded | I22: 01tdp000009GMxQAAW | J22: Deleted
A23: [Product2] | B23: 01tdp000009GMVdAAO | C23: 2025-12-08T20:37:44.000+0000 | D23: 2025-12-08T20:37:44.000+0000 | F23: 01tWC00000AYBaMYAX | H23: Succeeded | I23: 01tdp000009GMVdAAO | J23: Deleted
A24: [Product2] | B24: 01tdp000009GMxRAAW | C24: 2025-12-08T20:45:00.000+0000 | D24: 2025-12-08T20:45:00.000+0000 | F24: 01tWC00000AYBaNYAX | H24: Succeeded | I24: 01tdp000009GMxRAAW | J24: Deleted
A25: [Product2] | B25: 01tdp000009GMVeAAO | C25: 2025-12-08T20:37:44.000+0000 | D25: 2025-12-08T20:37:44.000+0000 | F25: 01tWC00000AYBaOYAX | H25: Succeeded | I25: 01tdp000009GMVeAAO | J25: Deleted
A26: [Product2] | B26: 01tdp000009GMVfAAO | C26: 2025-12-08T20:37:44.000+0000 | D26: 2025-12-08T20:37:44.000+0000 | F26: 01tWC00000AYBaPYAX | H26: Succeeded | I26: 01tdp000009GMVfAAO | J26: Deleted
A27: [Product2] | B27: 01tdp000009GMyfAAG | C27: 2025-12-08T20:45:00.000+0000 | D27: 2025-12-08T20:45:00.000+0000 | F27: 01tWC00000AYBaQYAX | H27: Succeeded | I27: 01tdp000009GMyfAAG | J27: Deleted
A28: [Product2] | B28: 01tdp000009GMQnAAO | C28: 2025-12-08T20:37:41.000+0000 | D28: 2025-12-08T20:37:41.000+0000 | F28: 01tWC00000AYBXxYAP | H28: Succeeded | I28: 01tdp000009GMQnAAO | J28: Deleted
A29: [Product2] | B29: 01tdp000009GMQoAAO | C29: 2025-12-08T20:37:41.000+0000 | D29: 2025-12-08T20:37:41.000+0000 | F29: 01tWC00000AYBXyYAP | H29: Succeeded | I29: 01tdp000009GMQoAAO | J29: Deleted
A30: [Product2] | B30: 01tdp000009GMQpAAO | C30: 2025-12-08T20:37:41.000+0000 | D30: 2025-12-08T20:37:41.000+0000 | F30: 01tWC00000AYBXzYAP | H30: Succeeded | I30: 01tdp000009GMQpAAO | J30: Deleted
A31: [Product2] | B31: 01tdp000009GMQqAAO | C31: 2025-12-08T20:37:41.000+0000 | D31: 2025-12-08T20:37:41.000+0000 | F31: 01tWC00000AYBY1YAP | H31: Succeeded | I31: 01tdp000009GMQqAAO | J31: Deleted
A32: [Product2] | B32: 01tdp000009GMtqAAG | C32: 2025-12-08T20:44:57.000+0000 | D32: 2025-12-08T20:44:57.000+0000 | F32: 01tWC00000AYBY2YAP | H32: Succeeded | I32: 01tdp000009GMtqAAG | J32: Deleted
... A76: [Product2] | B76: 01tdp000009GMvVAAW | C76: 2025-12-08T20:44:59.000+0000 | D76: 2025-12-08T20:44:59.000+0000 | F76: 01tWC00000AYBYsYAP | H76: Succeeded | I76: 01tdp000009GMvVAAW | J76: Deleted
A77: [Product2] | B77: 01tdp000009GMu7AAG | C77: 2025-12-08T20:44:57.000+0000 | D77: 2025-12-08T20:44:57.000+0000 | F77: 01tWC00000AYBYTYA5 | H77: Failed | I77: 01tdp000009GMu7AAG | K77: DELETE_FAILED: Your attempt to delete Premium (Class 2 S/MIME) could not be completed because it is associated with the following opportunity products.: New Logo - 2026 - AdForce Advertising Agency - Your attempt to delete Premium (Class 2 S/MIME) could not be completed because it is associated with the following quote line items.: Sanity_QA []
A78: [Product2] | B78: 01tdp000009GMSSAA4 | C78: 2025-12-08T20:37:42.000+0000 | D78: 2025-12-08T20:37:42.000+0000 | F78: 01tWC00000AYBYtYAP | H78: Succeeded | I78: 01tdp000009GMSSAA4 | J78: Deleted
A79: [Product2] | B79: 01tdp000009GMR1AAO | C79: 2025-12-08T20:37:41.000+0000 | D79: 2025-12-08T20:37:41.000+0000 | F79: 01tWC00000AYBYUYA5 | H79: Succeeded | I79: 01tdp000009GMR1AAO | J79: Deleted
A80: [Product2] | B80: 01tdp000009GMvWAAW | C80: 2025-12-08T20:44:59.000+0000 | D80: 2025-12-08T20:44:59.000+0000 | F80: 01tWC00000AYBYuYAP | H80: Succeeded | I80: 01tdp000009GMvWAAW | J80: Deleted
A81: [Product2] | B81: 01tdp000009GMu8AAG | C81: 2025-12-08T20:44:57.000+0000 | D81: 2025-12-08T20:44:57.000+0000 | F81: 01tWC00000AYBYVYA5 | H81: Succeeded | I81: 01tdp000009GMu8AAG | J81: Deleted
A82: [Product2] | B82: 01tdp000009GMvXAAW | C82: 2025-12-08T20:44:59.000+0000 | D82: 2025-12-08T20:44:59.000+0000 | F82: 01tWC00000AYBYvYAP | H82: Succeeded | I82: 01tdp000009GMvXAAW | J82: Deleted
A83: [Product2] | B83: 01tdp000009GMR2AAO | C83: 2025-12-08T20:37:41.000+0000 | D83: 2025-12-08T20:37:41.000+0000 | F83: 01tWC00000AYBYWYA5 | H83: Succeeded | I83: 01tdp000009GMR2AAO | J83: Deleted
A84: [Product2] | B84: 01tdp000009GMSTAA4 | C84: 2025-12-08T20:37:42.000+0000 | D84: 2025-12-08T20:37:42.000+0000 | F84: 01tWC00000AYBYwYAP | H84: Succeeded | I84: 01tdp000009GMSTAA4 | J84: Deleted
A85: [Product2] | B85: 01tdp000009GMR3AAO | C85: 2025-12-08T20:37:41.000+0000 | D85: 2025-12-08T20:37:41.000+0000 | F85: 01tWC00000AYBYXYA5 | H85: Succeeded | I85: 01tdp000009GMR3AAO | J85: Deleted
A86: [Product2] | B86: 01tdp000009GMvYAAW | C86: 2025-12-08T20:44:59.000+0000 | D86: 2025-12-08T20:44:59.000+0000 | F86: 01tWC00000AYBYxYAP | H86: Succeeded | I86: 01tdp000009GMvYAAW | J86: Deleted
A87: [Product2] | B87: 01tdp000009GMu9AAG | C87: 2025-12-08T20:44:57.000+0000 | D87: 2025-12-08T20:44:57.000+0000 | F87: 01tWC00000AYBYYYA5 | H87: Succeeded | I87: 01tdp000009GMu9AAG | J87: Deleted
A88: [Product2] | B88: 01tdp000009GMSUAA4 | C88: 2025-12-08T20:37:42.000+0000 | D88: 2025-12-08T20:37:42.000+0000 | F88: 01tWC00000AYBYyYAP | H88: Succeeded | I88: 01tdp000009GMSUAA4 | J88: Deleted
A89: [Product2] | B89: 01tdp000009GMR4AAO | C89: 2025-12-08T20:37:41.000+0000 | D89: 2025-12-08T20:37:41.000+0000 | F89: 01tWC00000AYBYZYA5 | H89: Succeeded | I89: 01tdp000009GMR4AAO | J89: Deleted
... A122: [Product2] | B122: 01tdp000009GMSiAAO | C122: 2025-12-08T20:37:42.000+0000 | D122: 2025-12-08T20:37:42.000+0000 | F122: 01tWC00000AYBZLYA5 | H122: Succeeded | I122: 01tdp000009GMSiAAO | J122: Deleted
A123: [Product2] | B123: 01tdp000009GMx7AAG | C123: 2025-12-08T20:45:00.000+0000 | D123: 2025-12-08T20:45:00.000+0000 | F123: 01tWC00000AYBZlYAP | H123: Failed | I123: 01tdp000009GMx7AAG | K123: DELETE_FAILED: Your attempt to delete Digicert Business Support could not be completed because it is associated with the following opportunity products.: New Logo - 2026 - 3 Day Blinds -, New Logo - 2026 - AdForce Advertising Agency -, New Logo - 2025 - DCFull-Account 1 - Your attempt to delete Digicert Business Support could not be completed because it is associated with the following quote line items.: Test_Quote_2, Test_Quote_1, Test_Quote_3, Sanity_QA, ... []
A124: [Product2] | B124: 01tdp000009GMviAAG | C124: 2025-12-08T20:44:59.000+0000 | D124: 2025-12-08T20:44:59.000+0000 | F124: 01tWC00000AYBZMYA5 | H124: Succeeded | I124: 01tdp000009GMviAAG | J124: Deleted
A125: [Product2] | B125: 01tdp000009GMU9AAO | C125: 2025-12-08T20:37:43.000+0000 | D125: 2025-12-08T20:37:43.000+0000 | F125: 01tWC00000AYBZmYAP | H125: Failed | I125: 01tdp000009GMU9AAO | K125: DELETE_FAILED: Your attempt to delete Digicert Premium Support could not be completed because it is associated with the following opportunity products.: New Logo - 2026 - 3 Day Blinds -, New Logo - 2026 - AdForce Advertising Agency - Your attempt to delete Digicert Premium Support could not be completed because it is associated with the following quote line items.: Test_Quote_1, Dec 15, Test_Quote_3, Sanity_QA, ... []
A126: [Product2] | B126: 01tdp000009GMSjAAO | C126: 2025-12-08T20:37:42.000+0000 | D126: 2025-12-08T20:37:42.000+0000 | F126: 01tWC00000AYBZNYA5 | H126: Succeeded | I126: 01tdp000009GMSjAAO | J126: Deleted
A127: [Product2] | B127: 01tdp000009GMUAAA4 | C127: 2025-12-08T20:37:43.000+0000 | D127: 2025-12-08T20:37:43.000+0000 | F127: 01tWC00000AYBZnYAP | H127: Succeeded | I127: 01tdp000009GMUAAA4 | J127: Deleted
A128: [Product2] | B128: 01tdp000009GMvjAAG | C128: 2025-12-08T20:44:59.000+0000 | D128: 2025-12-08T20:44:59.000+0000 | F128: 01tWC00000AYBZOYA5 | H128: Succeeded | I128: 01tdp000009GMvjAAG | J128: Deleted
A129: [Product2] | B129: 01tdp000009GMUBAA4 | C129: 2025-12-08T20:37:43.000+0000 | D129: 2025-12-08T20:37:43.000+0000 | F129: 01tWC00000AYBZoYAP | H129: Succeeded | I129: 01tdp000009GMUBAA4 | J129: Deleted
A130: [Product2] | B130: 01tdp000009GMSkAAO | C130: 2025-12-08T20:37:42.000+0000 | D130: 2025-12-08T20:37:42.000+0000 | F130: 01tWC00000AYBZPYA5 | H130: Succeeded | I130: 01tdp000009GMSkAAO | J130: Deleted
A131: [Product2] | B131: 01tdp000009GMUCAA4 | C131: 2025-12-08T20:37:43.000+0000 | D131: 2025-12-08T20:37:43.000+0000 | F131: 01tWC00000AYBZpYAP | H131: Succeeded | I131: 01tdp000009GMUCAA4 | J131: Deleted
A132: [Product2] | B132: 01tdp000009GMSlAAO | C132: 2025-12-08T20:37:42.000+0000 | D132: 2025-12-08T20:37:42.000+0000 | F132: 01tWC00000AYBZQYA5 | H132: Failed | I132: 01tdp000009GMSlAAO | K132: DELETE_FAILED: Your attempt to delete Dedicated Public CA Creation and Maintenance could not be completed because it is associated with the following asset action sources.: AAS-000000003 Your attempt to delete Dedicated Public CA Creation and Maintenance could not be completed because it is associated with the following opportunity products.: New Logo - 2026 - AdForce Advertising Agency - Your attempt to delete Dedicated Public CA Creation and Maintenance could not be completed because it is associated with the following order products.: 0000000012 Your attempt to delete Dedicated Public CA Creation and Maintenance could not be completed because it is associated with the following quote line items.: Test Quote, Sanity_QA []
A133: [Product2] | B133: 01tdp000009GMx8AAG | C133: 2025-12-08T20:45:00.000+0000 | D133: 2025-12-08T20:45:00.000+0000 | F133: 01tWC00000AYBZqYAP | H133: Succeeded | I133: 01tdp000009GMx8AAG | J133: Deleted
A134: [Product2] | B134: 01tdp000009GMSmAAO | C134: 2025-12-08T20:37:42.000+0000 | D134: 2025-12-08T20:37:42.000+0000 | F134: 01tWC00000AYBZRYA5 | H134: Succeeded | I134: 01tdp000009GMSmAAO | J134: Deleted
A135: [Product2] | B135: 01tdp000009GMx9AAG | C135: 2025-12-08T20:45:00.000+0000 | D135: 2025-12-08T20:45:00.000+0000 | F135: 01tWC00000AYBZrYAP | H135: Succeeded | I135: 01tdp000009GMx9AAG | J135: Deleted
A136: [Product2] | B136: 01tdp000009GMSnAAO | C136: 2025-12-08T20:37:42.000+0000 | D136: 2025-12-08T20:37:42.000+0000 | F136: 01tWC00000AYBZSYA5 | H136: Succeeded | I136: 01tdp000009GMSnAAO | J136: Deleted
A137: [Product2] | B137: 01tdp000009GMxAAAW | C137: 2025-12-08T20:45:00.000+0000 | D137: 2025-12-08T20:45:00.000+0000 | F137: 01tWC00000AYBZsYAP | H137: Succeeded | I137: 01tdp000009GMxAAAW | J137: Deleted
A138: [Product2] | B138: 01tdp000009GMvkAAG | C138: 2025-12-08T20:44:59.000+0000 | D138: 2025-12-08T20:44:59.000+0000 | F138: 01tWC00000AYBZTYA5 | H138: Succeeded | I138: 01tdp000009GMvkAAG | J138: Deleted
A139: [Product2] | B139: 01tdp000009GMxBAAW | C139: 2025-12-08T20:45:00.000+0000 | D139: 2025-12-08T20:45:00.000+0000 | F139: 01tWC00000AYBZtYAP | H139: Failed | I139: 01tdp000009GMxBAAW | K139: DELETE_FAILED: Your attempt to delete EU Qualified Website Authentication Certificate (QWAC) PSD2 could not be completed because it is associated with the following quote line items.: Test_Quote-4 []
A140: [Product2] | B140: 01tdp000009GMvlAAG | C140: 2025-12-08T20:44:59.000+0000 | D140: 2025-12-08T20:44:59.000+0000 | F140: 01tWC00000AYBZUYA5 | H140: Succeeded | I140: 01tdp000009GMvlAAG | J140: Deleted
A141: [Product2] | B141: 01tdp000009GMUDAA4 | C141: 2025-12-08T20:37:43.000+0000 | D141: 2025-12-08T20:37:43.000+0000 | F141: 01tWC00000AYBZuYAP | H141: Failed | I141: 01tdp000009GMUDAA4 | K141: DELETE_FAILED: Your attempt to delete EU Electronic Seal could not be completed because it is associated with the following asset action sources.: AAS-000000006 Your attempt to delete EU Electronic Seal could not be completed because it is associated with the following opportunity products.: New Logo - 2026 - 3 Day Blinds -, New Logo - 2026 - AdForce Advertising Agency - Your attempt to delete EU Electronic Seal could not be completed because it is associated with the following order products.: 0000000010 Your attempt to delete EU Electronic Seal could not be completed because it is associated with the following quote line items.: Test Quote, Test_Quote_1, Sanity_QA, Test_Quote-4 []
A142: [Product2] | B142: 01tdp000009GMvmAAG | C142: 2025-12-08T20:44:59.000+0000 | D142: 2025-12-08T20:44:59.000+0000 | F142: 01tWC00000AYBZVYA5 | H142: Succeeded | I142: 01tdp000009GMvmAAG | J142: Deleted
A143: [Product2] | B143: 01tdp000009GMUEAA4 | C143: 2025-12-08T20:37:43.000+0000 | D143: 2025-12-08T20:37:43.000+0000 | F143: 01tWC00000AYBZvYAP | H143: Failed | I143: 01tdp000009GMUEAA4 | K143: DELETE_FAILED: Your attempt to delete EU Electronic Seal PSD2 could not be completed because it is associated with the following asset action sources.: AAS-000000005 Your attempt to delete EU Electronic Seal PSD2 could not be completed because it is associated with the following order products.: 0000000008 Your attempt to delete EU Electronic Seal PSD2 could not be completed because it is associated with the following quote line items.: Test Quote []
A144: [Product2] | B144: 01tdp000009GMU1AAO | C144: 2025-12-08T20:37:43.000+0000 | D144: 2025-12-08T20:37:43.000+0000 | F144: 01tWC00000AYBZWYA5 | H144: Succeeded | I144: 01tdp000009GMU1AAO | J144: Deleted
A145: [Product2] | B145: 01tdp000009GMUFAA4 | C145: 2025-12-08T20:37:43.000+0000 | D145: 2025-12-08T20:37:43.000+0000 | F145: 01tWC00000AYBZwYAP | H145: Failed | I145: 01tdp000009GMUFAA4 | K145: DELETE_FAILED: Your attempt to delete EU Individual could not be completed because it is associated with the following opportunity products.: New Logo - 2026 - AdForce Advertising Agency - Your attempt to delete EU Individual could not be completed because it is associated with the following quote line items.: Sanity_QA []
A146: [Product2] | B146: 01tdp000009GMvnAAG | C146: 2025-12-08T20:44:59.000+0000 | D146: 2025-12-08T20:44:59.000+0000 | F146: 01tWC00000AYBZXYA5 | H146: Succeeded | I146: 01tdp000009GMvnAAG | J146: Deleted
A147: [Product2] | B147: 01tdp000009GMxCAAW | C147: 2025-12-08T20:45:00.000+0000 | D147: 2025-12-08T20:45:00.000+0000 | F147: 01tWC00000AYBZxYAP | H147: Succeeded | I147: 01tdp000009GMxCAAW | J147: Deleted
A148: [Product2] | B148: 01tdp000009GMvoAAG | C148: 2025-12-08T20:44:59.000+0000 | D148: 2025-12-08T20:44:59.000+0000 | F148: 01tWC00000AYBZYYA5 | H148: Succeeded | I148: 01tdp000009GMvoAAG | J148: Deleted
A149: [Product2] | B149: 01tdp000009GMUGAA4 | C149: 2025-12-08T20:37:43.000+0000 | D149: 2025-12-08T20:37:43.000+0000 | F149: 01tWC00000AYBZyYAP | H149: Succeeded | I149: 01tdp000009GMUGAA4 | J149: Deleted
A150: [Product2] | B150: 01tdp000009GMU2AAO | C150: 2025-12-08T20:37:43.000+0000 | D150: 2025-12-08T20:37:43.000+0000 | F150: 01tWC00000AYBZZYA5 | H150: Succeeded | I150: 01tdp000009GMU2AAO | J150: Deleted
A151: [Product2] | B151: 01tdp000009GMUHAA4 | C151: 2025-12-08T20:37:43.000+0000 | D151: 2025-12-08T20:37:43.000+0000 | F151: 01tWC00000AYBZzYAP | H151: Succeeded | I151: 01tdp000009GMUHAA4 | J151: Deleted
A152: [Product2] | B152: 01tdp000009GMypAAG | C152: 2025-12-08T20:45:00.000+0000 | D152: 2025-12-08T20:45:00.000+0000 | F152: 01tWC00000AYLfaYAH | H152: Succeeded | I152: 01tdp000009GMypAAG | J152: Deleted
A153: [Product2] | B153: 01tdp000009GMVkAAO | C153: 2025-12-08T20:37:44.000+0000 | D153: 2025-12-08T20:37:44.000+0000 | F153: 01tWC00000AYLfbYAH | H153: Succeeded | I153: 01tdp000009GMVkAAO | J153: Deleted
A154: [Product2] | B154: 01tdp000009GMyqAAG | C154: 2025-12-08T20:45:00.000+0000 | D154: 2025-12-08T20:45:00.000+0000 | F154: 01tWC00000AYLfcYAH | H154: Succeeded | I154: 01tdp000009GMyqAAG | J154: Deleted
A155: [Product2] | B155: 01tdp000009GMyrAAG | C155: 2025-12-08T20:45:00.000+0000 | D155: 2025-12-08T20:45:00.000+0000 | F155: 01tWC00000AYLfdYAH | H155: Succeeded | I155: 01tdp000009GMyrAAG | J155: Deleted
A156: [Product2] | B156: 01tdp000009GMysAAG | C156: 2025-12-08T20:45:00.000+0000 | D156: 2025-12-08T20:45:00.000+0000 | F156: 01tWC00000AYLfeYAH | H156: Succeeded | I156: 01tdp000009GMysAAG | J156: Deleted
A157: [Product2] | B157: 01tdp000009GMVlAAO | C157: 2025-12-08T20:37:44.000+0000 | D157: 2025-12-08T20:37:44.000+0000 | F157: 01tWC00000AYLffYAH | H157: Succeeded | I157: 01tdp000009GMVlAAO | J157: Deleted
... A233: [Product2] | B233: 01tdp000009GMXNAA4 | C233: 2025-12-08T20:37:45.000+0000 | D233: 2025-12-08T20:37:45.000+0000 | F233: 01tWC00000AYLgZYAX | H233: Succeeded | I233: 01tdp000009GMXNAA4 | J233: Deleted
A234: [Product2] | B234: 01tdp000009GN0fAAG | C234: 2025-12-08T20:45:01.000+0000 | D234: 2025-12-08T20:45:01.000+0000 | F234: 01tWC00000AYNajYAH | H234: Failed | I234: 01tdp000009GN0fAAG | K234: DELETE_FAILED: Your attempt to delete (GEMALTO) USB AUTHENTICATOR 5110CC PLUS NO PIN 3YR WARRANTY could not be completed because it is associated with the following quote line items.: Test Quote []
A235: [Product2] | B235: 01tdp000009GN1tAAG | C235: 2025-12-08T20:45:01.000+0000 | D235: 2025-12-08T20:45:01.000+0000 | F235: 01tWC00000AYNakYAH | H235: Succeeded | I235: 01tdp000009GN1tAAG | J235: Deleted
A236: [Product2] | B236: 01tdp000009GMXRAA4 | C236: 2025-12-08T20:37:45.000+0000 | D236: 2025-12-08T20:37:45.000+0000 | F236: 01tWC00000AYNalYAH | H236: Succeeded | I236: 01tdp000009GMXRAA4 | J236: Deleted
A237: [Product2] | B237: 01tdp000009GN1uAAG | C237: 2025-12-08T20:45:01.000+0000 | D237: 2025-12-08T20:45:01.000+0000 | F237: 01tWC00000AYNamYAH | H237: Failed | I237: 01tdp000009GN1uAAG | K237: DELETE_FAILED: Your attempt to delete vSEC:CMS S-Series Device License could not be completed because it is associated with the following quote line items.: Test_Quote-4 []
A238: [Product2] | B238: 01tdp000009GMXSAA4 | C238: 2025-12-08T20:37:45.000+0000 | D238: 2025-12-08T20:37:45.000+0000 | F238: 01tWC00000AYNanYAH | H238: Failed | I238: 01tdp000009GMXSAA4 | K238: DELETE_FAILED: Your attempt to delete Ascertia Signature Unit Pack could not be completed because it is associated with the following opportunity products.: New Logo - 2025 - AdForce Advertising Agency - Your attempt to delete Ascertia Signature Unit Pack could not be completed because it is associated with the following quote line items.: Test_Quote-4, Test_Quote-4, Test Quote 15-12-2025 []
A239: [Product2] | B239: 01tdp000009GMXTAA4 | C239: 2025-12-08T20:37:45.000+0000 | D239: 2025-12-08T20:37:45.000+0000 | F239: 01tWC00000AYNaoYAH | H239: Succeeded | I239: 01tdp000009GMXTAA4 | J239: Deleted
A240: [Product2] | B240: 01tdp000009GN1vAAG | C240: 2025-12-08T20:45:01.000+0000 | D240: 2025-12-08T20:45:01.000+0000 | F240: 01tWC00000AYNapYAH | H240: Succeeded | I240: 01tdp000009GN1vAAG | J240: Deleted
A241: [Product2] | B241: 01tdp000009GMXUAA4 | C241: 2025-12-08T20:37:45.000+0000 | D241: 2025-12-08T20:37:45.000+0000 | F241: 01tWC00000AYNaqYAH | H241: Succeeded | I241: 01tdp000009GMXUAA4 | J241: Deleted
A242: [Product2] | B242: 01tdp000009GMXVAA4 | C242: 2025-12-08T20:37:45.000+0000 | D242: 2025-12-08T20:37:45.000+0000 | F242: 01tWC00000AYNarYAH | H242: Succeeded | I242: 01tdp000009GMXVAA4 | J242: Deleted
A243: [Product2] | B243: 01tdp000009GN1wAAG | C243: 2025-12-08T20:45:01.000+0000 | D243: 2025-12-08T20:45:01.000+0000 | F243: 01tWC00000AYNasYAH | H243: Succeeded | I243: 01tdp000009GN1wAAG | J243: Deleted
A244: [Product2] | B244: 01tdp000009GN1xAAG | C244: 2025-12-08T20:45:01.000+0000 | D244: 2025-12-08T20:45:01.000+0000 | F244: 01tWC00000AYNatYAH | H244: Succeeded | I244: 01tdp000009GN1xAAG | J244: Deleted
A245: [Product2] | B245: 01tdp000009GN1yAAG | C245: 2025-12-08T20:45:01.000+0000 | D245: 2025-12-08T20:45:01.000+0000 | F245: 01tWC00000AYNauYAH | H245: Succeeded | I245: 01tdp000009GN1yAAG | J245: Deleted
A246: [Product2] | B246: 01tdp000009GN1zAAG | C246: 2025-12-08T20:45:01.000+0000 | D246: 2025-12-08T20:45:01.000+0000 | F246: 01tWC00000AYNavYAH | H246: Succeeded | I246: 01tdp000009GN1zAAG | J246: Deleted
A247: [Product2] | B247: 01tdp000009GMXWAA4 | C247: 2025-12-08T20:37:45.000+0000 | D247: 2025-12-08T20:37:45.000+0000 | F247: 01tWC00000AYNawYAH | H247: Succeeded | I247: 01tdp000009GMXWAA4 | J247: Deleted
A248: [Product2] | B248: 01tdp000009GN20AAG | C248: 2025-12-08T20:45:01.000+0000 | D248: 2025-12-08T20:45:01.000+0000 | F248: 01tWC00000AYNaxYAH | H248: Succeeded | I248: 01tdp000009GN20AAG | J248: Deleted
A249: [Product2] | B249: 01tdp000009GMXXAA4 | C249: 2025-12-08T20:37:45.000+0000 | D249: 2025-12-08T20:37:45.000+0000 | F249: 01tWC00000AYNayYAH | H249: Succeeded | I249: 01tdp000009GMXXAA4 | J249: Deleted
A250: [Product2] | B250: 01tdp000009GN21AAG | C250: 2025-12-08T20:45:01.000+0000 | D250: 2025-12-08T20:45:01.000+0000 | F250: 01tWC00000AYNazYAH | H250: Succeeded | I250: 01tdp000009GN21AAG | J250: Deleted
...

Sheet Inactivated
A1: _ | B1: Id | C1: Name | D1: CreatedDate | E1: LastModifiedDate | F1: IsActive
A2: [Product2] | B2: 01tdp000009GMSlAAO | C2: Dedicated Public CA Creation and Maintenance | D2: 2025-12-08T20:37:42.000+0000 | E2: 2025-12-08T20:37:42.000+0000 | F2: FALSE
A3: [Product2] | B3: 01tdp000009GMU9AAO | C3: Digicert Premium Support | D3: 2025-12-08T20:37:43.000+0000 | E3: 2025-12-08T20:37:43.000+0000 | F3: FALSE
A4: [Product2] | B4: 01tdp000009GMUDAA4 | C4: EU Electronic Seal | D4: 2025-12-08T20:37:43.000+0000 | E4: 2025-12-08T20:37:43.000+0000 | F4: FALSE
A5: [Product2] | B5: 01tdp000009GMUEAA4 | C5: EU Electronic Seal PSD2 | D5: 2025-12-08T20:37:43.000+0000 | E5: 2025-12-08T20:37:43.000+0000 | F5: FALSE
A6: [Product2] | B6: 01tdp000009GMUFAA4 | C6: EU Individual | D6: 2025-12-08T20:37:43.000+0000 | E6: 2025-12-08T20:37:43.000+0000 | F6: FALSE
A7: [Product2] | B7: 01tdp000009GMUOAA4 | C7: DigiCert KeyLocker | D7: 2025-12-08T20:37:43.000+0000 | E7: 2025-12-08T20:37:43.000+0000 | F7: FALSE
A8: [Product2] | B8: 01tdp000009GMUPAA4 | C8: Digicert Business Plus Support | D8: 2025-12-08T20:37:43.000+0000 | E8: 2025-12-08T20:37:43.000+0000 | F8: FALSE
A9: [Product2] | B9: 01tdp000009GMXSAA4 | C9: Ascertia Signature Unit Pack | D9: 2025-12-08T20:37:45.000+0000 | E9: 2025-12-08T20:37:45.000+0000 | F9: FALSE
A10: [Product2] | B10: 01tdp000009GMZ0AAO | C10: DigiCert MSP Hub | D10: 2025-12-08T20:37:45.000+0000 | E10: 2025-12-08T20:37:45.000+0000 | F10: FALSE
A11: [Product2] | B11: 01tdp000009GMaVAAW | C11: 3rd Party Professional Services Offerings | D11: 2025-12-08T20:37:45.000+0000 | E11: 2025-12-08T20:37:45.000+0000 | F11: FALSE
A12: [Product2] | B12: 01tdp000009GMamAAG | C12: Ascertia Service License | D12: 2025-12-08T20:37:45.000+0000 | E12: 2025-12-08T20:37:45.000+0000 | F12: FALSE
A13: [Product2] | B13: 01tdp000009GMu7AAG | C13: Premium (Class 2 S/MIME) | D13: 2025-12-08T20:44:57.000+0000 | E13: 2025-12-08T20:44:57.000+0000 | F13: FALSE
... A31: [Product2] | B31: 01tdp000009GN6qAAG | C31: Ascertia Level 2 support 24x7x365 | D31: 2025-12-08T20:45:02.000+0000 | E31: 2025-12-08T20:45:02.000+0000 | F31: FALSE

Sheet Dev - Product2
A1: _ | B1: Name | C1: ProductCode | D1: Description | E1: IsActive | F1: Family | G1: CurrencyIsoCode | H1: RecordTypeId | I1: ExternalDataSourceId | J1: Id | K1: RCA_ExternalId__c | L1: ExternalId | M1: DisplayUrl | N1: QuantityUnitOfMeasure | O1: StockKeepingUnit | P1: Type | Q1: AvailabilityDate | R1: DiscontinuedDate | S1: BasedOnId | T1: EndOfLifeDate | U1: HelpText | V1: IsAssetizable | W1: ConfigureDuringSale | X1: IsSoldOnlyWithOtherProds | Y1: SpecificationType | Z1: CanRamp | AA1: UsageModelType | AB1: Product_Type__c | AC1: GLOBAL_SPECIALIZATION__c | AD1: Internal_Peak__c | AE1: Oracle_Product_Code__c | AF1: Part_Number__c | AG1: Product_Category__c | AH1: Product_Family_Description__c | AI1: Product_Information__c | AJ1: Product_Subcategory__c | AK1: Quotable_Flag__c | AL1: SYMC_CreatedByID__c | AM1: SYMC_LastModifiedByID__c | AN1: Apttus_Config2__BundleInvoiceLevel__c | AO1: Zproduct_Id__c | AP1: Offering_Type__c | AQ1: Admin_Area_ID__c | AR1: Apttus_Config2__RenewalLeadTime__c | AS1: Category_L__c | AT1: Cost__c | AU1: FA_product_line__c | AV1: Genkaritsu__c | AW1: Hanbai_Keitai__c | AX1: Num_Hanbai__c | AY1: Product_Bunrui__c | AZ1: Public_Private__c | BA1: US_Report_Category__c | BB1: activedate_from__c | BC1: activedate_to__c | BD1: category_M__c | BE1: category_s__c | BF1: defered_term__c | BG1: delete_flags__c | BH1: ebs_account__c | BI1: ebs_business_unit__c | BJ1: ebs_business_unit_description__c | BK1: ebs_customer_order_enabled_flag__c | BL1: ebs_customer_order_flag__c | BM1: ebs_description__c | BN1: ebs_enabled_flag__c | BO1: ebs_invoice_enabled_flag__c | BP1: ebs_invoiceable_item_flag__c | BQ1: ebs_item_id__c | BR1: ebs_item_num__c | BS1: ebs_item_type__c | BT1: ebs_language__c | BU1: ebs_language_description__c | BV1: ebs_master_description__c | BW1: ebs_organization_id__c | BX1: ebs_product_line__c | BY1: ebs_product_line_description__c | BZ1: ebs_product_name__c | CA1: ebs_tax_code__c | CB1: ebs_unit_of_issue__c | CC1: kame_product_id__c | CD1: product_flag__c | CE1: revenue_type_id__c | CF1: servicelist__c | CG1: APTS_Apttus_Product__c | CH1: APTS_Cert_Category__c | CI1: APTS_Console__c | CJ1: APTS_Contract_Consumption_Method__c | CK1: APTS_Ext_ID__c | CL1: APTS_Is_Amendable__c | CM1: APTS_Is_Renewable__c | CN1: APTS_New_CPQ_CertCentral__c | CO1: APTS_Order__c | CP1: APTS_Product_Id_18__c | CQ1: APTS_Product_Line__c | CR1: APTS_Requires_CPF_Doc__c | CS1: APTS_Target_Channel__c | CT1: Type_QV__c | CU1: APTS_Config_Schema__c | CV1: APTS_Exclude_from_Ramping_Validation__c | CW1: ebs_invoicing_rule_id__c | CX1: APTS_Exclude_From_Channel_Discounts__c | CY1: APTS_True_Up_Product__c | CZ1: APTS_Japanese_Product_Name__c | DA1: Non_Recurring_Checkbox__c | DB1: Non_Future_Contracted__c | DC1: cc_product_api_id__c | DD1: APTS_Product_Category__c | DE1: APTS_Product_Line_L2__c | DF1: APTS_Product_Organisation_L1__c | DG1: APTS_Product_category_L3__c | DH1: APTS_Attributes_To_Consider_SKU__c | DI1: APTS_Do_not_consider_for_SKU_Code__c | DJ1: APTS_no_of_attributes_SKU__c | DK1: APTS_Level1_Abbrv__c | DL1: APTS_Level_2_Abbrv__c | DM1: APTS_Level_3_Abbrv__c | DN1: APTS_Product_Code_with_SKU__c | DO1: APTS_SKU_Code__c | DP1: Product_Category_SFDC__c | DQ1: APTS_Is_MSP_Quotable__c | DR1: Charge_Type__c | DS1: Is_Manual__c | DT1: Overage_Rate__c | DU1: Product_Alias__c | DV1: Product_Group__c | DW1: Unit__c | DX1: Charge_Model__c | DY1: ProductGroup__c | DZ1: RCA_Lifecycle_Status__c
A2: [Product2] | B2: Grid Robot Name | C2: Grid Robot Name | E2: TRUE | F2: DigiCert | G2: USD | H2: 012dp000005zfL7AAI | J2: 01t4z000008h0NLAAY | K2: 01t4z000008h0NLAAY | L2: 01t4z000008h0NLAAY | S2: 11BWC000002WLZ42AO | V2: TRUE | X2: TRUE | Y2: Commercial | Z2: FALSE | BG2: FALSE | CD2: FALSE | CG2: FALSE | CL2: FALSE | CM2: FALSE | CN2: FALSE | CP2: 01tWC00000AYBXxYAP | CR2: FALSE | CV2: FALSE | CX2: FALSE | CY2: FALSE | DA2: FALSE | DB2: FALSE | DI2: FALSE | DN2: Grid Robot Name | DQ2: FALSE | DS2: FALSE | DU2: Grid Robot Name | DY2: All SSL Product Grp | DZ2: Active
A3: [Product2] | B3: Verified Mark Certificate FQDN Price | C3: 99 | E3: TRUE | F3: DigiCert | G3: USD | H3: 012dp000005zfL7AAI | J3: 01t4z000008iBW3AAM | K3: 01t4z000008iBW3AAM | L3: 01t4z000008iBW3AAM | S3: 11BWC000002cka92AA | V3: TRUE | X3: TRUE | Y3: Commercial | Z3: FALSE | BG3: FALSE | CD3: FALSE | CG3: FALSE | CL3: FALSE | CM3: FALSE | CN3: FALSE | CP3: 01tWC00000AYBXyYAP | CR3: FALSE | CV3: FALSE | CX3: FALSE | CY3: FALSE | DA3: FALSE | DB3: FALSE | DI3: FALSE | DN3: 99 | DQ3: FALSE | DS3: FALSE | DU3: Verified Mark Certificate FQDN Price | DY3: All SSL Product Grp | DZ3: Active
A4: [Product2] | B4: Verified Mark Certificate | C4: 99-san | E4: TRUE | F4: DigiCert | G4: USD | H4: 012dp000005zfL7AAI | J4: 01t4z000008iBW4AAM | K4: 01t4z000008iBW4AAM | L4: 01t4z000008iBW4AAM | V4: TRUE | X4: TRUE | Y4: Commercial | Z4: FALSE | BG4: FALSE | CD4: FALSE | CG4: FALSE | CL4: FALSE | CM4: FALSE | CN4: FALSE | CP4: 01tWC00000AYBXzYAP | CR4: FALSE | CV4: FALSE | CX4: FALSE | CY4: FALSE | DA4: FALSE | DB4: FALSE | DI4: FALSE | DN4: 99-san | DQ4: FALSE | DS4: FALSE | DU4: Verified Mark Certificate | DZ4: Active
A5: [Product2] | B5: Code Signing (Units) | C5: Code Signing (Units) | E5: TRUE | F5: DigiCert | G5: USD | H5: 012dp000005zfL7AAI | J5: 01t4z000008jjfJAAQ | K5: 01t4z000008jjfJAAQ | L5: 01t4z000008jjfJAAQ | V5: TRUE | W5: Allowed | X5: TRUE | Y5: Commercial | Z5: FALSE | BG5: FALSE | CD5: FALSE | CG5: FALSE | CL5: FALSE | CM5: FALSE | CN5: FALSE | CP5: 01tWC00000AYBY1YAP | CR5: FALSE | CV5: FALSE | CX5: FALSE | CY5: FALSE | DA5: FALSE | DB5: FALSE | DI5: FALSE | DN5: Code Signing (Units) | DQ5: FALSE | DS5: FALSE | DU5: Code Signing (Units) | DZ5: Active
A6: [Product2] | B6: Authentication Only | C6: Authentication Only | E6: TRUE | F6: DigiCert | G6: USD | H6: 012dp000005zfL7AAI | J6: 01t0z000007f40zAAA | K6: 01t0z000007f40zAAA | L6: 01t0z000007f40zAAA | S6: 11BWC000002WLhn2AG | V6: TRUE | W6: Allowed | X6: TRUE | Y6: Commercial | Z6: FALSE | BG6: FALSE | CD6: FALSE | CG6: FALSE | CL6: FALSE | CM6: FALSE | CN6: FALSE | CP6: 01tWC00000AYBY2YAP | CR6: FALSE | CV6: FALSE | CX6: FALSE | CY6: FALSE | DA6: FALSE | DB6: FALSE | DI6: FALSE | DN6: Authentication Only | DQ6: FALSE | DS6: FALSE | DU6: Authentication Only | DZ6: Active
A7: [Product2] | B7: Authentication Only - Non-Repudiation | C7: Authentication Only - Non-Repudiation | E7: TRUE | F7: DigiCert | G7: USD | H7: 012dp000005zfL7AAI | J7: 01t0z000007f410AAA | K7: 01t0z000007f410AAA | L7: 01t0z000007f410AAA | S7: 11BWC000002WLhp2AG | V7: TRUE | W7: Allowed | X7: TRUE | Y7: Commercial | Z7: FALSE | BG7: FALSE | CD7: FALSE | CG7: FALSE | CL7: FALSE | CM7: FALSE | CN7: FALSE | CP7: 01tWC00000AYBY3YAP | CR7: FALSE | CV7: FALSE | CX7: FALSE | CY7: FALSE | DA7: FALSE | DB7: FALSE | DI7: FALSE | DN7: Authentication Only - Non-Repudiation | DQ7: FALSE | DS7: FALSE | DU7: Authentication Only - Non-Repudiation | DZ7: Active
A8: [Product2] | B8: Authentication Plus | C8: Authentication Plus | E8: TRUE | F8: DigiCert | G8: USD | H8: 012dp000005zfL7AAI | J8: 01t0z000007f411AAA | K8: 01t0z000007f411AAA | L8: 01t0z000007f411AAA | S8: 11BWC000002WLhl2AG | V8: TRUE | W8: Allowed | X8: TRUE | Y8: Commercial | Z8: FALSE | BG8: FALSE | CD8: FALSE | CG8: FALSE | CL8: FALSE | CM8: FALSE | CN8: FALSE | CP8: 01tWC00000AYBY4YAP | CR8: FALSE | CV8: FALSE | CX8: FALSE | CY8: FALSE | DA8: FALSE | DB8: FALSE | DI8: FALSE | DN8: Authentication Plus | DQ8: FALSE | DS8: FALSE | DU8: Authentication Plus | DZ8: Active
A9: [Product2] | B9: Authentication Plus (AD Integration) | C9: Authentication Plus (AD Integration) | E9: TRUE | F9: DigiCert | G9: USD | H9: 012dp000005zfL7AAI | J9: 01t0z000007f412AAA | K9: 01t0z000007f412AAA | L9: 01t0z000007f412AAA | S9: 11BWC000002WLYo2AO | V9: TRUE | W9: Allowed | X9: TRUE | Y9: Commercial | Z9: FALSE | BG9: FALSE | CD9: FALSE | CG9: FALSE | CL9: FALSE | CM9: FALSE | CN9: FALSE | CP9: 01tWC00000AYBY5YAP | CR9: FALSE | CV9: FALSE | CX9: FALSE | CY9: FALSE | DA9: FALSE | DB9: FALSE | DI9: FALSE | DN9: Authentication Plus (AD Integration) | DQ9: FALSE | DS9: FALSE | DU9: Authentication Plus (AD Integration) | DZ9: Active
A10: [Product2] | B10: Basic EV | C10: Basic EV | E10: TRUE | F10: DigiCert | G10: USD | H10: 012dp000005zfL7AAI | J10: 01t0z000007f413AAA | K10: 01t0z000007f413AAA | L10: 01t0z000007f413AAA | V10: TRUE | W10: Allowed | X10: TRUE | Y10: Commercial | Z10: FALSE | BG10: FALSE | CD10: FALSE | CG10: FALSE | CL10: FALSE | CM10: FALSE | CN10: FALSE | CP10: 01tWC00000AYBY6YAP | CR10: FALSE | CV10: FALSE | CX10: FALSE | CY10: FALSE | DA10: FALSE | DB10: FALSE | DI10: FALSE | DN10: Basic EV | DQ10: FALSE | DS10: FALSE | DU10: Basic EV | DY10: All SSL Product Grp | DZ10: Active
A11: [Product2] | B11: Basic EV FQDN SAN | C11: Basic EV FQDN SAN | E11: TRUE | F11: DigiCert | G11: USD | H11: 012dp000005zfL7AAI | J11: 01t0z000007f414AAA | K11: 01t0z000007f414AAA | L11: 01t0z000007f414AAA | S11: 11BWC000002cka92AA | V11: TRUE | X11: TRUE | Y11: Commercial | Z11: FALSE | BG11: FALSE | CD11: FALSE | CG11: FALSE | CL11: FALSE | CM11: FALSE | CN11: FALSE | CP11: 01tWC00000AYBY7YAP | CR11: FALSE | CV11: FALSE | CX11: FALSE | CY11: FALSE | DA11: FALSE | DB11: FALSE | DI11: FALSE | DN11: Basic EV FQDN SAN | DQ11: FALSE | DS11: FALSE | DU11: Basic EV FQDN SAN | DY11: All SSL Product Grp | DZ11: Active
A12: [Product2] | B12: Basic OV | C12: Basic OV | E12: TRUE | F12: DigiCert | G12: USD | H12: 012dp000005zfL7AAI | J12: 01t0z000007f415AAA | K12: 01t0z000007f415AAA | L12: 01t0z000007f415AAA | V12: TRUE | W12: Allowed | X12: TRUE | Y12: Commercial | Z12: FALSE | BG12: FALSE | CD12: FALSE | CG12: FALSE | CL12: FALSE | CM12: FALSE | CN12: FALSE | CP12: 01tWC00000AYBY8YAP | CR12: FALSE | CV12: FALSE | CX12: FALSE | CY12: FALSE | DA12: FALSE | DB12: FALSE | DI12: FALSE | DN12: Basic OV | DQ12: FALSE | DS12: FALSE | DU12: Basic OV | DY12: All SSL Product Grp | DZ12: Active
A13: [Product2] | B13: Basic OV FQDN SAN | C13: Basic OV FQDN SAN | E13: TRUE | F13: DigiCert | G13: USD | H13: 012dp000005zfL7AAI | J13: 01t0z000007f416AAA | K13: 01t0z000007f416AAA | L13: 01t0z000007f416AAA | S13: 11BWC000002cka92AA | V13: TRUE | X13: TRUE | Y13: Commercial | Z13: FALSE | BG13: FALSE | CD13: FALSE | CG13: FALSE | CL13: FALSE | CM13: FALSE | CN13: FALSE | CP13: 01tWC00000AYBY9YAP | CR13: FALSE | CV13: FALSE | CX13: FALSE | CY13: FALSE | DA13: FALSE | DB13: FALSE | DI13: FALSE | DN13: Basic OV FQDN SAN | DQ13: FALSE | DS13: FALSE | DU13: Basic OV FQDN SAN | DY13: All SSL Product Grp | DZ13: Active
A14: [Product2] | B14: Basic OV Wildcard SAN | C14: Basic OV Wildcard SAN | E14: TRUE | F14: DigiCert | G14: USD | H14: 012dp000005zfL7AAI | J14: 01t0z000007f417AAA | K14: 01t0z000007f417AAA | L14: 01t0z000007f417AAA | S14: 11BWC000002cka92AA | V14: TRUE | X14: TRUE | Y14: Commercial | Z14: FALSE | BG14: FALSE | CD14: FALSE | CG14: FALSE | CL14: FALSE | CM14: FALSE | CN14: FALSE | CP14: 01tWC00000AYBYAYA5 | CR14: FALSE | CV14: FALSE | CX14: FALSE | CY14: FALSE | DA14: FALSE | DB14: FALSE | DI14: FALSE | DN14: Basic OV Wildcard SAN | DQ14: FALSE | DS14: FALSE | DU14: Basic OV Wildcard SAN | DY14: All SSL Product Grp | DZ14: Active
A15: [Product2] | B15: Class 1 S/MIME | C15: Class 1 S/MIME | E15: TRUE | F15: DigiCert | G15: USD | H15: 012dp000005zfL7AAI | J15: 01t0z000007f418AAA | K15: 01t0z000007f418AAA | L15: 01t0z000007f418AAA | S15: 11BWC000002WLhq2AG | V15: TRUE | W15: Allowed | X15: TRUE | Y15: Commercial | Z15: FALSE | BG15: FALSE | CD15: FALSE | CG15: FALSE | CL15: FALSE | CM15: FALSE | CN15: FALSE | CP15: 01tWC00000AYBYBYA5 | CR15: FALSE | CV15: FALSE | CX15: FALSE | CY15: FALSE | DA15: FALSE | DB15: FALSE | DI15: FALSE | DN15: Class 1 S/MIME | DQ15: FALSE | DS15: FALSE | DU15: Class 1 S/MIME | DZ15: Active
A16: [Product2] | B16: Code Signing | C16: Code Signing | E16: TRUE | F16: DigiCert | G16: USD | H16: 012dp000005zfL7AAI | J16: 01t0z000007f419AAA | K16: 01t0z000007f419AAA | L16: 01t0z000007f419AAA | S16: 11BWC000002WLhh2AG | V16: TRUE | W16: Allowed | X16: TRUE | Y16: Commercial | Z16: FALSE | BG16: FALSE | CD16: FALSE | CG16: FALSE | CL16: FALSE | CM16: FALSE | CN16: FALSE | CP16: 01tWC00000AYBYCYA5 | CR16: FALSE | CV16: FALSE | CX16: FALSE | CY16: FALSE | DA16: FALSE | DB16: FALSE | DI16: FALSE | DN16: Code Signing | DQ16: FALSE | DS16: FALSE | DU16: Code Signing | DZ16: Active
A17: [Product2] | B17: Digital Signature Plus | C17: Digital Signature Plus | E17: TRUE | F17: DigiCert | G17: USD | H17: 012dp000005zfL7AAI | J17: 01t0z000007f41AAAQ | K17: 01t0z000007f41AAAQ | L17: 01t0z000007f41AAAQ | S17: 11BWC000002WLhj2AG | V17: TRUE | W17: Allowed | X17: TRUE | Y17: Commercial | Z17: FALSE | BG17: FALSE | CD17: FALSE | CG17: FALSE | CL17: FALSE | CM17: FALSE | CN17: FALSE | CP17: 01tWC00000AYBYDYA5 | CR17: FALSE | CV17: FALSE | CX17: FALSE | CY17: FALSE | DA17: FALSE | DB17: FALSE | DI17: FALSE | DN17: Digital Signature Plus | DQ17: FALSE | DS17: FALSE | DU17: Digital Signature Plus | DZ17: Active
A18: [Product2] | B18: Email Security Plus | C18: Email Security Plus | E18: TRUE | F18: DigiCert | G18: USD | H18: 012dp000005zfL7AAI | J18: 01t0z000007f41DAAQ | K18: 01t0z000007f41DAAQ | L18: 01t0z000007f41DAAQ | S18: 11BWC000002WLhk2AG | V18: TRUE | W18: Allowed | X18: TRUE | Y18: Commercial | Z18: FALSE | BG18: FALSE | CD18: FALSE | CG18: FALSE | CL18: FALSE | CM18: FALSE | CN18: FALSE | CP18: 01tWC00000AYBYEYA5 | CR18: FALSE | CV18: FALSE | CX18: FALSE | CY18: FALSE | DA18: FALSE | DB18: FALSE | DI18: FALSE | DN18: Email Security Plus | DQ18: FALSE | DS18: FALSE | DU18: Email Security Plus | DZ18: Active
A19: [Product2] | B19: Email Security Plus (AD Integration) | C19: Email Security Plus (AD Integration) | E19: TRUE | F19: DigiCert | G19: USD | H19: 012dp000005zfL7AAI | J19: 01t0z000007f41EAAQ | K19: 01t0z000007f41EAAQ | L19: 01t0z000007f41EAAQ | S19: 11BWC000002WLYm2AO | V19: TRUE | W19: Allowed | X19: TRUE | Y19: Commercial | Z19: FALSE | BG19: FALSE | CD19: FALSE | CG19: FALSE | CL19: FALSE | CM19: FALSE | CN19: FALSE | CP19: 01tWC00000AYBYFYA5 | CR19: FALSE | CV19: FALSE | CX19: FALSE | CY19: FALSE | DA19: FALSE | DB19: FALSE | DI19: FALSE | DN19: Email Security Plus (AD Integration) | DQ19: FALSE | DS19: FALSE | DU19: Email Security Plus (AD Integration) | DZ19: Active
A20: [Product2] | B20: Email Security Plus [SHA-2 Only] | C20: Email Security Plus [SHA-2 Only] | E20: TRUE | F20: DigiCert | G20: USD | H20: 012dp000005zfL7AAI | J20: 01t0z000007f41FAAQ | K20: 01t0z000007f41FAAQ | L20: 01t0z000007f41FAAQ | S20: 11BWC000002WLYn2AO | V20: TRUE | W20: Allowed | X20: TRUE | Y20: Commercial | Z20: FALSE | BG20: FALSE | CD20: FALSE | CG20: FALSE | CL20: FALSE | CM20: FALSE | CN20: FALSE | CP20: 01tWC00000AYBYGYA5 | CR20: FALSE | CV20: FALSE | CX20: FALSE | CY20: FALSE | DA20: FALSE | DB20: FALSE | DI20: FALSE | DN20: Email Security Plus [SHA-2 Only] | DQ20: FALSE | DS20: FALSE | DU20: Email Security Plus [SHA-2 Only] | DY20: All SSL Product Grp | DZ20: Active
A21: [Product2] | B21: EV Code Signing | C21: EV Code Signing | E21: TRUE | F21: DigiCert | G21: USD | H21: 012dp000005zfL7AAI | J21: 01t0z000007f41GAAQ | K21: 01t0z000007f41GAAQ | L21: 01t0z000007f41GAAQ | S21: 11BWC000002WLhi2AG | V21: TRUE | W21: Allowed | X21: TRUE | Y21: Commercial | Z21: FALSE | BG21: FALSE | CD21: FALSE | CG21: FALSE | CL21: FALSE | CM21: FALSE | CN21: FALSE | CP21: 01tWC00000AYBYHYA5 | CR21: FALSE | CV21: FALSE | CX21: FALSE | CY21: FALSE | DA21: FALSE | DB21: FALSE | DI21: FALSE | DN21: EV Code Signing | DQ21: FALSE | DS21: FALSE | DU21: EV Code Signing | DZ21: Active
A22: [Product2] | B22: GeoTrust Flex DV | C22: GeoTrust Flex DV | E22: TRUE | F22: Geotrust | G22: USD | H22: 012dp000005zfL7AAI | J22: 01t0z000007f41HAAQ | K22: 01t0z000007f41HAAQ | L22: 01t0z000007f41HAAQ | V22: TRUE | W22: Allowed | X22: TRUE | Y22: Commercial | Z22: FALSE | BG22: FALSE | CD22: FALSE | CG22: FALSE | CL22: FALSE | CM22: FALSE | CN22: FALSE | CP22: 01tWC00000AYBYIYA5 | CR22: FALSE | CV22: FALSE | CX22: FALSE | CY22: FALSE | DA22: FALSE | DB22: FALSE | DI22: FALSE | DN22: GeoTrust Flex DV | DQ22: FALSE | DS22: FALSE | DU22: GeoTrust Flex DV | DY22: All SSL Product Grp | DZ22: Active
A23: [Product2] | B23: GeoTrust Flex DV FQDN SAN | C23: GeoTrust Flex DV FQDN SAN | E23: TRUE | F23: Geotrust | G23: USD | H23: 012dp000005zfL7AAI | J23: 01t0z000007f41IAAQ | K23: 01t0z000007f41IAAQ | L23: 01t0z000007f41IAAQ | S23: 11BWC000002cka92AA | V23: TRUE | X23: TRUE | Y23: Commercial | Z23: FALSE | BG23: FALSE | CD23: FALSE | CG23: FALSE | CL23: FALSE | CM23: FALSE | CN23: FALSE | CP23: 01tWC00000AYBYJYA5 | CR23: FALSE | CV23: FALSE | CX23: FALSE | CY23: FALSE | DA23: FALSE | DB23: FALSE | DI23: FALSE | DN23: GeoTrust Flex DV FQDN SAN | DQ23: FALSE | DS23: FALSE | DU23: GeoTrust Flex DV FQDN SAN | DY23: All SSL Product Grp | DZ23: Active
A24: [Product2] | B24: GeoTrust Flex DV Wildcard SAN | C24: GeoTrust Flex DV Wildcard SAN | E24: TRUE | F24: Geotrust | G24: USD | H24: 012dp000005zfL7AAI | J24: 01t0z000007f41JAAQ | K24: 01t0z000007f41JAAQ | L24: 01t0z000007f41JAAQ | S24: 11BWC000002cka92AA | V24: TRUE | X24: TRUE | Y24: Commercial | Z24: FALSE | BG24: FALSE | CD24: FALSE | CG24: FALSE | CL24: FALSE | CM24: FALSE | CN24: FALSE | CP24: 01tWC00000AYBYKYA5 | CR24: FALSE | CV24: FALSE | CX24: FALSE | CY24: FALSE | DA24: FALSE | DB24: FALSE | DI24: FALSE | DN24: GeoTrust Flex DV Wildcard SAN | DQ24: FALSE | DS24: FALSE | DU24: GeoTrust Flex DV Wildcard SAN | DY24: All SSL Product Grp | DZ24: Active
A25: [Product2] | B25: GeoTrust TrueBusiness ID EV | C25: GeoTrust TrueBusiness ID EV | E25: TRUE | F25: Geotrust | G25: USD | H25: 012dp000005zfL7AAI | J25: 01t0z000007f41KAAQ | K25: 01t0z000007f41KAAQ | L25: 01t0z000007f41KAAQ | V25: TRUE | W25: Allowed | X25: TRUE | Y25: Commercial | Z25: FALSE | BG25: FALSE | CD25: FALSE | CG25: FALSE | CL25: FALSE | CM25: FALSE | CN25: FALSE | CP25: 01tWC00000AYBYLYA5 | CR25: FALSE | CV25: FALSE | CX25: FALSE | CY25: FALSE | DA25: FALSE | DB25: FALSE | DI25: FALSE | DN25: GeoTrust TrueBusiness ID EV | DQ25: FALSE | DS25: FALSE | DU25: GeoTrust TrueBusiness ID EV | DZ25: Active
A26: [Product2] | B26: GeoTrust TrueBusiness ID EV FQDN SAN | C26: GeoTrust TrueBusiness ID EV FQDN SAN | E26: TRUE | F26: Geotrust | G26: USD | H26: 012dp000005zfL7AAI | J26: 01t0z000007f41LAAQ | K26: 01t0z000007f41LAAQ | L26: 01t0z000007f41LAAQ | S26: 11BWC000002cka92AA | V26: TRUE | X26: TRUE | Y26: Commercial | Z26: FALSE | BG26: FALSE | CD26: FALSE | CG26: FALSE | CL26: FALSE | CM26: FALSE | CN26: FALSE | CP26: 01tWC00000AYBYMYA5 | CR26: FALSE | CV26: FALSE | CX26: FALSE | CY26: FALSE | DA26: FALSE | DB26: FALSE | DI26: FALSE | DN26: GeoTrust TrueBusiness ID EV FQDN SAN | DQ26: FALSE | DS26: FALSE | DU26: GeoTrust TrueBusiness ID EV FQDN SAN | DY26: All SSL Product Grp | DZ26: Active
A27: [Product2] | B27: GeoTrust TrueBusiness ID OV | C27: GeoTrust TrueBusiness ID OV | E27: TRUE | F27: Geotrust | G27: USD | H27: 012dp000005zfL7AAI | J27: 01t0z000007f41MAAQ | K27: 01t0z000007f41MAAQ | L27: 01t0z000007f41MAAQ | V27: TRUE | W27: Allowed | X27: TRUE | Y27: Commercial | Z27: FALSE | BG27: FALSE | CD27: FALSE | CG27: FALSE | CL27: FALSE | CM27: FALSE | CN27: FALSE | CP27: 01tWC00000AYBYNYA5 | CR27: FALSE | CV27: FALSE | CX27: FALSE | CY27: FALSE | DA27: FALSE | DB27: FALSE | DI27: FALSE | DN27: GeoTrust TrueBusiness ID OV | DQ27: FALSE | DS27: FALSE | DU27: GeoTrust TrueBusiness ID OV | DZ27: Active
A28: [Product2] | B28: GeoTrust TrueBusiness ID OV FQDN SAN | C28: GeoTrust TrueBusiness ID OV FQDN SAN | E28: TRUE | F28: Geotrust | G28: USD | H28: 012dp000005zfL7AAI | J28: 01t0z000007f41NAAQ | K28: 01t0z000007f41NAAQ | L28: 01t0z000007f41NAAQ | S28: 11BWC000002cka92AA | V28: TRUE | X28: TRUE | Y28: Commercial | Z28: FALSE | BG28: FALSE | CD28: FALSE | CG28: FALSE | CL28: FALSE | CM28: FALSE | CN28: FALSE | CP28: 01tWC00000AYBYOYA5 | CR28: FALSE | CV28: FALSE | CX28: FALSE | CY28: FALSE | DA28: FALSE | DB28: FALSE | DI28: FALSE | DN28: GeoTrust TrueBusiness ID OV FQDN SAN | DQ28: FALSE | DS28: FALSE | DU28: GeoTrust TrueBusiness ID OV FQDN SAN | DY28: All SSL Product Grp | DZ28: Active
A29: [Product2] | B29: GeoTrust TrueBusiness ID OV Wildcard SAN | C29: GeoTrust TrueBusiness ID OV Wildcard SAN | E29: TRUE | F29: Geotrust | G29: USD | H29: 012dp000005zfL7AAI | J29: 01t0z000007f41OAAQ | K29: 01t0z000007f41OAAQ | L29: 01t0z000007f41OAAQ | S29: 11BWC000002cka92AA | V29: TRUE | X29: TRUE | Y29: Commercial | Z29: FALSE | BG29: FALSE | CD29: FALSE | CG29: FALSE | CL29: FALSE | CM29: FALSE | CN29: FALSE | CP29: 01tWC00000AYBYPYA5 | CR29: FALSE | CV29: FALSE | CX29: FALSE | CY29: FALSE | DA29: FALSE | DB29: FALSE | DI29: FALSE | DN29: GeoTrust TrueBusiness ID OV Wildcard SAN | DQ29: FALSE | DS29: FALSE | DU29: GeoTrust TrueBusiness ID OV Wildcard SAN | DY29: All SSL Product Grp | DZ29: Active
A30: [Product2] | B30: LTANS Adobe Signing | C30: LTANS Adobe Signing | E30: TRUE | F30: DigiCert | G30: USD | H30: 012dp000005zfL7AAI | J30: 01t0z000007f41PAAQ | K30: 01t0z000007f41PAAQ | L30: 01t0z000007f41PAAQ | S30: 11BWC000002WLYs2AO | V30: TRUE | W30: Allowed | X30: TRUE | Y30: Commercial | Z30: FALSE | BG30: FALSE | CD30: FALSE | CG30: FALSE | CL30: FALSE | CM30: FALSE | CN30: FALSE | CP30: 01tWC00000AYBYQYA5 | CR30: FALSE | CV30: FALSE | CX30: FALSE | CY30: FALSE | DA30: FALSE | DB30: FALSE | DI30: FALSE | DN30: LTANS Adobe Signing | DQ30: FALSE | DS30: FALSE | DU30: LTANS Adobe Signing | DZ30: Active
A31: [Product2] | B31: Multi-Name Client Auth | C31: Multi-Name Client Auth | E31: TRUE | F31: DigiCert | G31: USD | H31: 012dp000005zfL7AAI | J31: 01t0z000007f41QAAQ | K31: 01t0z000007f41QAAQ | L31: 01t0z000007f41QAAQ | S31: 11BWC000002WLho2AG | V31: TRUE | W31: Allowed | X31: TRUE | Y31: Commercial | Z31: FALSE | BG31: FALSE | CD31: FALSE | CG31: FALSE | CL31: FALSE | CM31: FALSE | CN31: FALSE | CP31: 01tWC00000AYBYRYA5 | CR31: FALSE | CV31: FALSE | CX31: FALSE | CY31: FALSE | DA31: FALSE | DB31: FALSE | DI31: FALSE | DN31: Multi-Name Client Auth | DQ31: FALSE | DS31: FALSE | DU31: Multi-Name Client Auth | DZ31: Active
A32: [Product2] | B32: Premium (Class 2 S/MIME) | C32: Premium (Class 2 S/MIME) | E32: TRUE | F32: DigiCert | G32: USD | H32: 012dp000005zfL7AAI | J32: 01t0z000007f41SAAQ | K32: 01t0z000007f41SAAQ | L32: 01t0z000007f41SAAQ | S32: 11BWC000002WLhm2AG | V32: TRUE | W32: Allowed | X32: TRUE | Y32: Commercial | Z32: FALSE | BG32: FALSE | CD32: FALSE | CG32: FALSE | CL32: FALSE | CM32: FALSE | CN32: FALSE | CP32: 01tWC00000AYBYTYA5 | CR32: FALSE | CV32: FALSE | CX32: FALSE | CY32: FALSE | DA32: FALSE | DB32: FALSE | DI32: FALSE | DN32: Premium (Class 2 S/MIME) | DQ32: FALSE | DS32: FALSE | DU32: Premium (Class 2 S/MIME) | DZ32: Active
A33: [Product2] | B33: Premium - Data Encipherment | C33: Premium - Data Encipherment | E33: TRUE | F33: DigiCert | G33: USD | H33: 012dp000005zfL7AAI | J33: 01t0z000007f41TAAQ | K33: 01t0z000007f41TAAQ | L33: 01t0z000007f41TAAQ | S33: 11BWC000002WLYx2AO | V33: TRUE | W33: Allowed | X33: TRUE | Y33: Commercial | Z33: FALSE | BG33: FALSE | CD33: FALSE | CG33: FALSE | CL33: FALSE | CM33: FALSE | CN33: FALSE | CP33: 01tWC00000AYBYUYA5 | CR33: FALSE | CV33: FALSE | CX33: FALSE | CY33: FALSE | DA33: FALSE | DB33: FALSE | DI33: FALSE | DN33: Premium - Data Encipherment | DQ33: FALSE | DS33: FALSE | DU33: Premium - Data Encipherment | DZ33: Active
A34: [Product2] | B34: Premium - Non-Repudiation | C34: Premium - Non-Repudiation | E34: TRUE | F34: DigiCert | G34: USD | H34: 012dp000005zfL7AAI | J34: 01t0z000007f41UAAQ | K34: 01t0z000007f41UAAQ | L34: 01t0z000007f41UAAQ | S34: 11BWC000002WLYw2AO | V34: TRUE | W34: Allowed | X34: TRUE | Y34: Commercial | Z34: FALSE | BG34: FALSE | CD34: FALSE | CG34: FALSE | CL34: FALSE | CM34: FALSE | CN34: FALSE | CP34: 01tWC00000AYBYVYA5 | CR34: FALSE | CV34: FALSE | CX34: FALSE | CY34: FALSE | DA34: FALSE | DB34: FALSE | DI34: FALSE | DN34: Premium - Non-Repudiation | DQ34: FALSE | DS34: FALSE | DU34: Premium - Non-Repudiation | DZ34: Active
A35: [Product2] | B35: Premium (AD Integration) | C35: Premium (AD Integration) | E35: TRUE | F35: DigiCert | G35: USD | H35: 012dp000005zfL7AAI | J35: 01t0z000007f41VAAQ | K35: 01t0z000007f41VAAQ | L35: 01t0z000007f41VAAQ | S35: 11BWC000002WLYq2AO | V35: TRUE | W35: Allowed | X35: TRUE | Y35: Commercial | Z35: FALSE | BG35: FALSE | CD35: FALSE | CG35: FALSE | CL35: FALSE | CM35: FALSE | CN35: FALSE | CP35: 01tWC00000AYBYWYA5 | CR35: FALSE | CV35: FALSE | CX35: FALSE | CY35: FALSE | DA35: FALSE | DB35: FALSE | DI35: FALSE | DN35: Premium (AD Integration) | DQ35: FALSE | DS35: FALSE | DU35: Premium (AD Integration) | DZ35: Active
A36: [Product2] | B36: Premium [SHA-2 Only] | C36: Premium [SHA-2 Only] | E36: TRUE | F36: DigiCert | G36: USD | H36: 012dp000005zfL7AAI | J36: 01t0z000007f41WAAQ | K36: 01t0z000007f41WAAQ | L36: 01t0z000007f41WAAQ | S36: 11BWC000002WLYr2AO | V36: TRUE | W36: Allowed | X36: TRUE | Y36: Commercial | Z36: FALSE | BG36: FALSE | CD36: FALSE | CG36: FALSE | CL36: FALSE | CM36: FALSE | CN36: FALSE | CP36: 01tWC00000AYBYXYA5 | CR36: FALSE | CV36: FALSE | CX36: FALSE | CY36: FALSE | DA36: FALSE | DB36: FALSE | DI36: FALSE | DN36: Premium [SHA-2 Only] | DQ36: FALSE | DS36: FALSE | DU36: Premium [SHA-2 Only] | DY36: All SSL Product Grp | DZ36: Active
A37: [Product2] | B37: Private Premium | C37: 1022 | E37: TRUE | F37: DigiCert | G37: USD | H37: 012dp000005zfL7AAI | J37: 01t0z000007f41XAAQ | K37: 01t0z000007f41XAAQ | L37: 01t0z000007f41XAAQ | S37: 11BWC000002WLYu2AO | V37: TRUE | W37: Allowed | X37: TRUE | Y37: Commercial | Z37: FALSE | BG37: FALSE | CD37: FALSE | CG37: FALSE | CL37: FALSE | CM37: FALSE | CN37: FALSE | CP37: 01tWC00000AYBYYYA5 | CR37: FALSE | CV37: FALSE | CX37: FALSE | CY37: FALSE | DA37: FALSE | DB37: FALSE | DI37: FALSE | DN37: 1022 | DQ37: FALSE | DS37: FALSE | DU37: Private Premium | DZ37: Active
A38: [Product2] | B38: Private SSL Base | C38: Private SSL Base | E38: TRUE | F38: DigiCert | G38: USD | H38: 012dp000005zfL7AAI | J38: 01t0z000007f41YAAQ | K38: 01t0z000007f41YAAQ | L38: 01t0z000007f41YAAQ | S38: 11BWC000002WLYl2AO | V38: TRUE | W38: Allowed | X38: TRUE | Y38: Commercial | Z38: FALSE | BG38: FALSE | CD38: FALSE | CG38: FALSE | CL38: FALSE | CM38: FALSE | CN38: FALSE | CP38: 01tWC00000AYBYZYA5 | CR38: FALSE | CV38: FALSE | CX38: FALSE | CY38: FALSE | DA38: FALSE | DB38: FALSE | DI38: FALSE | DN38: Private SSL Base | DQ38: FALSE | DS38: FALSE | DU38: Private SSL Base | DY38: All SSL Product Grp | DZ38: Active
A39: [Product2] | B39: Private SSL FQDN SAN | C39: Private SSL FQDN SAN | E39: TRUE | F39: DigiCert | G39: USD | H39: 012dp000005zfL7AAI | J39: 01t0z000007f41ZAAQ | K39: 01t0z000007f41ZAAQ | L39: 01t0z000007f41ZAAQ | S39: 11BWC000002WLhs2AG | V39: TRUE | W39: Allowed | X39: TRUE | Y39: Commercial | Z39: FALSE | BG39: FALSE | CD39: FALSE | CG39: FALSE | CL39: FALSE | CM39: FALSE | CN39: FALSE | CP39: 01tWC00000AYBYaYAP | CR39: FALSE | CV39: FALSE | CX39: FALSE | CY39: FALSE | DA39: FALSE | DB39: FALSE | DI39: FALSE | DN39: Private SSL FQDN SAN | DQ39: FALSE | DS39: FALSE | DU39: Private SSL FQDN SAN | DY39: All SSL Product Grp | DZ39: Active
A40: [Product2] | B40: Private SSL Wildcard SAN | C40: Private SSL Wildcard SAN | E40: TRUE | F40: DigiCert | G40: USD | H40: 012dp000005zfL7AAI | J40: 01t0z000007f41aAAA | K40: 01t0z000007f41aAAA | L40: 01t0z000007f41aAAA | S40: 11BWC000002WLhr2AG | V40: TRUE | W40: Allowed | X40: TRUE | Y40: Commercial | Z40: FALSE | BG40: FALSE | CD40: FALSE | CG40: FALSE | CL40: FALSE | CM40: FALSE | CN40: FALSE | CP40: 01tWC00000AYBYbYAP | CR40: FALSE | CV40: FALSE | CX40: FALSE | CY40: FALSE | DA40: FALSE | DB40: FALSE | DI40: FALSE | DN40: Private SSL Wildcard SAN | DQ40: FALSE | DS40: FALSE | DU40: Private SSL Wildcard SAN | DY40: All SSL Product Grp | DZ40: Active
A41: [Product2] | B41: RapidSSL Standard DV | C41: RapidSSL Standard DV | E41: TRUE | F41: RapidSSL | G41: USD | H41: 012dp000005zfL7AAI | J41: 01t0z000007f41bAAA | K41: 01t0z000007f41bAAA | L41: 01t0z000007f41bAAA | V41: TRUE | W41: Allowed | X41: TRUE | Y41: Commercial | Z41: FALSE | BG41: FALSE | CD41: FALSE | CG41: FALSE | CL41: FALSE | CM41: FALSE | CN41: FALSE | CP41: 01tWC00000AYBYcYAP | CR41: FALSE | CV41: FALSE | CX41: FALSE | CY41: FALSE | DA41: FALSE | DB41: FALSE | DI41: FALSE | DN41: RapidSSL Standard DV | DQ41: FALSE | DS41: FALSE | DU41: RapidSSL Standard DV | DY41: All SSL Product Grp | DZ41: Active
A42: [Product2] | B42: RapidSSL Wildcard DV | C42: RapidSSL Wildcard DV | E42: TRUE | F42: RapidSSL | G42: USD | H42: 012dp000005zfL7AAI | J42: 01t0z000007f41cAAA | K42: 01t0z000007f41cAAA | L42: 01t0z000007f41cAAA | V42: TRUE | W42: Allowed | X42: TRUE | Y42: Commercial | Z42: FALSE | BG42: FALSE | CD42: FALSE | CG42: FALSE | CL42: FALSE | CM42: FALSE | CN42: FALSE | CP42: 01tWC00000AYBYdYAP | CR42: FALSE | CV42: FALSE | CX42: FALSE | CY42: FALSE | DA42: FALSE | DB42: FALSE | DI42: FALSE | DN42: RapidSSL Wildcard DV | DQ42: FALSE | DS42: FALSE | DU42: RapidSSL Wildcard DV | DY42: All SSL Product Grp | DZ42: Active
A43: [Product2] | B43: Secure Site EV SSL | C43: Secure Site EV SSL | E43: TRUE | F43: DigiCert | G43: USD | H43: 012dp000005zfL7AAI | J43: 01t0z000007f41dAAA | K43: 01t0z000007f41dAAA | L43: 01t0z000007f41dAAA | V43: TRUE | W43: Allowed | X43: TRUE | Y43: Commercial | Z43: FALSE | BG43: FALSE | CD43: FALSE | CG43: FALSE | CL43: FALSE | CM43: FALSE | CN43: FALSE | CP43: 01tWC00000AYBYeYAP | CR43: FALSE | CV43: FALSE | CX43: FALSE | CY43: FALSE | DA43: FALSE | DB43: FALSE | DI43: FALSE | DN43: Secure Site EV SSL | DQ43: FALSE | DS43: FALSE | DU43: Secure Site EV SSL | DY43: All SSL Product Grp | DZ43: Active
A44: [Product2] | B44: Secure Site EV SSL FQDN SAN | C44: Secure Site EV SSL FQDN SAN | E44: TRUE | F44: DigiCert | G44: USD | H44: 012dp000005zfL7AAI | J44: 01t0z000007f41eAAA | K44: 01t0z000007f41eAAA | L44: 01t0z000007f41eAAA | S44: 11BWC000002cka92AA | V44: TRUE | X44: TRUE | Y44: Commercial | Z44: FALSE | BG44: FALSE | CD44: FALSE | CG44: FALSE | CL44: FALSE | CM44: FALSE | CN44: FALSE | CP44: 01tWC00000AYBYfYAP | CR44: FALSE | CV44: FALSE | CX44: FALSE | CY44: FALSE | DA44: FALSE | DB44: FALSE | DI44: FALSE | DN44: Secure Site EV SSL FQDN SAN | DQ44: FALSE | DS44: FALSE | DU44: Secure Site EV SSL FQDN SAN | DY44: All SSL Product Grp | DZ44: Active
A45: [Product2] | B45: Secure Site Pro EV SSL | C45: Secure Site Pro EV SSL | E45: TRUE | F45: DigiCert | G45: USD | H45: 012dp000005zfL7AAI | J45: 01t0z000007f41fAAA | K45: 01t0z000007f41fAAA | L45: 01t0z000007f41fAAA | V45: TRUE | W45: Allowed | X45: TRUE | Y45: Commercial | Z45: FALSE | BG45: FALSE | CD45: FALSE | CG45: FALSE | CL45: FALSE | CM45: FALSE | CN45: FALSE | CP45: 01tWC00000AYBYgYAP | CR45: FALSE | CV45: FALSE | CX45: FALSE | CY45: FALSE | DA45: FALSE | DB45: FALSE | DI45: FALSE | DN45: Secure Site Pro EV SSL | DQ45: FALSE | DS45: FALSE | DU45: Secure Site Pro EV SSL | DZ45: Active
A46: [Product2] | B46: Secure Site Pro EV SSL FQDN SAN | C46: Secure Site Pro EV SSL FQDN SAN | E46: TRUE | F46: DigiCert | G46: USD | H46: 012dp000005zfL7AAI | J46: 01t0z000007f41gAAA | K46: 01t0z000007f41gAAA | L46: 01t0z000007f41gAAA | V46: TRUE | W46: Allowed | X46: TRUE | Y46: Commercial | Z46: FALSE | BG46: FALSE | CD46: FALSE | CG46: FALSE | CL46: FALSE | CM46: FALSE | CN46: FALSE | CP46: 01tWC00000AYBYhYAP | CR46: FALSE | CV46: FALSE | CX46: FALSE | CY46: FALSE | DA46: FALSE | DB46: FALSE | DI46: FALSE | DN46: Secure Site Pro EV SSL FQDN SAN | DQ46: FALSE | DS46: FALSE | DU46: Secure Site Pro EV SSL FQDN SAN | DY46: All SSL Product Grp | DZ46: Active
A47: [Product2] | B47: Secure Site Pro SSL | C47: Secure Site Pro SSL | E47: TRUE | F47: DigiCert | G47: USD | H47: 012dp000005zfL7AAI | J47: 01t0z000007f41hAAA | K47: 01t0z000007f41hAAA | L47: 01t0z000007f41hAAA | V47: TRUE | W47: Allowed | X47: TRUE | Y47: Commercial | Z47: FALSE | BG47: FALSE | CD47: FALSE | CG47: FALSE | CL47: FALSE | CM47: FALSE | CN47: FALSE | CP47: 01tWC00000AYBYiYAP | CR47: FALSE | CV47: FALSE | CX47: FALSE | CY47: FALSE | DA47: FALSE | DB47: FALSE | DI47: FALSE | DN47: Secure Site Pro SSL | DQ47: FALSE | DS47: FALSE | DU47: Secure Site Pro SSL | DZ47: Active
A48: [Product2] | B48: Secure Site Pro SSL FQDN SAN | C48: Secure Site Pro SSL FQDN SAN | E48: TRUE | F48: DigiCert | G48: USD | H48: 012dp000005zfL7AAI | J48: 01t0z000007f41iAAA | K48: 01t0z000007f41iAAA | L48: 01t0z000007f41iAAA | V48: TRUE | W48: Allowed | X48: TRUE | Y48: Commercial | Z48: FALSE | BG48: FALSE | CD48: FALSE | CG48: FALSE | CL48: FALSE | CM48: FALSE | CN48: FALSE | CP48: 01tWC00000AYBYjYAP | CR48: FALSE | CV48: FALSE | CX48: FALSE | CY48: FALSE | DA48: FALSE | DB48: FALSE | DI48: FALSE | DN48: Secure Site Pro SSL FQDN SAN | DQ48: FALSE | DS48: FALSE | DU48: Secure Site Pro SSL FQDN SAN | DY48: All SSL Product Grp | DZ48: Active
A49: [Product2] | B49: Secure Site Pro SSL Wildcard SAN | C49: Secure Site Pro SSL Wildcard SAN | E49: TRUE | F49: DigiCert | G49: USD | H49: 012dp000005zfL7AAI | J49: 01t0z000007f41jAAA | K49: 01t0z000007f41jAAA | L49: 01t0z000007f41jAAA | V49: TRUE | W49: Allowed | X49: TRUE | Y49: Commercial | Z49: FALSE | BG49: FALSE | CD49: FALSE | CG49: FALSE | CL49: FALSE | CM49: FALSE | CN49: FALSE | CP49: 01tWC00000AYBYkYAP | CR49: FALSE | CV49: FALSE | CX49: FALSE | CY49: FALSE | DA49: FALSE | DB49: FALSE | DI49: FALSE | DN49: Secure Site Pro SSL Wildcard SAN | DQ49: FALSE | DS49: FALSE | DU49: Secure Site Pro SSL Wildcard SAN | DY49: All SSL Product Grp | DZ49: Active
A50: [Product2] | B50: Secure Site OV | C50: Secure Site OV | E50: TRUE | F50: DigiCert | G50: USD | H50: 012dp000005zfL7AAI | J50: 01t0z000007f41kAAA | K50: 01t0z000007f41kAAA | L50: 01t0z000007f41kAAA | V50: TRUE | W50: Allowed | X50: TRUE | Y50: Commercial | Z50: FALSE | BG50: FALSE | CD50: FALSE | CG50: FALSE | CL50: FALSE | CM50: FALSE | CN50: FALSE | CP50: 01tWC00000AYBYlYAP | CR50: FALSE | CV50: FALSE | CX50: FALSE | CY50: FALSE | DA50: FALSE | DB50: FALSE | DI50: FALSE | DN50: Secure Site OV | DQ50: FALSE | DS50: FALSE | DU50: Secure Site OV | DZ50: Active
A51: [Product2] | B51: Secure Site OV FQDN SAN | C51: Secure Site OV FQDN SAN | E51: TRUE | F51: DigiCert | G51: USD | H51: 012dp000005zfL7AAI | J51: 01t0z000007f41lAAA | K51: 01t0z000007f41lAAA | L51: 01t0z000007f41lAAA | S51: 11BWC000002cka92AA | V51: TRUE | X51: TRUE | Y51: Commercial | Z51: FALSE | BG51: FALSE | CD51: FALSE | CG51: FALSE | CL51: FALSE | CM51: FALSE | CN51: FALSE | CP51: 01tWC00000AYBYmYAP | CR51: FALSE | CV51: FALSE | CX51: FALSE | CY51: FALSE | DA51: FALSE | DB51: FALSE | DI51: FALSE | DN51: Secure Site OV FQDN SAN | DQ51: FALSE | DS51: FALSE | DU51: Secure Site OV FQDN SAN | DY51: All SSL Product Grp | DZ51: Active
A52: [Product2] | B52: Secure Site OV Wildcard SAN | C52: Secure Site OV Wildcard SAN | E52: TRUE | F52: DigiCert | G52: USD | H52: 012dp000005zfL7AAI | J52: 01t0z000007f41mAAA | K52: 01t0z000007f41mAAA | L52: 01t0z000007f41mAAA | S52: 11BWC000002cka92AA | V52: TRUE | X52: TRUE | Y52: Commercial | Z52: FALSE | BG52: FALSE | CD52: FALSE | CG52: FALSE | CL52: FALSE | CM52: FALSE | CN52: FALSE | CP52: 01tWC00000AYBYnYAP | CR52: FALSE | CV52: FALSE | CX52: FALSE | CY52: FALSE | DA52: FALSE | DB52: FALSE | DI52: FALSE | DN52: Secure Site OV Wildcard SAN | DQ52: FALSE | DS52: FALSE | DU52: Secure Site OV Wildcard SAN | DY52: All SSL Product Grp | DZ52: Active
A53: [Product2] | B53: Test Authentication Only | C53: Test Authentication Only | E53: TRUE | F53: DigiCert | G53: USD | H53: 012dp000005zfL7AAI | J53: 01t0z000007f41nAAA | K53: 01t0z000007f41nAAA | L53: 01t0z000007f41nAAA | S53: 11BWC000002WLYp2AO | V53: TRUE | W53: Allowed | X53: TRUE | Y53: Commercial | Z53: FALSE | BG53: FALSE | CD53: FALSE | CG53: FALSE | CL53: FALSE | CM53: FALSE | CN53: FALSE | CP53: 01tWC00000AYBYoYAP | CR53: FALSE | CV53: FALSE | CX53: FALSE | CY53: FALSE | DA53: FALSE | DB53: FALSE | DI53: FALSE | DN53: Test Authentication Only | DQ53: FALSE | DS53: FALSE | DU53: Test Authentication Only | DY53: All SSL Product Grp | DZ53: Active
A54: [Product2] | B54: Test Private Client Authentication | C54: Test Private Client Authentication | E54: TRUE | F54: DigiCert | G54: USD | H54: 012dp000005zfL7AAI | J54: 01t0z000007f41oAAA | K54: 01t0z000007f41oAAA | L54: 01t0z000007f41oAAA | S54: 11BWC000002WLYv2AO | V54: TRUE | W54: Allowed | X54: TRUE | Y54: Commercial | Z54: FALSE | BG54: FALSE | CD54: FALSE | CG54: FALSE | CL54: FALSE | CM54: FALSE | CN54: FALSE | CP54: 01tWC00000AYBYpYAP | CR54: FALSE | CV54: FALSE | CX54: FALSE | CY54: FALSE | DA54: FALSE | DB54: FALSE | DI54: FALSE | DN54: Test Private Client Authentication | DQ54: FALSE | DS54: FALSE | DU54: Test Private Client Authentication | DY54: All SSL Product Grp | DZ54: Active
A55: [Product2] | B55: Thawte SSL 123 DV | C55: Thawte SSL 123 DV | E55: TRUE | F55: Thawte | G55: USD | H55: 012dp000005zfL7AAI | J55: 01t0z000007f41pAAA | K55: 01t0z000007f41pAAA | L55: 01t0z000007f41pAAA | V55: TRUE | W55: Allowed | X55: TRUE | Y55: Commercial | Z55: FALSE | BG55: FALSE | CD55: FALSE | CG55: FALSE | CL55: FALSE | CM55: FALSE | CN55: FALSE | CP55: 01tWC00000AYBYqYAP | CR55: FALSE | CV55: FALSE | CX55: FALSE | CY55: FALSE | DA55: FALSE | DB55: FALSE | DI55: FALSE | DN55: Thawte SSL 123 DV | DQ55: FALSE | DS55: FALSE | DU55: Thawte SSL 123 DV | DY55: All SSL Product Grp | DZ55: Active
A56: [Product2] | B56: Thawte SSL 123 DV FQDN SAN | C56: Thawte SSL 123 DV FQDN SAN | E56: TRUE | F56: Thawte | G56: USD | H56: 012dp000005zfL7AAI | J56: 01t0z000007f41qAAA | K56: 01t0z000007f41qAAA | L56: 01t0z000007f41qAAA | S56: 11BWC000002cka92AA | V56: TRUE | X56: TRUE | Y56: Commercial | Z56: FALSE | BG56: FALSE | CD56: FALSE | CG56: FALSE | CL56: FALSE | CM56: FALSE | CN56: FALSE | CP56: 01tWC00000AYBYrYAP | CR56: FALSE | CV56: FALSE | CX56: FALSE | CY56: FALSE | DA56: FALSE | DB56: FALSE | DI56: FALSE | DN56: Thawte SSL 123 DV FQDN SAN | DQ56: FALSE | DS56: FALSE | DU56: Thawte SSL 123 DV FQDN SAN | DY56: All SSL Product Grp | DZ56: Active
A57: [Product2] | B57: Thawte SSL 123 DV Wildcard SAN | C57: Thawte SSL 123 DV Wildcard SAN | E57: TRUE | F57: Thawte | G57: USD | H57: 012dp000005zfL7AAI | J57: 01t0z000007f41rAAA | K57: 01t0z000007f41rAAA | L57: 01t0z000007f41rAAA | S57: 11BWC000002cka92AA | V57: TRUE | X57: TRUE | Y57: Commercial | Z57: FALSE | BG57: FALSE | CD57: FALSE | CG57: FALSE | CL57: FALSE | CM57: FALSE | CN57: FALSE | CP57: 01tWC00000AYBYsYAP | CR57: FALSE | CV57: FALSE | CX57: FALSE | CY57: FALSE | DA57: FALSE | DB57: FALSE | DI57: FALSE | DN57: Thawte SSL 123 DV Wildcard SAN | DQ57: FALSE | DS57: FALSE | DU57: Thawte SSL 123 DV Wildcard SAN | DY57: All SSL Product Grp | DZ57: Active
A58: [Product2] | B58: Thawte SSL Webserver EV | C58: Thawte SSL Webserver EV | E58: TRUE | F58: Thawte | G58: USD | H58: 012dp000005zfL7AAI | J58: 01t0z000007f41sAAA | K58: 01t0z000007f41sAAA | L58: 01t0z000007f41sAAA | V58: TRUE | W58: Allowed | X58: TRUE | Y58: Commercial | Z58: FALSE | BG58: FALSE | CD58: FALSE | CG58: FALSE | CL58: FALSE | CM58: FALSE | CN58: FALSE | CP58: 01tWC00000AYBYtYAP | CR58: FALSE | CV58: FALSE | CX58: FALSE | CY58: FALSE | DA58: FALSE | DB58: FALSE | DI58: FALSE | DN58: Thawte SSL Webserver EV | DQ58: FALSE | DS58: FALSE | DU58: Thawte SSL Webserver EV | DZ58: Active
A59: [Product2] | B59: Thawte SSL Webserver EV FQDN SAN | C59: Thawte SSL Webserver EV FQDN SAN | E59: TRUE | F59: Thawte | G59: USD | H59: 012dp000005zfL7AAI | J59: 01t0z000007f41tAAA | K59: 01t0z000007f41tAAA | L59: 01t0z000007f41tAAA | S59: 11BWC000002cka92AA | V59: TRUE | X59: TRUE | Y59: Commercial | Z59: FALSE | BG59: FALSE | CD59: FALSE | CG59: FALSE | CL59: FALSE | CM59: FALSE | CN59: FALSE | CP59: 01tWC00000AYBYuYAP | CR59: FALSE | CV59: FALSE | CX59: FALSE | CY59: FALSE | DA59: FALSE | DB59: FALSE | DI59: FALSE | DN59: Thawte SSL Webserver EV FQDN SAN | DQ59: FALSE | DS59: FALSE | DU59: Thawte SSL Webserver EV FQDN SAN | DY59: All SSL Product Grp | DZ59: Active
A60: [Product2] | B60: Thawte SSL Webserver OV | C60: Thawte SSL Webserver OV | E60: TRUE | F60: Thawte | G60: USD | H60: 012dp000005zfL7AAI | J60: 01t0z000007f41uAAA | K60: 01t0z000007f41uAAA | L60: 01t0z000007f41uAAA | V60: TRUE | W60: Allowed | X60: TRUE | Y60: Commercial | Z60: FALSE | BG60: FALSE | CD60: FALSE | CG60: FALSE | CL60: FALSE | CM60: FALSE | CN60: FALSE | CP60: 01tWC00000AYBYvYAP | CR60: FALSE | CV60: FALSE | CX60: FALSE | CY60: FALSE | DA60: FALSE | DB60: FALSE | DI60: FALSE | DN60: Thawte SSL Webserver OV | DQ60: FALSE | DS60: FALSE | DU60: Thawte SSL Webserver OV | DZ60: Active
A61: [Product2] | B61: Thawte SSL Webserver OV FQDN SAN | C61: Thawte SSL Webserver OV FQDN SAN | E61: TRUE | F61: Thawte | G61: USD | H61: 012dp000005zfL7AAI | J61: 01t0z000007f41vAAA | K61: 01t0z000007f41vAAA | L61: 01t0z000007f41vAAA | S61: 11BWC000002cka92AA | V61: TRUE | X61: TRUE | Y61: Commercial | Z61: FALSE | BG61: FALSE | CD61: FALSE | CG61: FALSE | CL61: FALSE | CM61: FALSE | CN61: FALSE | CP61: 01tWC00000AYBYwYAP | CR61: FALSE | CV61: FALSE | CX61: FALSE | CY61: FALSE | DA61: FALSE | DB61: FALSE | DI61: FALSE | DN61: Thawte SSL Webserver OV FQDN SAN | DQ61: FALSE | DS61: FALSE | DU61: Thawte SSL Webserver OV FQDN SAN | DY61: All SSL Product Grp | DZ61: Active
A62: [Product2] | B62: Thawte SSL Webserver OV Wildcard SAN | C62: Thawte SSL Webserver OV Wildcard SAN | E62: TRUE | F62: Thawte | G62: USD | H62: 012dp000005zfL7AAI | J62: 01t0z000007f41wAAA | K62: 01t0z000007f41wAAA | L62: 01t0z000007f41wAAA | S62: 11BWC000002cka92AA | V62: TRUE | X62: TRUE | Y62: Commercial | Z62: FALSE | BG62: FALSE | CD62: FALSE | CG62: FALSE | CL62: FALSE | CM62: FALSE | CN62: FALSE | CP62: 01tWC00000AYBYxYAP | CR62: FALSE | CV62: FALSE | CX62: FALSE | CY62: FALSE | DA62: FALSE | DB62: FALSE | DI62: FALSE | DN62: Thawte SSL Webserver OV Wildcard SAN | DQ62: FALSE | DS62: FALSE | DU62: Thawte SSL Webserver OV Wildcard SAN | DY62: All SSL Product Grp | DZ62: Active
A63: [Product2] | B63: Timestamp Authority | C63: Timestamp Authority | E63: TRUE | F63: DigiCert | G63: USD | H63: 012dp000005zfL7AAI | J63: 01t0z000007f41xAAA | K63: 01t0z000007f41xAAA | L63: 01t0z000007f41xAAA | S63: 11BWC000002WLYt2AO | V63: TRUE | W63: Allowed | X63: TRUE | Y63: Commercial | Z63: FALSE | BG63: FALSE | CD63: FALSE | CG63: FALSE | CL63: FALSE | CM63: FALSE | CN63: FALSE | CP63: 01tWC00000AYBYyYAP | CR63: FALSE | CV63: FALSE | CX63: FALSE | CY63: FALSE | DA63: FALSE | DB63: FALSE | DI63: FALSE | DN63: Timestamp Authority | DQ63: FALSE | DS63: FALSE | DU63: Timestamp Authority | DY63: All SSL Product Grp | DZ63: Active
A64: [Product2] | B64: DigiCert KeyLocker (Units) | C64: DigiCert KeyLocker (Units) | E64: TRUE | F64: DigiCert | G64: USD | H64: 012dp000005zfL7AAI | J64: 01t4z000008br95AAA | K64: 01t4z000008br95AAA | L64: 01t4z000008br95AAA | V64: TRUE | W64: Allowed | X64: TRUE | Y64: Commercial | Z64: FALSE | BG64: FALSE | CD64: FALSE | CG64: FALSE | CL64: FALSE | CM64: FALSE | CN64: FALSE | CP64: 01tWC00000AYBZ0YAP | CR64: FALSE | CV64: FALSE | CX64: FALSE | CY64: FALSE | DA64: FALSE | DB64: FALSE | DI64: FALSE | DN64: DigiCert KeyLocker (Units) | DQ64: FALSE | DS64: FALSE | DU64: DigiCert KeyLocker (Units) | DZ64: Active
A65: [Product2] | B65: DIGICERT USB AUTHENTICATOR 5110FIPS PLUS NO PIN 3YR WARRANTY [Hardware Token] (Units) | C65: DIGICERT USB AUTHENTICATOR 5110FIPS PLUS NO PIN 3YR WARRANTY [Hardware Token] (Units) | E65: TRUE | F65: DigiCert | G65: USD | H65: 012dp000005zfL7AAI | J65: 01t4z000008br9ZAAQ | K65: 01t4z000008br9ZAAQ | L65: 01t4z000008br9ZAAQ | V65: TRUE | X65: TRUE | Y65: Commercial | Z65: FALSE | BG65: FALSE | CD65: FALSE | CG65: FALSE | CL65: FALSE | CM65: FALSE | CN65: FALSE | CP65: 01tWC00000AYBZ1YAP | CR65: FALSE | CV65: FALSE | CX65: FALSE | CY65: FALSE | DA65: FALSE | DB65: FALSE | DI65: FALSE | DN65: DIGICERT USB AUTHENTICATOR 5110FIPS PLUS NO PIN 3YR WARRANTY [Hardware Token] (Units) | DQ65: FALSE | DS65: FALSE | DU65: DIGICERT USB AUTHENTICATOR 5110FIPS PLUS NO PIN 3YR WARRANTY [Hardware Token] (Units) | DZ65: Active
A66: [Product2] | B66: Encryption Everywhere DV | C66: Encryption Everywhere DV | E66: TRUE | F66: DigiCert | G66: USD | H66: 012dp000005zfL7AAI | J66: 01t4z000008h0MrAAI | K66: 01t4z000008h0MrAAI | L66: 01t4z000008h0MrAAI | V66: TRUE | X66: TRUE | Y66: Commercial | Z66: FALSE | BG66: FALSE | CD66: FALSE | CG66: FALSE | CL66: FALSE | CM66: FALSE | CN66: FALSE | CP66: 01tWC00000AYBZ2YAP | CR66: FALSE | CV66: FALSE | CX66: FALSE | CY66: FALSE | DA66: FALSE | DB66: FALSE | DI66: FALSE | DN66: Encryption Everywhere DV | DQ66: FALSE | DS66: FALSE | DU66: Encryption Everywhere DV | DY66: All SSL Product Grp | DZ66: Active
A67: [Product2] | B67: Encryption Everywhere DV Wildcard SAN | C67: Encryption Everywhere DV Wildcard SAN | E67: TRUE | F67: DigiCert | G67: USD | H67: 012dp000005zfL7AAI | J67: 01t4z000008h0MwAAI | K67: 01t4z000008h0MwAAI | L67: 01t4z000008h0MwAAI | V67: TRUE | X67: TRUE | Y67: Commercial | Z67: FALSE | BG67: FALSE | CD67: FALSE | CG67: FALSE | CL67: FALSE | CM67: FALSE | CN67: FALSE | CP67: 01tWC00000AYBZ3YAP | CR67: FALSE | CV67: FALSE | CX67: FALSE | CY67: FALSE | DA67: FALSE | DB67: FALSE | DI67: FALSE | DN67: Encryption Everywhere DV Wildcard SAN | DQ67: FALSE | DS67: FALSE | DU67: Encryption Everywhere DV Wildcard SAN | DY67: All SSL Product Grp | DZ67: Active
A68: [Product2] | B68: Grid Host Multi-Domain SSL | C68: Grid Host Multi-Domain SSL | E68: TRUE | F68: DigiCert | G68: USD | H68: 012dp000005zfL7AAI | J68: 01t4z000008h0N1AAI | K68: 01t4z000008h0N1AAI | L68: 01t4z000008h0N1AAI | S68: 11BWC000002WLYz2AO | V68: TRUE | X68: TRUE | Y68: Commercial | Z68: FALSE | BG68: FALSE | CD68: FALSE | CG68: FALSE | CL68: FALSE | CM68: FALSE | CN68: FALSE | CP68: 01tWC00000AYBZ4YAP | CR68: FALSE | CV68: FALSE | CX68: FALSE | CY68: FALSE | DA68: FALSE | DB68: FALSE | DI68: FALSE | DN68: Grid Host Multi-Domain SSL | DQ68: FALSE | DS68: FALSE | DU68: Grid Host Multi-Domain SSL | DY68: All SSL Product Grp | DZ68: Active
A69: [Product2] | B69: Grid Host Multi-Domain SSL Addl. Names | C69: Grid Host Multi-Domain SSL Addl. Names | E69: TRUE | F69: DigiCert | G69: USD | H69: 012dp000005zfL7AAI | J69: 01t4z000008h0N6AAI | K69: 01t4z000008h0N6AAI | L69: 01t4z000008h0N6AAI | S69: 11BWC000002WLZ02AO | V69: TRUE | X69: TRUE | Y69: Commercial | Z69: FALSE | BG69: FALSE | CD69: FALSE | CG69: FALSE | CL69: FALSE | CM69: FALSE | CN69: FALSE | CP69: 01tWC00000AYBZ5YAP | CR69: FALSE | CV69: FALSE | CX69: FALSE | CY69: FALSE | DA69: FALSE | DB69: FALSE | DI69: FALSE | DN69: Grid Host Multi-Domain SSL Addl. Names | DQ69: FALSE | DS69: FALSE | DU69: Grid Host Multi-Domain SSL Addl. Names | DY69: All SSL Product Grp | DZ69: Active
A70: [Product2] | B70: Grid Host SSL | C70: Grid Host SSL | E70: TRUE | F70: DigiCert | G70: USD | H70: 012dp000005zfL7AAI | J70: 01t4z000008h0NBAAY | K70: 01t4z000008h0NBAAY | L70: 01t4z000008h0NBAAY | S70: 11BWC000002WLZ12AO | V70: TRUE | X70: TRUE | Y70: Commercial | Z70: FALSE | BG70: FALSE | CD70: FALSE | CG70: FALSE | CL70: FALSE | CM70: FALSE | CN70: FALSE | CP70: 01tWC00000AYBZ6YAP | CR70: FALSE | CV70: FALSE | CX70: FALSE | CY70: FALSE | DA70: FALSE | DB70: FALSE | DI70: FALSE | DN70: Grid Host SSL | DQ70: FALSE | DS70: FALSE | DU70: Grid Host SSL | DY70: All SSL Product Grp | DZ70: Active
A71: [Product2] | B71: Grid Premium | C71: Grid Premium | E71: TRUE | F71: DigiCert | G71: USD | H71: 012dp000005zfL7AAI | J71: 01t4z000008h0NGAAY | K71: 01t4z000008h0NGAAY | L71: 01t4z000008h0NGAAY | S71: 11BWC000002WLYy2AO | V71: TRUE | X71: TRUE | Y71: Commercial | Z71: FALSE | BG71: FALSE | CD71: FALSE | CG71: FALSE | CL71: FALSE | CM71: FALSE | CN71: FALSE | CP71: 01tWC00000AYBZ7YAP | CR71: FALSE | CV71: FALSE | CX71: FALSE | CY71: FALSE | DA71: FALSE | DB71: FALSE | DI71: FALSE | DN71: Grid Premium | DQ71: FALSE | DS71: FALSE | DU71: Grid Premium | DY71: All SSL Product Grp | DZ71: Active
A72: [Product2] | B72: Grid Robot Email | C72: Grid Robot Email | E72: TRUE | F72: DigiCert | G72: USD | H72: 012dp000005zfL7AAI | J72: 01t4z000008h0NHAAY | K72: 01t4z000008h0NHAAY | L72: 01t4z000008h0NHAAY | S72: 11BWC000002WLZ22AO | V72: TRUE | X72: TRUE | Y72: Commercial | Z72: FALSE | BG72: FALSE | CD72: FALSE | CG72: FALSE | CL72: FALSE | CM72: FALSE | CN72: FALSE | CP72: 01tWC00000AYBZ8YAP | CR72: FALSE | CV72: FALSE | CX72: FALSE | CY72: FALSE | DA72: FALSE | DB72: FALSE | DI72: FALSE | DN72: Grid Robot Email | DQ72: FALSE | DS72: FALSE | DU72: Grid Robot Email | DY72: All SSL Product Grp | DZ72: Active
A73: [Product2] | B73: Grid Robot FQDN | C73: Grid Robot FQDN | E73: TRUE | F73: DigiCert | G73: USD | H73: 012dp000005zfL7AAI | J73: 01t4z000008h0NIAAY | K73: 01t4z000008h0NIAAY | L73: 01t4z000008h0NIAAY | S73: 11BWC000002WLZ32AO | V73: TRUE | X73: TRUE | Y73: Commercial | Z73: FALSE | BG73: FALSE | CD73: FALSE | CG73: FALSE | CL73: FALSE | CM73: FALSE | CN73: FALSE | CP73: 01tWC00000AYBZ9YAP | CR73: FALSE | CV73: FALSE | CX73: FALSE | CY73: FALSE | DA73: FALSE | DB73: FALSE | DI73: FALSE | DN73: Grid Robot FQDN | DQ73: FALSE | DS73: FALSE | DU73: Grid Robot FQDN | DY73: All SSL Product Grp | DZ73: Active
A74: [Product2] | B74: Private SSL OV (Units) | C74: Private SSL OV (Units) | E74: TRUE | F74: DigiCert | G74: USD | H74: 012dp000005zfL7AAI | J74: 01t4z000008jjfOAAQ | K74: 01t4z000008jjfOAAQ | L74: 01t4z000008jjfOAAQ | V74: TRUE | W74: Allowed | X74: TRUE | Y74: Commercial | Z74: FALSE | BG74: FALSE | CD74: FALSE | CG74: FALSE | CL74: FALSE | CM74: FALSE | CN74: FALSE | CP74: 01tWC00000AYBZAYA5 | CR74: FALSE | CV74: FALSE | CX74: FALSE | CY74: FALSE | DA74: FALSE | DB74: FALSE | DI74: FALSE | DN74: Private SSL OV (Units) | DQ74: FALSE | DS74: FALSE | DU74: Private SSL OV (Units) | DZ74: Active
A75: [Product2] | B75: EV Code Signing (Units) | C75: EV Code Signing (Units) | E75: TRUE | F75: DigiCert | G75: USD | H75: 012dp000005zfL7AAI | J75: 01t4z000008jjfSAAQ | K75: 01t4z000008jjfSAAQ | L75: 01t4z000008jjfSAAQ | V75: TRUE | W75: Allowed | X75: TRUE | Y75: Commercial | Z75: FALSE | BG75: FALSE | CD75: FALSE | CG75: FALSE | CL75: FALSE | CM75: FALSE | CN75: FALSE | CP75: 01tWC00000AYBZBYA5 | CR75: FALSE | CV75: FALSE | CX75: FALSE | CY75: FALSE | DA75: FALSE | DB75: FALSE | DI75: FALSE | DN75: EV Code Signing (Units) | DQ75: FALSE | DS75: FALSE | DU75: EV Code Signing (Units) | DZ75: Active
A76: [Product2] | B76: GeoTrust TrueBusiness ID OV (Units) | C76: GeoTrust TrueBusiness ID OV (Units) | E76: TRUE | F76: Geotrust | G76: USD | H76: 012dp000005zfL7AAI | J76: 01t4z000008jjfXAAQ | K76: 01t4z000008jjfXAAQ | L76: 01t4z000008jjfXAAQ | V76: TRUE | W76: Allowed | X76: TRUE | Y76: Commercial | Z76: FALSE | BG76: FALSE | CD76: FALSE | CG76: FALSE | CL76: FALSE | CM76: FALSE | CN76: FALSE | CP76: 01tWC00000AYBZCYA5 | CR76: FALSE | CV76: FALSE | CX76: FALSE | CY76: FALSE | DA76: FALSE | DB76: FALSE | DI76: FALSE | DN76: GeoTrust TrueBusiness ID OV (Units) | DQ76: FALSE | DS76: FALSE | DU76: GeoTrust TrueBusiness ID OV (Units) | DZ76: Active
A77: [Product2] | B77: GeoTrust TrueBusiness ID EV (Units) | C77: GeoTrust TrueBusiness ID EV (Units) | E77: TRUE | F77: Geotrust | G77: USD | H77: 012dp000005zfL7AAI | J77: 01t4z000008jjfcAAA | K77: 01t4z000008jjfcAAA | L77: 01t4z000008jjfcAAA | V77: TRUE | W77: Allowed | X77: TRUE | Y77: Commercial | Z77: FALSE | BG77: FALSE | CD77: FALSE | CG77: FALSE | CL77: FALSE | CM77: FALSE | CN77: FALSE | CP77: 01tWC00000AYBZDYA5 | CR77: FALSE | CV77: FALSE | CX77: FALSE | CY77: FALSE | DA77: FALSE | DB77: FALSE | DI77: FALSE | DN77: GeoTrust TrueBusiness ID EV (Units) | DQ77: FALSE | DS77: FALSE | DU77: GeoTrust TrueBusiness ID EV (Units) | DZ77: Active
A78: [Product2] | B78: Secure Site EV (Units) | C78: Secure Site EV (Units) | E78: TRUE | F78: DigiCert | G78: USD | H78: 012dp000005zfL7AAI | J78: 01t4z000008jjfhAAA | K78: 01t4z000008jjfhAAA | L78: 01t4z000008jjfhAAA | V78: TRUE | W78: Allowed | X78: TRUE | Y78: Commercial | Z78: FALSE | BG78: FALSE | CD78: FALSE | CG78: FALSE | CL78: FALSE | CM78: FALSE | CN78: FALSE | CP78: 01tWC00000AYBZEYA5 | CR78: FALSE | CV78: FALSE | CX78: FALSE | CY78: FALSE | DA78: FALSE | DB78: FALSE | DI78: FALSE | DN78: Secure Site EV (Units) | DQ78: FALSE | DS78: FALSE | DU78: Secure Site EV (Units) | DZ78: Active
A79: [Product2] | B79: Secure Site OV (Units) | C79: Secure Site OV (Units) | E79: TRUE | F79: DigiCert | G79: USD | H79: 012dp000005zfL7AAI | J79: 01t4z000008jjfrAAA | K79: 01t4z000008jjfrAAA | L79: 01t4z000008jjfrAAA | V79: TRUE | W79: Allowed | X79: TRUE | Y79: Commercial | Z79: FALSE | BG79: FALSE | CD79: FALSE | CG79: FALSE | CL79: FALSE | CM79: FALSE | CN79: FALSE | CP79: 01tWC00000AYBZFYA5 | CR79: FALSE | CV79: FALSE | CX79: FALSE | CY79: FALSE | DA79: FALSE | DB79: FALSE | DI79: FALSE | DN79: Secure Site OV (Units) | DQ79: FALSE | DS79: FALSE | DU79: Secure Site OV (Units) | DZ79: Active
A80: [Product2] | B80: Secure Site Pro EV SSL (Units) | C80: Secure Site Pro EV SSL (Units) | E80: TRUE | F80: DigiCert | G80: USD | H80: 012dp000005zfL7AAI | J80: 01t4z000008jjfwAAA | K80: 01t4z000008jjfwAAA | L80: 01t4z000008jjfwAAA | V80: TRUE | W80: Allowed | X80: TRUE | Y80: Commercial | Z80: FALSE | BG80: FALSE | CD80: FALSE | CG80: FALSE | CL80: FALSE | CM80: FALSE | CN80: FALSE | CP80: 01tWC00000AYBZGYA5 | CR80: FALSE | CV80: FALSE | CX80: FALSE | CY80: FALSE | DA80: FALSE | DB80: FALSE | DI80: FALSE | DN80: Secure Site Pro EV SSL (Units) | DQ80: FALSE | DS80: FALSE | DU80: Secure Site Pro EV SSL (Units) | DZ80: Active
A81: [Product2] | B81: Secure Site Pro SSL (Units) | C81: Secure Site Pro SSL (Units) | E81: TRUE | F81: DigiCert | G81: USD | H81: 012dp000005zfL7AAI | J81: 01t4z000008jjfxAAA | K81: 01t4z000008jjfxAAA | L81: 01t4z000008jjfxAAA | V81: TRUE | W81: Allowed | X81: TRUE | Y81: Commercial | Z81: FALSE | BG81: FALSE | CD81: FALSE | CG81: FALSE | CL81: FALSE | CM81: FALSE | CN81: FALSE | CP81: 01tWC00000AYBZHYA5 | CR81: FALSE | CV81: FALSE | CX81: FALSE | CY81: FALSE | DA81: FALSE | DB81: FALSE | DI81: FALSE | DN81: Secure Site Pro SSL (Units) | DQ81: FALSE | DS81: FALSE | DU81: Secure Site Pro SSL (Units) | DZ81: Active
A82: [Product2] | B82: Thawte SSL Webserver EV (Units) | C82: Thawte SSL Webserver EV (Units) | E82: TRUE | F82: Thawte | G82: USD | H82: 012dp000005zfL7AAI | J82: 01t4z000008jjg1AAA | K82: 01t4z000008jjg1AAA | L82: 01t4z000008jjg1AAA | V82: TRUE | W82: Allowed | X82: TRUE | Y82: Commercial | Z82: FALSE | BG82: FALSE | CD82: FALSE | CG82: FALSE | CL82: FALSE | CM82: FALSE | CN82: FALSE | CP82: 01tWC00000AYBZIYA5 | CR82: FALSE | CV82: FALSE | CX82: FALSE | CY82: FALSE | DA82: FALSE | DB82: FALSE | DI82: FALSE | DN82: Thawte SSL Webserver EV (Units) | DQ82: FALSE | DS82: FALSE | DU82: Thawte SSL Webserver EV (Units) | DZ82: Active
A83: [Product2] | B83: Thawte SSL Webserver OV (Units) | C83: Thawte SSL Webserver OV (Units) | E83: TRUE | F83: Thawte | G83: USD | H83: 012dp000005zfL7AAI | J83: 01t4z000008jjg6AAA | K83: 01t4z000008jjg6AAA | L83: 01t4z000008jjg6AAA | V83: TRUE | W83: Allowed | X83: TRUE | Y83: Commercial | Z83: FALSE | BG83: FALSE | CD83: FALSE | CG83: FALSE | CL83: FALSE | CM83: FALSE | CN83: FALSE | CP83: 01tWC00000AYBZJYA5 | CR83: FALSE | CV83: FALSE | CX83: FALSE | CY83: FALSE | DA83: FALSE | DB83: FALSE | DI83: FALSE | DN83: Thawte SSL Webserver OV (Units) | DQ83: FALSE | DS83: FALSE | DU83: Thawte SSL Webserver OV (Units) | DZ83: Active
A84: [Product2] | B84: Verified Mark Certificate (Units) | C84: Verified Mark Certificate (Units) | E84: TRUE | F84: DigiCert | G84: USD | H84: 012dp000005zfL7AAI | J84: 01t4z000008jjgBAAQ | K84: 01t4z000008jjgBAAQ | L84: 01t4z000008jjgBAAQ | V84: TRUE | X84: TRUE | Y84: Commercial | Z84: FALSE | BG84: FALSE | CD84: FALSE | CG84: FALSE | CL84: FALSE | CM84: FALSE | CN84: FALSE | CP84: 01tWC00000AYBZKYA5 | CR84: FALSE | CV84: FALSE | CX84: FALSE | CY84: FALSE | DA84: FALSE | DB84: FALSE | DI84: FALSE | DN84: Verified Mark Certificate (Units) | DQ84: FALSE | DS84: FALSE | DU84: Verified Mark Certificate (Units) | DZ84: Active
A85: [Product2] | B85: Encryption Everywhere DV FQDN SAN | C85: Encryption Everywhere DV FQDN SAN | E85: TRUE | F85: DigiCert | G85: USD | H85: 012dp000005zfL7AAI | J85: 01t4z000008jyEyAAI | K85: 01t4z000008jyEyAAI | L85: 01t4z000008jyEyAAI | V85: TRUE | X85: TRUE | Y85: Commercial | Z85: FALSE | BG85: FALSE | CD85: FALSE | CG85: FALSE | CL85: FALSE | CM85: FALSE | CN85: FALSE | CP85: 01tWC00000AYBZLYA5 | CR85: FALSE | CV85: FALSE | CX85: FALSE | CY85: FALSE | DA85: FALSE | DB85: FALSE | DI85: FALSE | DN85: Encryption Everywhere DV FQDN SAN | DQ85: FALSE | DS85: FALSE | DU85: Encryption Everywhere DV FQDN SAN | DY85: All SSL Product Grp | DZ85: Active
A86: [Product2] | B86: DIGICERT USB AUTHENTICATOR 5110FIPS PLUS NO PIN 3YR WARRANTY (Hardware Token) | C86: 1125 | E86: TRUE | F86: DigiCert | G86: USD | H86: 012dp000005zfL7AAI | J86: 01t4z00000A1NAeAAN | K86: 01t4z00000A1NAeAAN | L86: 01t4z00000A1NAeAAN | V86: TRUE | X86: TRUE | Y86: Commercial | Z86: FALSE | BG86: FALSE | CD86: FALSE | CG86: FALSE | CL86: FALSE | CM86: FALSE | CN86: FALSE | CP86: 01tWC00000AYBZMYA5 | CR86: FALSE | CV86: FALSE | CX86: FALSE | CY86: FALSE | DA86: FALSE | DB86: FALSE | DI86: FALSE | DN86: 1125 | DQ86: FALSE | DS86: FALSE | DU86: DIGICERT USB AUTHENTICATOR 5110FIPS PLUS NO PIN 3YR WARRANTY (Hardware Token) | DY86: All SSL Product Grp | DZ86: Active
A87: [Product2] | B87: Platinum Support | C87: PSUPPORT | E87: TRUE | F87: DigiCert | G87: USD | H87: 012dp000005zfL7AAI | J87: 01t4z00000A3vuzAAB | K87: 01t4z00000A3vuzAAB | L87: 01t4z00000A3vuzAAB | S87: 11BWC000002WLiJ2AW | V87: TRUE | X87: TRUE | Y87: Commercial | Z87: FALSE | BG87: FALSE | CD87: FALSE | CG87: FALSE | CL87: FALSE | CM87: FALSE | CN87: FALSE | CP87: 01tWC00000AYBZNYA5 | CR87: FALSE | CV87: FALSE | CX87: FALSE | CY87: FALSE | DA87: FALSE | DB87: FALSE | DI87: FALSE | DN87: PSUPPORT | DQ87: FALSE | DS87: FALSE | DU87: Platinum Support | DZ87: Active
A88: [Product2] | B88: Gold Support | C88: GSUPPORT | E88: TRUE | F88: DigiCert | G88: USD | H88: 012dp000005zfL7AAI | J88: 01t4z00000A3vv4AAB | K88: 01t4z00000A3vv4AAB | L88: 01t4z00000A3vv4AAB | S88: 11BWC000002WLZ92AO | V88: TRUE | X88: TRUE | Y88: Commercial | Z88: FALSE | BG88: FALSE | CD88: FALSE | CG88: FALSE | CL88: FALSE | CM88: FALSE | CN88: FALSE | CP88: 01tWC00000AYBZOYA5 | CR88: FALSE | CV88: FALSE | CX88: FALSE | CY88: FALSE | DA88: FALSE | DB88: FALSE | DI88: FALSE | DN88: GSUPPORT | DQ88: FALSE | DS88: FALSE | DU88: Gold Support | DZ88: Active
A89: [Product2] | B89: Basic Support | C89: BSUPPORT | E89: TRUE | F89: DigiCert | G89: USD | H89: 012dp000005zfL7AAI | J89: 01t4z00000A3vv9AAB | K89: 01t4z00000A3vv9AAB | L89: 01t4z00000A3vv9AAB | V89: TRUE | X89: TRUE | Y89: Commercial | Z89: FALSE | BG89: FALSE | CD89: FALSE | CG89: FALSE | CL89: FALSE | CM89: FALSE | CN89: FALSE | CP89: 01tWC00000AYBZPYA5 | CR89: FALSE | CV89: FALSE | CX89: FALSE | CY89: FALSE | DA89: FALSE | DB89: FALSE | DI89: FALSE | DN89: BSUPPORT | DQ89: FALSE | DS89: FALSE | DU89: Basic Support | DZ89: Active
A90: [Product2] | B90: Dedicated Public CA Creation and Maintenance | C90: 2210 | E90: TRUE | F90: DigiCert | G90: USD | H90: 012dp000005zfL7AAI | J90: 01t4z00000A3wAFAAZ | K90: 01t4z00000A3wAFAAZ | L90: 01t4z00000A3wAFAAZ | V90: TRUE | X90: TRUE | Y90: Commercial | Z90: FALSE | BG90: FALSE | CD90: FALSE | CG90: FALSE | CL90: FALSE | CM90: FALSE | CN90: FALSE | CP90: 01tWC00000AYBZQYA5 | CR90: FALSE | CV90: FALSE | CX90: FALSE | CY90: FALSE | DA90: FALSE | DB90: FALSE | DI90: FALSE | DN90: 2210 | DQ90: FALSE | DS90: FALSE | DU90: Dedicated Public CA Creation and Maintenance | DY90: All SSL Product Grp | DZ90: Active
A91: [Product2] | B91: Digital Signature Plus (Units) | C91: Digital Signature Plus (Units) | E91: TRUE | F91: DigiCert | G91: USD | H91: 012dp000005zfL7AAI | J91: 01t4z00000A3wUNAAZ | K91: 01t4z00000A3wUNAAZ | L91: 01t4z00000A3wUNAAZ | V91: TRUE | W91: Allowed | X91: TRUE | Y91: Commercial | Z91: FALSE | BG91: FALSE | CD91: FALSE | CG91: FALSE | CL91: FALSE | CM91: FALSE | CN91: FALSE | CP91: 01tWC00000AYBZRYA5 | CR91: FALSE | CV91: FALSE | CX91: FALSE | CY91: FALSE | DA91: FALSE | DB91: FALSE | DI91: FALSE | DN91: Digital Signature Plus (Units) | DQ91: FALSE | DS91: FALSE | DU91: Digital Signature Plus (Units) | DZ91: Active
A92: [Product2] | B92: Email Security Plus (Units) | C92: Email Security Plus (Units) | E92: TRUE | F92: DigiCert | G92: USD | H92: 012dp000005zfL7AAI | J92: 01t4z00000A3wUQAAZ | K92: 01t4z00000A3wUQAAZ | L92: 01t4z00000A3wUQAAZ | V92: TRUE | W92: Allowed | X92: TRUE | Y92: Commercial | Z92: FALSE | BG92: FALSE | CD92: FALSE | CG92: FALSE | CL92: FALSE | CM92: FALSE | CN92: FALSE | CP92: 01tWC00000AYBZSYA5 | CR92: FALSE | CV92: FALSE | CX92: FALSE | CY92: FALSE | DA92: FALSE | DB92: FALSE | DI92: FALSE | DN92: Email Security Plus (Units) | DQ92: FALSE | DS92: FALSE | DU92: Email Security Plus (Units) | DZ92: Active
A93: [Product2] | B93: Email Security Plus [AD Integration] (Units) | C93: Email Security Plus [AD Integration] (Units) | E93: TRUE | F93: DigiCert | G93: USD | H93: 012dp000005zfL7AAI | J93: 01t4z00000A3wURAAZ | K93: 01t4z00000A3wURAAZ | L93: 01t4z00000A3wURAAZ | V93: TRUE | W93: Allowed | X93: TRUE | Y93: Commercial | Z93: FALSE | BG93: FALSE | CD93: FALSE | CG93: FALSE | CL93: FALSE | CM93: FALSE | CN93: FALSE | CP93: 01tWC00000AYBZTYA5 | CR93: FALSE | CV93: FALSE | CX93: FALSE | CY93: FALSE | DA93: FALSE | DB93: FALSE | DI93: FALSE | DN93: Email Security Plus [AD Integration] (Units) | DQ93: FALSE | DS93: FALSE | DU93: Email Security Plus [AD Integration] (Units) | DZ93: Active
A94: [Product2] | B94: Email Security Plus [SHA-2 Only] (Units) | C94: Email Security Plus [SHA-2 Only] (Units) | E94: TRUE | F94: DigiCert | G94: USD | H94: 012dp000005zfL7AAI | J94: 01t4z00000A3wUSAAZ | K94: 01t4z00000A3wUSAAZ | L94: 01t4z00000A3wUSAAZ | V94: TRUE | W94: Allowed | X94: TRUE | Y94: Commercial | Z94: FALSE | BG94: FALSE | CD94: FALSE | CG94: FALSE | CL94: FALSE | CM94: FALSE | CN94: FALSE | CP94: 01tWC00000AYBZUYA5 | CR94: FALSE | CV94: FALSE | CX94: FALSE | CY94: FALSE | DA94: FALSE | DB94: FALSE | DI94: FALSE | DN94: Email Security Plus [SHA-2 Only] (Units) | DQ94: FALSE | DS94: FALSE | DU94: Email Security Plus [SHA-2 Only] (Units) | DZ94: Active
A95: [Product2] | B95: Class 1 S/MIME (Units) | C95: Class 1 S/MIME (Units) | E95: TRUE | F95: DigiCert | G95: USD | H95: 012dp000005zfL7AAI | J95: 01t4z00000A3wUTAAZ | K95: 01t4z00000A3wUTAAZ | L95: 01t4z00000A3wUTAAZ | V95: TRUE | W95: Allowed | X95: TRUE | Y95: Commercial | Z95: FALSE | BG95: FALSE | CD95: FALSE | CG95: FALSE | CL95: FALSE | CM95: FALSE | CN95: FALSE | CP95: 01tWC00000AYBZVYA5 | CR95: FALSE | CV95: FALSE | CX95: FALSE | CY95: FALSE | DA95: FALSE | DB95: FALSE | DI95: FALSE | DN95: Class 1 S/MIME (Units) | DQ95: FALSE | DS95: FALSE | DU95: Class 1 S/MIME (Units) | DZ95: Active
A96: [Product2] | B96: Class 1 S/MIME [no email] (Units) | C96: Class 1 S/MIME [no email] (Units) | E96: TRUE | F96: DigiCert | G96: USD | H96: 012dp000005zfL7AAI | J96: 01t4z00000A3wUUAAZ | K96: 01t4z00000A3wUUAAZ | L96: 01t4z00000A3wUUAAZ | V96: TRUE | W96: Allowed | X96: TRUE | Y96: Commercial | Z96: FALSE | BG96: FALSE | CD96: FALSE | CG96: FALSE | CL96: FALSE | CM96: FALSE | CN96: FALSE | CP96: 01tWC00000AYBZWYA5 | CR96: FALSE | CV96: FALSE | CX96: FALSE | CY96: FALSE | DA96: FALSE | DB96: FALSE | DI96: FALSE | DN96: Class 1 S/MIME [no email] (Units) | DQ96: FALSE | DS96: FALSE | DU96: Class 1 S/MIME [no email] (Units) | DZ96: Active
A97: [Product2] | B97: Authentication Plus (Units) | C97: Authentication Plus (Units) | E97: TRUE | F97: DigiCert | G97: USD | H97: 012dp000005zfL7AAI | J97: 01t4z00000A3wUVAAZ | K97: 01t4z00000A3wUVAAZ | L97: 01t4z00000A3wUVAAZ | V97: TRUE | W97: Allowed | X97: TRUE | Y97: Commercial | Z97: FALSE | BG97: FALSE | CD97: FALSE | CG97: FALSE | CL97: FALSE | CM97: FALSE | CN97: FALSE | CP97: 01tWC00000AYBZXYA5 | CR97: FALSE | CV97: FALSE | CX97: FALSE | CY97: FALSE | DA97: FALSE | DB97: FALSE | DI97: FALSE | DN97: Authentication Plus (Units) | DQ97: FALSE | DS97: FALSE | DU97: Authentication Plus (Units) | DZ97: Active
A98: [Product2] | B98: Authentication Plus [AD Integration] (Units) | C98: Authentication Plus [AD Integration] (Units) | E98: TRUE | F98: DigiCert | G98: USD | H98: 012dp000005zfL7AAI | J98: 01t4z00000A3wUWAAZ | K98: 01t4z00000A3wUWAAZ | L98: 01t4z00000A3wUWAAZ | V98: TRUE | W98: Allowed | X98: TRUE | Y98: Commercial | Z98: FALSE | BG98: FALSE | CD98: FALSE | CG98: FALSE | CL98: FALSE | CM98: FALSE | CN98: FALSE | CP98: 01tWC00000AYBZYYA5 | CR98: FALSE | CV98: FALSE | CX98: FALSE | CY98: FALSE | DA98: FALSE | DB98: FALSE | DI98: FALSE | DN98: Authentication Plus [AD Integration] (Units) | DQ98: FALSE | DS98: FALSE | DU98: Authentication Plus [AD Integration] (Units) | DZ98: Active
A99: [Product2] | B99: Premium [Class 2 S/MIME] (Units) | C99: Premium [Class 2 S/MIME] (Units) | E99: TRUE | F99: DigiCert | G99: USD | H99: 012dp000005zfL7AAI | J99: 01t4z00000A3wUXAAZ | K99: 01t4z00000A3wUXAAZ | L99: 01t4z00000A3wUXAAZ | V99: TRUE | W99: Allowed | X99: TRUE | Y99: Commercial | Z99: FALSE | BG99: FALSE | CD99: FALSE | CG99: FALSE | CL99: FALSE | CM99: FALSE | CN99: FALSE | CP99: 01tWC00000AYBZZYA5 | CR99: FALSE | CV99: FALSE | CX99: FALSE | CY99: FALSE | DA99: FALSE | DB99: FALSE | DI99: FALSE | DN99: Premium [Class 2 S/MIME] (Units) | DQ99: FALSE | DS99: FALSE | DU99: Premium [Class 2 S/MIME] (Units) | DZ99: Active
A100: [Product2] | B100: Premium [no email - Class 2 S/MIME] (Units) | C100: Premium [no email - Class 2 S/MIME] (Units) | E100: TRUE | F100: DigiCert | G100: USD | H100: 012dp000005zfL7AAI | J100: 01t4z00000A3wUYAAZ | K100: 01t4z00000A3wUYAAZ | L100: 01t4z00000A3wUYAAZ | V100: TRUE | W100: Allowed | X100: TRUE | Y100: Commercial | Z100: FALSE | BG100: FALSE | CD100: FALSE | CG100: FALSE | CL100: FALSE | CM100: FALSE | CN100: FALSE | CP100: 01tWC00000AYBZaYAP | CR100: FALSE | CV100: FALSE | CX100: FALSE | CY100: FALSE | DA100: FALSE | DB100: FALSE | DI100: FALSE | DN100: Premium [no email - Class 2 S/MIME] (Units) | DQ100: FALSE | DS100: FALSE | DU100: Premium [no email - Class 2 S/MIME] (Units) | DZ100: Active
...

Sheet Sheet3
A1: _ | B1: Name | C1: ProductCode | D1: Description | E1: IsActive | F1: Family | G1: CurrencyIsoCode | H1: RecordTypeId | I1: ExternalDataSourceId | J1: Id | K1: RCA_ExternalId__c | L1: ExternalId | M1: DisplayUrl | N1: QuantityUnitOfMeasure | O1: StockKeepingUnit | P1: AvailabilityDate | Q1: DiscontinuedDate | R1: BasedOn:ProductClassification:RCA_ExternalId__c | S1: EndOfLifeDate | T1: HelpText | U1: IsAssetizable | V1: ConfigureDuringSale | W1: IsSoldOnlyWithOtherProds | X1: _SpecificationType | Y1: _CanRamp | Z1: UsageModelType | AA1: Product_Type__c | AB1: GLOBAL_SPECIALIZATION__c | AC1: Internal_Peak__c | AD1: Oracle_Product_Code__c | AE1: Part_Number__c | AF1: Product_Category__c | AG1: Product_Family_Description__c | AH1: Product_Information__c | AI1: Product_Subcategory__c | AJ1: Quotable_Flag__c | AK1: SYMC_CreatedByID__c | AL1: SYMC_LastModifiedByID__c | AM1: Apttus_Config2__BundleInvoiceLevel__c | AN1: Zproduct_Id__c | AO1: Offering_Type__c | AP1: Admin_Area_ID__c | AQ1: Apttus_Config2__RenewalLeadTime__c | AR1: Category_L__c | AS1: Cost__c | AT1: FA_product_line__c | AU1: Genkaritsu__c | AV1: Hanbai_Keitai__c | AW1: Num_Hanbai__c | AX1: Product_Bunrui__c | AY1: Public_Private__c | AZ1: US_Report_Category__c | BA1: activedate_from__c | BB1: activedate_to__c | BC1: category_M__c | BD1: category_s__c | BE1: defered_term__c | BF1: delete_flags__c | BG1: ebs_account__c | BH1: ebs_business_unit__c | BI1: ebs_business_unit_description__c | BJ1: ebs_customer_order_enabled_flag__c | BK1: ebs_customer_order_flag__c | BL1: ebs_description__c | BM1: ebs_enabled_flag__c | BN1: ebs_invoice_enabled_flag__c | BO1: ebs_invoiceable_item_flag__c | BP1: ebs_item_id__c | BQ1: ebs_item_num__c | BR1: ebs_item_type__c | BS1: ebs_language__c | BT1: ebs_language_description__c | BU1: ebs_master_description__c | BV1: ebs_organization_id__c | BW1: ebs_product_line__c | BX1: ebs_product_line_description__c | BY1: ebs_product_name__c | BZ1: ebs_tax_code__c | CA1: ebs_unit_of_issue__c | CB1: kame_product_id__c | CC1: product_flag__c | CD1: revenue_type_id__c | CE1: servicelist__c | CF1: APTS_Apttus_Product__c | CG1: APTS_Cert_Category__c | CH1: APTS_Console__c | CI1: APTS_Contract_Consumption_Method__c | CJ1: APTS_Ext_ID__c | CK1: APTS_Is_Amendable__c | CL1: APTS_Is_Renewable__c | CM1: APTS_New_CPQ_CertCentral__c | CN1: APTS_Order__c | CO1: _APTS_Product_Id_18__c | CP1: APTS_Product_Line__c | CQ1: APTS_Requires_CPF_Doc__c | CR1: APTS_Target_Channel__c | CS1: Type_QV__c | CT1: APTS_Config_Schema__c | CU1: APTS_Exclude_from_Ramping_Validation__c | CV1: ebs_invoicing_rule_id__c | CW1: APTS_Exclude_From_Channel_Discounts__c | CX1: APTS_True_Up_Product__c | CY1: APTS_Japanese_Product_Name__c | CZ1: Non_Recurring_Checkbox__c | DA1: Non_Future_Contracted__c | DB1: cc_product_api_id__c | DC1: APTS_Product_Category__c | DD1: APTS_Product_Line_L2__c | DE1: APTS_Product_Organisation_L1__c | DF1: APTS_Product_category_L3__c | DG1: APTS_Attributes_To_Consider_SKU__c | DH1: APTS_Do_not_consider_for_SKU_Code__c | DI1: APTS_no_of_attributes_SKU__c | DJ1: _APTS_Level1_Abbrv__c | DK1: _APTS_Level_2_Abbrv__c | DL1: _APTS_Level_3_Abbrv__c | DM1: _APTS_Product_Code_with_SKU__c | DN1: _APTS_SKU_Code__c | DO1: Product_Category_SFDC__c | DP1: APTS_Is_MSP_Quotable__c | DQ1: Charge_Type__c | DR1: Is_Manual__c | DS1: Overage_Rate__c | DT1: _Product_Alias__c | DU1: Product_Group__c | DV1: Unit__c | DW1: Charge_Model__c | DX1: ProductGroup__c | DY1: RCA_Lifecycle_Status__c | DZ1: __Status | EA1: __Id | EB1: __Action | EC1: __Errors
A2: [Product2] | B2: Grid Robot Name | C2: Grid Robot Name | E2: TRUE | F2: DigiCert | G2: USD | H2: 012dp000005zfL7AAI | J2: 01t4z000008h0NLAAY | K2: 01t4z000008h0NLAAY | L2: 01t4z000008h0NLAAY | R2: 11BWC000002WLZ42AO | U2: TRUE | W2: TRUE | X2: Commercial | Y2: FALSE | BF2: FALSE | CC2: FALSE | CF2: FALSE | CK2: FALSE | CL2: FALSE | CM2: FALSE | CO2: 01tWC00000AYBXxYAP | CQ2: FALSE | CU2: FALSE | CW2: FALSE | CX2: FALSE | CZ2: FALSE | DA2: FALSE | DH2: FALSE | DM2: Grid Robot Name | DP2: FALSE | DR2: FALSE | DT2: Grid Robot Name | DX2: All SSL Product Grp | DY2: Active | DZ2: Failed | EA2: 01t4z000008h0NLAAY | EC2: INVALID_FIELD_FOR_INSERT_UPDATE: Unable to create/update fields: APTS_Product_Id_18__c, Type. Please check the security settings of this field and verify that it is read/write for your profile or permission set. [APTS_Product_Id_18__c, Type]
A3: [Product2] | B3: Verified Mark Certificate FQDN Price | C3: 99 | E3: TRUE | F3: DigiCert | G3: USD | H3: 012dp000005zfL7AAI | J3: 01t4z000008iBW3AAM | K3: 01t4z000008iBW3AAM | L3: 01t4z000008iBW3AAM | R3: 11BWC000002cka92AA | U3: TRUE | W3: TRUE | X3: Commercial | Y3: FALSE | BF3: FALSE | CC3: FALSE | CF3: FALSE | CK3: FALSE | CL3: FALSE | CM3: FALSE | CO3: 01tWC00000AYBXyYAP | CQ3: FALSE | CU3: FALSE | CW3: FALSE | CX3: FALSE | CZ3: FALSE | DA3: FALSE | DH3: FALSE | DM3: 99 | DP3: FALSE | DR3: FALSE | DT3: Verified Mark Certificate FQDN Price | DX3: All SSL Product Grp | DY3: Active | DZ3: Failed | EA3: 01t4z000008iBW3AAM | EC3: INVALID_FIELD_FOR_INSERT_UPDATE: Unable to create/update fields: APTS_Product_Id_18__c, Type. Please check the security settings of this field and verify that it is read/write for your profile or permission set. [APTS_Product_Id_18__c, Type]
A4: [Product2] | B4: Verified Mark Certificate | C4: 99-san | E4: TRUE | F4: DigiCert | G4: USD | H4: 012dp000005zfL7AAI | J4: 01t4z000008iBW4AAM | K4: 01t4z000008iBW4AAM | L4: 01t4z000008iBW4AAM | U4: TRUE | W4: TRUE | X4: Commercial | Y4: FALSE | BF4: FALSE | CC4: FALSE | CF4: FALSE | CK4: FALSE | CL4: FALSE | CM4: FALSE | CO4: 01tWC00000AYBXzYAP | CQ4: FALSE | CU4: FALSE | CW4: FALSE | CX4: FALSE | CZ4: FALSE | DA4: FALSE | DH4: FALSE | DM4: 99-san | DP4: FALSE | DR4: FALSE | DT4: Verified Mark Certificate | DY4: Active | DZ4: Failed | EA4: 01t4z000008iBW4AAM | EC4: INVALID_FIELD_FOR_INSERT_UPDATE: Unable to create/update fields: APTS_Product_Id_18__c, Type. Please check the security settings of this field and verify that it is read/write for your profile or permission set. [APTS_Product_Id_18__c, Type]
A5: [Product2] | B5: Code Signing (Units) | C5: Code Signing (Units) | E5: TRUE | F5: DigiCert | G5: USD | H5: 012dp000005zfL7AAI | J5: 01t4z000008jjfJAAQ | K5: 01t4z000008jjfJAAQ | L5: 01t4z000008jjfJAAQ | U5: TRUE | V5: Allowed | W5: TRUE | X5: Commercial | Y5: FALSE | BF5: FALSE | CC5: FALSE | CF5: FALSE | CK5: FALSE | CL5: FALSE | CM5: FALSE | CO5: 01tWC00000AYBY1YAP | CQ5: FALSE | CU5: FALSE | CW5: FALSE | CX5: FALSE | CZ5: FALSE | DA5: FALSE | DH5: FALSE | DM5: Code Signing (Units) | DP5: FALSE | DR5: FALSE | DT5: Code Signing (Units) | DY5: Active | DZ5: Failed | EA5: 01t4z000008jjfJAAQ | EC5: INVALID_FIELD_FOR_INSERT_UPDATE: Unable to create/update fields: APTS_Product_Id_18__c, Type. Please check the security settings of this field and verify that it is read/write for your profile or permission set. [APTS_Product_Id_18__c, Type]
A6: [Product2] | B6: Authentication Only | C6: Authentication Only | E6: TRUE | F6: DigiCert | G6: USD | H6: 012dp000005zfL7AAI | J6: 01t0z000007f40zAAA | K6: 01t0z000007f40zAAA | L6: 01t0z000007f40zAAA | R6: 11BWC000002WLhn2AG | U6: TRUE | V6: Allowed | W6: TRUE | X6: Commercial | Y6: FALSE | BF6: FALSE | CC6: FALSE | CF6: FALSE | CK6: FALSE | CL6: FALSE | CM6: FALSE | CO6: 01tWC00000AYBY2YAP | CQ6: FALSE | CU6: FALSE | CW6: FALSE | CX6: FALSE | CZ6: FALSE | DA6: FALSE | DH6: FALSE | DM6: Authentication Only | DP6: FALSE | DR6: FALSE | DT6: Authentication Only | DY6: Active | DZ6: Failed | EA6: 01t0z000007f40zAAA | EC6: INVALID_FIELD_FOR_INSERT_UPDATE: Unable to create/update fields: APTS_Product_Id_18__c, Type. Please check the security settings of this field and verify that it is read/write for your profile or permission set. [APTS_Product_Id_18__c, Type]
A7: [Product2] | B7: Authentication Only - Non-Repudiation | C7: Authentication Only - Non-Repudiation | E7: TRUE | F7: DigiCert | G7: USD | H7: 012dp000005zfL7AAI | J7: 01t0z000007f410AAA | K7: 01t0z000007f410AAA | L7: 01t0z000007f410AAA | R7: 11BWC000002WLhp2AG | U7: TRUE | V7: Allowed | W7: TRUE | X7: Commercial | Y7: FALSE | BF7: FALSE | CC7: FALSE | CF7: FALSE | CK7: FALSE | CL7: FALSE | CM7: FALSE | CO7: 01tWC00000AYBY3YAP | CQ7: FALSE | CU7: FALSE | CW7: FALSE | CX7: FALSE | CZ7: FALSE | DA7: FALSE | DH7: FALSE | DM7: Authentication Only - Non-Repudiation | DP7: FALSE | DR7: FALSE | DT7: Authentication Only - Non-Repudiation | DY7: Active | DZ7: Failed | EA7: 01t0z000007f410AAA | EC7: INVALID_FIELD_FOR_INSERT_UPDATE: Unable to create/update fields: APTS_Product_Id_18__c, Type. Please check the security settings of this field and verify that it is read/write for your profile or permission set. [APTS_Product_Id_18__c, Type]
A8: [Product2] | B8: Authentication Plus | C8: Authentication Plus | E8: TRUE | F8: DigiCert | G8: USD | H8: 012dp000005zfL7AAI | J8: 01t0z000007f411AAA | K8: 01t0z000007f411AAA | L8: 01t0z000007f411AAA | R8: 11BWC000002WLhl2AG | U8: TRUE | V8: Allowed | W8: TRUE | X8: Commercial | Y8: FALSE | BF8: FALSE | CC8: FALSE | CF8: FALSE | CK8: FALSE | CL8: FALSE | CM8: FALSE | CO8: 01tWC00000AYBY4YAP | CQ8: FALSE | CU8: FALSE | CW8: FALSE | CX8: FALSE | CZ8: FALSE | DA8: FALSE | DH8: FALSE | DM8: Authentication Plus | DP8: FALSE | DR8: FALSE | DT8: Authentication Plus | DY8: Active | DZ8: Failed | EA8: 01t0z000007f411AAA | EC8: INVALID_FIELD_FOR_INSERT_UPDATE: Unable to create/update fields: APTS_Product_Id_18__c, Type. Please check the security settings of this field and verify that it is read/write for your profile or permission set. [APTS_Product_Id_18__c, Type]
A9: [Product2] | B9: Authentication Plus (AD Integration) | C9: Authentication Plus (AD Integration) | E9: TRUE | F9: DigiCert | G9: USD | H9: 012dp000005zfL7AAI | J9: 01t0z000007f412AAA | K9: 01t0z000007f412AAA | L9: 01t0z000007f412AAA | R9: 11BWC000002WLYo2AO | U9: TRUE | V9: Allowed | W9: TRUE | X9: Commercial | Y9: FALSE | BF9: FALSE | CC9: FALSE | CF9: FALSE | CK9: FALSE | CL9: FALSE | CM9: FALSE | CO9: 01tWC00000AYBY5YAP | CQ9: FALSE | CU9: FALSE | CW9: FALSE | CX9: FALSE | CZ9: FALSE | DA9: FALSE | DH9: FALSE | DM9: Authentication Plus (AD Integration) | DP9: FALSE | DR9: FALSE | DT9: Authentication Plus (AD Integration) | DY9: Active | DZ9: Failed | EA9: 01t0z000007f412AAA | EC9: INVALID_FIELD_FOR_INSERT_UPDATE: Unable to create/update fields: APTS_Product_Id_18__c, Type. Please check the security settings of this field and verify that it is read/write for your profile or permission set. [APTS_Product_Id_18__c, Type]
A10: [Product2] | B10: Basic EV | C10: Basic EV | E10: TRUE | F10: DigiCert | G10: USD | H10: 012dp000005zfL7AAI | J10: 01t0z000007f413AAA | K10: 01t0z000007f413AAA | L10: 01t0z000007f413AAA | U10: TRUE | V10: Allowed | W10: TRUE | X10: Commercial | Y10: FALSE | BF10: FALSE | CC10: FALSE | CF10: FALSE | CK10: FALSE | CL10: FALSE | CM10: FALSE | CO10: 01tWC00000AYBY6YAP | CQ10: FALSE | CU10: FALSE | CW10: FALSE | CX10: FALSE | CZ10: FALSE | DA10: FALSE | DH10: FALSE | DM10: Basic EV | DP10: FALSE | DR10: FALSE | DT10: Basic EV | DX10: All SSL Product Grp | DY10: Active | DZ10: Failed | EA10: 01t0z000007f413AAA | EC10: INVALID_FIELD_FOR_INSERT_UPDATE: Unable to create/update fields: APTS_Product_Id_18__c, Type. Please check the security settings of this field and verify that it is read/write for your profile or permission set. [APTS_Product_Id_18__c, Type]
A11: [Product2] | B11: Basic EV FQDN SAN | C11: Basic EV FQDN SAN | E11: TRUE | F11: DigiCert | G11: USD | H11: 012dp000005zfL7AAI | J11: 01t0z000007f414AAA | K11: 01t0z000007f414AAA | L11: 01t0z000007f414AAA | R11: 11BWC000002cka92AA | U11: TRUE | W11: TRUE | X11: Commercial | Y11: FALSE | BF11: FALSE | CC11: FALSE | CF11: FALSE | CK11: FALSE | CL11: FALSE | CM11: FALSE | CO11: 01tWC00000AYBY7YAP | CQ11: FALSE | CU11: FALSE | CW11: FALSE | CX11: FALSE | CZ11: FALSE | DA11: FALSE | DH11: FALSE | DM11: Basic EV FQDN SAN | DP11: FALSE | DR11: FALSE | DT11: Basic EV FQDN SAN | DX11: All SSL Product Grp | DY11: Active | DZ11: Failed | EA11: 01t0z000007f414AAA | EC11: INVALID_FIELD_FOR_INSERT_UPDATE: Unable to create/update fields: APTS_Product_Id_18__c, Type. Please check the security settings of this field and verify that it is read/write for your profile or permission set. [APTS_Product_Id_18__c, Type]
A12: [Product2] | B12: Basic OV | C12: Basic OV | E12: TRUE | F12: DigiCert | G12: USD | H12: 012dp000005zfL7AAI | J12: 01t0z000007f415AAA | K12: 01t0z000007f415AAA | L12: 01t0z000007f415AAA | U12: TRUE | V12: Allowed | W12: TRUE | X12: Commercial | Y12: FALSE | BF12: FALSE | CC12: FALSE | CF12: FALSE | CK12: FALSE | CL12: FALSE | CM12: FALSE | CO12: 01tWC00000AYBY8YAP | CQ12: FALSE | CU12: FALSE | CW12: FALSE | CX12: FALSE | CZ12: FALSE | DA12: FALSE | DH12: FALSE | DM12: Basic OV | DP12: FALSE | DR12: FALSE | DT12: Basic OV | DX12: All SSL Product Grp | DY12: Active | DZ12: Failed | EA12: 01t0z000007f415AAA | EC12: INVALID_FIELD_FOR_INSERT_UPDATE: Unable to create/update fields: APTS_Product_Id_18__c, Type. Please check the security settings of this field and verify that it is read/write for your profile or permission set. [APTS_Product_Id_18__c, Type]
A13: [Product2] | B13: Basic OV FQDN SAN | C13: Basic OV FQDN SAN | E13: TRUE | F13: DigiCert | G13: USD | H13: 012dp000005zfL7AAI | J13: 01t0z000007f416AAA | K13: 01t0z000007f416AAA | L13: 01t0z000007f416AAA | R13: 11BWC000002cka92AA | U13: TRUE | W13: TRUE | X13: Commercial | Y13: FALSE | BF13: FALSE | CC13: FALSE | CF13: FALSE | CK13: FALSE | CL13: FALSE | CM13: FALSE | CO13: 01tWC00000AYBY9YAP | CQ13: FALSE | CU13: FALSE | CW13: FALSE | CX13: FALSE | CZ13: FALSE | DA13: FALSE | DH13: FALSE | DM13: Basic OV FQDN SAN | DP13: FALSE | DR13: FALSE | DT13: Basic OV FQDN SAN | DX13: All SSL Product Grp | DY13: Active | DZ13: Failed | EA13: 01t0z000007f416AAA | EC13: INVALID_FIELD_FOR_INSERT_UPDATE: Unable to create/update fields: APTS_Product_Id_18__c, Type. Please check the security settings of this field and verify that it is read/write for your profile or permission set. [APTS_Product_Id_18__c, Type]
A14: [Product2] | B14: Basic OV Wildcard SAN | C14: Basic OV Wildcard SAN | E14: TRUE | F14: DigiCert | G14: USD | H14: 012dp000005zfL7AAI | J14: 01t0z000007f417AAA | K14: 01t0z000007f417AAA | L14: 01t0z000007f417AAA | R14: 11BWC000002cka92AA | U14: TRUE | W14: TRUE | X14: Commercial | Y14: FALSE | BF14: FALSE | CC14: FALSE | CF14: FALSE | CK14: FALSE | CL14: FALSE | CM14: FALSE | CO14: 01tWC00000AYBYAYA5 | CQ14: FALSE | CU14: FALSE | CW14: FALSE | CX14: FALSE | CZ14: FALSE | DA14: FALSE | DH14: FALSE | DM14: Basic OV Wildcard SAN | DP14: FALSE | DR14: FALSE | DT14: Basic OV Wildcard SAN | DX14: All SSL Product Grp | DY14: Active | DZ14: Failed | EA14: 01t0z000007f417AAA | EC14: INVALID_FIELD_FOR_INSERT_UPDATE: Unable to create/update fields: APTS_Product_Id_18__c, Type. Please check the security settings of this field and verify that it is read/write for your profile or permission set. [APTS_Product_Id_18__c, Type]
A15: [Product2] | B15: Class 1 S/MIME | C15: Class 1 S/MIME | E15: TRUE | F15: DigiCert | G15: USD | H15: 012dp000005zfL7AAI | J15: 01t0z000007f418AAA | K15: 01t0z000007f418AAA | L15: 01t0z000007f418AAA | R15: 11BWC000002WLhq2AG | U15: TRUE | V15: Allowed | W15: TRUE | X15: Commercial | Y15: FALSE | BF15: FALSE | CC15: FALSE | CF15: FALSE | CK15: FALSE | CL15: FALSE | CM15: FALSE | CO15: 01tWC00000AYBYBYA5 | CQ15: FALSE | CU15: FALSE | CW15: FALSE | CX15: FALSE | CZ15: FALSE | DA15: FALSE | DH15: FALSE | DM15: Class 1 S/MIME | DP15: FALSE | DR15: FALSE | DT15: Class 1 S/MIME | DY15: Active | DZ15: Failed | EA15: 01t0z000007f418AAA | EC15: INVALID_FIELD_FOR_INSERT_UPDATE: Unable to create/update fields: APTS_Product_Id_18__c, Type. Please check the security settings of this field and verify that it is read/write for your profile or permission set. [APTS_Product_Id_18__c, Type]
A16: [Product2] | B16: Code Signing | C16: Code Signing | E16: TRUE | F16: DigiCert | G16: USD | H16: 012dp000005zfL7AAI | J16: 01t0z000007f419AAA | K16: 01t0z000007f419AAA | L16: 01t0z000007f419AAA | R16: 11BWC000002WLhh2AG | U16: TRUE | V16: Allowed | W16: TRUE | X16: Commercial | Y16: FALSE | BF16: FALSE | CC16: FALSE | CF16: FALSE | CK16: FALSE | CL16: FALSE | CM16: FALSE | CO16: 01tWC00000AYBYCYA5 | CQ16: FALSE | CU16: FALSE | CW16: FALSE | CX16: FALSE | CZ16: FALSE | DA16: FALSE | DH16: FALSE | DM16: Code Signing | DP16: FALSE | DR16: FALSE | DT16: Code Signing | DY16: Active | DZ16: Failed | EA16: 01t0z000007f419AAA | EC16: INVALID_FIELD_FOR_INSERT_UPDATE: Unable to create/update fields: APTS_Product_Id_18__c, Type. Please check the security settings of this field and verify that it is read/write for your profile or permission set. [APTS_Product_Id_18__c, Type]
A17: [Product2] | B17: Digital Signature Plus | C17: Digital Signature Plus | E17: TRUE | F17: DigiCert | G17: USD | H17: 012dp000005zfL7AAI | J17: 01t0z000007f41AAAQ | K17: 01t0z000007f41AAAQ | L17: 01t0z000007f41AAAQ | R17: 11BWC000002WLhj2AG | U17: TRUE | V17: Allowed | W17: TRUE | X17: Commercial | Y17: FALSE | BF17: FALSE | CC17: FALSE | CF17: FALSE | CK17: FALSE | CL17: FALSE | CM17: FALSE | CO17: 01tWC00000AYBYDYA5 | CQ17: FALSE | CU17: FALSE | CW17: FALSE | CX17: FALSE | CZ17: FALSE | DA17: FALSE | DH17: FALSE | DM17: Digital Signature Plus | DP17: FALSE | DR17: FALSE | DT17: Digital Signature Plus | DY17: Active | DZ17: Failed | EA17: 01t0z000007f41AAAQ | EC17: INVALID_FIELD_FOR_INSERT_UPDATE: Unable to create/update fields: APTS_Product_Id_18__c, Type. Please check the security settings of this field and verify that it is read/write for your profile or permission set. [APTS_Product_Id_18__c, Type]
A18: [Product2] | B18: Email Security Plus | C18: Email Security Plus | E18: TRUE | F18: DigiCert | G18: USD | H18: 012dp000005zfL7AAI | J18: 01t0z000007f41DAAQ | K18: 01t0z000007f41DAAQ | L18: 01t0z000007f41DAAQ | R18: 11BWC000002WLhk2AG | U18: TRUE | V18: Allowed | W18: TRUE | X18: Commercial | Y18: FALSE | BF18: FALSE | CC18: FALSE | CF18: FALSE | CK18: FALSE | CL18: FALSE | CM18: FALSE | CO18: 01tWC00000AYBYEYA5 | CQ18: FALSE | CU18: FALSE | CW18: FALSE | CX18: FALSE | CZ18: FALSE | DA18: FALSE | DH18: FALSE | DM18: Email Security Plus | DP18: FALSE | DR18: FALSE | DT18: Email Security Plus | DY18: Active | DZ18: Failed | EA18: 01t0z000007f41DAAQ | EC18: INVALID_FIELD_FOR_INSERT_UPDATE: Unable to create/update fields: APTS_Product_Id_18__c, Type. Please check the security settings of this field and verify that it is read/write for your profile or permission set. [APTS_Product_Id_18__c, Type]
A19: [Product2] | B19: Email Security Plus (AD Integration) | C19: Email Security Plus (AD Integration) | E19: TRUE | F19: DigiCert | G19: USD | H19: 012dp000005zfL7AAI | J19: 01t0z000007f41EAAQ | K19: 01t0z000007f41EAAQ | L19: 01t0z000007f41EAAQ | R19: 11BWC000002WLYm2AO | U19: TRUE | V19: Allowed | W19: TRUE | X19: Commercial | Y19: FALSE | BF19: FALSE | CC19: FALSE | CF19: FALSE | CK19: FALSE | CL19: FALSE | CM19: FALSE | CO19: 01tWC00000AYBYFYA5 | CQ19: FALSE | CU19: FALSE | CW19: FALSE | CX19: FALSE | CZ19: FALSE | DA19: FALSE | DH19: FALSE | DM19: Email Security Plus (AD Integration) | DP19: FALSE | DR19: FALSE | DT19: Email Security Plus (AD Integration) | DY19: Active | DZ19: Failed | EA19: 01t0z000007f41EAAQ | EC19: INVALID_FIELD_FOR_INSERT_UPDATE: Unable to create/update fields: APTS_Product_Id_18__c, Type. Please check the security settings of this field and verify that it is read/write for your profile or permission set. [APTS_Product_Id_18__c, Type]
A20: [Product2] | B20: Email Security Plus [SHA-2 Only] | C20: Email Security Plus [SHA-2 Only] | E20: TRUE | F20: DigiCert | G20: USD | H20: 012dp000005zfL7AAI | J20: 01t0z000007f41FAAQ | K20: 01t0z000007f41FAAQ | L20: 01t0z000007f41FAAQ | R20: 11BWC000002WLYn2AO | U20: TRUE | V20: Allowed | W20: TRUE | X20: Commercial | Y20: FALSE | BF20: FALSE | CC20: FALSE | CF20: FALSE | CK20: FALSE | CL20: FALSE | CM20: FALSE | CO20: 01tWC00000AYBYGYA5 | CQ20: FALSE | CU20: FALSE | CW20: FALSE | CX20: FALSE | CZ20: FALSE | DA20: FALSE | DH20: FALSE | DM20: Email Security Plus [SHA-2 Only] | DP20: FALSE | DR20: FALSE | DT20: Email Security Plus [SHA-2 Only] | DX20: All SSL Product Grp | DY20: Active | DZ20: Failed | EA20: 01t0z000007f41FAAQ | EC20: INVALID_FIELD_FOR_INSERT_UPDATE: Unable to create/update fields: APTS_Product_Id_18__c, Type. Please check the security settings of this field and verify that it is read/write for your profile or permission set. [APTS_Product_Id_18__c, Type]
A21: [Product2] | B21: EV Code Signing | C21: EV Code Signing | E21: TRUE | F21: DigiCert | G21: USD | H21: 012dp000005zfL7AAI | J21: 01t0z000007f41GAAQ | K21: 01t0z000007f41GAAQ | L21: 01t0z000007f41GAAQ | R21: 11BWC000002WLhi2AG | U21: TRUE | V21: Allowed | W21: TRUE | X21: Commercial | Y21: FALSE | BF21: FALSE | CC21: FALSE | CF21: FALSE | CK21: FALSE | CL21: FALSE | CM21: FALSE | CO21: 01tWC00000AYBYHYA5 | CQ21: FALSE | CU21: FALSE | CW21: FALSE | CX21: FALSE | CZ21: FALSE | DA21: FALSE | DH21: FALSE | DM21: EV Code Signing | DP21: FALSE | DR21: FALSE | DT21: EV Code Signing | DY21: Active | DZ21: Failed | EA21: 01t0z000007f41GAAQ | EC21: INVALID_FIELD_FOR_INSERT_UPDATE: Unable to create/update fields: APTS_Product_Id_18__c, Type. Please check the security settings of this field and verify that it is read/write for your profile or permission set. [APTS_Product_Id_18__c, Type]
A22: [Product2] | B22: GeoTrust Flex DV | C22: GeoTrust Flex DV | E22: TRUE | F22: Geotrust | G22: USD | H22: 012dp000005zfL7AAI | J22: 01t0z000007f41HAAQ | K22: 01t0z000007f41HAAQ | L22: 01t0z000007f41HAAQ | U22: TRUE | V22: Allowed | W22: TRUE | X22: Commercial | Y22: FALSE | BF22: FALSE | CC22: FALSE | CF22: FALSE | CK22: FALSE | CL22: FALSE | CM22: FALSE | CO22: 01tWC00000AYBYIYA5 | CQ22: FALSE | CU22: FALSE | CW22: FALSE | CX22: FALSE | CZ22: FALSE | DA22: FALSE | DH22: FALSE | DM22: GeoTrust Flex DV | DP22: FALSE | DR22: FALSE | DT22: GeoTrust Flex DV | DX22: All SSL Product Grp | DY22: Active | DZ22: Failed | EA22: 01t0z000007f41HAAQ | EC22: INVALID_FIELD_FOR_INSERT_UPDATE: Unable to create/update fields: APTS_Product_Id_18__c, Type. Please check the security settings of this field and verify that it is read/write for your profile or permission set. [APTS_Product_Id_18__c, Type]
A23: [Product2] | B23: GeoTrust Flex DV FQDN SAN | C23: GeoTrust Flex DV FQDN SAN | E23: TRUE | F23: Geotrust | G23: USD | H23: 012dp000005zfL7AAI | J23: 01t0z000007f41IAAQ | K23: 01t0z000007f41IAAQ | L23: 01t0z000007f41IAAQ | R23: 11BWC000002cka92AA | U23: TRUE | W23: TRUE | X23: Commercial | Y23: FALSE | BF23: FALSE | CC23: FALSE | CF23: FALSE | CK23: FALSE | CL23: FALSE | CM23: FALSE | CO23: 01tWC00000AYBYJYA5 | CQ23: FALSE | CU23: FALSE | CW23: FALSE | CX23: FALSE | CZ23: FALSE | DA23: FALSE | DH23: FALSE | DM23: GeoTrust Flex DV FQDN SAN | DP23: FALSE | DR23: FALSE | DT23: GeoTrust Flex DV FQDN SAN | DX23: All SSL Product Grp | DY23: Active | DZ23: Failed | EA23: 01t0z000007f41IAAQ | EC23: INVALID_FIELD_FOR_INSERT_UPDATE: Unable to create/update fields: APTS_Product_Id_18__c, Type. Please check the security settings of this field and verify that it is read/write for your profile or permission set. [APTS_Product_Id_18__c, Type]
A24: [Product2] | B24: GeoTrust Flex DV Wildcard SAN | C24: GeoTrust Flex DV Wildcard SAN | E24: TRUE | F24: Geotrust | G24: USD | H24: 012dp000005zfL7AAI | J24: 01t0z000007f41JAAQ | K24: 01t0z000007f41JAAQ | L24: 01t0z000007f41JAAQ | R24: 11BWC000002cka92AA | U24: TRUE | W24: TRUE | X24: Commercial | Y24: FALSE | BF24: FALSE | CC24: FALSE | CF24: FALSE | CK24: FALSE | CL24: FALSE | CM24: FALSE | CO24: 01tWC00000AYBYKYA5 | CQ24: FALSE | CU24: FALSE | CW24: FALSE | CX24: FALSE | CZ24: FALSE | DA24: FALSE | DH24: FALSE | DM24: GeoTrust Flex DV Wildcard SAN | DP24: FALSE | DR24: FALSE | DT24: GeoTrust Flex DV Wildcard SAN | DX24: All SSL Product Grp | DY24: Active | DZ24: Failed | EA24: 01t0z000007f41JAAQ | EC24: INVALID_FIELD_FOR_INSERT_UPDATE: Unable to create/update fields: APTS_Product_Id_18__c, Type. Please check the security settings of this field and verify that it is read/write for your profile or permission set. [APTS_Product_Id_18__c, Type]
A25: [Product2] | B25: GeoTrust TrueBusiness ID EV | C25: GeoTrust TrueBusiness ID EV | E25: TRUE | F25: Geotrust | G25: USD | H25: 012dp000005zfL7AAI | J25: 01t0z000007f41KAAQ | K25: 01t0z000007f41KAAQ | L25: 01t0z000007f41KAAQ | U25: TRUE | V25: Allowed | W25: TRUE | X25: Commercial | Y25: FALSE | BF25: FALSE | CC25: FALSE | CF25: FALSE | CK25: FALSE | CL25: FALSE | CM25: FALSE | CO25: 01tWC00000AYBYLYA5 | CQ25: FALSE | CU25: FALSE | CW25: FALSE | CX25: FALSE | CZ25: FALSE | DA25: FALSE | DH25: FALSE | DM25: GeoTrust TrueBusiness ID EV | DP25: FALSE | DR25: FALSE | DT25: GeoTrust TrueBusiness ID EV | DY25: Active | DZ25: Failed | EA25: 01t0z000007f41KAAQ | EC25: INVALID_FIELD_FOR_INSERT_UPDATE: Unable to create/update fields: APTS_Product_Id_18__c, Type. Please check the security settings of this field and verify that it is read/write for your profile or permission set. [APTS_Product_Id_18__c, Type]
A26: [Product2] | B26: GeoTrust TrueBusiness ID EV FQDN SAN | C26: GeoTrust TrueBusiness ID EV FQDN SAN | E26: TRUE | F26: Geotrust | G26: USD | H26: 012dp000005zfL7AAI | J26: 01t0z000007f41LAAQ | K26: 01t0z000007f41LAAQ | L26: 01t0z000007f41LAAQ | R26: 11BWC000002cka92AA | U26: TRUE | W26: TRUE | X26: Commercial | Y26: FALSE | BF26: FALSE | CC26: FALSE | CF26: FALSE | CK26: FALSE | CL26: FALSE | CM26: FALSE | CO26: 01tWC00000AYBYMYA5 | CQ26: FALSE | CU26: FALSE | CW26: FALSE | CX26: FALSE | CZ26: FALSE | DA26: FALSE | DH26: FALSE | DM26: GeoTrust TrueBusiness ID EV FQDN SAN | DP26: FALSE | DR26: FALSE | DT26: GeoTrust TrueBusiness ID EV FQDN SAN | DX26: All SSL Product Grp | DY26: Active | DZ26: Failed | EA26: 01t0z000007f41LAAQ | EC26: INVALID_FIELD_FOR_INSERT_UPDATE: Unable to create/update fields: APTS_Product_Id_18__c, Type. Please check the security settings of this field and verify that it is read/write for your profile or permission set. [APTS_Product_Id_18__c, Type]
A27: [Product2] | B27: GeoTrust TrueBusiness ID OV | C27: GeoTrust TrueBusiness ID OV | E27: TRUE | F27: Geotrust | G27: USD | H27: 012dp000005zfL7AAI | J27: 01t0z000007f41MAAQ | K27: 01t0z000007f41MAAQ | L27: 01t0z000007f41MAAQ | U27: TRUE | V27: Allowed | W27: TRUE | X27: Commercial | Y27: FALSE | BF27: FALSE | CC27: FALSE | CF27: FALSE | CK27: FALSE | CL27: FALSE | CM27: FALSE | CO27: 01tWC00000AYBYNYA5 | CQ27: FALSE | CU27: FALSE | CW27: FALSE | CX27: FALSE | CZ27: FALSE | DA27: FALSE | DH27: FALSE | DM27: GeoTrust TrueBusiness ID OV | DP27: FALSE | DR27: FALSE | DT27: GeoTrust TrueBusiness ID OV | DY27: Active | DZ27: Failed | EA27: 01t0z000007f41MAAQ | EC27: INVALID_FIELD_FOR_INSERT_UPDATE: Unable to create/update fields: APTS_Product_Id_18__c, Type. Please check the security settings of this field and verify that it is read/write for your profile or permission set. [APTS_Product_Id_18__c, Type]
A28: [Product2] | B28: GeoTrust TrueBusiness ID OV FQDN SAN | C28: GeoTrust TrueBusiness ID OV FQDN SAN | E28: TRUE | F28: Geotrust | G28: USD | H28: 012dp000005zfL7AAI | J28: 01t0z000007f41NAAQ | K28: 01t0z000007f41NAAQ | L28: 01t0z000007f41NAAQ | R28: 11BWC000002cka92AA | U28: TRUE | W28: TRUE | X28: Commercial | Y28: FALSE | BF28: FALSE | CC28: FALSE | CF28: FALSE | CK28: FALSE | CL28: FALSE | CM28: FALSE | CO28: 01tWC00000AYBYOYA5 | CQ28: FALSE | CU28: FALSE | CW28: FALSE | CX28: FALSE | CZ28: FALSE | DA28: FALSE | DH28: FALSE | DM28: GeoTrust TrueBusiness ID OV FQDN SAN | DP28: FALSE | DR28: FALSE | DT28: GeoTrust TrueBusiness ID OV FQDN SAN | DX28: All SSL Product Grp | DY28: Active | DZ28: Failed | EA28: 01t0z000007f41NAAQ | EC28: INVALID_FIELD_FOR_INSERT_UPDATE: Unable to create/update fields: APTS_Product_Id_18__c, Type. Please check the security settings of this field and verify that it is read/write for your profile or permission set. [APTS_Product_Id_18__c, Type]
A29: [Product2] | B29: GeoTrust TrueBusiness ID OV Wildcard SAN | C29: GeoTrust TrueBusiness ID OV Wildcard SAN | E29: TRUE | F29: Geotrust | G29: USD | H29: 012dp000005zfL7AAI | J29: 01t0z000007f41OAAQ | K29: 01t0z000007f41OAAQ | L29: 01t0z000007f41OAAQ | R29: 11BWC000002cka92AA | U29: TRUE | W29: TRUE | X29: Commercial | Y29: FALSE | BF29: FALSE | CC29: FALSE | CF29: FALSE | CK29: FALSE | CL29: FALSE | CM29: FALSE | CO29: 01tWC00000AYBYPYA5 | CQ29: FALSE | CU29: FALSE | CW29: FALSE | CX29: FALSE | CZ29: FALSE | DA29: FALSE | DH29: FALSE | DM29: GeoTrust TrueBusiness ID OV Wildcard SAN | DP29: FALSE | DR29: FALSE | DT29: GeoTrust TrueBusiness ID OV Wildcard SAN | DX29: All SSL Product Grp | DY29: Active | DZ29: Failed | EA29: 01t0z000007f41OAAQ | EC29: INVALID_FIELD_FOR_INSERT_UPDATE: Unable to create/update fields: APTS_Product_Id_18__c, Type. Please check the security settings of this field and verify that it is read/write for your profile or permission set. [APTS_Product_Id_18__c, Type]
A30: [Product2] | B30: LTANS Adobe Signing | C30: LTANS Adobe Signing | E30: TRUE | F30: DigiCert | G30: USD | H30: 012dp000005zfL7AAI | J30: 01t0z000007f41PAAQ | K30: 01t0z000007f41PAAQ | L30: 01t0z000007f41PAAQ | R30: 11BWC000002WLYs2AO | U30: TRUE | V30: Allowed | W30: TRUE | X30: Commercial | Y30: FALSE | BF30: FALSE | CC30: FALSE | CF30: FALSE | CK30: FALSE | CL30: FALSE | CM30: FALSE | CO30: 01tWC00000AYBYQYA5 | CQ30: FALSE | CU30: FALSE | CW30: FALSE | CX30: FALSE | CZ30: FALSE | DA30: FALSE | DH30: FALSE | DM30: LTANS Adobe Signing | DP30: FALSE | DR30: FALSE | DT30: LTANS Adobe Signing | DY30: Active | DZ30: Failed | EA30: 01t0z000007f41PAAQ | EC30: INVALID_FIELD_FOR_INSERT_UPDATE: Unable to create/update fields: APTS_Product_Id_18__c, Type. Please check the security settings of this field and verify that it is read/write for your profile or permission set. [APTS_Product_Id_18__c, Type]
A31: [Product2] | B31: Multi-Name Client Auth | C31: Multi-Name Client Auth | E31: TRUE | F31: DigiCert | G31: USD | H31: 012dp000005zfL7AAI | J31: 01t0z000007f41QAAQ | K31: 01t0z000007f41QAAQ | L31: 01t0z000007f41QAAQ | R31: 11BWC000002WLho2AG | U31: TRUE | V31: Allowed | W31: TRUE | X31: Commercial | Y31: FALSE | BF31: FALSE | CC31: FALSE | CF31: FALSE | CK31: FALSE | CL31: FALSE | CM31: FALSE | CO31: 01tWC00000AYBYRYA5 | CQ31: FALSE | CU31: FALSE | CW31: FALSE | CX31: FALSE | CZ31: FALSE | DA31: FALSE | DH31: FALSE | DM31: Multi-Name Client Auth | DP31: FALSE | DR31: FALSE | DT31: Multi-Name Client Auth | DY31: Active | DZ31: Failed | EA31: 01t0z000007f41QAAQ | EC31: INVALID_FIELD_FOR_INSERT_UPDATE: Unable to create/update fields: APTS_Product_Id_18__c, Type. Please check the security settings of this field and verify that it is read/write for your profile or permission set. [APTS_Product_Id_18__c, Type]
A32: [Product2] | B32: Premium (Class 2 S/MIME) | C32: Premium (Class 2 S/MIME) | E32: TRUE | F32: DigiCert | G32: USD | H32: 012dp000005zfL7AAI | J32: 01t0z000007f41SAAQ | K32: 01t0z000007f41SAAQ | L32: 01t0z000007f41SAAQ | R32: 11BWC000002WLhm2AG | U32: TRUE | V32: Allowed | W32: TRUE | X32: Commercial | Y32: FALSE | BF32: FALSE | CC32: FALSE | CF32: FALSE | CK32: FALSE | CL32: FALSE | CM32: FALSE | CO32: 01tWC00000AYBYTYA5 | CQ32: FALSE | CU32: FALSE | CW32: FALSE | CX32: FALSE | CZ32: FALSE | DA32: FALSE | DH32: FALSE | DM32: Premium (Class 2 S/MIME) | DP32: FALSE | DR32: FALSE | DT32: Premium (Class 2 S/MIME) | DY32: Active | DZ32: Failed | EA32: 01t0z000007f41SAAQ | EC32: INVALID_FIELD_FOR_INSERT_UPDATE: Unable to create/update fields: APTS_Product_Id_18__c, Type. Please check the security settings of this field and verify that it is read/write for your profile or permission set. [APTS_Product_Id_18__c, Type]
A33: [Product2] | B33: Premium - Data Encipherment | C33: Premium - Data Encipherment | E33: TRUE | F33: DigiCert | G33: USD | H33: 012dp000005zfL7AAI | J33: 01t0z000007f41TAAQ | K33: 01t0z000007f41TAAQ | L33: 01t0z000007f41TAAQ | R33: 11BWC000002WLYx2AO | U33: TRUE | V33: Allowed | W33: TRUE | X33: Commercial | Y33: FALSE | BF33: FALSE | CC33: FALSE | CF33: FALSE | CK33: FALSE | CL33: FALSE | CM33: FALSE | CO33: 01tWC00000AYBYUYA5 | CQ33: FALSE | CU33: FALSE | CW33: FALSE | CX33: FALSE | CZ33: FALSE | DA33: FALSE | DH33: FALSE | DM33: Premium - Data Encipherment | DP33: FALSE | DR33: FALSE | DT33: Premium - Data Encipherment | DY33: Active | DZ33: Failed | EA33: 01t0z000007f41TAAQ | EC33: INVALID_FIELD_FOR_INSERT_UPDATE: Unable to create/update fields: APTS_Product_Id_18__c, Type. Please check the security settings of this field and verify that it is read/write for your profile or permission set. [APTS_Product_Id_18__c, Type]
A34: [Product2] | B34: Premium - Non-Repudiation | C34: Premium - Non-Repudiation | E34: TRUE | F34: DigiCert | G34: USD | H34: 012dp000005zfL7AAI | J34: 01t0z000007f41UAAQ | K34: 01t0z000007f41UAAQ | L34: 01t0z000007f41UAAQ | R34: 11BWC000002WLYw2AO | U34: TRUE | V34: Allowed | W34: TRUE | X34: Commercial | Y34: FALSE | BF34: FALSE | CC34: FALSE | CF34: FALSE | CK34: FALSE | CL34: FALSE | CM34: FALSE | CO34: 01tWC00000AYBYVYA5 | CQ34: FALSE | CU34: FALSE | CW34: FALSE | CX34: FALSE | CZ34: FALSE | DA34: FALSE | DH34: FALSE | DM34: Premium - Non-Repudiation | DP34: FALSE | DR34: FALSE | DT34: Premium - Non-Repudiation | DY34: Active | DZ34: Failed | EA34: 01t0z000007f41UAAQ | EC34: INVALID_FIELD_FOR_INSERT_UPDATE: Unable to create/update fields: APTS_Product_Id_18__c, Type. Please check the security settings of this field and verify that it is read/write for your profile or permission set. [APTS_Product_Id_18__c, Type]
A35: [Product2] | B35: Premium (AD Integration) | C35: Premium (AD Integration) | E35: TRUE | F35: DigiCert | G35: USD | H35: 012dp000005zfL7AAI | J35: 01t0z000007f41VAAQ | K35: 01t0z000007f41VAAQ | L35: 01t0z000007f41VAAQ | R35: 11BWC000002WLYq2AO | U35: TRUE | V35: Allowed | W35: TRUE | X35: Commercial | Y35: FALSE | BF35: FALSE | CC35: FALSE | CF35: FALSE | CK35: FALSE | CL35: FALSE | CM35: FALSE | CO35: 01tWC00000AYBYWYA5 | CQ35: FALSE | CU35: FALSE | CW35: FALSE | CX35: FALSE | CZ35: FALSE | DA35: FALSE | DH35: FALSE | DM35: Premium (AD Integration) | DP35: FALSE | DR35: FALSE | DT35: Premium (AD Integration) | DY35: Active | DZ35: Failed | EA35: 01t0z000007f41VAAQ | EC35: INVALID_FIELD_FOR_INSERT_UPDATE: Unable to create/update fields: APTS_Product_Id_18__c, Type. Please check the security settings of this field and verify that it is read/write for your profile or permission set. [APTS_Product_Id_18__c, Type]
A36: [Product2] | B36: Premium [SHA-2 Only] | C36: Premium [SHA-2 Only] | E36: TRUE | F36: DigiCert | G36: USD | H36: 012dp000005zfL7AAI | J36: 01t0z000007f41WAAQ | K36: 01t0z000007f41WAAQ | L36: 01t0z000007f41WAAQ | R36: 11BWC000002WLYr2AO | U36: TRUE | V36: Allowed | W36: TRUE | X36: Commercial | Y36: FALSE | BF36: FALSE | CC36: FALSE | CF36: FALSE | CK36: FALSE | CL36: FALSE | CM36: FALSE | CO36: 01tWC00000AYBYXYA5 | CQ36: FALSE | CU36: FALSE | CW36: FALSE | CX36: FALSE | CZ36: FALSE | DA36: FALSE | DH36: FALSE | DM36: Premium [SHA-2 Only] | DP36: FALSE | DR36: FALSE | DT36: Premium [SHA-2 Only] | DX36: All SSL Product Grp | DY36: Active | DZ36: Failed | EA36: 01t0z000007f41WAAQ | EC36: INVALID_FIELD_FOR_INSERT_UPDATE: Unable to create/update fields: APTS_Product_Id_18__c, Type. Please check the security settings of this field and verify that it is read/write for your profile or permission set. [APTS_Product_Id_18__c, Type]
A37: [Product2] | B37: Private Premium | C37: 1022 | E37: TRUE | F37: DigiCert | G37: USD | H37: 012dp000005zfL7AAI | J37: 01t0z000007f41XAAQ | K37: 01t0z000007f41XAAQ | L37: 01t0z000007f41XAAQ | R37: 11BWC000002WLYu2AO | U37: TRUE | V37: Allowed | W37: TRUE | X37: Commercial | Y37: FALSE | BF37: FALSE | CC37: FALSE | CF37: FALSE | CK37: FALSE | CL37: FALSE | CM37: FALSE | CO37: 01tWC00000AYBYYYA5 | CQ37: FALSE | CU37: FALSE | CW37: FALSE | CX37: FALSE | CZ37: FALSE | DA37: FALSE | DH37: FALSE | DM37: 1022 | DP37: FALSE | DR37: FALSE | DT37: Private Premium | DY37: Active | DZ37: Failed | EA37: 01t0z000007f41XAAQ | EC37: INVALID_FIELD_FOR_INSERT_UPDATE: Unable to create/update fields: APTS_Product_Id_18__c, Type. Please check the security settings of this field and verify that it is read/write for your profile or permission set. [APTS_Product_Id_18__c, Type]
A38: [Product2] | B38: Private SSL Base | C38: Private SSL Base | E38: TRUE | F38: DigiCert | G38: USD | H38: 012dp000005zfL7AAI | J38: 01t0z000007f41YAAQ | K38: 01t0z000007f41YAAQ | L38: 01t0z000007f41YAAQ | R38: 11BWC000002WLYl2AO | U38: TRUE | V38: Allowed | W38: TRUE | X38: Commercial | Y38: FALSE | BF38: FALSE | CC38: FALSE | CF38: FALSE | CK38: FALSE | CL38: FALSE | CM38: FALSE | CO38: 01tWC00000AYBYZYA5 | CQ38: FALSE | CU38: FALSE | CW38: FALSE | CX38: FALSE | CZ38: FALSE | DA38: FALSE | DH38: FALSE | DM38: Private SSL Base | DP38: FALSE | DR38: FALSE | DT38: Private SSL Base | DX38: All SSL Product Grp | DY38: Active | DZ38: Failed | EA38: 01t0z000007f41YAAQ | EC38: INVALID_FIELD_FOR_INSERT_UPDATE: Unable to create/update fields: APTS_Product_Id_18__c, Type. Please check the security settings of this field and verify that it is read/write for your profile or permission set. [APTS_Product_Id_18__c, Type]
A39: [Product2] | B39: Private SSL FQDN SAN | C39: Private SSL FQDN SAN | E39: TRUE | F39: DigiCert | G39: USD | H39: 012dp000005zfL7AAI | J39: 01t0z000007f41ZAAQ | K39: 01t0z000007f41ZAAQ | L39: 01t0z000007f41ZAAQ | R39: 11BWC000002WLhs2AG | U39: TRUE | V39: Allowed | W39: TRUE | X39: Commercial | Y39: FALSE | BF39: FALSE | CC39: FALSE | CF39: FALSE | CK39: FALSE | CL39: FALSE | CM39: FALSE | CO39: 01tWC00000AYBYaYAP | CQ39: FALSE | CU39: FALSE | CW39: FALSE | CX39: FALSE | CZ39: FALSE | DA39: FALSE | DH39: FALSE | DM39: Private SSL FQDN SAN | DP39: FALSE | DR39: FALSE | DT39: Private SSL FQDN SAN | DX39: All SSL Product Grp | DY39: Active | DZ39: Failed | EA39: 01t0z000007f41ZAAQ | EC39: INVALID_FIELD_FOR_INSERT_UPDATE: Unable to create/update fields: APTS_Product_Id_18__c, Type. Please check the security settings of this field and verify that it is read/write for your profile or permission set. [APTS_Product_Id_18__c, Type]
A40: [Product2] | B40: Private SSL Wildcard SAN | C40: Private SSL Wildcard SAN | E40: TRUE | F40: DigiCert | G40: USD | H40: 012dp000005zfL7AAI | J40: 01t0z000007f41aAAA | K40: 01t0z000007f41aAAA | L40: 01t0z000007f41aAAA | R40: 11BWC000002WLhr2AG | U40: TRUE | V40: Allowed | W40: TRUE | X40: Commercial | Y40: FALSE | BF40: FALSE | CC40: FALSE | CF40: FALSE | CK40: FALSE | CL40: FALSE | CM40: FALSE | CO40: 01tWC00000AYBYbYAP | CQ40: FALSE | CU40: FALSE | CW40: FALSE | CX40: FALSE | CZ40: FALSE | DA40: FALSE | DH40: FALSE | DM40: Private SSL Wildcard SAN | DP40: FALSE | DR40: FALSE | DT40: Private SSL Wildcard SAN | DX40: All SSL Product Grp | DY40: Active | DZ40: Failed | EA40: 01t0z000007f41aAAA | EC40: INVALID_FIELD_FOR_INSERT_UPDATE: Unable to create/update fields: APTS_Product_Id_18__c, Type. Please check the security settings of this field and verify that it is read/write for your profile or permission set. [APTS_Product_Id_18__c, Type]
A41: [Product2] | B41: RapidSSL Standard DV | C41: RapidSSL Standard DV | E41: TRUE | F41: RapidSSL | G41: USD | H41: 012dp000005zfL7AAI | J41: 01t0z000007f41bAAA | K41: 01t0z000007f41bAAA | L41: 01t0z000007f41bAAA | U41: TRUE | V41: Allowed | W41: TRUE | X41: Commercial | Y41: FALSE | BF41: FALSE | CC41: FALSE | CF41: FALSE | CK41: FALSE | CL41: FALSE | CM41: FALSE | CO41: 01tWC00000AYBYcYAP | CQ41: FALSE | CU41: FALSE | CW41: FALSE | CX41: FALSE | CZ41: FALSE | DA41: FALSE | DH41: FALSE | DM41: RapidSSL Standard DV | DP41: FALSE | DR41: FALSE | DT41: RapidSSL Standard DV | DX41: All SSL Product Grp | DY41: Active | DZ41: Failed | EA41: 01t0z000007f41bAAA | EC41: INVALID_FIELD_FOR_INSERT_UPDATE: Unable to create/update fields: APTS_Product_Id_18__c, Type. Please check the security settings of this field and verify that it is read/write for your profile or permission set. [APTS_Product_Id_18__c, Type]
A42: [Product2] | B42: RapidSSL Wildcard DV | C42: RapidSSL Wildcard DV | E42: TRUE | F42: RapidSSL | G42: USD | H42: 012dp000005zfL7AAI | J42: 01t0z000007f41cAAA | K42: 01t0z000007f41cAAA | L42: 01t0z000007f41cAAA | U42: TRUE | V42: Allowed | W42: TRUE | X42: Commercial | Y42: FALSE | BF42: FALSE | CC42: FALSE | CF42: FALSE | CK42: FALSE | CL42: FALSE | CM42: FALSE | CO42: 01tWC00000AYBYdYAP | CQ42: FALSE | CU42: FALSE | CW42: FALSE | CX42: FALSE | CZ42: FALSE | DA42: FALSE | DH42: FALSE | DM42: RapidSSL Wildcard DV | DP42: FALSE | DR42: FALSE | DT42: RapidSSL Wildcard DV | DX42: All SSL Product Grp | DY42: Active | DZ42: Failed | EA42: 01t0z000007f41cAAA | EC42: INVALID_FIELD_FOR_INSERT_UPDATE: Unable to create/update fields: APTS_Product_Id_18__c, Type. Please check the security settings of this field and verify that it is read/write for your profile or permission set. [APTS_Product_Id_18__c, Type]
A43: [Product2] | B43: Secure Site EV SSL | C43: Secure Site EV SSL | E43: TRUE | F43: DigiCert | G43: USD | H43: 012dp000005zfL7AAI | J43: 01t0z000007f41dAAA | K43: 01t0z000007f41dAAA | L43: 01t0z000007f41dAAA | U43: TRUE | V43: Allowed | W43: TRUE | X43: Commercial | Y43: FALSE | BF43: FALSE | CC43: FALSE | CF43: FALSE | CK43: FALSE | CL43: FALSE | CM43: FALSE | CO43: 01tWC00000AYBYeYAP | CQ43: FALSE | CU43: FALSE | CW43: FALSE | CX43: FALSE | CZ43: FALSE | DA43: FALSE | DH43: FALSE | DM43: Secure Site EV SSL | DP43: FALSE | DR43: FALSE | DT43: Secure Site EV SSL | DX43: All SSL Product Grp | DY43: Active | DZ43: Failed | EA43: 01t0z000007f41dAAA | EC43: INVALID_FIELD_FOR_INSERT_UPDATE: Unable to create/update fields: APTS_Product_Id_18__c, Type. Please check the security settings of this field and verify that it is read/write for your profile or permission set. [APTS_Product_Id_18__c, Type]
A44: [Product2] | B44: Secure Site EV SSL FQDN SAN | C44: Secure Site EV SSL FQDN SAN | E44: TRUE | F44: DigiCert | G44: USD | H44: 012dp000005zfL7AAI | J44: 01t0z000007f41eAAA | K44: 01t0z000007f41eAAA | L44: 01t0z000007f41eAAA | R44: 11BWC000002cka92AA | U44: TRUE | W44: TRUE | X44: Commercial | Y44: FALSE | BF44: FALSE | CC44: FALSE | CF44: FALSE | CK44: FALSE | CL44: FALSE | CM44: FALSE | CO44: 01tWC00000AYBYfYAP | CQ44: FALSE | CU44: FALSE | CW44: FALSE | CX44: FALSE | CZ44: FALSE | DA44: FALSE | DH44: FALSE | DM44: Secure Site EV SSL FQDN SAN | DP44: FALSE | DR44: FALSE | DT44: Secure Site EV SSL FQDN SAN | DX44: All SSL Product Grp | DY44: Active | DZ44: Failed | EA44: 01t0z000007f41eAAA | EC44: INVALID_FIELD_FOR_INSERT_UPDATE: Unable to create/update fields: APTS_Product_Id_18__c, Type. Please check the security settings of this field and verify that it is read/write for your profile or permission set. [APTS_Product_Id_18__c, Type]
A45: [Product2] | B45: Secure Site Pro EV SSL | C45: Secure Site Pro EV SSL | E45: TRUE | F45: DigiCert | G45: USD | H45: 012dp000005zfL7AAI | J45: 01t0z000007f41fAAA | K45: 01t0z000007f41fAAA | L45: 01t0z000007f41fAAA | U45: TRUE | V45: Allowed | W45: TRUE | X45: Commercial | Y45: FALSE | BF45: FALSE | CC45: FALSE | CF45: FALSE | CK45: FALSE | CL45: FALSE | CM45: FALSE | CO45: 01tWC00000AYBYgYAP | CQ45: FALSE | CU45: FALSE | CW45: FALSE | CX45: FALSE | CZ45: FALSE | DA45: FALSE | DH45: FALSE | DM45: Secure Site Pro EV SSL | DP45: FALSE | DR45: FALSE | DT45: Secure Site Pro EV SSL | DY45: Active | DZ45: Failed | EA45: 01t0z000007f41fAAA | EC45: INVALID_FIELD_FOR_INSERT_UPDATE: Unable to create/update fields: APTS_Product_Id_18__c, Type. Please check the security settings of this field and verify that it is read/write for your profile or permission set. [APTS_Product_Id_18__c, Type]
A46: [Product2] | B46: Secure Site Pro EV SSL FQDN SAN | C46: Secure Site Pro EV SSL FQDN SAN | E46: TRUE | F46: DigiCert | G46: USD | H46: 012dp000005zfL7AAI | J46: 01t0z000007f41gAAA | K46: 01t0z000007f41gAAA | L46: 01t0z000007f41gAAA | U46: TRUE | V46: Allowed | W46: TRUE | X46: Commercial | Y46: FALSE | BF46: FALSE | CC46: FALSE | CF46: FALSE | CK46: FALSE | CL46: FALSE | CM46: FALSE | CO46: 01tWC00000AYBYhYAP | CQ46: FALSE | CU46: FALSE | CW46: FALSE | CX46: FALSE | CZ46: FALSE | DA46: FALSE | DH46: FALSE | DM46: Secure Site Pro EV SSL FQDN SAN | DP46: FALSE | DR46: FALSE | DT46: Secure Site Pro EV SSL FQDN SAN | DX46: All SSL Product Grp | DY46: Active | DZ46: Failed | EA46: 01t0z000007f41gAAA | EC46: INVALID_FIELD_FOR_INSERT_UPDATE: Unable to create/update fields: APTS_Product_Id_18__c, Type. Please check the security settings of this field and verify that it is read/write for your profile or permission set. [APTS_Product_Id_18__c, Type]
A47: [Product2] | B47: Secure Site Pro SSL | C47: Secure Site Pro SSL | E47: TRUE | F47: DigiCert | G47: USD | H47: 012dp000005zfL7AAI | J47: 01t0z000007f41hAAA | K47: 01t0z000007f41hAAA | L47: 01t0z000007f41hAAA | U47: TRUE | V47: Allowed | W47: TRUE | X47: Commercial | Y47: FALSE | BF47: FALSE | CC47: FALSE | CF47: FALSE | CK47: FALSE | CL47: FALSE | CM47: FALSE | CO47: 01tWC00000AYBYiYAP | CQ47: FALSE | CU47: FALSE | CW47: FALSE | CX47: FALSE | CZ47: FALSE | DA47: FALSE | DH47: FALSE | DM47: Secure Site Pro SSL | DP47: FALSE | DR47: FALSE | DT47: Secure Site Pro SSL | DY47: Active | DZ47: Failed | EA47: 01t0z000007f41hAAA | EC47: INVALID_FIELD_FOR_INSERT_UPDATE: Unable to create/update fields: APTS_Product_Id_18__c, Type. Please check the security settings of this field and verify that it is read/write for your profile or permission set. [APTS_Product_Id_18__c, Type]
A48: [Product2] | B48: Secure Site Pro SSL FQDN SAN | C48: Secure Site Pro SSL FQDN SAN | E48: TRUE | F48: DigiCert | G48: USD | H48: 012dp000005zfL7AAI | J48: 01t0z000007f41iAAA | K48: 01t0z000007f41iAAA | L48: 01t0z000007f41iAAA | U48: TRUE | V48: Allowed | W48: TRUE | X48: Commercial | Y48: FALSE | BF48: FALSE | CC48: FALSE | CF48: FALSE | CK48: FALSE | CL48: FALSE | CM48: FALSE | CO48: 01tWC00000AYBYjYAP | CQ48: FALSE | CU48: FALSE | CW48: FALSE | CX48: FALSE | CZ48: FALSE | DA48: FALSE | DH48: FALSE | DM48: Secure Site Pro SSL FQDN SAN | DP48: FALSE | DR48: FALSE | DT48: Secure Site Pro SSL FQDN SAN | DX48: All SSL Product Grp | DY48: Active | DZ48: Failed | EA48: 01t0z000007f41iAAA | EC48: INVALID_FIELD_FOR_INSERT_UPDATE: Unable to create/update fields: APTS_Product_Id_18__c, Type. Please check the security settings of this field and verify that it is read/write for your profile or permission set. [APTS_Product_Id_18__c, Type]
A49: [Product2] | B49: Secure Site Pro SSL Wildcard SAN | C49: Secure Site Pro SSL Wildcard SAN | E49: TRUE | F49: DigiCert | G49: USD | H49: 012dp000005zfL7AAI | J49: 01t0z000007f41jAAA | K49: 01t0z000007f41jAAA | L49: 01t0z000007f41jAAA | U49: TRUE | V49: Allowed | W49: TRUE | X49: Commercial | Y49: FALSE | BF49: FALSE | CC49: FALSE | CF49: FALSE | CK49: FALSE | CL49: FALSE | CM49: FALSE | CO49: 01tWC00000AYBYkYAP | CQ49: FALSE | CU49: FALSE | CW49: FALSE | CX49: FALSE | CZ49: FALSE | DA49: FALSE | DH49: FALSE | DM49: Secure Site Pro SSL Wildcard SAN | DP49: FALSE | DR49: FALSE | DT49: Secure Site Pro SSL Wildcard SAN | DX49: All SSL Product Grp | DY49: Active | DZ49: Failed | EA49: 01t0z000007f41jAAA | EC49: INVALID_FIELD_FOR_INSERT_UPDATE: Unable to create/update fields: APTS_Product_Id_18__c, Type. Please check the security settings of this field and verify that it is read/write for your profile or permission set. [APTS_Product_Id_18__c, Type]
A50: [Product2] | B50: Secure Site OV | C50: Secure Site OV | E50: TRUE | F50: DigiCert | G50: USD | H50: 012dp000005zfL7AAI | J50: 01t0z000007f41kAAA | K50: 01t0z000007f41kAAA | L50: 01t0z000007f41kAAA | U50: TRUE | V50: Allowed | W50: TRUE | X50: Commercial | Y50: FALSE | BF50: FALSE | CC50: FALSE | CF50: FALSE | CK50: FALSE | CL50: FALSE | CM50: FALSE | CO50: 01tWC00000AYBYlYAP | CQ50: FALSE | CU50: FALSE | CW50: FALSE | CX50: FALSE | CZ50: FALSE | DA50: FALSE | DH50: FALSE | DM50: Secure Site OV | DP50: FALSE | DR50: FALSE | DT50: Secure Site OV | DY50: Active | DZ50: Failed | EA50: 01t0z000007f41kAAA | EC50: INVALID_FIELD_FOR_INSERT_UPDATE: Unable to create/update fields: APTS_Product_Id_18__c, Type. Please check the security settings of this field and verify that it is read/write for your profile or permission set. [APTS_Product_Id_18__c, Type]
A51: [Product2] | B51: Secure Site OV FQDN SAN | C51: Secure Site OV FQDN SAN | E51: TRUE | F51: DigiCert | G51: USD | H51: 012dp000005zfL7AAI | J51: 01t0z000007f41lAAA | K51: 01t0z000007f41lAAA | L51: 01t0z000007f41lAAA | R51: 11BWC000002cka92AA | U51: TRUE | W51: TRUE | X51: Commercial | Y51: FALSE | BF51: FALSE | CC51: FALSE | CF51: FALSE | CK51: FALSE | CL51: FALSE | CM51: FALSE | CO51: 01tWC00000AYBYmYAP | CQ51: FALSE | CU51: FALSE | CW51: FALSE | CX51: FALSE | CZ51: FALSE | DA51: FALSE | DH51: FALSE | DM51: Secure Site OV FQDN SAN | DP51: FALSE | DR51: FALSE | DT51: Secure Site OV FQDN SAN | DX51: All SSL Product Grp | DY51: Active | DZ51: Failed | EA51: 01t0z000007f41lAAA | EC51: INVALID_FIELD_FOR_INSERT_UPDATE: Unable to create/update fields: APTS_Product_Id_18__c, Type. Please check the security settings of this field and verify that it is read/write for your profile or permission set. [APTS_Product_Id_18__c, Type]
A52: [Product2] | B52: Secure Site OV Wildcard SAN | C52: Secure Site OV Wildcard SAN | E52: TRUE | F52: DigiCert | G52: USD | H52: 012dp000005zfL7AAI | J52: 01t0z000007f41mAAA | K52: 01t0z000007f41mAAA | L52: 01t0z000007f41mAAA | R52: 11BWC000002cka92AA | U52: TRUE | W52: TRUE | X52: Commercial | Y52: FALSE | BF52: FALSE | CC52: FALSE | CF52: FALSE | CK52: FALSE | CL52: FALSE | CM52: FALSE | CO52: 01tWC00000AYBYnYAP | CQ52: FALSE | CU52: FALSE | CW52: FALSE | CX52: FALSE | CZ52: FALSE | DA52: FALSE | DH52: FALSE | DM52: Secure Site OV Wildcard SAN | DP52: FALSE | DR52: FALSE | DT52: Secure Site OV Wildcard SAN | DX52: All SSL Product Grp | DY52: Active | DZ52: Failed | EA52: 01t0z000007f41mAAA | EC52: INVALID_FIELD_FOR_INSERT_UPDATE: Unable to create/update fields: APTS_Product_Id_18__c, Type. Please check the security settings of this field and verify that it is read/write for your profile or permission set. [APTS_Product_Id_18__c, Type]
A53: [Product2] | B53: Test Authentication Only | C53: Test Authentication Only | E53: TRUE | F53: DigiCert | G53: USD | H53: 012dp000005zfL7AAI | J53: 01t0z000007f41nAAA | K53: 01t0z000007f41nAAA | L53: 01t0z000007f41nAAA | R53: 11BWC000002WLYp2AO | U53: TRUE | V53: Allowed | W53: TRUE | X53: Commercial | Y53: FALSE | BF53: FALSE | CC53: FALSE | CF53: FALSE | CK53: FALSE | CL53: FALSE | CM53: FALSE | CO53: 01tWC00000AYBYoYAP | CQ53: FALSE | CU53: FALSE | CW53: FALSE | CX53: FALSE | CZ53: FALSE | DA53: FALSE | DH53: FALSE | DM53: Test Authentication Only | DP53: FALSE | DR53: FALSE | DT53: Test Authentication Only | DX53: All SSL Product Grp | DY53: Active | DZ53: Failed | EA53: 01t0z000007f41nAAA | EC53: INVALID_FIELD_FOR_INSERT_UPDATE: Unable to create/update fields: APTS_Product_Id_18__c, Type. Please check the security settings of this field and verify that it is read/write for your profile or permission set. [APTS_Product_Id_18__c, Type]
A54: [Product2] | B54: Test Private Client Authentication | C54: Test Private Client Authentication | E54: TRUE | F54: DigiCert | G54: USD | H54: 012dp000005zfL7AAI | J54: 01t0z000007f41oAAA | K54: 01t0z000007f41oAAA | L54: 01t0z000007f41oAAA | R54: 11BWC000002WLYv2AO | U54: TRUE | V54: Allowed | W54: TRUE | X54: Commercial | Y54: FALSE | BF54: FALSE | CC54: FALSE | CF54: FALSE | CK54: FALSE | CL54: FALSE | CM54: FALSE | CO54: 01tWC00000AYBYpYAP | CQ54: FALSE | CU54: FALSE | CW54: FALSE | CX54: FALSE | CZ54: FALSE | DA54: FALSE | DH54: FALSE | DM54: Test Private Client Authentication | DP54: FALSE | DR54: FALSE | DT54: Test Private Client Authentication | DX54: All SSL Product Grp | DY54: Active | DZ54: Failed | EA54: 01t0z000007f41oAAA | EC54: INVALID_FIELD_FOR_INSERT_UPDATE: Unable to create/update fields: APTS_Product_Id_18__c, Type. Please check the security settings of this field and verify that it is read/write for your profile or permission set. [APTS_Product_Id_18__c, Type]
A55: [Product2] | B55: Thawte SSL 123 DV | C55: Thawte SSL 123 DV | E55: TRUE | F55: Thawte | G55: USD | H55: 012dp000005zfL7AAI | J55: 01t0z000007f41pAAA | K55: 01t0z000007f41pAAA | L55: 01t0z000007f41pAAA | U55: TRUE | V55: Allowed | W55: TRUE | X55: Commercial | Y55: FALSE | BF55: FALSE | CC55: FALSE | CF55: FALSE | CK55: FALSE | CL55: FALSE | CM55: FALSE | CO55: 01tWC00000AYBYqYAP | CQ55: FALSE | CU55: FALSE | CW55: FALSE | CX55: FALSE | CZ55: FALSE | DA55: FALSE | DH55: FALSE | DM55: Thawte SSL 123 DV | DP55: FALSE | DR55: FALSE | DT55: Thawte SSL 123 DV | DX55: All SSL Product Grp | DY55: Active | DZ55: Failed | EA55: 01t0z000007f41pAAA | EC55: INVALID_FIELD_FOR_INSERT_UPDATE: Unable to create/update fields: APTS_Product_Id_18__c, Type. Please check the security settings of this field and verify that it is read/write for your profile or permission set. [APTS_Product_Id_18__c, Type]
A56: [Product2] | B56: Thawte SSL 123 DV FQDN SAN | C56: Thawte SSL 123 DV FQDN SAN | E56: TRUE | F56: Thawte | G56: USD | H56: 012dp000005zfL7AAI | J56: 01t0z000007f41qAAA | K56: 01t0z000007f41qAAA | L56: 01t0z000007f41qAAA | R56: 11BWC000002cka92AA | U56: TRUE | W56: TRUE | X56: Commercial | Y56: FALSE | BF56: FALSE | CC56: FALSE | CF56: FALSE | CK56: FALSE | CL56: FALSE | CM56: FALSE | CO56: 01tWC00000AYBYrYAP | CQ56: FALSE | CU56: FALSE | CW56: FALSE | CX56: FALSE | CZ56: FALSE | DA56: FALSE | DH56: FALSE | DM56: Thawte SSL 123 DV FQDN SAN | DP56: FALSE | DR56: FALSE | DT56: Thawte SSL 123 DV FQDN SAN | DX56: All SSL Product Grp | DY56: Active | DZ56: Failed | EA56: 01t0z000007f41qAAA | EC56: INVALID_FIELD_FOR_INSERT_UPDATE: Unable to create/update fields: APTS_Product_Id_18__c, Type. Please check the security settings of this field and verify that it is read/write for your profile or permission set. [APTS_Product_Id_18__c, Type]
A57: [Product2] | B57: Thawte SSL 123 DV Wildcard SAN | C57: Thawte SSL 123 DV Wildcard SAN | E57: TRUE | F57: Thawte | G57: USD | H57: 012dp000005zfL7AAI | J57: 01t0z000007f41rAAA | K57: 01t0z000007f41rAAA | L57: 01t0z000007f41rAAA | R57: 11BWC000002cka92AA | U57: TRUE | W57: TRUE | X57: Commercial | Y57: FALSE | BF57: FALSE | CC57: FALSE | CF57: FALSE | CK57: FALSE | CL57: FALSE | CM57: FALSE | CO57: 01tWC00000AYBYsYAP | CQ57: FALSE | CU57: FALSE | CW57: FALSE | CX57: FALSE | CZ57: FALSE | DA57: FALSE | DH57: FALSE | DM57: Thawte SSL 123 DV Wildcard SAN | DP57: FALSE | DR57: FALSE | DT57: Thawte SSL 123 DV Wildcard SAN | DX57: All SSL Product Grp | DY57: Active | DZ57: Failed | EA57: 01t0z000007f41rAAA | EC57: INVALID_FIELD_FOR_INSERT_UPDATE: Unable to create/update fields: APTS_Product_Id_18__c, Type. Please check the security settings of this field and verify that it is read/write for your profile or permission set. [APTS_Product_Id_18__c, Type]
A58: [Product2] | B58: Thawte SSL Webserver EV | C58: Thawte SSL Webserver EV | E58: TRUE | F58: Thawte | G58: USD | H58: 012dp000005zfL7AAI | J58: 01t0z000007f41sAAA | K58: 01t0z000007f41sAAA | L58: 01t0z000007f41sAAA | U58: TRUE | V58: Allowed | W58: TRUE | X58: Commercial | Y58: FALSE | BF58: FALSE | CC58: FALSE | CF58: FALSE | CK58: FALSE | CL58: FALSE | CM58: FALSE | CO58: 01tWC00000AYBYtYAP | CQ58: FALSE | CU58: FALSE | CW58: FALSE | CX58: FALSE | CZ58: FALSE | DA58: FALSE | DH58: FALSE | DM58: Thawte SSL Webserver EV | DP58: FALSE | DR58: FALSE | DT58: Thawte SSL Webserver EV | DY58: Active | DZ58: Failed | EA58: 01t0z000007f41sAAA | EC58: INVALID_FIELD_FOR_INSERT_UPDATE: Unable to create/update fields: APTS_Product_Id_18__c, Type. Please check the security settings of this field and verify that it is read/write for your profile or permission set. [APTS_Product_Id_18__c, Type]
A59: [Product2] | B59: Thawte SSL Webserver EV FQDN SAN | C59: Thawte SSL Webserver EV FQDN SAN | E59: TRUE | F59: Thawte | G59: USD | H59: 012dp000005zfL7AAI | J59: 01t0z000007f41tAAA | K59: 01t0z000007f41tAAA | L59: 01t0z000007f41tAAA | R59: 11BWC000002cka92AA | U59: TRUE | W59: TRUE | X59: Commercial | Y59: FALSE | BF59: FALSE | CC59: FALSE | CF59: FALSE | CK59: FALSE | CL59: FALSE | CM59: FALSE | CO59: 01tWC00000AYBYuYAP | CQ59: FALSE | CU59: FALSE | CW59: FALSE | CX59: FALSE | CZ59: FALSE | DA59: FALSE | DH59: FALSE | DM59: Thawte SSL Webserver EV FQDN SAN | DP59: FALSE | DR59: FALSE | DT59: Thawte SSL Webserver EV FQDN SAN | DX59: All SSL Product Grp | DY59: Active | DZ59: Failed | EA59: 01t0z000007f41tAAA | EC59: INVALID_FIELD_FOR_INSERT_UPDATE: Unable to create/update fields: APTS_Product_Id_18__c, Type. Please check the security settings of this field and verify that it is read/write for your profile or permission set. [APTS_Product_Id_18__c, Type]
A60: [Product2] | B60: Thawte SSL Webserver OV | C60: Thawte SSL Webserver OV | E60: TRUE | F60: Thawte | G60: USD | H60: 012dp000005zfL7AAI | J60: 01t0z000007f41uAAA | K60: 01t0z000007f41uAAA | L60: 01t0z000007f41uAAA | U60: TRUE | V60: Allowed | W60: TRUE | X60: Commercial | Y60: FALSE | BF60: FALSE | CC60: FALSE | CF60: FALSE | CK60: FALSE | CL60: FALSE | CM60: FALSE | CO60: 01tWC00000AYBYvYAP | CQ60: FALSE | CU60: FALSE | CW60: FALSE | CX60: FALSE | CZ60: FALSE | DA60: FALSE | DH60: FALSE | DM60: Thawte SSL Webserver OV | DP60: FALSE | DR60: FALSE | DT60: Thawte SSL Webserver OV | DY60: Active | DZ60: Failed | EA60: 01t0z000007f41uAAA | EC60: INVALID_FIELD_FOR_INSERT_UPDATE: Unable to create/update fields: APTS_Product_Id_18__c, Type. Please check the security settings of this field and verify that it is read/write for your profile or permission set. [APTS_Product_Id_18__c, Type]
A61: [Product2] | B61: Thawte SSL Webserver OV FQDN SAN | C61: Thawte SSL Webserver OV FQDN SAN | E61: TRUE | F61: Thawte | G61: USD | H61: 012dp000005zfL7AAI | J61: 01t0z000007f41vAAA | K61: 01t0z000007f41vAAA | L61: 01t0z000007f41vAAA | R61: 11BWC000002cka92AA | U61: TRUE | W61: TRUE | X61: Commercial | Y61: FALSE | BF61: FALSE | CC61: FALSE | CF61: FALSE | CK61: FALSE | CL61: FALSE | CM61: FALSE | CO61: 01tWC00000AYBYwYAP | CQ61: FALSE | CU61: FALSE | CW61: FALSE | CX61: FALSE | CZ61: FALSE | DA61: FALSE | DH61: FALSE | DM61: Thawte SSL Webserver OV FQDN SAN | DP61: FALSE | DR61: FALSE | DT61: Thawte SSL Webserver OV FQDN SAN | DX61: All SSL Product Grp | DY61: Active | DZ61: Failed | EA61: 01t0z000007f41vAAA | EC61: INVALID_FIELD_FOR_INSERT_UPDATE: Unable to create/update fields: APTS_Product_Id_18__c, Type. Please check the security settings of this field and verify that it is read/write for your profile or permission set. [APTS_Product_Id_18__c, Type]
A62: [Product2] | B62: Thawte SSL Webserver OV Wildcard SAN | C62: Thawte SSL Webserver OV Wildcard SAN | E62: TRUE | F62: Thawte | G62: USD | H62: 012dp000005zfL7AAI | J62: 01t0z000007f41wAAA | K62: 01t0z000007f41wAAA | L62: 01t0z000007f41wAAA | R62: 11BWC000002cka92AA | U62: TRUE | W62: TRUE | X62: Commercial | Y62: FALSE | BF62: FALSE | CC62: FALSE | CF62: FALSE | CK62: FALSE | CL62: FALSE | CM62: FALSE | CO62: 01tWC00000AYBYxYAP | CQ62: FALSE | CU62: FALSE | CW62: FALSE | CX62: FALSE | CZ62: FALSE | DA62: FALSE | DH62: FALSE | DM62: Thawte SSL Webserver OV Wildcard SAN | DP62: FALSE | DR62: FALSE | DT62: Thawte SSL Webserver OV Wildcard SAN | DX62: All SSL Product Grp | DY62: Active | DZ62: Failed | EA62: 01t0z000007f41wAAA | EC62: INVALID_FIELD_FOR_INSERT_UPDATE: Unable to create/update fields: APTS_Product_Id_18__c, Type. Please check the security settings of this field and verify that it is read/write for your profile or permission set. [APTS_Product_Id_18__c, Type]
A63: [Product2] | B63: Timestamp Authority | C63: Timestamp Authority | E63: TRUE | F63: DigiCert | G63: USD | H63: 012dp000005zfL7AAI | J63: 01t0z000007f41xAAA | K63: 01t0z000007f41xAAA | L63: 01t0z000007f41xAAA | R63: 11BWC000002WLYt2AO | U63: TRUE | V63: Allowed | W63: TRUE | X63: Commercial | Y63: FALSE | BF63: FALSE | CC63: FALSE | CF63: FALSE | CK63: FALSE | CL63: FALSE | CM63: FALSE | CO63: 01tWC00000AYBYyYAP | CQ63: FALSE | CU63: FALSE | CW63: FALSE | CX63: FALSE | CZ63: FALSE | DA63: FALSE | DH63: FALSE | DM63: Timestamp Authority | DP63: FALSE | DR63: FALSE | DT63: Timestamp Authority | DX63: All SSL Product Grp | DY63: Active | DZ63: Failed | EA63: 01t0z000007f41xAAA | EC63: INVALID_FIELD_FOR_INSERT_UPDATE: Unable to create/update fields: APTS_Product_Id_18__c, Type. Please check the security settings of this field and verify that it is read/write for your profile or permission set. [APTS_Product_Id_18__c, Type]
A64: [Product2] | B64: DigiCert KeyLocker (Units) | C64: DigiCert KeyLocker (Units) | E64: TRUE | F64: DigiCert | G64: USD | H64: 012dp000005zfL7AAI | J64: 01t4z000008br95AAA | K64: 01t4z000008br95AAA | L64: 01t4z000008br95AAA | U64: TRUE | V64: Allowed | W64: TRUE | X64: Commercial | Y64: FALSE | BF64: FALSE | CC64: FALSE | CF64: FALSE | CK64: FALSE | CL64: FALSE | CM64: FALSE | CO64: 01tWC00000AYBZ0YAP | CQ64: FALSE | CU64: FALSE | CW64: FALSE | CX64: FALSE | CZ64: FALSE | DA64: FALSE | DH64: FALSE | DM64: DigiCert KeyLocker (Units) | DP64: FALSE | DR64: FALSE | DT64: DigiCert KeyLocker (Units) | DY64: Active | DZ64: Failed | EA64: 01t4z000008br95AAA | EC64: INVALID_FIELD_FOR_INSERT_UPDATE: Unable to create/update fields: APTS_Product_Id_18__c, Type. Please check the security settings of this field and verify that it is read/write for your profile or permission set. [APTS_Product_Id_18__c, Type]
A65: [Product2] | B65: DIGICERT USB AUTHENTICATOR 5110FIPS PLUS NO PIN 3YR WARRANTY [Hardware Token] (Units) | C65: DIGICERT USB AUTHENTICATOR 5110FIPS PLUS NO PIN 3YR WARRANTY [Hardware Token] (Units) | E65: TRUE | F65: DigiCert | G65: USD | H65: 012dp000005zfL7AAI | J65: 01t4z000008br9ZAAQ | K65: 01t4z000008br9ZAAQ | L65: 01t4z000008br9ZAAQ | U65: TRUE | W65: TRUE | X65: Commercial | Y65: FALSE | BF65: FALSE | CC65: FALSE | CF65: FALSE | CK65: FALSE | CL65: FALSE | CM65: FALSE | CO65: 01tWC00000AYBZ1YAP | CQ65: FALSE | CU65: FALSE | CW65: FALSE | CX65: FALSE | CZ65: FALSE | DA65: FALSE | DH65: FALSE | DM65: DIGICERT USB AUTHENTICATOR 5110FIPS PLUS NO PIN 3YR WARRANTY [Hardware Token] (Units) | DP65: FALSE | DR65: FALSE | DT65: DIGICERT USB AUTHENTICATOR 5110FIPS PLUS NO PIN 3YR WARRANTY [Hardware Token] (Units) | DY65: Active | DZ65: Failed | EA65: 01t4z000008br9ZAAQ | EC65: INVALID_FIELD_FOR_INSERT_UPDATE: Unable to create/update fields: APTS_Product_Id_18__c, Type. Please check the security settings of this field and verify that it is read/write for your profile or permission set. [APTS_Product_Id_18__c, Type]
A66: [Product2] | B66: Encryption Everywhere DV | C66: Encryption Everywhere DV | E66: TRUE | F66: DigiCert | G66: USD | H66: 012dp000005zfL7AAI | J66: 01t4z000008h0MrAAI | K66: 01t4z000008h0MrAAI | L66: 01t4z000008h0MrAAI | U66: TRUE | W66: TRUE | X66: Commercial | Y66: FALSE | BF66: FALSE | CC66: FALSE | CF66: FALSE | CK66: FALSE | CL66: FALSE | CM66: FALSE | CO66: 01tWC00000AYBZ2YAP | CQ66: FALSE | CU66: FALSE | CW66: FALSE | CX66: FALSE | CZ66: FALSE | DA66: FALSE | DH66: FALSE | DM66: Encryption Everywhere DV | DP66: FALSE | DR66: FALSE | DT66: Encryption Everywhere DV | DX66: All SSL Product Grp | DY66: Active | DZ66: Failed | EA66: 01t4z000008h0MrAAI | EC66: INVALID_FIELD_FOR_INSERT_UPDATE: Unable to create/update fields: APTS_Product_Id_18__c, Type. Please check the security settings of this field and verify that it is read/write for your profile or permission set. [APTS_Product_Id_18__c, Type]
A67: [Product2] | B67: Encryption Everywhere DV Wildcard SAN | C67: Encryption Everywhere DV Wildcard SAN | E67: TRUE | F67: DigiCert | G67: USD | H67: 012dp000005zfL7AAI | J67: 01t4z000008h0MwAAI | K67: 01t4z000008h0MwAAI | L67: 01t4z000008h0MwAAI | U67: TRUE | W67: TRUE | X67: Commercial | Y67: FALSE | BF67: FALSE | CC67: FALSE | CF67: FALSE | CK67: FALSE | CL67: FALSE | CM67: FALSE | CO67: 01tWC00000AYBZ3YAP | CQ67: FALSE | CU67: FALSE | CW67: FALSE | CX67: FALSE | CZ67: FALSE | DA67: FALSE | DH67: FALSE | DM67: Encryption Everywhere DV Wildcard SAN | DP67: FALSE | DR67: FALSE | DT67: Encryption Everywhere DV Wildcard SAN | DX67: All SSL Product Grp | DY67: Active | DZ67: Failed | EA67: 01t4z000008h0MwAAI | EC67: INVALID_FIELD_FOR_INSERT_UPDATE: Unable to create/update fields: APTS_Product_Id_18__c, Type. Please check the security settings of this field and verify that it is read/write for your profile or permission set. [APTS_Product_Id_18__c, Type]
A68: [Product2] | B68: Grid Host Multi-Domain SSL | C68: Grid Host Multi-Domain SSL | E68: TRUE | F68: DigiCert | G68: USD | H68: 012dp000005zfL7AAI | J68: 01t4z000008h0N1AAI | K68: 01t4z000008h0N1AAI | L68: 01t4z000008h0N1AAI | R68: 11BWC000002WLYz2AO | U68: TRUE | W68: TRUE | X68: Commercial | Y68: FALSE | BF68: FALSE | CC68: FALSE | CF68: FALSE | CK68: FALSE | CL68: FALSE | CM68: FALSE | CO68: 01tWC00000AYBZ4YAP | CQ68: FALSE | CU68: FALSE | CW68: FALSE | CX68: FALSE | CZ68: FALSE | DA68: FALSE | DH68: FALSE | DM68: Grid Host Multi-Domain SSL | DP68: FALSE | DR68: FALSE | DT68: Grid Host Multi-Domain SSL | DX68: All SSL Product Grp | DY68: Active | DZ68: Failed | EA68: 01t4z000008h0N1AAI | EC68: INVALID_FIELD_FOR_INSERT_UPDATE: Unable to create/update fields: APTS_Product_Id_18__c, Type. Please check the security settings of this field and verify that it is read/write for your profile or permission set. [APTS_Product_Id_18__c, Type]
A69: [Product2] | B69: Grid Host Multi-Domain SSL Addl. Names | C69: Grid Host Multi-Domain SSL Addl. Names | E69: TRUE | F69: DigiCert | G69: USD | H69: 012dp000005zfL7AAI | J69: 01t4z000008h0N6AAI | K69: 01t4z000008h0N6AAI | L69: 01t4z000008h0N6AAI | R69: 11BWC000002WLZ02AO | U69: TRUE | W69: TRUE | X69: Commercial | Y69: FALSE | BF69: FALSE | CC69: FALSE | CF69: FALSE | CK69: FALSE | CL69: FALSE | CM69: FALSE | CO69: 01tWC00000AYBZ5YAP | CQ69: FALSE | CU69: FALSE | CW69: FALSE | CX69: FALSE | CZ69: FALSE | DA69: FALSE | DH69: FALSE | DM69: Grid Host Multi-Domain SSL Addl. Names | DP69: FALSE | DR69: FALSE | DT69: Grid Host Multi-Domain SSL Addl. Names | DX69: All SSL Product Grp | DY69: Active | DZ69: Failed | EA69: 01t4z000008h0N6AAI | EC69: INVALID_FIELD_FOR_INSERT_UPDATE: Unable to create/update fields: APTS_Product_Id_18__c, Type. Please check the security settings of this field and verify that it is read/write for your profile or permission set. [APTS_Product_Id_18__c, Type]
A70: [Product2] | B70: Grid Host SSL | C70: Grid Host SSL | E70: TRUE | F70: DigiCert | G70: USD | H70: 012dp000005zfL7AAI | J70: 01t4z000008h0NBAAY | K70: 01t4z000008h0NBAAY | L70: 01t4z000008h0NBAAY | R70: 11BWC000002WLZ12AO | U70: TRUE | W70: TRUE | X70: Commercial | Y70: FALSE | BF70: FALSE | CC70: FALSE | CF70: FALSE | CK70: FALSE | CL70: FALSE | CM70: FALSE | CO70: 01tWC00000AYBZ6YAP | CQ70: FALSE | CU70: FALSE | CW70: FALSE | CX70: FALSE | CZ70: FALSE | DA70: FALSE | DH70: FALSE | DM70: Grid Host SSL | DP70: FALSE | DR70: FALSE | DT70: Grid Host SSL | DX70: All SSL Product Grp | DY70: Active | DZ70: Failed | EA70: 01t4z000008h0NBAAY | EC70: INVALID_FIELD_FOR_INSERT_UPDATE: Unable to create/update fields: APTS_Product_Id_18__c, Type. Please check the security settings of this field and verify that it is read/write for your profile or permission set. [APTS_Product_Id_18__c, Type]
A71: [Product2] | B71: Grid Premium | C71: Grid Premium | E71: TRUE | F71: DigiCert | G71: USD | H71: 012dp000005zfL7AAI | J71: 01t4z000008h0NGAAY | K71: 01t4z000008h0NGAAY | L71: 01t4z000008h0NGAAY | R71: 11BWC000002WLYy2AO | U71: TRUE | W71: TRUE | X71: Commercial | Y71: FALSE | BF71: FALSE | CC71: FALSE | CF71: FALSE | CK71: FALSE | CL71: FALSE | CM71: FALSE | CO71: 01tWC00000AYBZ7YAP | CQ71: FALSE | CU71: FALSE | CW71: FALSE | CX71: FALSE | CZ71: FALSE | DA71: FALSE | DH71: FALSE | DM71: Grid Premium | DP71: FALSE | DR71: FALSE | DT71: Grid Premium | DX71: All SSL Product Grp | DY71: Active | DZ71: Failed | EA71: 01t4z000008h0NGAAY | EC71: INVALID_FIELD_FOR_INSERT_UPDATE: Unable to create/update fields: APTS_Product_Id_18__c, Type. Please check the security settings of this field and verify that it is read/write for your profile or permission set. [APTS_Product_Id_18__c, Type]
A72: [Product2] | B72: Grid Robot Email | C72: Grid Robot Email | E72: TRUE | F72: DigiCert | G72: USD | H72: 012dp000005zfL7AAI | J72: 01t4z000008h0NHAAY | K72: 01t4z000008h0NHAAY | L72: 01t4z000008h0NHAAY | R72: 11BWC000002WLZ22AO | U72: TRUE | W72: TRUE | X72: Commercial | Y72: FALSE | BF72: FALSE | CC72: FALSE | CF72: FALSE | CK72: FALSE | CL72: FALSE | CM72: FALSE | CO72: 01tWC00000AYBZ8YAP | CQ72: FALSE | CU72: FALSE | CW72: FALSE | CX72: FALSE | CZ72: FALSE | DA72: FALSE | DH72: FALSE | DM72: Grid Robot Email | DP72: FALSE | DR72: FALSE | DT72: Grid Robot Email | DX72: All SSL Product Grp | DY72: Active | DZ72: Failed | EA72: 01t4z000008h0NHAAY | EC72: INVALID_FIELD_FOR_INSERT_UPDATE: Unable to create/update fields: APTS_Product_Id_18__c, Type. Please check the security settings of this field and verify that it is read/write for your profile or permission set. [APTS_Product_Id_18__c, Type]
A73: [Product2] | B73: Grid Robot FQDN | C73: Grid Robot FQDN | E73: TRUE | F73: DigiCert | G73: USD | H73: 012dp000005zfL7AAI | J73: 01t4z000008h0NIAAY | K73: 01t4z000008h0NIAAY | L73: 01t4z000008h0NIAAY | R73: 11BWC000002WLZ32AO | U73: TRUE | W73: TRUE | X73: Commercial | Y73: FALSE | BF73: FALSE | CC73: FALSE | CF73: FALSE | CK73: FALSE | CL73: FALSE | CM73: FALSE | CO73: 01tWC00000AYBZ9YAP | CQ73: FALSE | CU73: FALSE | CW73: FALSE | CX73: FALSE | CZ73: FALSE | DA73: FALSE | DH73: FALSE | DM73: Grid Robot FQDN | DP73: FALSE | DR73: FALSE | DT73: Grid Robot FQDN | DX73: All SSL Product Grp | DY73: Active | DZ73: Failed | EA73: 01t4z000008h0NIAAY | EC73: INVALID_FIELD_FOR_INSERT_UPDATE: Unable to create/update fields: APTS_Product_Id_18__c, Type. Please check the security settings of this field and verify that it is read/write for your profile or permission set. [APTS_Product_Id_18__c, Type]
A74: [Product2] | B74: Private SSL OV (Units) | C74: Private SSL OV (Units) | E74: TRUE | F74: DigiCert | G74: USD | H74: 012dp000005zfL7AAI | J74: 01t4z000008jjfOAAQ | K74: 01t4z000008jjfOAAQ | L74: 01t4z000008jjfOAAQ | U74: TRUE | V74: Allowed | W74: TRUE | X74: Commercial | Y74: FALSE | BF74: FALSE | CC74: FALSE | CF74: FALSE | CK74: FALSE | CL74: FALSE | CM74: FALSE | CO74: 01tWC00000AYBZAYA5 | CQ74: FALSE | CU74: FALSE | CW74: FALSE | CX74: FALSE | CZ74: FALSE | DA74: FALSE | DH74: FALSE | DM74: Private SSL OV (Units) | DP74: FALSE | DR74: FALSE | DT74: Private SSL OV (Units) | DY74: Active | DZ74: Failed | EA74: 01t4z000008jjfOAAQ | EC74: INVALID_FIELD_FOR_INSERT_UPDATE: Unable to create/update fields: APTS_Product_Id_18__c, Type. Please check the security settings of this field and verify that it is read/write for your profile or permission set. [APTS_Product_Id_18__c, Type]
A75: [Product2] | B75: EV Code Signing (Units) | C75: EV Code Signing (Units) | E75: TRUE | F75: DigiCert | G75: USD | H75: 012dp000005zfL7AAI | J75: 01t4z000008jjfSAAQ | K75: 01t4z000008jjfSAAQ | L75: 01t4z000008jjfSAAQ | U75: TRUE | V75: Allowed | W75: TRUE | X75: Commercial | Y75: FALSE | BF75: FALSE | CC75: FALSE | CF75: FALSE | CK75: FALSE | CL75: FALSE | CM75: FALSE | CO75: 01tWC00000AYBZBYA5 | CQ75: FALSE | CU75: FALSE | CW75: FALSE | CX75: FALSE | CZ75: FALSE | DA75: FALSE | DH75: FALSE | DM75: EV Code Signing (Units) | DP75: FALSE | DR75: FALSE | DT75: EV Code Signing (Units) | DY75: Active | DZ75: Failed | EA75: 01t4z000008jjfSAAQ | EC75: INVALID_FIELD_FOR_INSERT_UPDATE: Unable to create/update fields: APTS_Product_Id_18__c, Type. Please check the security settings of this field and verify that it is read/write for your profile or permission set. [APTS_Product_Id_18__c, Type]
A76: [Product2] | B76: GeoTrust TrueBusiness ID OV (Units) | C76: GeoTrust TrueBusiness ID OV (Units) | E76: TRUE | F76: Geotrust | G76: USD | H76: 012dp000005zfL7AAI | J76: 01t4z000008jjfXAAQ | K76: 01t4z000008jjfXAAQ | L76: 01t4z000008jjfXAAQ | U76: TRUE | V76: Allowed | W76: TRUE | X76: Commercial | Y76: FALSE | BF76: FALSE | CC76: FALSE | CF76: FALSE | CK76: FALSE | CL76: FALSE | CM76: FALSE | CO76: 01tWC00000AYBZCYA5 | CQ76: FALSE | CU76: FALSE | CW76: FALSE | CX76: FALSE | CZ76: FALSE | DA76: FALSE | DH76: FALSE | DM76: GeoTrust TrueBusiness ID OV (Units) | DP76: FALSE | DR76: FALSE | DT76: GeoTrust TrueBusiness ID OV (Units) | DY76: Active | DZ76: Failed | EA76: 01t4z000008jjfXAAQ | EC76: INVALID_FIELD_FOR_INSERT_UPDATE: Unable to create/update fields: APTS_Product_Id_18__c, Type. Please check the security settings of this field and verify that it is read/write for your profile or permission set. [APTS_Product_Id_18__c, Type]
A77: [Product2] | B77: GeoTrust TrueBusiness ID EV (Units) | C77: GeoTrust TrueBusiness ID EV (Units) | E77: TRUE | F77: Geotrust | G77: USD | H77: 012dp000005zfL7AAI | J77: 01t4z000008jjfcAAA | K77: 01t4z000008jjfcAAA | L77: 01t4z000008jjfcAAA | U77: TRUE | V77: Allowed | W77: TRUE | X77: Commercial | Y77: FALSE | BF77: FALSE | CC77: FALSE | CF77: FALSE | CK77: FALSE | CL77: FALSE | CM77: FALSE | CO77: 01tWC00000AYBZDYA5 | CQ77: FALSE | CU77: FALSE | CW77: FALSE | CX77: FALSE | CZ77: FALSE | DA77: FALSE | DH77: FALSE | DM77: GeoTrust TrueBusiness ID EV (Units) | DP77: FALSE | DR77: FALSE | DT77: GeoTrust TrueBusiness ID EV (Units) | DY77: Active | DZ77: Failed | EA77: 01t4z000008jjfcAAA | EC77: INVALID_FIELD_FOR_INSERT_UPDATE: Unable to create/update fields: APTS_Product_Id_18__c, Type. Please check the security settings of this field and verify that it is read/write for your profile or permission set. [APTS_Product_Id_18__c, Type]
A78: [Product2] | B78: Secure Site EV (Units) | C78: Secure Site EV (Units) | E78: TRUE | F78: DigiCert | G78: USD | H78: 012dp000005zfL7AAI | J78: 01t4z000008jjfhAAA | K78: 01t4z000008jjfhAAA | L78: 01t4z000008jjfhAAA | U78: TRUE | V78: Allowed | W78: TRUE | X78: Commercial | Y78: FALSE | BF78: FALSE | CC78: FALSE | CF78: FALSE | CK78: FALSE | CL78: FALSE | CM78: FALSE | CO78: 01tWC00000AYBZEYA5 | CQ78: FALSE | CU78: FALSE | CW78: FALSE | CX78: FALSE | CZ78: FALSE | DA78: FALSE | DH78: FALSE | DM78: Secure Site EV (Units) | DP78: FALSE | DR78: FALSE | DT78: Secure Site EV (Units) | DY78: Active | DZ78: Failed | EA78: 01t4z000008jjfhAAA | EC78: INVALID_FIELD_FOR_INSERT_UPDATE: Unable to create/update fields: APTS_Product_Id_18__c, Type. Please check the security settings of this field and verify that it is read/write for your profile or permission set. [APTS_Product_Id_18__c, Type]
A79: [Product2] | B79: Secure Site OV (Units) | C79: Secure Site OV (Units) | E79: TRUE | F79: DigiCert | G79: USD | H79: 012dp000005zfL7AAI | J79: 01t4z000008jjfrAAA | K79: 01t4z000008jjfrAAA | L79: 01t4z000008jjfrAAA | U79: TRUE | V79: Allowed | W79: TRUE | X79: Commercial | Y79: FALSE | BF79: FALSE | CC79: FALSE | CF79: FALSE | CK79: FALSE | CL79: FALSE | CM79: FALSE | CO79: 01tWC00000AYBZFYA5 | CQ79: FALSE | CU79: FALSE | CW79: FALSE | CX79: FALSE | CZ79: FALSE | DA79: FALSE | DH79: FALSE | DM79: Secure Site OV (Units) | DP79: FALSE | DR79: FALSE | DT79: Secure Site OV (Units) | DY79: Active | DZ79: Failed | EA79: 01t4z000008jjfrAAA | EC79: INVALID_FIELD_FOR_INSERT_UPDATE: Unable to create/update fields: APTS_Product_Id_18__c, Type. Please check the security settings of this field and verify that it is read/write for your profile or permission set. [APTS_Product_Id_18__c, Type]
A80: [Product2] | B80: Secure Site Pro EV SSL (Units) | C80: Secure Site Pro EV SSL (Units) | E80: TRUE | F80: DigiCert | G80: USD | H80: 012dp000005zfL7AAI | J80: 01t4z000008jjfwAAA | K80: 01t4z000008jjfwAAA | L80: 01t4z000008jjfwAAA | U80: TRUE | V80: Allowed | W80: TRUE | X80: Commercial | Y80: FALSE | BF80: FALSE | CC80: FALSE | CF80: FALSE | CK80: FALSE | CL80: FALSE | CM80: FALSE | CO80: 01tWC00000AYBZGYA5 | CQ80: FALSE | CU80: FALSE | CW80: FALSE | CX80: FALSE | CZ80: FALSE | DA80: FALSE | DH80: FALSE | DM80: Secure Site Pro EV SSL (Units) | DP80: FALSE | DR80: FALSE | DT80: Secure Site Pro EV SSL (Units) | DY80: Active | DZ80: Failed | EA80: 01t4z000008jjfwAAA | EC80: INVALID_FIELD_FOR_INSERT_UPDATE: Unable to create/update fields: APTS_Product_Id_18__c, Type. Please check the security settings of this field and verify that it is read/write for your profile or permission set. [APTS_Product_Id_18__c, Type]
A81: [Product2] | B81: Secure Site Pro SSL (Units) | C81: Secure Site Pro SSL (Units) | E81: TRUE | F81: DigiCert | G81: USD | H81: 012dp000005zfL7AAI | J81: 01t4z000008jjfxAAA | K81: 01t4z000008jjfxAAA | L81: 01t4z000008jjfxAAA | U81: TRUE | V81: Allowed | W81: TRUE | X81: Commercial | Y81: FALSE | BF81: FALSE | CC81: FALSE | CF81: FALSE | CK81: FALSE | CL81: FALSE | CM81: FALSE | CO81: 01tWC00000AYBZHYA5 | CQ81: FALSE | CU81: FALSE | CW81: FALSE | CX81: FALSE | CZ81: FALSE | DA81: FALSE | DH81: FALSE | DM81: Secure Site Pro SSL (Units) | DP81: FALSE | DR81: FALSE | DT81: Secure Site Pro SSL (Units) | DY81: Active | DZ81: Failed | EA81: 01t4z000008jjfxAAA | EC81: INVALID_FIELD_FOR_INSERT_UPDATE: Unable to create/update fields: APTS_Product_Id_18__c, Type. Please check the security settings of this field and verify that it is read/write for your profile or permission set. [APTS_Product_Id_18__c, Type]
A82: [Product2] | B82: Thawte SSL Webserver EV (Units) | C82: Thawte SSL Webserver EV (Units) | E82: TRUE | F82: Thawte | G82: USD | H82: 012dp000005zfL7AAI | J82: 01t4z000008jjg1AAA | K82: 01t4z000008jjg1AAA | L82: 01t4z000008jjg1AAA | U82: TRUE | V82: Allowed | W82: TRUE | X82: Commercial | Y82: FALSE | BF82: FALSE | CC82: FALSE | CF82: FALSE | CK82: FALSE | CL82: FALSE | CM82: FALSE | CO82: 01tWC00000AYBZIYA5 | CQ82: FALSE | CU82: FALSE | CW82: FALSE | CX82: FALSE | CZ82: FALSE | DA82: FALSE | DH82: FALSE | DM82: Thawte SSL Webserver EV (Units) | DP82: FALSE | DR82: FALSE | DT82: Thawte SSL Webserver EV (Units) | DY82: Active | DZ82: Failed | EA82: 01t4z000008jjg1AAA | EC82: INVALID_FIELD_FOR_INSERT_UPDATE: Unable to create/update fields: APTS_Product_Id_18__c, Type. Please check the security settings of this field and verify that it is read/write for your profile or permission set. [APTS_Product_Id_18__c, Type]
A83: [Product2] | B83: Thawte SSL Webserver OV (Units) | C83: Thawte SSL Webserver OV (Units) | E83: TRUE | F83: Thawte | G83: USD | H83: 012dp000005zfL7AAI | J83: 01t4z000008jjg6AAA | K83: 01t4z000008jjg6AAA | L83: 01t4z000008jjg6AAA | U83: TRUE | V83: Allowed | W83: TRUE | X83: Commercial | Y83: FALSE | BF83: FALSE | CC83: FALSE | CF83: FALSE | CK83: FALSE | CL83: FALSE | CM83: FALSE | CO83: 01tWC00000AYBZJYA5 | CQ83: FALSE | CU83: FALSE | CW83: FALSE | CX83: FALSE | CZ83: FALSE | DA83: FALSE | DH83: FALSE | DM83: Thawte SSL Webserver OV (Units) | DP83: FALSE | DR83: FALSE | DT83: Thawte SSL Webserver OV (Units) | DY83: Active | DZ83: Failed | EA83: 01t4z000008jjg6AAA | EC83: INVALID_FIELD_FOR_INSERT_UPDATE: Unable to create/update fields: APTS_Product_Id_18__c, Type. Please check the security settings of this field and verify that it is read/write for your profile or permission set. [APTS_Product_Id_18__c, Type]
A84: [Product2] | B84: Verified Mark Certificate (Units) | C84: Verified Mark Certificate (Units) | E84: TRUE | F84: DigiCert | G84: USD | H84: 012dp000005zfL7AAI | J84: 01t4z000008jjgBAAQ | K84: 01t4z000008jjgBAAQ | L84: 01t4z000008jjgBAAQ | U84: TRUE | W84: TRUE | X84: Commercial | Y84: FALSE | BF84: FALSE | CC84: FALSE | CF84: FALSE | CK84: FALSE | CL84: FALSE | CM84: FALSE | CO84: 01tWC00000AYBZKYA5 | CQ84: FALSE | CU84: FALSE | CW84: FALSE | CX84: FALSE | CZ84: FALSE | DA84: FALSE | DH84: FALSE | DM84: Verified Mark Certificate (Units) | DP84: FALSE | DR84: FALSE | DT84: Verified Mark Certificate (Units) | DY84: Active | DZ84: Failed | EA84: 01t4z000008jjgBAAQ | EC84: INVALID_FIELD_FOR_INSERT_UPDATE: Unable to create/update fields: APTS_Product_Id_18__c, Type. Please check the security settings of this field and verify that it is read/write for your profile or permission set. [APTS_Product_Id_18__c, Type]
A85: [Product2] | B85: Encryption Everywhere DV FQDN SAN | C85: Encryption Everywhere DV FQDN SAN | E85: TRUE | F85: DigiCert | G85: USD | H85: 012dp000005zfL7AAI | J85: 01t4z000008jyEyAAI | K85: 01t4z000008jyEyAAI | L85: 01t4z000008jyEyAAI | U85: TRUE | W85: TRUE | X85: Commercial | Y85: FALSE | BF85: FALSE | CC85: FALSE | CF85: FALSE | CK85: FALSE | CL85: FALSE | CM85: FALSE | CO85: 01tWC00000AYBZLYA5 | CQ85: FALSE | CU85: FALSE | CW85: FALSE | CX85: FALSE | CZ85: FALSE | DA85: FALSE | DH85: FALSE | DM85: Encryption Everywhere DV FQDN SAN | DP85: FALSE | DR85: FALSE | DT85: Encryption Everywhere DV FQDN SAN | DX85: All SSL Product Grp | DY85: Active | DZ85: Failed | EA85: 01t4z000008jyEyAAI | EC85: INVALID_FIELD_FOR_INSERT_UPDATE: Unable to create/update fields: APTS_Product_Id_18__c, Type. Please check the security settings of this field and verify that it is read/write for your profile or permission set. [APTS_Product_Id_18__c, Type]
